Workbook
Name 切片器_平均最低分: #N/A
Name 切片器_2024最低分: #N/A
Name 切片器_2025最低分: #N/A
Name 切片器_类型: #N/A

Sheet 高考志愿填报指南
A1: 100%不滑挡、不退档志愿填报六步法
A2: 第一步：查位次（这是基础中的基础！）不要只看分数，更重要看位次，并按照自己位次*1.05来定位。
A3: 第二步：筛范围（别被众多院校淹没！）
A4: 思路1：圈定地域 你想留在家乡还是去北上广深？或者是向往那些山清水秀的城市？先把低于圈定！
A5: 思路2：筛选院校层次 如果过了本科线，优先关注具有保研资格的370所院校。
A6: 第三步：找标杆（志愿填报的分水岭）什么是标杆院校？就是以你的位次为基准，找到刚好能录取的那所学校！标杆等位分加权计算法则=（2023等效分*40%）+（2022等效分*35%）+（2021等效分*25%）
A7: 标杆院校是你志愿规划的“分水岭”：
A8: .标杆以上的院校=“冲”
A9: .标杆以下的院校=“稳和保”
A10: 第四步：险冲稳保垫兜（志愿填报的黄金配比）这一步是精髓所在！
A11: 我建议的黄金配比是险（10%）、冲（10%）、稳（30%）、保（20%）、垫（10%）、兜（10%）
A12: 【险】志愿（5个）
... A57: “院校+专业组”模式（其余省份）：调剂限于同一专业组内

Sheet 院校录取信息表
A1: 核对备份 不能修改及删除 | D1: 广东春季学考3+证书
C2: 志愿 初选标记 | F2: 2026年广东学考一对一志愿填报 | L2: 填报志愿3月初190公办
F3: 面向高中生 | G3: 分数 | I3: 370 | K3: 位次 | M3: 9367 | R3: 院校信息
D5: 类型 | E5: 院校 代码 | F5: 院校名称 | G5: 专业组代码 | H5: 2025计划数 | I5: 2024计划数 | J5: 2025投档数 | K5: 2024投档数 | L5: 2025最低分 | M5: 2024最低分 | N5: 2025最低位次 | O5: 2024最低位次 | P5: 平均最低分 | Q5: 平均最低位次 | R5: 省份 | S5: 城市 | T5: 院校类型 | U5: 院校层次 | V5: 主管 部门 | W5: 办学 性质 | X5: 城市 水平标签 | Y5: 院校标签 | Z5: 院校 水平 | AA5: 院校简介 | AB5: 历史沿革 | AC5: 学校官网 | AD5: 招生网址 | AE5: 招办电话 | AF5: 院校地址 | AG5: 校园VR | AH5: 院校排名 | AI5: 院校百科 | AJ5: 招生章程
A6: 1 | B6: =C6 -> 1 | C6: 1 | D6: 依据学考 | E6: 11113 | F6: 深圳职业技术大学 | G6: 601 | H6: 449 | I6: 545 | J6: 449 | K6: 545 | L6: 403 | M6: 409 | N6: 2426 | O6: 2276 | P6: =IFERROR(AVERAGE(L6:M6),"/") -> 406 | Q6: =IFERROR(AVERAGE(N6:O6),"/") -> 2351 | R6: 广东省 | S6: 深圳市 | T6: 广东省 | U6: 职业本科 | V6: 广东省 | W6: 公办 | X6: 一线城市 | Y6: 省属/双高计划/高水平学校建设单位/国家级示范 | Z6: 第一类高水平学校A档示范高职 | AA6: 深圳职业技术学院1993年创建，是国内最早独立举办高等职业技术教育的院校之一。建校以来，深职院人艰苦创业，开拓进取，不断创新教育教学理念、办学体制机制和人才培养模式，创造了中国高职教育的多个第一。学校依托珠三角产业发展，秉承深圳特区改革创新精神，坚持把立德树人作为学校教育的根本任务，立足于职业教育产教融合的办学特色，各项事业取得骄人成绩，被誉为中国高职教育的“一面旗帜”。为紧密契合“中国制造2025”等国家重大战略和深圳创新驱动发展战略，学校在2016年底召开的第三次党代会工作报告中提出“三个服务、五个定位、一个率先”的战略发展目标，始终坚持为党和国家服务、为深圳经济社会发展服务、为学生健康成长成才服务，努力成为职业教育创新发展的先行者、复合式创新型高素质技术技能人才的摇篮、企业家的摇篮、深圳中小微企业技术研发中心、深圳市民终身教育学校与中国职业教育师资培训重要基地，率先建成中国特色、世界一流职业院校，为世界职业教育发展贡献“深圳模式”。////学校现有留仙洞、西丽湖、官龙山、华侨城、凤凰山五个校区，校园总面积212万平方米，学校产权校舍建筑面积57.34万平方米，其中教室10.75万平方米，图书馆5万平方米，体育馆3.34万平方米，实训实习场所10.14万平方米。现有固定资产总值23.66亿元，其中教学仪器设备总值9.58亿元,教学用计算机14525台。图书馆藏有纸质图书261.2万册，电子图书130万册，电子期刊60.54万册，中外文数据库46个，音视频16.07万小时。////全校现有教职员工2380人，其中专任教师1243人，正高217人，副高657人，博士408人，享受国务院特殊津贴专家2名，珠江学者5人、海外高层次人才25人、国家“万人计划”教学名师1人、国家级教学名师3人、省级教学名师8人、国家特支计划教师1人、广东特支计划教学名师4人。学校拥有教育部首批黄大年式教师团队1个；引进美国霍夫曼诺奖团队等一批重量级团队，成立霍夫曼先进材料研究院、智能科学与工程研究院、智能制造研究院、新时代中国职业教育研究院、社会与经济发展研究院等高端平台，为珠三角产业发展提供有力支撑。////学校设有电子与通信工程学院等17个二级学院和体育部、工业中心、国际教育部等教学单位，招生专业80个。全校普通全日制在校生22750人，其中港澳台留学生79人，四年制高职生284人，应用型本科生292人，外国留学生127人。自办专科教育在校生3536人。国家级教学成果奖14项，国家职业教育专业教学资源库3项，国家重点支持建设示范专业12个，中央财政支持实训基地9个，国家级精品教材12部，国家精品课程53门，国家级精品资源共享课43门。////学校一直把人才培养作为中心工作，以培养适应智能时代需要的复合式创新型高素质技术技能人才为目标，更新教育教学理念，探索实施以学生学习成效为导向的OBE（Outcome/Based/Education）人才培养模式改革，深入推进产教融合、职普融合、理实融合、技术与文化融合、教育与生活融合、现代信息技术与教学融合等“六个融合”，提升学生的就业能力、职业生涯拓展能力和幸福生活创造能力。瞄准未来社会和经济发展，紧贴深圳四大支柱产业和新兴产业布局专业，打造品牌专业，与华为、ARM、阿里巴巴、平安、比亚迪、裕同、天健等一流企业紧密合作，共建华为信息与网络技术学院、ARM智能硬件学院、阿里巴巴数字贸易学院、平安金融科技学院、比亚迪应用技术学院、裕同数字图文学院、天健建工学院等7所特色产业学院，校企共同制定专业标准、共同开发课程、共建师资团队、共同培养技术技能人才，在服务一流企业中成就自身一流。开设专业文化课程，大力培育工匠精神，厚植工匠文化，全面推进职业院校文化育人。学校已累计培养11万余名全日制专科毕业生，毕业生初次就业率始终保持在96%以上，多项人才培养质量指标位居全国高职院校前列，深受用人单位欢迎。其中，238人次获CCIE证书，13人获RHCA证书，57人获OCM证书，163人获HCIE证书，13人获RHCE证书。////学校探索实施创新创业教育改革，以“五维一体”的创新创业教育理念（重心在“教育”、路径在“分层”、目标在“万众”、核心在“创新”、关键在“实践”）为引领，打造深圳中小微企业技术研发中心、全球技术技能人才创新创业教育中心，以及创新型人才和企业家培养的成长摇篮。通过系统设计、科学构建，协同推进从启蒙教育、预科教育、专门教育到指导创办企业的进阶式创业人才培养体系，搭建“四会两赛三联盟”双创交流平台和“创新型社团—创客中心—学生创意创业园”双创实践平台，逐步完善跨界融合、产品试制、创业孵化、创业投资的双创服务体系，取得良好的社会效益。近年来获评首批全国创新创业典型经验高校、全国深化创新创业教育改革示范高校、广东省大众创业万众创新示范基地、深圳首批十大创新创业基地等。近四届毕业生毕业一年内自主创业比例达到5%，毕业三年后创业比例12.7%。////学校坚持以“产学研用”一体化的科研导向，重视技术转移和科技成果转化。近年来，学校不断深化科研体制机制改革，大力加强与政府职能部门以及行业企业合作，组建成立了应用技术研发院、文化创意产品研发院、经济与社会发展研究院等三大综合性研发平台，建成43个市区级以上科研平台,抢抓产业发展新机遇，服务地方经济社会和中小企业发展。全校累计承担各级各类科研课题5196项，其中国家级项目84项,年度新增国家自然科学基金项目10项。科研经费到账总经费达到8.06亿元，其中技术转移（横向科研）项目到账经费2.98亿元；出版各类学术专著226部、编著、译著和作品集共199部，61项科研成果获部、省、市级奖励；获国家专利授权1726项，软件著作权登记1136件，发明专利345项。主导或参与制定国际、国家、行业标准74项。////学校重视社会服务，发挥品牌优势，致力于推动现代职业教育培训体系和学习型社会建设。做好高水平师资培训，打造世界级的职业教育培训中心；做好职业培训、职业技能鉴定及职业资格认证工作，服务好地方经济发展需要；联合社区街道组建社区学院、特色学院，开展针对社区居民的健康、养老、旅游等培训项目，服务好地方社会发展需要；以办学理念和教学模式输出为主要内容，构建“理念—教学—师资—管理”四位一体的精准帮扶体系，服务好对口支援地区和院校的发展。全年重点对口帮扶11所职业院校，累计对口支援西藏、新疆、贵州等地11个省、自治区的200余所职业院校。全年举办33个全国高职高专师资培训班，累计为全国680余所职业院校培训骨干教师1.2万人次，连续5年名列全国第一。年均开展各类培训、职业技能鉴定与资格认证12万人次。组建西丽社区学院、大鹏旅游学院等社区学院，与社区共同培养技能人才，打造开放办学、产教融合的“职教特区”；选派核心团队建设管理吉安职业技术学院，开创了特区与老区携手共同发展职业教育的典范。////学校紧扣国家发展战略，加快国际化办学步伐，充分利用区域与自身优势，深化国际教育交流与合作。建校以来，已累计与32个国家和地区的162所高校和教育机构建立了友好合作关系，包括英国、德国、法国、美国等发达国家以及新西兰、马来西亚、保加利亚、土耳其、波兰、匈牙利、缅甸、老挝等14个“一带一路”沿线国家。双方在学生交换、课程合作、科研合作、短期研修等领域开展了全方位、多层次、形式多样的教师和学生国际交流活动，取得了丰硕的成果。近年来，我校年均接待境外来访师生及外宾108批次，658人次；我校赴境外参加国际交流的师生52批次，276人次。开办了国际商务（中澳）、金融管理（中澳）、物流管理（中美）和软件技术（中美）4个中外合作办学专业；与香港专业教育学院黄克竞分校合办电气服务工程高级文凭合作课程，毕业生获得深港两地毕业资格，并成为首批获得招收海外留学生资质的高职院校和首个获批面向港澳台自主招生的高职院校。学校还联合中兴、招商港口等一批世界一流企业“走出去”，服务国家“一带一路”倡议。在马来西亚马六甲应用技术大学设立职业教育与培训中心，推动马来西亚全国各类职业院校全面对接深职院标准。依托在保加利亚成立的职业教育与培训中心，输出学校专业标准。应邀为柬埔寨、蒙古等国家职业教育代表团举行专题培训班，输出职业教育经验。加强与职业教育国际组织的合作，成为联合国教科文组织国际职教全球联系中心之一，获批成立联合国教科文组织职业教育计划亚非研究与培训中心。在提高学校国际知名度与影响力的同时，为推动中国职业教育与语言文化走出去做出了积极贡献。////学校办学成绩显著。2001年首家通过国家示范性高职院校实践教学基地优秀评估，2009年通过国家示范性高等职业院校建设项目验收，成为我国高等职业教育领域首批国家级示范校。近年来，学校先后荣获“全国文明单位”、“全国职业教育先进单位”、“全国一流高职院校建设单位”、“首批全国创新创业典型经验高校”、“全国高校毕业生就业工作先进集体”、“中国十大最具就业力高职院校”、“全国毕业生就业工作典型经验高校”、“全国职业院校就业竞争力示范校”、“中国十大创新型高职院校”、“黄炎培优秀学校奖”、“全国高校实践育人创新创业基地”“广东省文明单位”、“广东省职业技术教育工作先进集体”、“广东省首批大学生创新创业教育示范学校”、“广东省一流高职院校建设单位”“深圳市创新创业基地”等荣誉称号。 | AB6: 深圳职业技术大学于1993年创建，前身为深圳职业技术学院，是中国国内最早独立举办高等职业技术教育的院校之一。2000年、2004年原深圳市职业技术学校、深圳市卫生学校分别并入深圳职业技术学院。2006年深圳职业技术学院被确定为“国家示范性高等职业院校建设计划”首批立项建设院校，2009年学校顺利通过验收成为首批国家示范性高等职业院校。2023年6月，教育部发文同意以深圳职业技术学院为基础整合资源设立深圳职业技术大学，同时撤销深圳职业技术学院的建制。 | AC6: http://www.szpt.edu.cn/ | AD6: https://zhaosheng.szpt.edu.cn/ | AE6: 0755/26731715、26731216 | AF6: 深圳市南山区西丽街道留仙大道7098号 | AG6: https://www.720yun.com/t/d8vksm7e0d9 | AH6: 158 | AI6: https://baike.baidu.com/item/%E6%B7%B1%E5%9C%B3%E8%81%8C%E4%B8%9A%E6%8A%80%E6%9C%AF%E5%A4%A7%E5%AD%A6 | AJ6: https://gaokao.chsi.com.cn/zsgs/zhangcheng/listZszc//schId/734.dhtml | AK6: /
A7: 2 | B7: =C7 -> 2 | C7: 2 | D7: 依据学考 | E7: 11113 | F7: 深圳职业技术大学 | G7: 606 | H7: 165 | I7: 221 | J7: 165 | K7: 221 | L7: 396 | M7: 405 | N7: 5357 | O7: 4329 | P7: =IFERROR(AVERAGE(L7:M7),"/") -> 400.5 | Q7: =IFERROR(AVERAGE(N7:O7),"/") -> 4843 | R7: 广东省 | S7: 深圳市 | T7: 广东省 | U7: 职业本科 | V7: 广东省 | W7: 公办 | X7: 一线城市 | Y7: 省属/双高计划/高水平学校建设单位/国家级示范 | Z7: 第一类高水平学校A档示范高职 | AA7: 深圳职业技术学院1993年创建，是国内最早独立举办高等职业技术教育的院校之一。建校以来，深职院人艰苦创业，开拓进取，不断创新教育教学理念、办学体制机制和人才培养模式，创造了中国高职教育的多个第一。学校依托珠三角产业发展，秉承深圳特区改革创新精神，坚持把立德树人作为学校教育的根本任务，立足于职业教育产教融合的办学特色，各项事业取得骄人成绩，被誉为中国高职教育的“一面旗帜”。为紧密契合“中国制造2025”等国家重大战略和深圳创新驱动发展战略，学校在2016年底召开的第三次党代会工作报告中提出“三个服务、五个定位、一个率先”的战略发展目标，始终坚持为党和国家服务、为深圳经济社会发展服务、为学生健康成长成才服务，努力成为职业教育创新发展的先行者、复合式创新型高素质技术技能人才的摇篮、企业家的摇篮、深圳中小微企业技术研发中心、深圳市民终身教育学校与中国职业教育师资培训重要基地，率先建成中国特色、世界一流职业院校，为世界职业教育发展贡献“深圳模式”。////学校现有留仙洞、西丽湖、官龙山、华侨城、凤凰山五个校区，校园总面积212万平方米，学校产权校舍建筑面积57.34万平方米，其中教室10.75万平方米，图书馆5万平方米，体育馆3.34万平方米，实训实习场所10.14万平方米。现有固定资产总值23.66亿元，其中教学仪器设备总值9.58亿元,教学用计算机14525台。图书馆藏有纸质图书261.2万册，电子图书130万册，电子期刊60.54万册，中外文数据库46个，音视频16.07万小时。////全校现有教职员工2380人，其中专任教师1243人，正高217人，副高657人，博士408人，享受国务院特殊津贴专家2名，珠江学者5人、海外高层次人才25人、国家“万人计划”教学名师1人、国家级教学名师3人、省级教学名师8人、国家特支计划教师1人、广东特支计划教学名师4人。学校拥有教育部首批黄大年式教师团队1个；引进美国霍夫曼诺奖团队等一批重量级团队，成立霍夫曼先进材料研究院、智能科学与工程研究院、智能制造研究院、新时代中国职业教育研究院、社会与经济发展研究院等高端平台，为珠三角产业发展提供有力支撑。////学校设有电子与通信工程学院等17个二级学院和体育部、工业中心、国际教育部等教学单位，招生专业80个。全校普通全日制在校生22750人，其中港澳台留学生79人，四年制高职生284人，应用型本科生292人，外国留学生127人。自办专科教育在校生3536人。国家级教学成果奖14项，国家职业教育专业教学资源库3项，国家重点支持建设示范专业12个，中央财政支持实训基地9个，国家级精品教材12部，国家精品课程53门，国家级精品资源共享课43门。////学校一直把人才培养作为中心工作，以培养适应智能时代需要的复合式创新型高素质技术技能人才为目标，更新教育教学理念，探索实施以学生学习成效为导向的OBE（Outcome/Based/Education）人才培养模式改革，深入推进产教融合、职普融合、理实融合、技术与文化融合、教育与生活融合、现代信息技术与教学融合等“六个融合”，提升学生的就业能力、职业生涯拓展能力和幸福生活创造能力。瞄准未来社会和经济发展，紧贴深圳四大支柱产业和新兴产业布局专业，打造品牌专业，与华为、ARM、阿里巴巴、平安、比亚迪、裕同、天健等一流企业紧密合作，共建华为信息与网络技术学院、ARM智能硬件学院、阿里巴巴数字贸易学院、平安金融科技学院、比亚迪应用技术学院、裕同数字图文学院、天健建工学院等7所特色产业学院，校企共同制定专业标准、共同开发课程、共建师资团队、共同培养技术技能人才，在服务一流企业中成就自身一流。开设专业文化课程，大力培育工匠精神，厚植工匠文化，全面推进职业院校文化育人。学校已累计培养11万余名全日制专科毕业生，毕业生初次就业率始终保持在96%以上，多项人才培养质量指标位居全国高职院校前列，深受用人单位欢迎。其中，238人次获CCIE证书，13人获RHCA证书，57人获OCM证书，163人获HCIE证书，13人获RHCE证书。////学校探索实施创新创业教育改革，以“五维一体”的创新创业教育理念（重心在“教育”、路径在“分层”、目标在“万众”、核心在“创新”、关键在“实践”）为引领，打造深圳中小微企业技术研发中心、全球技术技能人才创新创业教育中心，以及创新型人才和企业家培养的成长摇篮。通过系统设计、科学构建，协同推进从启蒙教育、预科教育、专门教育到指导创办企业的进阶式创业人才培养体系，搭建“四会两赛三联盟”双创交流平台和“创新型社团—创客中心—学生创意创业园”双创实践平台，逐步完善跨界融合、产品试制、创业孵化、创业投资的双创服务体系，取得良好的社会效益。近年来获评首批全国创新创业典型经验高校、全国深化创新创业教育改革示范高校、广东省大众创业万众创新示范基地、深圳首批十大创新创业基地等。近四届毕业生毕业一年内自主创业比例达到5%，毕业三年后创业比例12.7%。////学校坚持以“产学研用”一体化的科研导向，重视技术转移和科技成果转化。近年来，学校不断深化科研体制机制改革，大力加强与政府职能部门以及行业企业合作，组建成立了应用技术研发院、文化创意产品研发院、经济与社会发展研究院等三大综合性研发平台，建成43个市区级以上科研平台,抢抓产业发展新机遇，服务地方经济社会和中小企业发展。全校累计承担各级各类科研课题5196项，其中国家级项目84项,年度新增国家自然科学基金项目10项。科研经费到账总经费达到8.06亿元，其中技术转移（横向科研）项目到账经费2.98亿元；出版各类学术专著226部、编著、译著和作品集共199部，61项科研成果获部、省、市级奖励；获国家专利授权1726项，软件著作权登记1136件，发明专利345项。主导或参与制定国际、国家、行业标准74项。////学校重视社会服务，发挥品牌优势，致力于推动现代职业教育培训体系和学习型社会建设。做好高水平师资培训，打造世界级的职业教育培训中心；做好职业培训、职业技能鉴定及职业资格认证工作，服务好地方经济发展需要；联合社区街道组建社区学院、特色学院，开展针对社区居民的健康、养老、旅游等培训项目，服务好地方社会发展需要；以办学理念和教学模式输出为主要内容，构建“理念—教学—师资—管理”四位一体的精准帮扶体系，服务好对口支援地区和院校的发展。全年重点对口帮扶11所职业院校，累计对口支援西藏、新疆、贵州等地11个省、自治区的200余所职业院校。全年举办33个全国高职高专师资培训班，累计为全国680余所职业院校培训骨干教师1.2万人次，连续5年名列全国第一。年均开展各类培训、职业技能鉴定与资格认证12万人次。组建西丽社区学院、大鹏旅游学院等社区学院，与社区共同培养技能人才，打造开放办学、产教融合的“职教特区”；选派核心团队建设管理吉安职业技术学院，开创了特区与老区携手共同发展职业教育的典范。////学校紧扣国家发展战略，加快国际化办学步伐，充分利用区域与自身优势，深化国际教育交流与合作。建校以来，已累计与32个国家和地区的162所高校和教育机构建立了友好合作关系，包括英国、德国、法国、美国等发达国家以及新西兰、马来西亚、保加利亚、土耳其、波兰、匈牙利、缅甸、老挝等14个“一带一路”沿线国家。双方在学生交换、课程合作、科研合作、短期研修等领域开展了全方位、多层次、形式多样的教师和学生国际交流活动，取得了丰硕的成果。近年来，我校年均接待境外来访师生及外宾108批次，658人次；我校赴境外参加国际交流的师生52批次，276人次。开办了国际商务（中澳）、金融管理（中澳）、物流管理（中美）和软件技术（中美）4个中外合作办学专业；与香港专业教育学院黄克竞分校合办电气服务工程高级文凭合作课程，毕业生获得深港两地毕业资格，并成为首批获得招收海外留学生资质的高职院校和首个获批面向港澳台自主招生的高职院校。学校还联合中兴、招商港口等一批世界一流企业“走出去”，服务国家“一带一路”倡议。在马来西亚马六甲应用技术大学设立职业教育与培训中心，推动马来西亚全国各类职业院校全面对接深职院标准。依托在保加利亚成立的职业教育与培训中心，输出学校专业标准。应邀为柬埔寨、蒙古等国家职业教育代表团举行专题培训班，输出职业教育经验。加强与职业教育国际组织的合作，成为联合国教科文组织国际职教全球联系中心之一，获批成立联合国教科文组织职业教育计划亚非研究与培训中心。在提高学校国际知名度与影响力的同时，为推动中国职业教育与语言文化走出去做出了积极贡献。////学校办学成绩显著。2001年首家通过国家示范性高职院校实践教学基地优秀评估，2009年通过国家示范性高等职业院校建设项目验收，成为我国高等职业教育领域首批国家级示范校。近年来，学校先后荣获“全国文明单位”、“全国职业教育先进单位”、“全国一流高职院校建设单位”、“首批全国创新创业典型经验高校”、“全国高校毕业生就业工作先进集体”、“中国十大最具就业力高职院校”、“全国毕业生就业工作典型经验高校”、“全国职业院校就业竞争力示范校”、“中国十大创新型高职院校”、“黄炎培优秀学校奖”、“全国高校实践育人创新创业基地”“广东省文明单位”、“广东省职业技术教育工作先进集体”、“广东省首批大学生创新创业教育示范学校”、“广东省一流高职院校建设单位”“深圳市创新创业基地”等荣誉称号。 | AB7: 深圳职业技术大学于1993年创建，前身为深圳职业技术学院，是中国国内最早独立举办高等职业技术教育的院校之一。2000年、2004年原深圳市职业技术学校、深圳市卫生学校分别并入深圳职业技术学院。2006年深圳职业技术学院被确定为“国家示范性高等职业院校建设计划”首批立项建设院校，2009年学校顺利通过验收成为首批国家示范性高等职业院校。2023年6月，教育部发文同意以深圳职业技术学院为基础整合资源设立深圳职业技术大学，同时撤销深圳职业技术学院的建制。 | AC7: http://www.szpt.edu.cn/ | AD7: https://zhaosheng.szpt.edu.cn/ | AE7: 0755/26731715、26731216 | AF7: 深圳市南山区西丽街道留仙大道7098号 | AG7: https://www.720yun.com/t/d8vksm7e0d9 | AH7: 158 | AI7: https://baike.baidu.com/item/%E6%B7%B1%E5%9C%B3%E8%81%8C%E4%B8%9A%E6%8A%80%E6%9C%AF%E5%A4%A7%E5%AD%A6 | AJ7: https://gaokao.chsi.com.cn/zsgs/zhangcheng/listZszc//schId/734.dhtml | AK7: /
A8: 3 | B8: =C8 -> 3 | C8: 3 | D8: 依据学考 | E8: 11113 | F8: 深圳职业技术大学 | G8: 602 | H8: 500 | I8: 607 | J8: 500 | K8: 608 | L8: 397 | M8: 403 | N8: 5171 | O8: 5580 | P8: =IFERROR(AVERAGE(L8:M8),"/") -> 400 | Q8: =IFERROR(AVERAGE(N8:O8),"/") -> 5375.5 | R8: 广东省 | S8: 深圳市 | T8: 广东省 | U8: 职业本科 | V8: 广东省 | W8: 公办 | X8: 一线城市 | Y8: 省属/双高计划/高水平学校建设单位/国家级示范 | Z8: 第一类高水平学校A档示范高职 | AA8: 深圳职业技术学院1993年创建，是国内最早独立举办高等职业技术教育的院校之一。建校以来，深职院人艰苦创业，开拓进取，不断创新教育教学理念、办学体制机制和人才培养模式，创造了中国高职教育的多个第一。学校依托珠三角产业发展，秉承深圳特区改革创新精神，坚持把立德树人作为学校教育的根本任务，立足于职业教育产教融合的办学特色，各项事业取得骄人成绩，被誉为中国高职教育的“一面旗帜”。为紧密契合“中国制造2025”等国家重大战略和深圳创新驱动发展战略，学校在2016年底召开的第三次党代会工作报告中提出“三个服务、五个定位、一个率先”的战略发展目标，始终坚持为党和国家服务、为深圳经济社会发展服务、为学生健康成长成才服务，努力成为职业教育创新发展的先行者、复合式创新型高素质技术技能人才的摇篮、企业家的摇篮、深圳中小微企业技术研发中心、深圳市民终身教育学校与中国职业教育师资培训重要基地，率先建成中国特色、世界一流职业院校，为世界职业教育发展贡献“深圳模式”。////学校现有留仙洞、西丽湖、官龙山、华侨城、凤凰山五个校区，校园总面积212万平方米，学校产权校舍建筑面积57.34万平方米，其中教室10.75万平方米，图书馆5万平方米，体育馆3.34万平方米，实训实习场所10.14万平方米。现有固定资产总值23.66亿元，其中教学仪器设备总值9.58亿元,教学用计算机14525台。图书馆藏有纸质图书261.2万册，电子图书130万册，电子期刊60.54万册，中外文数据库46个，音视频16.07万小时。////全校现有教职员工2380人，其中专任教师1243人，正高217人，副高657人，博士408人，享受国务院特殊津贴专家2名，珠江学者5人、海外高层次人才25人、国家“万人计划”教学名师1人、国家级教学名师3人、省级教学名师8人、国家特支计划教师1人、广东特支计划教学名师4人。学校拥有教育部首批黄大年式教师团队1个；引进美国霍夫曼诺奖团队等一批重量级团队，成立霍夫曼先进材料研究院、智能科学与工程研究院、智能制造研究院、新时代中国职业教育研究院、社会与经济发展研究院等高端平台，为珠三角产业发展提供有力支撑。////学校设有电子与通信工程学院等17个二级学院和体育部、工业中心、国际教育部等教学单位，招生专业80个。全校普通全日制在校生22750人，其中港澳台留学生79人，四年制高职生284人，应用型本科生292人，外国留学生127人。自办专科教育在校生3536人。国家级教学成果奖14项，国家职业教育专业教学资源库3项，国家重点支持建设示范专业12个，中央财政支持实训基地9个，国家级精品教材12部，国家精品课程53门，国家级精品资源共享课43门。////学校一直把人才培养作为中心工作，以培养适应智能时代需要的复合式创新型高素质技术技能人才为目标，更新教育教学理念，探索实施以学生学习成效为导向的OBE（Outcome/Based/Education）人才培养模式改革，深入推进产教融合、职普融合、理实融合、技术与文化融合、教育与生活融合、现代信息技术与教学融合等“六个融合”，提升学生的就业能力、职业生涯拓展能力和幸福生活创造能力。瞄准未来社会和经济发展，紧贴深圳四大支柱产业和新兴产业布局专业，打造品牌专业，与华为、ARM、阿里巴巴、平安、比亚迪、裕同、天健等一流企业紧密合作，共建华为信息与网络技术学院、ARM智能硬件学院、阿里巴巴数字贸易学院、平安金融科技学院、比亚迪应用技术学院、裕同数字图文学院、天健建工学院等7所特色产业学院，校企共同制定专业标准、共同开发课程、共建师资团队、共同培养技术技能人才，在服务一流企业中成就自身一流。开设专业文化课程，大力培育工匠精神，厚植工匠文化，全面推进职业院校文化育人。学校已累计培养11万余名全日制专科毕业生，毕业生初次就业率始终保持在96%以上，多项人才培养质量指标位居全国高职院校前列，深受用人单位欢迎。其中，238人次获CCIE证书，13人获RHCA证书，57人获OCM证书，163人获HCIE证书，13人获RHCE证书。////学校探索实施创新创业教育改革，以“五维一体”的创新创业教育理念（重心在“教育”、路径在“分层”、目标在“万众”、核心在“创新”、关键在“实践”）为引领，打造深圳中小微企业技术研发中心、全球技术技能人才创新创业教育中心，以及创新型人才和企业家培养的成长摇篮。通过系统设计、科学构建，协同推进从启蒙教育、预科教育、专门教育到指导创办企业的进阶式创业人才培养体系，搭建“四会两赛三联盟”双创交流平台和“创新型社团—创客中心—学生创意创业园”双创实践平台，逐步完善跨界融合、产品试制、创业孵化、创业投资的双创服务体系，取得良好的社会效益。近年来获评首批全国创新创业典型经验高校、全国深化创新创业教育改革示范高校、广东省大众创业万众创新示范基地、深圳首批十大创新创业基地等。近四届毕业生毕业一年内自主创业比例达到5%，毕业三年后创业比例12.7%。////学校坚持以“产学研用”一体化的科研导向，重视技术转移和科技成果转化。近年来，学校不断深化科研体制机制改革，大力加强与政府职能部门以及行业企业合作，组建成立了应用技术研发院、文化创意产品研发院、经济与社会发展研究院等三大综合性研发平台，建成43个市区级以上科研平台,抢抓产业发展新机遇，服务地方经济社会和中小企业发展。全校累计承担各级各类科研课题5196项，其中国家级项目84项,年度新增国家自然科学基金项目10项。科研经费到账总经费达到8.06亿元，其中技术转移（横向科研）项目到账经费2.98亿元；出版各类学术专著226部、编著、译著和作品集共199部，61项科研成果获部、省、市级奖励；获国家专利授权1726项，软件著作权登记1136件，发明专利345项。主导或参与制定国际、国家、行业标准74项。////学校重视社会服务，发挥品牌优势，致力于推动现代职业教育培训体系和学习型社会建设。做好高水平师资培训，打造世界级的职业教育培训中心；做好职业培训、职业技能鉴定及职业资格认证工作，服务好地方经济发展需要；联合社区街道组建社区学院、特色学院，开展针对社区居民的健康、养老、旅游等培训项目，服务好地方社会发展需要；以办学理念和教学模式输出为主要内容，构建“理念—教学—师资—管理”四位一体的精准帮扶体系，服务好对口支援地区和院校的发展。全年重点对口帮扶11所职业院校，累计对口支援西藏、新疆、贵州等地11个省、自治区的200余所职业院校。全年举办33个全国高职高专师资培训班，累计为全国680余所职业院校培训骨干教师1.2万人次，连续5年名列全国第一。年均开展各类培训、职业技能鉴定与资格认证12万人次。组建西丽社区学院、大鹏旅游学院等社区学院，与社区共同培养技能人才，打造开放办学、产教融合的“职教特区”；选派核心团队建设管理吉安职业技术学院，开创了特区与老区携手共同发展职业教育的典范。////学校紧扣国家发展战略，加快国际化办学步伐，充分利用区域与自身优势，深化国际教育交流与合作。建校以来，已累计与32个国家和地区的162所高校和教育机构建立了友好合作关系，包括英国、德国、法国、美国等发达国家以及新西兰、马来西亚、保加利亚、土耳其、波兰、匈牙利、缅甸、老挝等14个“一带一路”沿线国家。双方在学生交换、课程合作、科研合作、短期研修等领域开展了全方位、多层次、形式多样的教师和学生国际交流活动，取得了丰硕的成果。近年来，我校年均接待境外来访师生及外宾108批次，658人次；我校赴境外参加国际交流的师生52批次，276人次。开办了国际商务（中澳）、金融管理（中澳）、物流管理（中美）和软件技术（中美）4个中外合作办学专业；与香港专业教育学院黄克竞分校合办电气服务工程高级文凭合作课程，毕业生获得深港两地毕业资格，并成为首批获得招收海外留学生资质的高职院校和首个获批面向港澳台自主招生的高职院校。学校还联合中兴、招商港口等一批世界一流企业“走出去”，服务国家“一带一路”倡议。在马来西亚马六甲应用技术大学设立职业教育与培训中心，推动马来西亚全国各类职业院校全面对接深职院标准。依托在保加利亚成立的职业教育与培训中心，输出学校专业标准。应邀为柬埔寨、蒙古等国家职业教育代表团举行专题培训班，输出职业教育经验。加强与职业教育国际组织的合作，成为联合国教科文组织国际职教全球联系中心之一，获批成立联合国教科文组织职业教育计划亚非研究与培训中心。在提高学校国际知名度与影响力的同时，为推动中国职业教育与语言文化走出去做出了积极贡献。////学校办学成绩显著。2001年首家通过国家示范性高职院校实践教学基地优秀评估，2009年通过国家示范性高等职业院校建设项目验收，成为我国高等职业教育领域首批国家级示范校。近年来，学校先后荣获“全国文明单位”、“全国职业教育先进单位”、“全国一流高职院校建设单位”、“首批全国创新创业典型经验高校”、“全国高校毕业生就业工作先进集体”、“中国十大最具就业力高职院校”、“全国毕业生就业工作典型经验高校”、“全国职业院校就业竞争力示范校”、“中国十大创新型高职院校”、“黄炎培优秀学校奖”、“全国高校实践育人创新创业基地”“广东省文明单位”、“广东省职业技术教育工作先进集体”、“广东省首批大学生创新创业教育示范学校”、“广东省一流高职院校建设单位”“深圳市创新创业基地”等荣誉称号。 | AB8: 深圳职业技术大学于1993年创建，前身为深圳职业技术学院，是中国国内最早独立举办高等职业技术教育的院校之一。2000年、2004年原深圳市职业技术学校、深圳市卫生学校分别并入深圳职业技术学院。2006年深圳职业技术学院被确定为“国家示范性高等职业院校建设计划”首批立项建设院校，2009年学校顺利通过验收成为首批国家示范性高等职业院校。2023年6月，教育部发文同意以深圳职业技术学院为基础整合资源设立深圳职业技术大学，同时撤销深圳职业技术学院的建制。 | AC8: http://www.szpt.edu.cn/ | AD8: https://zhaosheng.szpt.edu.cn/ | AE8: 0755/26731715、26731216 | AF8: 深圳市南山区西丽街道留仙大道7098号 | AG8: https://www.720yun.com/t/d8vksm7e0d9 | AH8: 158 | AI8: https://baike.baidu.com/item/%E6%B7%B1%E5%9C%B3%E8%81%8C%E4%B8%9A%E6%8A%80%E6%9C%AF%E5%A4%A7%E5%AD%A6 | AJ8: https://gaokao.chsi.com.cn/zsgs/zhangcheng/listZszc//schId/734.dhtml | AK8: /
A9: 4 | B9: =C9 -> 4 | C9: 4 | D9: 依据学考 | E9: 11113 | F9: 深圳职业技术大学 | G9: 607 | H9: 229 | I9: 258 | J9: 229 | K9: 259 | L9: 394 | M9: 403 | N9: 6763 | O9: 6133 | P9: =IFERROR(AVERAGE(L9:M9),"/") -> 398.5 | Q9: =IFERROR(AVERAGE(N9:O9),"/") -> 6448 | R9: 广东省 | S9: 深圳市 | T9: 广东省 | U9: 职业本科 | V9: 广东省 | W9: 公办 | X9: 一线城市 | Y9: 省属/双高计划/高水平学校建设单位/国家级示范 | Z9: 第一类高水平学校A档示范高职 | AA9: 深圳职业技术学院1993年创建，是国内最早独立举办高等职业技术教育的院校之一。建校以来，深职院人艰苦创业，开拓进取，不断创新教育教学理念、办学体制机制和人才培养模式，创造了中国高职教育的多个第一。学校依托珠三角产业发展，秉承深圳特区改革创新精神，坚持把立德树人作为学校教育的根本任务，立足于职业教育产教融合的办学特色，各项事业取得骄人成绩，被誉为中国高职教育的“一面旗帜”。为紧密契合“中国制造2025”等国家重大战略和深圳创新驱动发展战略，学校在2016年底召开的第三次党代会工作报告中提出“三个服务、五个定位、一个率先”的战略发展目标，始终坚持为党和国家服务、为深圳经济社会发展服务、为学生健康成长成才服务，努力成为职业教育创新发展的先行者、复合式创新型高素质技术技能人才的摇篮、企业家的摇篮、深圳中小微企业技术研发中心、深圳市民终身教育学校与中国职业教育师资培训重要基地，率先建成中国特色、世界一流职业院校，为世界职业教育发展贡献“深圳模式”。////学校现有留仙洞、西丽湖、官龙山、华侨城、凤凰山五个校区，校园总面积212万平方米，学校产权校舍建筑面积57.34万平方米，其中教室10.75万平方米，图书馆5万平方米，体育馆3.34万平方米，实训实习场所10.14万平方米。现有固定资产总值23.66亿元，其中教学仪器设备总值9.58亿元,教学用计算机14525台。图书馆藏有纸质图书261.2万册，电子图书130万册，电子期刊60.54万册，中外文数据库46个，音视频16.07万小时。////全校现有教职员工2380人，其中专任教师1243人，正高217人，副高657人，博士408人，享受国务院特殊津贴专家2名，珠江学者5人、海外高层次人才25人、国家“万人计划”教学名师1人、国家级教学名师3人、省级教学名师8人、国家特支计划教师1人、广东特支计划教学名师4人。学校拥有教育部首批黄大年式教师团队1个；引进美国霍夫曼诺奖团队等一批重量级团队，成立霍夫曼先进材料研究院、智能科学与工程研究院、智能制造研究院、新时代中国职业教育研究院、社会与经济发展研究院等高端平台，为珠三角产业发展提供有力支撑。////学校设有电子与通信工程学院等17个二级学院和体育部、工业中心、国际教育部等教学单位，招生专业80个。全校普通全日制在校生22750人，其中港澳台留学生79人，四年制高职生284人，应用型本科生292人，外国留学生127人。自办专科教育在校生3536人。国家级教学成果奖14项，国家职业教育专业教学资源库3项，国家重点支持建设示范专业12个，中央财政支持实训基地9个，国家级精品教材12部，国家精品课程53门，国家级精品资源共享课43门。////学校一直把人才培养作为中心工作，以培养适应智能时代需要的复合式创新型高素质技术技能人才为目标，更新教育教学理念，探索实施以学生学习成效为导向的OBE（Outcome/Based/Education）人才培养模式改革，深入推进产教融合、职普融合、理实融合、技术与文化融合、教育与生活融合、现代信息技术与教学融合等“六个融合”，提升学生的就业能力、职业生涯拓展能力和幸福生活创造能力。瞄准未来社会和经济发展，紧贴深圳四大支柱产业和新兴产业布局专业，打造品牌专业，与华为、ARM、阿里巴巴、平安、比亚迪、裕同、天健等一流企业紧密合作，共建华为信息与网络技术学院、ARM智能硬件学院、阿里巴巴数字贸易学院、平安金融科技学院、比亚迪应用技术学院、裕同数字图文学院、天健建工学院等7所特色产业学院，校企共同制定专业标准、共同开发课程、共建师资团队、共同培养技术技能人才，在服务一流企业中成就自身一流。开设专业文化课程，大力培育工匠精神，厚植工匠文化，全面推进职业院校文化育人。学校已累计培养11万余名全日制专科毕业生，毕业生初次就业率始终保持在96%以上，多项人才培养质量指标位居全国高职院校前列，深受用人单位欢迎。其中，238人次获CCIE证书，13人获RHCA证书，57人获OCM证书，163人获HCIE证书，13人获RHCE证书。////学校探索实施创新创业教育改革，以“五维一体”的创新创业教育理念（重心在“教育”、路径在“分层”、目标在“万众”、核心在“创新”、关键在“实践”）为引领，打造深圳中小微企业技术研发中心、全球技术技能人才创新创业教育中心，以及创新型人才和企业家培养的成长摇篮。通过系统设计、科学构建，协同推进从启蒙教育、预科教育、专门教育到指导创办企业的进阶式创业人才培养体系，搭建“四会两赛三联盟”双创交流平台和“创新型社团—创客中心—学生创意创业园”双创实践平台，逐步完善跨界融合、产品试制、创业孵化、创业投资的双创服务体系，取得良好的社会效益。近年来获评首批全国创新创业典型经验高校、全国深化创新创业教育改革示范高校、广东省大众创业万众创新示范基地、深圳首批十大创新创业基地等。近四届毕业生毕业一年内自主创业比例达到5%，毕业三年后创业比例12.7%。////学校坚持以“产学研用”一体化的科研导向，重视技术转移和科技成果转化。近年来，学校不断深化科研体制机制改革，大力加强与政府职能部门以及行业企业合作，组建成立了应用技术研发院、文化创意产品研发院、经济与社会发展研究院等三大综合性研发平台，建成43个市区级以上科研平台,抢抓产业发展新机遇，服务地方经济社会和中小企业发展。全校累计承担各级各类科研课题5196项，其中国家级项目84项,年度新增国家自然科学基金项目10项。科研经费到账总经费达到8.06亿元，其中技术转移（横向科研）项目到账经费2.98亿元；出版各类学术专著226部、编著、译著和作品集共199部，61项科研成果获部、省、市级奖励；获国家专利授权1726项，软件著作权登记1136件，发明专利345项。主导或参与制定国际、国家、行业标准74项。////学校重视社会服务，发挥品牌优势，致力于推动现代职业教育培训体系和学习型社会建设。做好高水平师资培训，打造世界级的职业教育培训中心；做好职业培训、职业技能鉴定及职业资格认证工作，服务好地方经济发展需要；联合社区街道组建社区学院、特色学院，开展针对社区居民的健康、养老、旅游等培训项目，服务好地方社会发展需要；以办学理念和教学模式输出为主要内容，构建“理念—教学—师资—管理”四位一体的精准帮扶体系，服务好对口支援地区和院校的发展。全年重点对口帮扶11所职业院校，累计对口支援西藏、新疆、贵州等地11个省、自治区的200余所职业院校。全年举办33个全国高职高专师资培训班，累计为全国680余所职业院校培训骨干教师1.2万人次，连续5年名列全国第一。年均开展各类培训、职业技能鉴定与资格认证12万人次。组建西丽社区学院、大鹏旅游学院等社区学院，与社区共同培养技能人才，打造开放办学、产教融合的“职教特区”；选派核心团队建设管理吉安职业技术学院，开创了特区与老区携手共同发展职业教育的典范。////学校紧扣国家发展战略，加快国际化办学步伐，充分利用区域与自身优势，深化国际教育交流与合作。建校以来，已累计与32个国家和地区的162所高校和教育机构建立了友好合作关系，包括英国、德国、法国、美国等发达国家以及新西兰、马来西亚、保加利亚、土耳其、波兰、匈牙利、缅甸、老挝等14个“一带一路”沿线国家。双方在学生交换、课程合作、科研合作、短期研修等领域开展了全方位、多层次、形式多样的教师和学生国际交流活动，取得了丰硕的成果。近年来，我校年均接待境外来访师生及外宾108批次，658人次；我校赴境外参加国际交流的师生52批次，276人次。开办了国际商务（中澳）、金融管理（中澳）、物流管理（中美）和软件技术（中美）4个中外合作办学专业；与香港专业教育学院黄克竞分校合办电气服务工程高级文凭合作课程，毕业生获得深港两地毕业资格，并成为首批获得招收海外留学生资质的高职院校和首个获批面向港澳台自主招生的高职院校。学校还联合中兴、招商港口等一批世界一流企业“走出去”，服务国家“一带一路”倡议。在马来西亚马六甲应用技术大学设立职业教育与培训中心，推动马来西亚全国各类职业院校全面对接深职院标准。依托在保加利亚成立的职业教育与培训中心，输出学校专业标准。应邀为柬埔寨、蒙古等国家职业教育代表团举行专题培训班，输出职业教育经验。加强与职业教育国际组织的合作，成为联合国教科文组织国际职教全球联系中心之一，获批成立联合国教科文组织职业教育计划亚非研究与培训中心。在提高学校国际知名度与影响力的同时，为推动中国职业教育与语言文化走出去做出了积极贡献。////学校办学成绩显著。2001年首家通过国家示范性高职院校实践教学基地优秀评估，2009年通过国家示范性高等职业院校建设项目验收，成为我国高等职业教育领域首批国家级示范校。近年来，学校先后荣获“全国文明单位”、“全国职业教育先进单位”、“全国一流高职院校建设单位”、“首批全国创新创业典型经验高校”、“全国高校毕业生就业工作先进集体”、“中国十大最具就业力高职院校”、“全国毕业生就业工作典型经验高校”、“全国职业院校就业竞争力示范校”、“中国十大创新型高职院校”、“黄炎培优秀学校奖”、“全国高校实践育人创新创业基地”“广东省文明单位”、“广东省职业技术教育工作先进集体”、“广东省首批大学生创新创业教育示范学校”、“广东省一流高职院校建设单位”“深圳市创新创业基地”等荣誉称号。 | AB9: 深圳职业技术大学于1993年创建，前身为深圳职业技术学院，是中国国内最早独立举办高等职业技术教育的院校之一。2000年、2004年原深圳市职业技术学校、深圳市卫生学校分别并入深圳职业技术学院。2006年深圳职业技术学院被确定为“国家示范性高等职业院校建设计划”首批立项建设院校，2009年学校顺利通过验收成为首批国家示范性高等职业院校。2023年6月，教育部发文同意以深圳职业技术学院为基础整合资源设立深圳职业技术大学，同时撤销深圳职业技术学院的建制。 | AC9: http://www.szpt.edu.cn/ | AD9: https://zhaosheng.szpt.edu.cn/ | AE9: 0755/26731715、26731216 | AF9: 深圳市南山区西丽街道留仙大道7098号 | AG9: https://www.720yun.com/t/d8vksm7e0d9 | AH9: 158 | AI9: https://baike.baidu.com/item/%E6%B7%B1%E5%9C%B3%E8%81%8C%E4%B8%9A%E6%8A%80%E6%9C%AF%E5%A4%A7%E5%AD%A6 | AJ9: https://gaokao.chsi.com.cn/zsgs/zhangcheng/listZszc//schId/734.dhtml | AK9: /
A10: 5 | B10: =C10 -> 5 | C10: 5 | D10: 依据学考 | E10: 12957 | F10: 深圳信息职业技术大学 | G10: 602 | H10: 219 | I10: 172 | J10: 219 | K10: 174 | L10: 391 | M10: 402 | N10: 8461 | O10: 6626 | P10: =IFERROR(AVERAGE(L10:M10),"/") -> 396.5 | Q10: =IFERROR(AVERAGE(N10:O10),"/") -> 7543.5 | R10: 广东省 | S10: 深圳市 | T10: 广东省 | U10: 职业本科 | V10: 广东省 | W10: 公办 | X10: 一线城市 | Y10: 双高计划/高水平学校建设单位/国家级骨干/现代学徒制试点学院 | Z10: 第二类高水平学校B档骨干高职现代学徒 | AA10: 深圳信息职业技术学院创办于2002年4月，是经广东省人民政府批准、教育部备案，由深圳市人民政府举办的公办全日制高等院校。//学校现为国家示范（骨干）高职院校、国家示范性软件职业技术学院、教育部“中德职教汽车机电合作项目”试点院校，现拥有3个国家级高等职业教育专业教学资源库（含1个备选项目）。学校拥有现代化、生态型、信息化的校园，占地92.6万平方米（1389亩），建筑面积58.86万平方米。学校现有教学科研仪器设备总值为36786.36万元，图书馆藏书131.33万册。//学校对接深圳支柱产业，打造信息技术特色，共设软件学院、电子与通信学院、计算机学院、数字媒体学院、智能制造与装备学院、交通与环境学院、管理学院、财经学院、应用外语学院、中德学院、马克思主义学院、继续教育学院、创新创业学院、创新教育研究院、公共课教学部、体育部、信息技术研究所等14院2部1所；开设信息类为主的专业44个。现有国家骨干校重点建设专业4个，国家高等职业学校提升专业服务产业发展能力建设专业2个，全国职业院校示范专业点2个，国家高等职业教育教学资源库建设项目3个（含1个备选项目），广东省示范性专业4个，省级重点建设专业6个，省级品牌专业11个；国家级精品资源共享课7门、省级精品资源共享课（含精品在线开放课）38门、省级思想政治理论优质建设课程2门。//学校现有教职工796人，在590位专任教师中，副高及以上职称教师301人，其中，博士、博士后275人，“双师素质”教师九成。目前，学校拥有国家级教学团队1个，获国家级教学名师奖1人，获全国五一劳动奖章1人，国家万人计划教学名师1名，广东省教学名师奖3人，广东省“特支计划”教学名师3人，省级教学团队7个，南粤优秀教师7人，广东省“千百十人才培养工程”省级培养对象6人，广东省“珠江学者”特聘教授4人，深圳市“鹏城学者”特聘教授3人，深圳市政府特殊津贴1人，黄炎培职业教育杰出教师奖1人，深圳市高层次专业人才地方级领军人才9名，后备级领军人才21人，博士后创新实践基地在站博士后3人。//学校坚持科研引领、教研创新、突出应用、服务社会。已主持国家自然科学基金等国家级项目26项、省市级科研项目517项，教研课题国家级6项、省市级49项，深圳市首批教育科研专家工作室1个。获得国家级高等学校教学成果一等奖1项、二等奖2项，省级教学成果一等奖6项、二等奖4项，广东省科学技术二等奖2项、三等奖2项，国家教师科研基金“十一五”规划重点课题科研成果一等奖1项，深圳市科技进步奖2项，深圳市科技创新奖2项，深圳市科学技术奖自然科学奖1项，深圳市哲学社会科学优秀成果奖7项，中国人工智能学会进步奖二等奖；拥有发明专利62项，实用新型专利203项，外观设计专利8项。//学校坚持校企合作办学，积极推进产教融合协同育人，创新合作办学机制，探索校企合作模式，在校内构建了“三会两办”的办学机制，并打造了“学院+行业企业”的校企合作模式。学校用2万平米实训场地，引企入校，合作共建实践教学基地、科技创新平台等，基地目前建有2个省级创新平台、1个先进土木研究中心、1个智能制造实训中心、5个校级协同创新中心等创新载体。学校有国家级高等职业教育实训基地2个，省级高等职业教育实训基地11个，省级公共实训中心1个，省级大学生校外实践教学基地12个，深圳市高职教育校外公共实训基地33个。//学校建构高素质高技能人才培养机制，不断提升高就业率、高满意度办学效益。现有全日制在校生15468人，学校坚持产教融合、校企合作、因材施教、特色发展。近三年，学生参加专业技能竞赛共获国家级奖项137个，省级二等奖以上315个。毕业生“下得去、留得住、用得上、干得好”，毕业生总体就业率均在98%以上。毕业生被华为、腾讯、深圳地铁、中国联通等著名企业录用，产生了被《华尔街日报》报道为“中国最年轻90后千万富豪”丁仕源、拥有8家公司的速运邦邦CEO陈家良等创业典型。//学校积极引进国际先进教学资源，不断形成国际化办学特色。2012年，学校成为教育部“中德职教汽车机电合作项目”试点院校；2013年11月学校与西双版纳职业技术学院正式签署合作协议共建“深圳信息/西双版纳国际留学生基地”/并揭牌；2016年9月，由深圳市教育局和德国巴伐利亚州文教部推动，我校与德国巴伐利亚州帕绍技术学校、兰茨胡特应用技术大学合作创办中德学院；2018年5月，学校与芬兰于韦斯屈莱应用科技大学签订战略合作协议全面启动两校战略合作项目；此外，学校还与加拿大谢尔丹理工学院、韩国京畿大学、台湾地区朝阳科技大学、树德科技大学、龙华科技大学、台北城市科技大学、亚太创意技术学院等26所高校开展了师生交流、合作科研等项目。//学校跨越发展，已跻身全国高职院校“第一方阵”。2004年，学校成为“国家示范性软件职业技术学院”建设院校；2007年，以优异成绩通过教育部人才培养工作水平评估；2010年，成为国家骨干高职院校建设单位；2011年，获国家高等职业教育网络技术专业共享型教学资源库建设立项；2012年，入选教育部“中德职教汽车机电合作项目”试点院校；2014年获国家高等职业教育数字媒体专业群教学资源库立项；2015年，深圳市人力资源与社会保障局同意批准我校设立博士后创新实践基地；2016年，学校国家骨干校建设项目以“优秀”等级通过国家验收、获广东省“一流校”建设立项、学校“2188创客空间”被国家科学技术部认定为国家级众创空间，2016年学校又成功召开了第二次党代会，进一步确立了“全力打造有特色国际化一流职业院校”的奋斗目标。//青春深信成新锐，勇向潮头唱大风。学校将继续开拓奋进，勇于不断创新，努力把学校打造成有特色国际化一流职业院校。 | AB10: 学校原名为深圳信息职业技术学院，于2002年4月由深圳教育学院、深圳市工业学校、深圳市财经学校三所学校合并组建；2011年9月，学校从深圳市罗湖区迁至深圳市龙岗区。2012年，学校入选教育部“中德职教汽车机电合作项目”试点院校。2021年，学校获批设立广东省博士工作站。2025年6月，教育部发函广东省，同意以深圳信息职业技术学院为基础设立深圳信息职业技术大学，同时撤销深圳信息职业技术学院的建制。2026年1月，深圳信息职业技术大学正式成立。 | AC10: http://www.sziit.com.cn/ | AD10: http://zhaob.sziit.edu.cn/index.htm | AE10: 075589226360、075589226361 | AF10: 深圳市龙岗区龙翔大道2188号 | AG10: https://www.720yun.com/t/d4528mpguus | AH10: 184 | AI10: https://baike.baidu.com/item/%E6%B7%B1%E5%9C%B3%E4%BF%A1%E6%81%AF%E8%81%8C%E4%B8%9A%E6%8A%80%E6%9C%AF%E5%AD%A6%E9%99%A2 | AJ10: https://gaokao.chsi.com.cn/zsgs/zhangcheng/listZszc//schId/1429.dhtml | AK10: /
A11: 6 | B11: =C11 -> 6 | C11: 6 | D11: 依据学考 | E11: 12957 | F11: 深圳信息职业技术大学 | G11: 601 | H11: 276 | I11: 28 | J11: 276 | K11: 28 | L11: 395 | M11: 400 | N11: 6289 | O11: 9192 | P11: =IFERROR(AVERAGE(L11:M11),"/") -> 397.5 | Q11: =IFERROR(AVERAGE(N11:O11),"/") -> 7740.5 | R11: 广东省 | S11: 深圳市 | T11: 广东省 | U11: 职业本科 | V11: 广东省 | W11: 公办 | X11: 一线城市 | Y11: 双高计划/高水平学校建设单位/国家级骨干/现代学徒制试点学院 | Z11: 第二类高水平学校B档骨干高职现代学徒 | AA11: 深圳信息职业技术学院创办于2002年4月，是经广东省人民政府批准、教育部备案，由深圳市人民政府举办的公办全日制高等院校。//学校现为国家示范（骨干）高职院校、国家示范性软件职业技术学院、教育部“中德职教汽车机电合作项目”试点院校，现拥有3个国家级高等职业教育专业教学资源库（含1个备选项目）。学校拥有现代化、生态型、信息化的校园，占地92.6万平方米（1389亩），建筑面积58.86万平方米。学校现有教学科研仪器设备总值为36786.36万元，图书馆藏书131.33万册。//学校对接深圳支柱产业，打造信息技术特色，共设软件学院、电子与通信学院、计算机学院、数字媒体学院、智能制造与装备学院、交通与环境学院、管理学院、财经学院、应用外语学院、中德学院、马克思主义学院、继续教育学院、创新创业学院、创新教育研究院、公共课教学部、体育部、信息技术研究所等14院2部1所；开设信息类为主的专业44个。现有国家骨干校重点建设专业4个，国家高等职业学校提升专业服务产业发展能力建设专业2个，全国职业院校示范专业点2个，国家高等职业教育教学资源库建设项目3个（含1个备选项目），广东省示范性专业4个，省级重点建设专业6个，省级品牌专业11个；国家级精品资源共享课7门、省级精品资源共享课（含精品在线开放课）38门、省级思想政治理论优质建设课程2门。//学校现有教职工796人，在590位专任教师中，副高及以上职称教师301人，其中，博士、博士后275人，“双师素质”教师九成。目前，学校拥有国家级教学团队1个，获国家级教学名师奖1人，获全国五一劳动奖章1人，国家万人计划教学名师1名，广东省教学名师奖3人，广东省“特支计划”教学名师3人，省级教学团队7个，南粤优秀教师7人，广东省“千百十人才培养工程”省级培养对象6人，广东省“珠江学者”特聘教授4人，深圳市“鹏城学者”特聘教授3人，深圳市政府特殊津贴1人，黄炎培职业教育杰出教师奖1人，深圳市高层次专业人才地方级领军人才9名，后备级领军人才21人，博士后创新实践基地在站博士后3人。//学校坚持科研引领、教研创新、突出应用、服务社会。已主持国家自然科学基金等国家级项目26项、省市级科研项目517项，教研课题国家级6项、省市级49项，深圳市首批教育科研专家工作室1个。获得国家级高等学校教学成果一等奖1项、二等奖2项，省级教学成果一等奖6项、二等奖4项，广东省科学技术二等奖2项、三等奖2项，国家教师科研基金“十一五”规划重点课题科研成果一等奖1项，深圳市科技进步奖2项，深圳市科技创新奖2项，深圳市科学技术奖自然科学奖1项，深圳市哲学社会科学优秀成果奖7项，中国人工智能学会进步奖二等奖；拥有发明专利62项，实用新型专利203项，外观设计专利8项。//学校坚持校企合作办学，积极推进产教融合协同育人，创新合作办学机制，探索校企合作模式，在校内构建了“三会两办”的办学机制，并打造了“学院+行业企业”的校企合作模式。学校用2万平米实训场地，引企入校，合作共建实践教学基地、科技创新平台等，基地目前建有2个省级创新平台、1个先进土木研究中心、1个智能制造实训中心、5个校级协同创新中心等创新载体。学校有国家级高等职业教育实训基地2个，省级高等职业教育实训基地11个，省级公共实训中心1个，省级大学生校外实践教学基地12个，深圳市高职教育校外公共实训基地33个。//学校建构高素质高技能人才培养机制，不断提升高就业率、高满意度办学效益。现有全日制在校生15468人，学校坚持产教融合、校企合作、因材施教、特色发展。近三年，学生参加专业技能竞赛共获国家级奖项137个，省级二等奖以上315个。毕业生“下得去、留得住、用得上、干得好”，毕业生总体就业率均在98%以上。毕业生被华为、腾讯、深圳地铁、中国联通等著名企业录用，产生了被《华尔街日报》报道为“中国最年轻90后千万富豪”丁仕源、拥有8家公司的速运邦邦CEO陈家良等创业典型。//学校积极引进国际先进教学资源，不断形成国际化办学特色。2012年，学校成为教育部“中德职教汽车机电合作项目”试点院校；2013年11月学校与西双版纳职业技术学院正式签署合作协议共建“深圳信息/西双版纳国际留学生基地”/并揭牌；2016年9月，由深圳市教育局和德国巴伐利亚州文教部推动，我校与德国巴伐利亚州帕绍技术学校、兰茨胡特应用技术大学合作创办中德学院；2018年5月，学校与芬兰于韦斯屈莱应用科技大学签订战略合作协议全面启动两校战略合作项目；此外，学校还与加拿大谢尔丹理工学院、韩国京畿大学、台湾地区朝阳科技大学、树德科技大学、龙华科技大学、台北城市科技大学、亚太创意技术学院等26所高校开展了师生交流、合作科研等项目。//学校跨越发展，已跻身全国高职院校“第一方阵”。2004年，学校成为“国家示范性软件职业技术学院”建设院校；2007年，以优异成绩通过教育部人才培养工作水平评估；2010年，成为国家骨干高职院校建设单位；2011年，获国家高等职业教育网络技术专业共享型教学资源库建设立项；2012年，入选教育部“中德职教汽车机电合作项目”试点院校；2014年获国家高等职业教育数字媒体专业群教学资源库立项；2015年，深圳市人力资源与社会保障局同意批准我校设立博士后创新实践基地；2016年，学校国家骨干校建设项目以“优秀”等级通过国家验收、获广东省“一流校”建设立项、学校“2188创客空间”被国家科学技术部认定为国家级众创空间，2016年学校又成功召开了第二次党代会，进一步确立了“全力打造有特色国际化一流职业院校”的奋斗目标。//青春深信成新锐，勇向潮头唱大风。学校将继续开拓奋进，勇于不断创新，努力把学校打造成有特色国际化一流职业院校。 | AB11: 学校原名为深圳信息职业技术学院，于2002年4月由深圳教育学院、深圳市工业学校、深圳市财经学校三所学校合并组建；2011年9月，学校从深圳市罗湖区迁至深圳市龙岗区。2012年，学校入选教育部“中德职教汽车机电合作项目”试点院校。2021年，学校获批设立广东省博士工作站。2025年6月，教育部发函广东省，同意以深圳信息职业技术学院为基础设立深圳信息职业技术大学，同时撤销深圳信息职业技术学院的建制。2026年1月，深圳信息职业技术大学正式成立。 | AC11: http://www.sziit.com.cn/ | AD11: http://zhaob.sziit.edu.cn/index.htm | AE11: 075589226360、075589226361 | AF11: 深圳市龙岗区龙翔大道2188号 | AG11: https://www.720yun.com/t/d4528mpguus | AH11: 184 | AI11: https://baike.baidu.com/item/%E6%B7%B1%E5%9C%B3%E4%BF%A1%E6%81%AF%E8%81%8C%E4%B8%9A%E6%8A%80%E6%9C%AF%E5%AD%A6%E9%99%A2 | AJ11: https://gaokao.chsi.com.cn/zsgs/zhangcheng/listZszc//schId/1429.dhtml | AK11: /
A12: 7 | B12: =C12 -> 0 | D12: 依据学考 | E12: 11113 | F12: 深圳职业技术大学 | G12: 603 | H12: 703 | I12: 851 | J12: 703 | K12: 851 | L12: 390 | M12: 401 | N12: 9367 | O12: 7328 | P12: =IFERROR(AVERAGE(L12:M12),"/") -> 395.5 | Q12: =IFERROR(AVERAGE(N12:O12),"/") -> 8347.5 | R12: 广东省 | S12: 深圳市 | T12: 广东省 | U12: 职业本科 | V12: 广东省 | W12: 公办 | X12: 一线城市 | Y12: 省属/双高计划/高水平学校建设单位/国家级示范 | Z12: 第一类高水平学校A档示范高职 | AA12: 深圳职业技术学院1993年创建，是国内最早独立举办高等职业技术教育的院校之一。建校以来，深职院人艰苦创业，开拓进取，不断创新教育教学理念、办学体制机制和人才培养模式，创造了中国高职教育的多个第一。学校依托珠三角产业发展，秉承深圳特区改革创新精神，坚持把立德树人作为学校教育的根本任务，立足于职业教育产教融合的办学特色，各项事业取得骄人成绩，被誉为中国高职教育的“一面旗帜”。为紧密契合“中国制造2025”等国家重大战略和深圳创新驱动发展战略，学校在2016年底召开的第三次党代会工作报告中提出“三个服务、五个定位、一个率先”的战略发展目标，始终坚持为党和国家服务、为深圳经济社会发展服务、为学生健康成长成才服务，努力成为职业教育创新发展的先行者、复合式创新型高素质技术技能人才的摇篮、企业家的摇篮、深圳中小微企业技术研发中心、深圳市民终身教育学校与中国职业教育师资培训重要基地，率先建成中国特色、世界一流职业院校，为世界职业教育发展贡献“深圳模式”。////学校现有留仙洞、西丽湖、官龙山、华侨城、凤凰山五个校区，校园总面积212万平方米，学校产权校舍建筑面积57.34万平方米，其中教室10.75万平方米，图书馆5万平方米，体育馆3.34万平方米，实训实习场所10.14万平方米。现有固定资产总值23.66亿元，其中教学仪器设备总值9.58亿元,教学用计算机14525台。图书馆藏有纸质图书261.2万册，电子图书130万册，电子期刊60.54万册，中外文数据库46个，音视频16.07万小时。////全校现有教职员工2380人，其中专任教师1243人，正高217人，副高657人，博士408人，享受国务院特殊津贴专家2名，珠江学者5人、海外高层次人才25人、国家“万人计划”教学名师1人、国家级教学名师3人、省级教学名师8人、国家特支计划教师1人、广东特支计划教学名师4人。学校拥有教育部首批黄大年式教师团队1个；引进美国霍夫曼诺奖团队等一批重量级团队，成立霍夫曼先进材料研究院、智能科学与工程研究院、智能制造研究院、新时代中国职业教育研究院、社会与经济发展研究院等高端平台，为珠三角产业发展提供有力支撑。////学校设有电子与通信工程学院等17个二级学院和体育部、工业中心、国际教育部等教学单位，招生专业80个。全校普通全日制在校生22750人，其中港澳台留学生79人，四年制高职生284人，应用型本科生292人，外国留学生127人。自办专科教育在校生3536人。国家级教学成果奖14项，国家职业教育专业教学资源库3项，国家重点支持建设示范专业12个，中央财政支持实训基地9个，国家级精品教材12部，国家精品课程53门，国家级精品资源共享课43门。////学校一直把人才培养作为中心工作，以培养适应智能时代需要的复合式创新型高素质技术技能人才为目标，更新教育教学理念，探索实施以学生学习成效为导向的OBE（Outcome/Based/Education）人才培养模式改革，深入推进产教融合、职普融合、理实融合、技术与文化融合、教育与生活融合、现代信息技术与教学融合等“六个融合”，提升学生的就业能力、职业生涯拓展能力和幸福生活创造能力。瞄准未来社会和经济发展，紧贴深圳四大支柱产业和新兴产业布局专业，打造品牌专业，与华为、ARM、阿里巴巴、平安、比亚迪、裕同、天健等一流企业紧密合作，共建华为信息与网络技术学院、ARM智能硬件学院、阿里巴巴数字贸易学院、平安金融科技学院、比亚迪应用技术学院、裕同数字图文学院、天健建工学院等7所特色产业学院，校企共同制定专业标准、共同开发课程、共建师资团队、共同培养技术技能人才，在服务一流企业中成就自身一流。开设专业文化课程，大力培育工匠精神，厚植工匠文化，全面推进职业院校文化育人。学校已累计培养11万余名全日制专科毕业生，毕业生初次就业率始终保持在96%以上，多项人才培养质量指标位居全国高职院校前列，深受用人单位欢迎。其中，238人次获CCIE证书，13人获RHCA证书，57人获OCM证书，163人获HCIE证书，13人获RHCE证书。////学校探索实施创新创业教育改革，以“五维一体”的创新创业教育理念（重心在“教育”、路径在“分层”、目标在“万众”、核心在“创新”、关键在“实践”）为引领，打造深圳中小微企业技术研发中心、全球技术技能人才创新创业教育中心，以及创新型人才和企业家培养的成长摇篮。通过系统设计、科学构建，协同推进从启蒙教育、预科教育、专门教育到指导创办企业的进阶式创业人才培养体系，搭建“四会两赛三联盟”双创交流平台和“创新型社团—创客中心—学生创意创业园”双创实践平台，逐步完善跨界融合、产品试制、创业孵化、创业投资的双创服务体系，取得良好的社会效益。近年来获评首批全国创新创业典型经验高校、全国深化创新创业教育改革示范高校、广东省大众创业万众创新示范基地、深圳首批十大创新创业基地等。近四届毕业生毕业一年内自主创业比例达到5%，毕业三年后创业比例12.7%。////学校坚持以“产学研用”一体化的科研导向，重视技术转移和科技成果转化。近年来，学校不断深化科研体制机制改革，大力加强与政府职能部门以及行业企业合作，组建成立了应用技术研发院、文化创意产品研发院、经济与社会发展研究院等三大综合性研发平台，建成43个市区级以上科研平台,抢抓产业发展新机遇，服务地方经济社会和中小企业发展。全校累计承担各级各类科研课题5196项，其中国家级项目84项,年度新增国家自然科学基金项目10项。科研经费到账总经费达到8.06亿元，其中技术转移（横向科研）项目到账经费2.98亿元；出版各类学术专著226部、编著、译著和作品集共199部，61项科研成果获部、省、市级奖励；获国家专利授权1726项，软件著作权登记1136件，发明专利345项。主导或参与制定国际、国家、行业标准74项。////学校重视社会服务，发挥品牌优势，致力于推动现代职业教育培训体系和学习型社会建设。做好高水平师资培训，打造世界级的职业教育培训中心；做好职业培训、职业技能鉴定及职业资格认证工作，服务好地方经济发展需要；联合社区街道组建社区学院、特色学院，开展针对社区居民的健康、养老、旅游等培训项目，服务好地方社会发展需要；以办学理念和教学模式输出为主要内容，构建“理念—教学—师资—管理”四位一体的精准帮扶体系，服务好对口支援地区和院校的发展。全年重点对口帮扶11所职业院校，累计对口支援西藏、新疆、贵州等地11个省、自治区的200余所职业院校。全年举办33个全国高职高专师资培训班，累计为全国680余所职业院校培训骨干教师1.2万人次，连续5年名列全国第一。年均开展各类培训、职业技能鉴定与资格认证12万人次。组建西丽社区学院、大鹏旅游学院等社区学院，与社区共同培养技能人才，打造开放办学、产教融合的“职教特区”；选派核心团队建设管理吉安职业技术学院，开创了特区与老区携手共同发展职业教育的典范。////学校紧扣国家发展战略，加快国际化办学步伐，充分利用区域与自身优势，深化国际教育交流与合作。建校以来，已累计与32个国家和地区的162所高校和教育机构建立了友好合作关系，包括英国、德国、法国、美国等发达国家以及新西兰、马来西亚、保加利亚、土耳其、波兰、匈牙利、缅甸、老挝等14个“一带一路”沿线国家。双方在学生交换、课程合作、科研合作、短期研修等领域开展了全方位、多层次、形式多样的教师和学生国际交流活动，取得了丰硕的成果。近年来，我校年均接待境外来访师生及外宾108批次，658人次；我校赴境外参加国际交流的师生52批次，276人次。开办了国际商务（中澳）、金融管理（中澳）、物流管理（中美）和软件技术（中美）4个中外合作办学专业；与香港专业教育学院黄克竞分校合办电气服务工程高级文凭合作课程，毕业生获得深港两地毕业资格，并成为首批获得招收海外留学生资质的高职院校和首个获批面向港澳台自主招生的高职院校。学校还联合中兴、招商港口等一批世界一流企业“走出去”，服务国家“一带一路”倡议。在马来西亚马六甲应用技术大学设立职业教育与培训中心，推动马来西亚全国各类职业院校全面对接深职院标准。依托在保加利亚成立的职业教育与培训中心，输出学校专业标准。应邀为柬埔寨、蒙古等国家职业教育代表团举行专题培训班，输出职业教育经验。加强与职业教育国际组织的合作，成为联合国教科文组织国际职教全球联系中心之一，获批成立联合国教科文组织职业教育计划亚非研究与培训中心。在提高学校国际知名度与影响力的同时，为推动中国职业教育与语言文化走出去做出了积极贡献。////学校办学成绩显著。2001年首家通过国家示范性高职院校实践教学基地优秀评估，2009年通过国家示范性高等职业院校建设项目验收，成为我国高等职业教育领域首批国家级示范校。近年来，学校先后荣获“全国文明单位”、“全国职业教育先进单位”、“全国一流高职院校建设单位”、“首批全国创新创业典型经验高校”、“全国高校毕业生就业工作先进集体”、“中国十大最具就业力高职院校”、“全国毕业生就业工作典型经验高校”、“全国职业院校就业竞争力示范校”、“中国十大创新型高职院校”、“黄炎培优秀学校奖”、“全国高校实践育人创新创业基地”“广东省文明单位”、“广东省职业技术教育工作先进集体”、“广东省首批大学生创新创业教育示范学校”、“广东省一流高职院校建设单位”“深圳市创新创业基地”等荣誉称号。 | AB12: 深圳职业技术大学于1993年创建，前身为深圳职业技术学院，是中国国内最早独立举办高等职业技术教育的院校之一。2000年、2004年原深圳市职业技术学校、深圳市卫生学校分别并入深圳职业技术学院。2006年深圳职业技术学院被确定为“国家示范性高等职业院校建设计划”首批立项建设院校，2009年学校顺利通过验收成为首批国家示范性高等职业院校。2023年6月，教育部发文同意以深圳职业技术学院为基础整合资源设立深圳职业技术大学，同时撤销深圳职业技术学院的建制。 | AC12: http://www.szpt.edu.cn/ | AD12: https://zhaosheng.szpt.edu.cn/ | AE12: 0755/26731715、26731216 | AF12: 深圳市南山区西丽街道留仙大道7098号 | AG12: https://www.720yun.com/t/d8vksm7e0d9 | AH12: 158 | AI12: https://baike.baidu.com/item/%E6%B7%B1%E5%9C%B3%E8%81%8C%E4%B8%9A%E6%8A%80%E6%9C%AF%E5%A4%A7%E5%AD%A6 | AJ12: https://gaokao.chsi.com.cn/zsgs/zhangcheng/listZszc//schId/734.dhtml | AK12: /
A13: 8 | B13: =C13 -> 0 | D13: 依据学考 | E13: 11113 | F13: 深圳职业技术大学 | G13: 604 | H13: 282 | I13: 343 | J13: 282 | K13: 343 | L13: 390 | M13: 401 | N13: 9890 | O13: 7402 | P13: =IFERROR(AVERAGE(L13:M13),"/") -> 395.5 | Q13: =IFERROR(AVERAGE(N13:O13),"/") -> 8646 | R13: 广东省 | S13: 深圳市 | T13: 广东省 | U13: 职业本科 | V13: 广东省 | W13: 公办 | X13: 一线城市 | Y13: 省属/双高计划/高水平学校建设单位/国家级示范 | Z13: 第一类高水平学校A档示范高职 | AA13: 深圳职业技术学院1993年创建，是国内最早独立举办高等职业技术教育的院校之一。建校以来，深职院人艰苦创业，开拓进取，不断创新教育教学理念、办学体制机制和人才培养模式，创造了中国高职教育的多个第一。学校依托珠三角产业发展，秉承深圳特区改革创新精神，坚持把立德树人作为学校教育的根本任务，立足于职业教育产教融合的办学特色，各项事业取得骄人成绩，被誉为中国高职教育的“一面旗帜”。为紧密契合“中国制造2025”等国家重大战略和深圳创新驱动发展战略，学校在2016年底召开的第三次党代会工作报告中提出“三个服务、五个定位、一个率先”的战略发展目标，始终坚持为党和国家服务、为深圳经济社会发展服务、为学生健康成长成才服务，努力成为职业教育创新发展的先行者、复合式创新型高素质技术技能人才的摇篮、企业家的摇篮、深圳中小微企业技术研发中心、深圳市民终身教育学校与中国职业教育师资培训重要基地，率先建成中国特色、世界一流职业院校，为世界职业教育发展贡献“深圳模式”。////学校现有留仙洞、西丽湖、官龙山、华侨城、凤凰山五个校区，校园总面积212万平方米，学校产权校舍建筑面积57.34万平方米，其中教室10.75万平方米，图书馆5万平方米，体育馆3.34万平方米，实训实习场所10.14万平方米。现有固定资产总值23.66亿元，其中教学仪器设备总值9.58亿元,教学用计算机14525台。图书馆藏有纸质图书261.2万册，电子图书130万册，电子期刊60.54万册，中外文数据库46个，音视频16.07万小时。////全校现有教职员工2380人，其中专任教师1243人，正高217人，副高657人，博士408人，享受国务院特殊津贴专家2名，珠江学者5人、海外高层次人才25人、国家“万人计划”教学名师1人、国家级教学名师3人、省级教学名师8人、国家特支计划教师1人、广东特支计划教学名师4人。学校拥有教育部首批黄大年式教师团队1个；引进美国霍夫曼诺奖团队等一批重量级团队，成立霍夫曼先进材料研究院、智能科学与工程研究院、智能制造研究院、新时代中国职业教育研究院、社会与经济发展研究院等高端平台，为珠三角产业发展提供有力支撑。////学校设有电子与通信工程学院等17个二级学院和体育部、工业中心、国际教育部等教学单位，招生专业80个。全校普通全日制在校生22750人，其中港澳台留学生79人，四年制高职生284人，应用型本科生292人，外国留学生127人。自办专科教育在校生3536人。国家级教学成果奖14项，国家职业教育专业教学资源库3项，国家重点支持建设示范专业12个，中央财政支持实训基地9个，国家级精品教材12部，国家精品课程53门，国家级精品资源共享课43门。////学校一直把人才培养作为中心工作，以培养适应智能时代需要的复合式创新型高素质技术技能人才为目标，更新教育教学理念，探索实施以学生学习成效为导向的OBE（Outcome/Based/Education）人才培养模式改革，深入推进产教融合、职普融合、理实融合、技术与文化融合、教育与生活融合、现代信息技术与教学融合等“六个融合”，提升学生的就业能力、职业生涯拓展能力和幸福生活创造能力。瞄准未来社会和经济发展，紧贴深圳四大支柱产业和新兴产业布局专业，打造品牌专业，与华为、ARM、阿里巴巴、平安、比亚迪、裕同、天健等一流企业紧密合作，共建华为信息与网络技术学院、ARM智能硬件学院、阿里巴巴数字贸易学院、平安金融科技学院、比亚迪应用技术学院、裕同数字图文学院、天健建工学院等7所特色产业学院，校企共同制定专业标准、共同开发课程、共建师资团队、共同培养技术技能人才，在服务一流企业中成就自身一流。开设专业文化课程，大力培育工匠精神，厚植工匠文化，全面推进职业院校文化育人。学校已累计培养11万余名全日制专科毕业生，毕业生初次就业率始终保持在96%以上，多项人才培养质量指标位居全国高职院校前列，深受用人单位欢迎。其中，238人次获CCIE证书，13人获RHCA证书，57人获OCM证书，163人获HCIE证书，13人获RHCE证书。////学校探索实施创新创业教育改革，以“五维一体”的创新创业教育理念（重心在“教育”、路径在“分层”、目标在“万众”、核心在“创新”、关键在“实践”）为引领，打造深圳中小微企业技术研发中心、全球技术技能人才创新创业教育中心，以及创新型人才和企业家培养的成长摇篮。通过系统设计、科学构建，协同推进从启蒙教育、预科教育、专门教育到指导创办企业的进阶式创业人才培养体系，搭建“四会两赛三联盟”双创交流平台和“创新型社团—创客中心—学生创意创业园”双创实践平台，逐步完善跨界融合、产品试制、创业孵化、创业投资的双创服务体系，取得良好的社会效益。近年来获评首批全国创新创业典型经验高校、全国深化创新创业教育改革示范高校、广东省大众创业万众创新示范基地、深圳首批十大创新创业基地等。近四届毕业生毕业一年内自主创业比例达到5%，毕业三年后创业比例12.7%。////学校坚持以“产学研用”一体化的科研导向，重视技术转移和科技成果转化。近年来，学校不断深化科研体制机制改革，大力加强与政府职能部门以及行业企业合作，组建成立了应用技术研发院、文化创意产品研发院、经济与社会发展研究院等三大综合性研发平台，建成43个市区级以上科研平台,抢抓产业发展新机遇，服务地方经济社会和中小企业发展。全校累计承担各级各类科研课题5196项，其中国家级项目84项,年度新增国家自然科学基金项目10项。科研经费到账总经费达到8.06亿元，其中技术转移（横向科研）项目到账经费2.98亿元；出版各类学术专著226部、编著、译著和作品集共199部，61项科研成果获部、省、市级奖励；获国家专利授权1726项，软件著作权登记1136件，发明专利345项。主导或参与制定国际、国家、行业标准74项。////学校重视社会服务，发挥品牌优势，致力于推动现代职业教育培训体系和学习型社会建设。做好高水平师资培训，打造世界级的职业教育培训中心；做好职业培训、职业技能鉴定及职业资格认证工作，服务好地方经济发展需要；联合社区街道组建社区学院、特色学院，开展针对社区居民的健康、养老、旅游等培训项目，服务好地方社会发展需要；以办学理念和教学模式输出为主要内容，构建“理念—教学—师资—管理”四位一体的精准帮扶体系，服务好对口支援地区和院校的发展。全年重点对口帮扶11所职业院校，累计对口支援西藏、新疆、贵州等地11个省、自治区的200余所职业院校。全年举办33个全国高职高专师资培训班，累计为全国680余所职业院校培训骨干教师1.2万人次，连续5年名列全国第一。年均开展各类培训、职业技能鉴定与资格认证12万人次。组建西丽社区学院、大鹏旅游学院等社区学院，与社区共同培养技能人才，打造开放办学、产教融合的“职教特区”；选派核心团队建设管理吉安职业技术学院，开创了特区与老区携手共同发展职业教育的典范。////学校紧扣国家发展战略，加快国际化办学步伐，充分利用区域与自身优势，深化国际教育交流与合作。建校以来，已累计与32个国家和地区的162所高校和教育机构建立了友好合作关系，包括英国、德国、法国、美国等发达国家以及新西兰、马来西亚、保加利亚、土耳其、波兰、匈牙利、缅甸、老挝等14个“一带一路”沿线国家。双方在学生交换、课程合作、科研合作、短期研修等领域开展了全方位、多层次、形式多样的教师和学生国际交流活动，取得了丰硕的成果。近年来，我校年均接待境外来访师生及外宾108批次，658人次；我校赴境外参加国际交流的师生52批次，276人次。开办了国际商务（中澳）、金融管理（中澳）、物流管理（中美）和软件技术（中美）4个中外合作办学专业；与香港专业教育学院黄克竞分校合办电气服务工程高级文凭合作课程，毕业生获得深港两地毕业资格，并成为首批获得招收海外留学生资质的高职院校和首个获批面向港澳台自主招生的高职院校。学校还联合中兴、招商港口等一批世界一流企业“走出去”，服务国家“一带一路”倡议。在马来西亚马六甲应用技术大学设立职业教育与培训中心，推动马来西亚全国各类职业院校全面对接深职院标准。依托在保加利亚成立的职业教育与培训中心，输出学校专业标准。应邀为柬埔寨、蒙古等国家职业教育代表团举行专题培训班，输出职业教育经验。加强与职业教育国际组织的合作，成为联合国教科文组织国际职教全球联系中心之一，获批成立联合国教科文组织职业教育计划亚非研究与培训中心。在提高学校国际知名度与影响力的同时，为推动中国职业教育与语言文化走出去做出了积极贡献。////学校办学成绩显著。2001年首家通过国家示范性高职院校实践教学基地优秀评估，2009年通过国家示范性高等职业院校建设项目验收，成为我国高等职业教育领域首批国家级示范校。近年来，学校先后荣获“全国文明单位”、“全国职业教育先进单位”、“全国一流高职院校建设单位”、“首批全国创新创业典型经验高校”、“全国高校毕业生就业工作先进集体”、“中国十大最具就业力高职院校”、“全国毕业生就业工作典型经验高校”、“全国职业院校就业竞争力示范校”、“中国十大创新型高职院校”、“黄炎培优秀学校奖”、“全国高校实践育人创新创业基地”“广东省文明单位”、“广东省职业技术教育工作先进集体”、“广东省首批大学生创新创业教育示范学校”、“广东省一流高职院校建设单位”“深圳市创新创业基地”等荣誉称号。 | AB13: 深圳职业技术大学于1993年创建，前身为深圳职业技术学院，是中国国内最早独立举办高等职业技术教育的院校之一。2000年、2004年原深圳市职业技术学校、深圳市卫生学校分别并入深圳职业技术学院。2006年深圳职业技术学院被确定为“国家示范性高等职业院校建设计划”首批立项建设院校，2009年学校顺利通过验收成为首批国家示范性高等职业院校。2023年6月，教育部发文同意以深圳职业技术学院为基础整合资源设立深圳职业技术大学，同时撤销深圳职业技术学院的建制。 | AC13: http://www.szpt.edu.cn/ | AD13: https://zhaosheng.szpt.edu.cn/ | AE13: 0755/26731715、26731216 | AF13: 深圳市南山区西丽街道留仙大道7098号 | AG13: https://www.720yun.com/t/d8vksm7e0d9 | AH13: 158 | AI13: https://baike.baidu.com/item/%E6%B7%B1%E5%9C%B3%E8%81%8C%E4%B8%9A%E6%8A%80%E6%9C%AF%E5%A4%A7%E5%AD%A6 | AJ13: https://gaokao.chsi.com.cn/zsgs/zhangcheng/listZszc//schId/734.dhtml | AK13: /
A14: 9 | B14: =C14 -> 0 | D14: 依据学考 | E14: 10833 | F14: 广东轻工职业技术大学 | G14: 603 | H14: 175 | I14: 120 | J14: 175 | K14: 120 | L14: 388 | M14: 400 | N14: 11128 | O14: 8363 | P14: =IFERROR(AVERAGE(L14:M14),"/") -> 394 | Q14: =IFERROR(AVERAGE(N14:O14),"/") -> 9745.5 | R14: 广东省 | S14: 广州市 | T14: 广东省 | U14: 职业本科 | V14: 广东省 | W14: 公办 | X14: 一线城市 | Y14: 省属/双高计划/高水平学校建设单位/国家级示范/现代学徒制试点学院 | Z14: 第二类高水平学校B档示范高职现代学徒 | AA14: 广东轻工职业技术学院创建于1933年，是省属唯一国家示范性高等职业院校，全国“双高”高职院校建设单位。前身是“广东省立第一职业学校”，至今已有86年职业教育历史，其中1959/1963年和1978/1983年两段时期，学校开办本科教育，现有全日制在校生21000余人。学校秉承“德能兼备，学以成之”的校训和“自强、敬业、求实、创新”的广轻精神，为珠三角地区乃至全国输送数万名高素质高技能应用型人才。////办学条件好////学校现有广州和南海两个校区，其中广州校区定位为“大文科校区”，文科、艺术类专业面向广州现代服务业；南海校区成为“大工科校区”，工科专业面向珠江西岸高端制造业，校园总面积1700多亩，校舍建筑面积43万多平方米，其中教学科研实训用房近20万平方米，图书馆3万多平方米，学生公寓近16万平方米。固定资产总值15.5亿元，教学仪器设备总值2亿多元，学校图书馆拥有藏书近160万册，电子图书200多万册。网络信息点数2万多个，音视频电子资源1万多小时，学校校园无线网络全覆盖。建有校内实践教学基地近350个、校外实训实习基地900多个。////办学成果优异////学校是广东省唯一拥有7个省级工程技术开发中心的高职院校，是同时拥有省级协同发展中心及协同育人平台的两所高职院校之一，是全国第一批教育信息化试点单位、教育部现代学徒制试点单位、全国高校思政研究会高职高专专业委员会副会长单位（广东省会长单位）、全国跨境电商专业人才培养示范校、全国群众体育先进单位、全国高职“一校一品”示范单位、全国社会实践工作优秀单位、广东省依法治校示范校单位、广东省创新创业示范校单位、广东省安全文明校园示范校单位、广东省示范职业教育集团、广东省集团化办学单位、国防教育特色学校。学校立项“国家标杆党支部”1个，并先后获得全国高等职业院校全国服务贡献50强（连续两年）、全国高等职业院校实习管理50强、全国高等职业院校教学资源50强、全国高等职业院校学生管理50强、全国高等职业院校教学管理50强、全国高等职业院校育人成效50强、亚太职业院校影响力50强、全国示范性高职院校影响力排行榜30强、全国普通高校竞赛评估（高职）20强，全国高职院校思政工作创新优秀示范案例50强。全国高职院校创新创业示范校50强。2019年中国高职高专院校综合竞争力排行榜第9名。////多功能文化食堂、智能垃圾分类系统等创新性后勤改革领先全国。////师资队伍结构合理，业务水平高////学校现有教职工1200余人，其中高级职称教师400余人（二级教授9人），珠江学者9/人，“双师”素质教师70/0余人；国务院特殊津贴专家2人，全国模范教师2人，国家级教学名师2人，国家级教学团队2个，国家“万人计划”教学名师1人，全国技术能手2人，全国青年岗位能手1人，全国高校思想政治理论课教师影响力人物2人，全国轻工行业先进工作者1人，中国轻工职业教育教学名师1人，全国辅导员年度人物1名，广东省高校“千百十工程”国家级培养对象2人，南粤优秀教师11人，南粤优秀教育工作者4人，广东省“特支计划”教学名师、广东省教学名师、专业领军人才等名师专家近70人。建立了一个由企业一线工作的技术人员、能工巧匠、高级经理人等组成的优质兼职教师资源库，兼职教师与专业专任教师数之比达到1:1以上。学校在广东省高职院校教师队伍建设考核中连续三年排名第一。2019年全国高职院校教师教学发展指数排前十名。////教学成果丰硕////学校设有机电技术学院、食品与生物技术学院、轻化工技术学院、信息技术学院、汽车技术学院、生态环境技术学院、艺术设计学院、财贸学院、管理学院、应用外语学院、创业学院、马克思主义学院和继续教育学院，三个协同教学中心（工业机器人协同教学中心、现代信息技术与新工科协同教学中心、应用外语协同教学中心），设20个专业群、69个招生专业。2016年11月，学校成立创业学院，面向全体学生进行创新创业通识教育，面向精英学生进行创新创业定制培养。学校已建成国家示范性专业4个、央财“支持高等职业学校提升专业服务产业发展能力”项目经费支持专业2个、省级示范性专业3个、省级重点（建设）专业13个、省级品牌专业建设项目13个，建有国家级教学资源库1个、国家级精品课程10门、国家级精品资源共享课程9门、全国高校职业发展与就业指导示范课程1门、国家教指委精品课程22门、省级精品课程21门、省级优质课程2门，立项省级精品开放课程4/5门，其中已验收3门，在建省级专业资源库2个。2009年以来，学校共获得国家级优秀教学成果二等奖10项，行业教指会特等奖2个，省级优秀教学成果一等奖9项，省级优秀教学成果二等奖5项。////职教特色明显，人才培养质量高////学校是教育部现代学徒制试点单位，已立项国家级现代学徒制试点项目3项，省级现代学徒制试点项目/9项。学校积极构建职业教育“立交桥”，全面实施“纵向延伸，横向拓展”协同育人模式，开展了“3+2”中高衔接、“2+2”和“4+0”高本联培、“3+2”高本衔接、工程硕士培养等多种形式的协同培养，其中本科专业共1/3个，搭建起“中/高/本/硕”现代职业教育体系框架。连续多年，录取人数和录取分数线均位居省内同类院校前茅，文理类、艺术类高考录取分数线均高于本科省控线。毕业生深受用人单位欢迎，母校的满意度和薪资水平高于全国示范校平均水平，初次就业率高于98%，用人单位满意度99%以上。学生在各级各类技能大赛中获奖数量与质量节节攀升。近三年来，共获得国家级奖项500多个、省部级奖项1000余个。////产教融合，社会服务能力强////学校构建并不断完善政校行企协同促进产教融合长效机制，围绕高水平专业群建设，打造“一群一院一联盟”，搭建了广东轻工职教集团、轻工行业应用技术协同创新发展中心、南海职业教育政校行企协同创新联盟、广东省工业互联网产教联盟、粤港澳数字创意产教联盟、粤港澳跨境电商产教联盟、广东酒店职业教育联盟、全国精准营养食品与果蔬加工产教联盟、国家中小微企业知识产权培训基地等产学研创新、科技研发与转化平台，与华为等世界500强知名企业合作成立了华为ICT学院、瀚蓝环境学院、白天鹅学院、雷诺钟表学院、许鸿飞国际文创学院等10个产业学院，实现校企精准对接，产教深度融合，精准育人。近五年，获国家级科技项目4项、省级36项；国家级、省级科技奖励13项；面向企业开展科技攻关项目200余项。申报专利近430项，授权近300项，专利申请量连续多年位列广州地区高校（含本科）前十名。////坚持对外合作，国际化办学水平高////学校积极广泛开展对外交流与合作，已与国（境）外多所高等院校建立了合作关系，在引进智力与优质教育资源、人才培养、合作办学、汉语言培训等方面开展了实质性的合作。累计已招收来自30多个国家的留学生4/00余名。2017年，学校牵头组建广东省“一带一路”职业教育联盟，输出广轻职教模式，服务“一带一路”沿线国家及地区，国际化办学呈现新气象。////构建终身教育体系，服务广东经济社会////依托“国家中小微企业知识产权培训（南海）基地”“广东轻工培训中心”“职教师资优质省级基地”“广东省专业技术人员继续教育基地”“广东省职业技能鉴定所”等国家级和省级平台，并设有专门和专业性培训机构30多个，面向社会、社区和产业、行业积极开展各级各类培训服务，年培训量超15万人天；与本科院校进行网络远程教育及自学考试合作，并在深圳、佛山、珠海、韶关等地设立12个校外专科继续教育教学点，学校各类学历继续教育在读人数4000余人。////“十三五”期间，学校将遵循“三大一强”院校治理理念，围绕“创新强校工程”及一流高职院校建设，努力把学校建成“国内一流、国际知名”国家优质高职院校，成为高职院校治理的标准与典范，成为高素质技术技能型人才培养的典范。 | AB14: 学校创建于1933年，原名广东省立第一职业学校，学校数易其名，先后更名为广东省立广州农工业职业学校、广东省立广州工业职业学校、广东省立广州高级工业职业学校、广东省广州高级工业技术学校、广东省轻工业学校、广东轻工业学院、广州轻工业学校等 ，1959～1963年和1978～1983年曾开办本科职业教育。 1999年，学校升格为广东轻工职业技术学院。 2020年，广东省轻工职业技术学校、广东省石油化工职业技术学校并入。 2024年6月，教育部正式同意在广东轻工职业技术学院的基础上设立广东轻工职业技术大学。 9月3日，广东轻工职业技术大学正式揭牌。 | AC14: http://www.gdqy.edu.cn/ | AD14: http://gdqyzs.jysd.com/ | AE14: 020/61230198 | AF14: 广州市新港西路152号 | AG14: / | AH14: 369 | AI14: https://baike.baidu.com/item/%E5%B9%BF%E4%B8%9C%E8%BD%BB%E5%B7%A5%E8%81%8C%E4%B8%9A%E6%8A%80%E6%9C%AF%E5%A4%A7%E5%AD%A6 | AJ14: https://gaokao.chsi.com.cn/zsgs/zhangcheng/listZszc//schId/620.dhtml | AK14: /
A15: 10 | B15: =C15 -> 0 | D15: 依据学考 | E15: 12957 | F15: 深圳信息职业技术大学 | G15: 606 | H15: 28 | I15: 73 | J15: 28 | K15: 73 | L15: 387 | M15: 398 | N15: 11959 | O15: 11459 | P15: =IFERROR(AVERAGE(L15:M15),"/") -> 392.5 | Q15: =IFERROR(AVERAGE(N15:O15),"/") -> 11709 | R15: 广东省 | S15: 深圳市 | T15: 广东省 | U15: 职业本科 | V15: 广东省 | W15: 公办 | X15: 一线城市 | Y15: 双高计划/高水平学校建设单位/国家级骨干/现代学徒制试点学院 | Z15: 第二类高水平学校B档骨干高职现代学徒 | AA15: 深圳信息职业技术学院创办于2002年4月，是经广东省人民政府批准、教育部备案，由深圳市人民政府举办的公办全日制高等院校。//学校现为国家示范（骨干）高职院校、国家示范性软件职业技术学院、教育部“中德职教汽车机电合作项目”试点院校，现拥有3个国家级高等职业教育专业教学资源库（含1个备选项目）。学校拥有现代化、生态型、信息化的校园，占地92.6万平方米（1389亩），建筑面积58.86万平方米。学校现有教学科研仪器设备总值为36786.36万元，图书馆藏书131.33万册。//学校对接深圳支柱产业，打造信息技术特色，共设软件学院、电子与通信学院、计算机学院、数字媒体学院、智能制造与装备学院、交通与环境学院、管理学院、财经学院、应用外语学院、中德学院、马克思主义学院、继续教育学院、创新创业学院、创新教育研究院、公共课教学部、体育部、信息技术研究所等14院2部1所；开设信息类为主的专业44个。现有国家骨干校重点建设专业4个，国家高等职业学校提升专业服务产业发展能力建设专业2个，全国职业院校示范专业点2个，国家高等职业教育教学资源库建设项目3个（含1个备选项目），广东省示范性专业4个，省级重点建设专业6个，省级品牌专业11个；国家级精品资源共享课7门、省级精品资源共享课（含精品在线开放课）38门、省级思想政治理论优质建设课程2门。//学校现有教职工796人，在590位专任教师中，副高及以上职称教师301人，其中，博士、博士后275人，“双师素质”教师九成。目前，学校拥有国家级教学团队1个，获国家级教学名师奖1人，获全国五一劳动奖章1人，国家万人计划教学名师1名，广东省教学名师奖3人，广东省“特支计划”教学名师3人，省级教学团队7个，南粤优秀教师7人，广东省“千百十人才培养工程”省级培养对象6人，广东省“珠江学者”特聘教授4人，深圳市“鹏城学者”特聘教授3人，深圳市政府特殊津贴1人，黄炎培职业教育杰出教师奖1人，深圳市高层次专业人才地方级领军人才9名，后备级领军人才21人，博士后创新实践基地在站博士后3人。//学校坚持科研引领、教研创新、突出应用、服务社会。已主持国家自然科学基金等国家级项目26项、省市级科研项目517项，教研课题国家级6项、省市级49项，深圳市首批教育科研专家工作室1个。获得国家级高等学校教学成果一等奖1项、二等奖2项，省级教学成果一等奖6项、二等奖4项，广东省科学技术二等奖2项、三等奖2项，国家教师科研基金“十一五”规划重点课题科研成果一等奖1项，深圳市科技进步奖2项，深圳市科技创新奖2项，深圳市科学技术奖自然科学奖1项，深圳市哲学社会科学优秀成果奖7项，中国人工智能学会进步奖二等奖；拥有发明专利62项，实用新型专利203项，外观设计专利8项。//学校坚持校企合作办学，积极推进产教融合协同育人，创新合作办学机制，探索校企合作模式，在校内构建了“三会两办”的办学机制，并打造了“学院+行业企业”的校企合作模式。学校用2万平米实训场地，引企入校，合作共建实践教学基地、科技创新平台等，基地目前建有2个省级创新平台、1个先进土木研究中心、1个智能制造实训中心、5个校级协同创新中心等创新载体。学校有国家级高等职业教育实训基地2个，省级高等职业教育实训基地11个，省级公共实训中心1个，省级大学生校外实践教学基地12个，深圳市高职教育校外公共实训基地33个。//学校建构高素质高技能人才培养机制，不断提升高就业率、高满意度办学效益。现有全日制在校生15468人，学校坚持产教融合、校企合作、因材施教、特色发展。近三年，学生参加专业技能竞赛共获国家级奖项137个，省级二等奖以上315个。毕业生“下得去、留得住、用得上、干得好”，毕业生总体就业率均在98%以上。毕业生被华为、腾讯、深圳地铁、中国联通等著名企业录用，产生了被《华尔街日报》报道为“中国最年轻90后千万富豪”丁仕源、拥有8家公司的速运邦邦CEO陈家良等创业典型。//学校积极引进国际先进教学资源，不断形成国际化办学特色。2012年，学校成为教育部“中德职教汽车机电合作项目”试点院校；2013年11月学校与西双版纳职业技术学院正式签署合作协议共建“深圳信息/西双版纳国际留学生基地”/并揭牌；2016年9月，由深圳市教育局和德国巴伐利亚州文教部推动，我校与德国巴伐利亚州帕绍技术学校、兰茨胡特应用技术大学合作创办中德学院；2018年5月，学校与芬兰于韦斯屈莱应用科技大学签订战略合作协议全面启动两校战略合作项目；此外，学校还与加拿大谢尔丹理工学院、韩国京畿大学、台湾地区朝阳科技大学、树德科技大学、龙华科技大学、台北城市科技大学、亚太创意技术学院等26所高校开展了师生交流、合作科研等项目。//学校跨越发展，已跻身全国高职院校“第一方阵”。2004年，学校成为“国家示范性软件职业技术学院”建设院校；2007年，以优异成绩通过教育部人才培养工作水平评估；2010年，成为国家骨干高职院校建设单位；2011年，获国家高等职业教育网络技术专业共享型教学资源库建设立项；2012年，入选教育部“中德职教汽车机电合作项目”试点院校；2014年获国家高等职业教育数字媒体专业群教学资源库立项；2015年，深圳市人力资源与社会保障局同意批准我校设立博士后创新实践基地；2016年，学校国家骨干校建设项目以“优秀”等级通过国家验收、获广东省“一流校”建设立项、学校“2188创客空间”被国家科学技术部认定为国家级众创空间，2016年学校又成功召开了第二次党代会，进一步确立了“全力打造有特色国际化一流职业院校”的奋斗目标。//青春深信成新锐，勇向潮头唱大风。学校将继续开拓奋进，勇于不断创新，努力把学校打造成有特色国际化一流职业院校。 | AB15: 学校原名为深圳信息职业技术学院，于2002年4月由深圳教育学院、深圳市工业学校、深圳市财经学校三所学校合并组建；2011年9月，学校从深圳市罗湖区迁至深圳市龙岗区。2012年，学校入选教育部“中德职教汽车机电合作项目”试点院校。2021年，学校获批设立广东省博士工作站。2025年6月，教育部发函广东省，同意以深圳信息职业技术学院为基础设立深圳信息职业技术大学，同时撤销深圳信息职业技术学院的建制。2026年1月，深圳信息职业技术大学正式成立。 | AC15: http://www.sziit.com.cn/ | AD15: http://zhaob.sziit.edu.cn/index.htm | AE15: 075589226360、075589226361 | AF15: 深圳市龙岗区龙翔大道2188号 | AG15: https://www.720yun.com/t/d4528mpguus | AH15: 184 | AI15: https://baike.baidu.com/item/%E6%B7%B1%E5%9C%B3%E4%BF%A1%E6%81%AF%E8%81%8C%E4%B8%9A%E6%8A%80%E6%9C%AF%E5%AD%A6%E9%99%A2 | AJ15: https://gaokao.chsi.com.cn/zsgs/zhangcheng/listZszc//schId/1429.dhtml | AK15: /
A16: 11 | B16: =C16 -> 0 | D16: 依据学考 | E16: 12957 | F16: 深圳信息职业技术大学 | G16: 605 | H16: 23 | I16: 25 | J16: 23 | K16: 25 | L16: 388 | M16: 397 | N16: 11740 | O16: 11856 | P16: =IFERROR(AVERAGE(L16:M16),"/") -> 392.5 | Q16: =IFERROR(AVERAGE(N16:O16),"/") -> 11798 | R16: 广东省 | S16: 深圳市 | T16: 广东省 | U16: 职业本科 | V16: 广东省 | W16: 公办 | X16: 一线城市 | Y16: 双高计划/高水平学校建设单位/国家级骨干/现代学徒制试点学院 | Z16: 第二类高水平学校B档骨干高职现代学徒 | AA16: 深圳信息职业技术学院创办于2002年4月，是经广东省人民政府批准、教育部备案，由深圳市人民政府举办的公办全日制高等院校。//学校现为国家示范（骨干）高职院校、国家示范性软件职业技术学院、教育部“中德职教汽车机电合作项目”试点院校，现拥有3个国家级高等职业教育专业教学资源库（含1个备选项目）。学校拥有现代化、生态型、信息化的校园，占地92.6万平方米（1389亩），建筑面积58.86万平方米。学校现有教学科研仪器设备总值为36786.36万元，图书馆藏书131.33万册。//学校对接深圳支柱产业，打造信息技术特色，共设软件学院、电子与通信学院、计算机学院、数字媒体学院、智能制造与装备学院、交通与环境学院、管理学院、财经学院、应用外语学院、中德学院、马克思主义学院、继续教育学院、创新创业学院、创新教育研究院、公共课教学部、体育部、信息技术研究所等14院2部1所；开设信息类为主的专业44个。现有国家骨干校重点建设专业4个，国家高等职业学校提升专业服务产业发展能力建设专业2个，全国职业院校示范专业点2个，国家高等职业教育教学资源库建设项目3个（含1个备选项目），广东省示范性专业4个，省级重点建设专业6个，省级品牌专业11个；国家级精品资源共享课7门、省级精品资源共享课（含精品在线开放课）38门、省级思想政治理论优质建设课程2门。//学校现有教职工796人，在590位专任教师中，副高及以上职称教师301人，其中，博士、博士后275人，“双师素质”教师九成。目前，学校拥有国家级教学团队1个，获国家级教学名师奖1人，获全国五一劳动奖章1人，国家万人计划教学名师1名，广东省教学名师奖3人，广东省“特支计划”教学名师3人，省级教学团队7个，南粤优秀教师7人，广东省“千百十人才培养工程”省级培养对象6人，广东省“珠江学者”特聘教授4人，深圳市“鹏城学者”特聘教授3人，深圳市政府特殊津贴1人，黄炎培职业教育杰出教师奖1人，深圳市高层次专业人才地方级领军人才9名，后备级领军人才21人，博士后创新实践基地在站博士后3人。//学校坚持科研引领、教研创新、突出应用、服务社会。已主持国家自然科学基金等国家级项目26项、省市级科研项目517项，教研课题国家级6项、省市级49项，深圳市首批教育科研专家工作室1个。获得国家级高等学校教学成果一等奖1项、二等奖2项，省级教学成果一等奖6项、二等奖4项，广东省科学技术二等奖2项、三等奖2项，国家教师科研基金“十一五”规划重点课题科研成果一等奖1项，深圳市科技进步奖2项，深圳市科技创新奖2项，深圳市科学技术奖自然科学奖1项，深圳市哲学社会科学优秀成果奖7项，中国人工智能学会进步奖二等奖；拥有发明专利62项，实用新型专利203项，外观设计专利8项。//学校坚持校企合作办学，积极推进产教融合协同育人，创新合作办学机制，探索校企合作模式，在校内构建了“三会两办”的办学机制，并打造了“学院+行业企业”的校企合作模式。学校用2万平米实训场地，引企入校，合作共建实践教学基地、科技创新平台等，基地目前建有2个省级创新平台、1个先进土木研究中心、1个智能制造实训中心、5个校级协同创新中心等创新载体。学校有国家级高等职业教育实训基地2个，省级高等职业教育实训基地11个，省级公共实训中心1个，省级大学生校外实践教学基地12个，深圳市高职教育校外公共实训基地33个。//学校建构高素质高技能人才培养机制，不断提升高就业率、高满意度办学效益。现有全日制在校生15468人，学校坚持产教融合、校企合作、因材施教、特色发展。近三年，学生参加专业技能竞赛共获国家级奖项137个，省级二等奖以上315个。毕业生“下得去、留得住、用得上、干得好”，毕业生总体就业率均在98%以上。毕业生被华为、腾讯、深圳地铁、中国联通等著名企业录用，产生了被《华尔街日报》报道为“中国最年轻90后千万富豪”丁仕源、拥有8家公司的速运邦邦CEO陈家良等创业典型。//学校积极引进国际先进教学资源，不断形成国际化办学特色。2012年，学校成为教育部“中德职教汽车机电合作项目”试点院校；2013年11月学校与西双版纳职业技术学院正式签署合作协议共建“深圳信息/西双版纳国际留学生基地”/并揭牌；2016年9月，由深圳市教育局和德国巴伐利亚州文教部推动，我校与德国巴伐利亚州帕绍技术学校、兰茨胡特应用技术大学合作创办中德学院；2018年5月，学校与芬兰于韦斯屈莱应用科技大学签订战略合作协议全面启动两校战略合作项目；此外，学校还与加拿大谢尔丹理工学院、韩国京畿大学、台湾地区朝阳科技大学、树德科技大学、龙华科技大学、台北城市科技大学、亚太创意技术学院等26所高校开展了师生交流、合作科研等项目。//学校跨越发展，已跻身全国高职院校“第一方阵”。2004年，学校成为“国家示范性软件职业技术学院”建设院校；2007年，以优异成绩通过教育部人才培养工作水平评估；2010年，成为国家骨干高职院校建设单位；2011年，获国家高等职业教育网络技术专业共享型教学资源库建设立项；2012年，入选教育部“中德职教汽车机电合作项目”试点院校；2014年获国家高等职业教育数字媒体专业群教学资源库立项；2015年，深圳市人力资源与社会保障局同意批准我校设立博士后创新实践基地；2016年，学校国家骨干校建设项目以“优秀”等级通过国家验收、获广东省“一流校”建设立项、学校“2188创客空间”被国家科学技术部认定为国家级众创空间，2016年学校又成功召开了第二次党代会，进一步确立了“全力打造有特色国际化一流职业院校”的奋斗目标。//青春深信成新锐，勇向潮头唱大风。学校将继续开拓奋进，勇于不断创新，努力把学校打造成有特色国际化一流职业院校。 | AB16: 学校原名为深圳信息职业技术学院，于2002年4月由深圳教育学院、深圳市工业学校、深圳市财经学校三所学校合并组建；2011年9月，学校从深圳市罗湖区迁至深圳市龙岗区。2012年，学校入选教育部“中德职教汽车机电合作项目”试点院校。2021年，学校获批设立广东省博士工作站。2025年6月，教育部发函广东省，同意以深圳信息职业技术学院为基础设立深圳信息职业技术大学，同时撤销深圳信息职业技术学院的建制。2026年1月，深圳信息职业技术大学正式成立。 | AC16: http://www.sziit.com.cn/ | AD16: http://zhaob.sziit.edu.cn/index.htm | AE16: 075589226360、075589226361 | AF16: 深圳市龙岗区龙翔大道2188号 | AG16: https://www.720yun.com/t/d4528mpguus | AH16: 184 | AI16: https://baike.baidu.com/item/%E6%B7%B1%E5%9C%B3%E4%BF%A1%E6%81%AF%E8%81%8C%E4%B8%9A%E6%8A%80%E6%9C%AF%E5%AD%A6%E9%99%A2 | AJ16: https://gaokao.chsi.com.cn/zsgs/zhangcheng/listZszc//schId/1429.dhtml | AK16: /
A17: 12 | B17: =C17 -> 0 | D17: 依据学考 | E17: 10833 | F17: 广东轻工职业技术大学 | G17: 609 | H17: 85 | I17: 120 | J17: 85 | K17: 120 | L17: 386 | M17: 398 | N17: 13427 | O17: 10558 | P17: =IFERROR(AVERAGE(L17:M17),"/") -> 392 | Q17: =IFERROR(AVERAGE(N17:O17),"/") -> 11992.5 | R17: 广东省 | S17: 广州市 | T17: 广东省 | U17: 职业本科 | V17: 广东省 | W17: 公办 | X17: 一线城市 | Y17: 省属/双高计划/高水平学校建设单位/国家级示范/现代学徒制试点学院 | Z17: 第二类高水平学校B档示范高职现代学徒 | AA17: 广东轻工职业技术学院创建于1933年，是省属唯一国家示范性高等职业院校，全国“双高”高职院校建设单位。前身是“广东省立第一职业学校”，至今已有86年职业教育历史，其中1959/1963年和1978/1983年两段时期，学校开办本科教育，现有全日制在校生21000余人。学校秉承“德能兼备，学以成之”的校训和“自强、敬业、求实、创新”的广轻精神，为珠三角地区乃至全国输送数万名高素质高技能应用型人才。////办学条件好////学校现有广州和南海两个校区，其中广州校区定位为“大文科校区”，文科、艺术类专业面向广州现代服务业；南海校区成为“大工科校区”，工科专业面向珠江西岸高端制造业，校园总面积1700多亩，校舍建筑面积43万多平方米，其中教学科研实训用房近20万平方米，图书馆3万多平方米，学生公寓近16万平方米。固定资产总值15.5亿元，教学仪器设备总值2亿多元，学校图书馆拥有藏书近160万册，电子图书200多万册。网络信息点数2万多个，音视频电子资源1万多小时，学校校园无线网络全覆盖。建有校内实践教学基地近350个、校外实训实习基地900多个。////办学成果优异////学校是广东省唯一拥有7个省级工程技术开发中心的高职院校，是同时拥有省级协同发展中心及协同育人平台的两所高职院校之一，是全国第一批教育信息化试点单位、教育部现代学徒制试点单位、全国高校思政研究会高职高专专业委员会副会长单位（广东省会长单位）、全国跨境电商专业人才培养示范校、全国群众体育先进单位、全国高职“一校一品”示范单位、全国社会实践工作优秀单位、广东省依法治校示范校单位、广东省创新创业示范校单位、广东省安全文明校园示范校单位、广东省示范职业教育集团、广东省集团化办学单位、国防教育特色学校。学校立项“国家标杆党支部”1个，并先后获得全国高等职业院校全国服务贡献50强（连续两年）、全国高等职业院校实习管理50强、全国高等职业院校教学资源50强、全国高等职业院校学生管理50强、全国高等职业院校教学管理50强、全国高等职业院校育人成效50强、亚太职业院校影响力50强、全国示范性高职院校影响力排行榜30强、全国普通高校竞赛评估（高职）20强，全国高职院校思政工作创新优秀示范案例50强。全国高职院校创新创业示范校50强。2019年中国高职高专院校综合竞争力排行榜第9名。////多功能文化食堂、智能垃圾分类系统等创新性后勤改革领先全国。////师资队伍结构合理，业务水平高////学校现有教职工1200余人，其中高级职称教师400余人（二级教授9人），珠江学者9/人，“双师”素质教师70/0余人；国务院特殊津贴专家2人，全国模范教师2人，国家级教学名师2人，国家级教学团队2个，国家“万人计划”教学名师1人，全国技术能手2人，全国青年岗位能手1人，全国高校思想政治理论课教师影响力人物2人，全国轻工行业先进工作者1人，中国轻工职业教育教学名师1人，全国辅导员年度人物1名，广东省高校“千百十工程”国家级培养对象2人，南粤优秀教师11人，南粤优秀教育工作者4人，广东省“特支计划”教学名师、广东省教学名师、专业领军人才等名师专家近70人。建立了一个由企业一线工作的技术人员、能工巧匠、高级经理人等组成的优质兼职教师资源库，兼职教师与专业专任教师数之比达到1:1以上。学校在广东省高职院校教师队伍建设考核中连续三年排名第一。2019年全国高职院校教师教学发展指数排前十名。////教学成果丰硕////学校设有机电技术学院、食品与生物技术学院、轻化工技术学院、信息技术学院、汽车技术学院、生态环境技术学院、艺术设计学院、财贸学院、管理学院、应用外语学院、创业学院、马克思主义学院和继续教育学院，三个协同教学中心（工业机器人协同教学中心、现代信息技术与新工科协同教学中心、应用外语协同教学中心），设20个专业群、69个招生专业。2016年11月，学校成立创业学院，面向全体学生进行创新创业通识教育，面向精英学生进行创新创业定制培养。学校已建成国家示范性专业4个、央财“支持高等职业学校提升专业服务产业发展能力”项目经费支持专业2个、省级示范性专业3个、省级重点（建设）专业13个、省级品牌专业建设项目13个，建有国家级教学资源库1个、国家级精品课程10门、国家级精品资源共享课程9门、全国高校职业发展与就业指导示范课程1门、国家教指委精品课程22门、省级精品课程21门、省级优质课程2门，立项省级精品开放课程4/5门，其中已验收3门，在建省级专业资源库2个。2009年以来，学校共获得国家级优秀教学成果二等奖10项，行业教指会特等奖2个，省级优秀教学成果一等奖9项，省级优秀教学成果二等奖5项。////职教特色明显，人才培养质量高////学校是教育部现代学徒制试点单位，已立项国家级现代学徒制试点项目3项，省级现代学徒制试点项目/9项。学校积极构建职业教育“立交桥”，全面实施“纵向延伸，横向拓展”协同育人模式，开展了“3+2”中高衔接、“2+2”和“4+0”高本联培、“3+2”高本衔接、工程硕士培养等多种形式的协同培养，其中本科专业共1/3个，搭建起“中/高/本/硕”现代职业教育体系框架。连续多年，录取人数和录取分数线均位居省内同类院校前茅，文理类、艺术类高考录取分数线均高于本科省控线。毕业生深受用人单位欢迎，母校的满意度和薪资水平高于全国示范校平均水平，初次就业率高于98%，用人单位满意度99%以上。学生在各级各类技能大赛中获奖数量与质量节节攀升。近三年来，共获得国家级奖项500多个、省部级奖项1000余个。////产教融合，社会服务能力强////学校构建并不断完善政校行企协同促进产教融合长效机制，围绕高水平专业群建设，打造“一群一院一联盟”，搭建了广东轻工职教集团、轻工行业应用技术协同创新发展中心、南海职业教育政校行企协同创新联盟、广东省工业互联网产教联盟、粤港澳数字创意产教联盟、粤港澳跨境电商产教联盟、广东酒店职业教育联盟、全国精准营养食品与果蔬加工产教联盟、国家中小微企业知识产权培训基地等产学研创新、科技研发与转化平台，与华为等世界500强知名企业合作成立了华为ICT学院、瀚蓝环境学院、白天鹅学院、雷诺钟表学院、许鸿飞国际文创学院等10个产业学院，实现校企精准对接，产教深度融合，精准育人。近五年，获国家级科技项目4项、省级36项；国家级、省级科技奖励13项；面向企业开展科技攻关项目200余项。申报专利近430项，授权近300项，专利申请量连续多年位列广州地区高校（含本科）前十名。////坚持对外合作，国际化办学水平高////学校积极广泛开展对外交流与合作，已与国（境）外多所高等院校建立了合作关系，在引进智力与优质教育资源、人才培养、合作办学、汉语言培训等方面开展了实质性的合作。累计已招收来自30多个国家的留学生4/00余名。2017年，学校牵头组建广东省“一带一路”职业教育联盟，输出广轻职教模式，服务“一带一路”沿线国家及地区，国际化办学呈现新气象。////构建终身教育体系，服务广东经济社会////依托“国家中小微企业知识产权培训（南海）基地”“广东轻工培训中心”“职教师资优质省级基地”“广东省专业技术人员继续教育基地”“广东省职业技能鉴定所”等国家级和省级平台，并设有专门和专业性培训机构30多个，面向社会、社区和产业、行业积极开展各级各类培训服务，年培训量超15万人天；与本科院校进行网络远程教育及自学考试合作，并在深圳、佛山、珠海、韶关等地设立12个校外专科继续教育教学点，学校各类学历继续教育在读人数4000余人。////“十三五”期间，学校将遵循“三大一强”院校治理理念，围绕“创新强校工程”及一流高职院校建设，努力把学校建成“国内一流、国际知名”国家优质高职院校，成为高职院校治理的标准与典范，成为高素质技术技能型人才培养的典范。 | AB17: 学校创建于1933年，原名广东省立第一职业学校，学校数易其名，先后更名为广东省立广州农工业职业学校、广东省立广州工业职业学校、广东省立广州高级工业职业学校、广东省广州高级工业技术学校、广东省轻工业学校、广东轻工业学院、广州轻工业学校等 ，1959～1963年和1978～1983年曾开办本科职业教育。 1999年，学校升格为广东轻工职业技术学院。 2020年，广东省轻工职业技术学校、广东省石油化工职业技术学校并入。 2024年6月，教育部正式同意在广东轻工职业技术学院的基础上设立广东轻工职业技术大学。 9月3日，广东轻工职业技术大学正式揭牌。 | AC17: http://www.gdqy.edu.cn/ | AD17: http://gdqyzs.jysd.com/ | AE17: 020/61230198 | AF17: 广州市新港西路152号 | AG17: / | AH17: 369 | AI17: https://baike.baidu.com/item/%E5%B9%BF%E4%B8%9C%E8%BD%BB%E5%B7%A5%E8%81%8C%E4%B8%9A%E6%8A%80%E6%9C%AF%E5%A4%A7%E5%AD%A6 | AJ17: https://gaokao.chsi.com.cn/zsgs/zhangcheng/listZszc//schId/620.dhtml | AK17: /
A18: 13 | B18: =C18 -> 0 | D18: 依据学考 | E18: 11113 | F18: 深圳职业技术大学 | G18: 605 | H18: 95 | I18: 114 | J18: 95 | K18: 114 | L18: 387 | M18: 398 | N18: 12684 | O18: 11322 | P18: =IFERROR(AVERAGE(L18:M18),"/") -> 392.5 | Q18: =IFERROR(AVERAGE(N18:O18),"/") -> 12003 | R18: 广东省 | S18: 深圳市 | T18: 广东省 | U18: 职业本科 | V18: 广东省 | W18: 公办 | X18: 一线城市 | Y18: 省属/双高计划/高水平学校建设单位/国家级示范 | Z18: 第一类高水平学校A档示范高职 | AA18: 深圳职业技术学院1993年创建，是国内最早独立举办高等职业技术教育的院校之一。建校以来，深职院人艰苦创业，开拓进取，不断创新教育教学理念、办学体制机制和人才培养模式，创造了中国高职教育的多个第一。学校依托珠三角产业发展，秉承深圳特区改革创新精神，坚持把立德树人作为学校教育的根本任务，立足于职业教育产教融合的办学特色，各项事业取得骄人成绩，被誉为中国高职教育的“一面旗帜”。为紧密契合“中国制造2025”等国家重大战略和深圳创新驱动发展战略，学校在2016年底召开的第三次党代会工作报告中提出“三个服务、五个定位、一个率先”的战略发展目标，始终坚持为党和国家服务、为深圳经济社会发展服务、为学生健康成长成才服务，努力成为职业教育创新发展的先行者、复合式创新型高素质技术技能人才的摇篮、企业家的摇篮、深圳中小微企业技术研发中心、深圳市民终身教育学校与中国职业教育师资培训重要基地，率先建成中国特色、世界一流职业院校，为世界职业教育发展贡献“深圳模式”。////学校现有留仙洞、西丽湖、官龙山、华侨城、凤凰山五个校区，校园总面积212万平方米，学校产权校舍建筑面积57.34万平方米，其中教室10.75万平方米，图书馆5万平方米，体育馆3.34万平方米，实训实习场所10.14万平方米。现有固定资产总值23.66亿元，其中教学仪器设备总值9.58亿元,教学用计算机14525台。图书馆藏有纸质图书261.2万册，电子图书130万册，电子期刊60.54万册，中外文数据库46个，音视频16.07万小时。////全校现有教职员工2380人，其中专任教师1243人，正高217人，副高657人，博士408人，享受国务院特殊津贴专家2名，珠江学者5人、海外高层次人才25人、国家“万人计划”教学名师1人、国家级教学名师3人、省级教学名师8人、国家特支计划教师1人、广东特支计划教学名师4人。学校拥有教育部首批黄大年式教师团队1个；引进美国霍夫曼诺奖团队等一批重量级团队，成立霍夫曼先进材料研究院、智能科学与工程研究院、智能制造研究院、新时代中国职业教育研究院、社会与经济发展研究院等高端平台，为珠三角产业发展提供有力支撑。////学校设有电子与通信工程学院等17个二级学院和体育部、工业中心、国际教育部等教学单位，招生专业80个。全校普通全日制在校生22750人，其中港澳台留学生79人，四年制高职生284人，应用型本科生292人，外国留学生127人。自办专科教育在校生3536人。国家级教学成果奖14项，国家职业教育专业教学资源库3项，国家重点支持建设示范专业12个，中央财政支持实训基地9个，国家级精品教材12部，国家精品课程53门，国家级精品资源共享课43门。////学校一直把人才培养作为中心工作，以培养适应智能时代需要的复合式创新型高素质技术技能人才为目标，更新教育教学理念，探索实施以学生学习成效为导向的OBE（Outcome/Based/Education）人才培养模式改革，深入推进产教融合、职普融合、理实融合、技术与文化融合、教育与生活融合、现代信息技术与教学融合等“六个融合”，提升学生的就业能力、职业生涯拓展能力和幸福生活创造能力。瞄准未来社会和经济发展，紧贴深圳四大支柱产业和新兴产业布局专业，打造品牌专业，与华为、ARM、阿里巴巴、平安、比亚迪、裕同、天健等一流企业紧密合作，共建华为信息与网络技术学院、ARM智能硬件学院、阿里巴巴数字贸易学院、平安金融科技学院、比亚迪应用技术学院、裕同数字图文学院、天健建工学院等7所特色产业学院，校企共同制定专业标准、共同开发课程、共建师资团队、共同培养技术技能人才，在服务一流企业中成就自身一流。开设专业文化课程，大力培育工匠精神，厚植工匠文化，全面推进职业院校文化育人。学校已累计培养11万余名全日制专科毕业生，毕业生初次就业率始终保持在96%以上，多项人才培养质量指标位居全国高职院校前列，深受用人单位欢迎。其中，238人次获CCIE证书，13人获RHCA证书，57人获OCM证书，163人获HCIE证书，13人获RHCE证书。////学校探索实施创新创业教育改革，以“五维一体”的创新创业教育理念（重心在“教育”、路径在“分层”、目标在“万众”、核心在“创新”、关键在“实践”）为引领，打造深圳中小微企业技术研发中心、全球技术技能人才创新创业教育中心，以及创新型人才和企业家培养的成长摇篮。通过系统设计、科学构建，协同推进从启蒙教育、预科教育、专门教育到指导创办企业的进阶式创业人才培养体系，搭建“四会两赛三联盟”双创交流平台和“创新型社团—创客中心—学生创意创业园”双创实践平台，逐步完善跨界融合、产品试制、创业孵化、创业投资的双创服务体系，取得良好的社会效益。近年来获评首批全国创新创业典型经验高校、全国深化创新创业教育改革示范高校、广东省大众创业万众创新示范基地、深圳首批十大创新创业基地等。近四届毕业生毕业一年内自主创业比例达到5%，毕业三年后创业比例12.7%。////学校坚持以“产学研用”一体化的科研导向，重视技术转移和科技成果转化。近年来，学校不断深化科研体制机制改革，大力加强与政府职能部门以及行业企业合作，组建成立了应用技术研发院、文化创意产品研发院、经济与社会发展研究院等三大综合性研发平台，建成43个市区级以上科研平台,抢抓产业发展新机遇，服务地方经济社会和中小企业发展。全校累计承担各级各类科研课题5196项，其中国家级项目84项,年度新增国家自然科学基金项目10项。科研经费到账总经费达到8.06亿元，其中技术转移（横向科研）项目到账经费2.98亿元；出版各类学术专著226部、编著、译著和作品集共199部，61项科研成果获部、省、市级奖励；获国家专利授权1726项，软件著作权登记1136件，发明专利345项。主导或参与制定国际、国家、行业标准74项。////学校重视社会服务，发挥品牌优势，致力于推动现代职业教育培训体系和学习型社会建设。做好高水平师资培训，打造世界级的职业教育培训中心；做好职业培训、职业技能鉴定及职业资格认证工作，服务好地方经济发展需要；联合社区街道组建社区学院、特色学院，开展针对社区居民的健康、养老、旅游等培训项目，服务好地方社会发展需要；以办学理念和教学模式输出为主要内容，构建“理念—教学—师资—管理”四位一体的精准帮扶体系，服务好对口支援地区和院校的发展。全年重点对口帮扶11所职业院校，累计对口支援西藏、新疆、贵州等地11个省、自治区的200余所职业院校。全年举办33个全国高职高专师资培训班，累计为全国680余所职业院校培训骨干教师1.2万人次，连续5年名列全国第一。年均开展各类培训、职业技能鉴定与资格认证12万人次。组建西丽社区学院、大鹏旅游学院等社区学院，与社区共同培养技能人才，打造开放办学、产教融合的“职教特区”；选派核心团队建设管理吉安职业技术学院，开创了特区与老区携手共同发展职业教育的典范。////学校紧扣国家发展战略，加快国际化办学步伐，充分利用区域与自身优势，深化国际教育交流与合作。建校以来，已累计与32个国家和地区的162所高校和教育机构建立了友好合作关系，包括英国、德国、法国、美国等发达国家以及新西兰、马来西亚、保加利亚、土耳其、波兰、匈牙利、缅甸、老挝等14个“一带一路”沿线国家。双方在学生交换、课程合作、科研合作、短期研修等领域开展了全方位、多层次、形式多样的教师和学生国际交流活动，取得了丰硕的成果。近年来，我校年均接待境外来访师生及外宾108批次，658人次；我校赴境外参加国际交流的师生52批次，276人次。开办了国际商务（中澳）、金融管理（中澳）、物流管理（中美）和软件技术（中美）4个中外合作办学专业；与香港专业教育学院黄克竞分校合办电气服务工程高级文凭合作课程，毕业生获得深港两地毕业资格，并成为首批获得招收海外留学生资质的高职院校和首个获批面向港澳台自主招生的高职院校。学校还联合中兴、招商港口等一批世界一流企业“走出去”，服务国家“一带一路”倡议。在马来西亚马六甲应用技术大学设立职业教育与培训中心，推动马来西亚全国各类职业院校全面对接深职院标准。依托在保加利亚成立的职业教育与培训中心，输出学校专业标准。应邀为柬埔寨、蒙古等国家职业教育代表团举行专题培训班，输出职业教育经验。加强与职业教育国际组织的合作，成为联合国教科文组织国际职教全球联系中心之一，获批成立联合国教科文组织职业教育计划亚非研究与培训中心。在提高学校国际知名度与影响力的同时，为推动中国职业教育与语言文化走出去做出了积极贡献。////学校办学成绩显著。2001年首家通过国家示范性高职院校实践教学基地优秀评估，2009年通过国家示范性高等职业院校建设项目验收，成为我国高等职业教育领域首批国家级示范校。近年来，学校先后荣获“全国文明单位”、“全国职业教育先进单位”、“全国一流高职院校建设单位”、“首批全国创新创业典型经验高校”、“全国高校毕业生就业工作先进集体”、“中国十大最具就业力高职院校”、“全国毕业生就业工作典型经验高校”、“全国职业院校就业竞争力示范校”、“中国十大创新型高职院校”、“黄炎培优秀学校奖”、“全国高校实践育人创新创业基地”“广东省文明单位”、“广东省职业技术教育工作先进集体”、“广东省首批大学生创新创业教育示范学校”、“广东省一流高职院校建设单位”“深圳市创新创业基地”等荣誉称号。 | AB18: 深圳职业技术大学于1993年创建，前身为深圳职业技术学院，是中国国内最早独立举办高等职业技术教育的院校之一。2000年、2004年原深圳市职业技术学校、深圳市卫生学校分别并入深圳职业技术学院。2006年深圳职业技术学院被确定为“国家示范性高等职业院校建设计划”首批立项建设院校，2009年学校顺利通过验收成为首批国家示范性高等职业院校。2023年6月，教育部发文同意以深圳职业技术学院为基础整合资源设立深圳职业技术大学，同时撤销深圳职业技术学院的建制。 | AC18: http://www.szpt.edu.cn/ | AD18: https://zhaosheng.szpt.edu.cn/ | AE18: 0755/26731715、26731216 | AF18: 深圳市南山区西丽街道留仙大道7098号 | AG18: https://www.720yun.com/t/d8vksm7e0d9 | AH18: 158 | AI18: https://baike.baidu.com/item/%E6%B7%B1%E5%9C%B3%E8%81%8C%E4%B8%9A%E6%8A%80%E6%9C%AF%E5%A4%A7%E5%AD%A6 | AJ18: https://gaokao.chsi.com.cn/zsgs/zhangcheng/listZszc//schId/734.dhtml | AK18: /
A19: 14 | B19: =C19 -> 0 | D19: 依据学考 | E19: 12957 | F19: 深圳信息职业技术大学 | G19: 603 | H19: 544 | I19: 409 | J19: 545 | K19: 410 | L19: 386 | M19: 398 | N19: 12874 | O19: 11510 | P19: =IFERROR(AVERAGE(L19:M19),"/") -> 392 | Q19: =IFERROR(AVERAGE(N19:O19),"/") -> 12192 | R19: 广东省 | S19: 深圳市 | T19: 广东省 | U19: 职业本科 | V19: 广东省 | W19: 公办 | X19: 一线城市 | Y19: 双高计划/高水平学校建设单位/国家级骨干/现代学徒制试点学院 | Z19: 第二类高水平学校B档骨干高职现代学徒 | AA19: 深圳信息职业技术学院创办于2002年4月，是经广东省人民政府批准、教育部备案，由深圳市人民政府举办的公办全日制高等院校。//学校现为国家示范（骨干）高职院校、国家示范性软件职业技术学院、教育部“中德职教汽车机电合作项目”试点院校，现拥有3个国家级高等职业教育专业教学资源库（含1个备选项目）。学校拥有现代化、生态型、信息化的校园，占地92.6万平方米（1389亩），建筑面积58.86万平方米。学校现有教学科研仪器设备总值为36786.36万元，图书馆藏书131.33万册。//学校对接深圳支柱产业，打造信息技术特色，共设软件学院、电子与通信学院、计算机学院、数字媒体学院、智能制造与装备学院、交通与环境学院、管理学院、财经学院、应用外语学院、中德学院、马克思主义学院、继续教育学院、创新创业学院、创新教育研究院、公共课教学部、体育部、信息技术研究所等14院2部1所；开设信息类为主的专业44个。现有国家骨干校重点建设专业4个，国家高等职业学校提升专业服务产业发展能力建设专业2个，全国职业院校示范专业点2个，国家高等职业教育教学资源库建设项目3个（含1个备选项目），广东省示范性专业4个，省级重点建设专业6个，省级品牌专业11个；国家级精品资源共享课7门、省级精品资源共享课（含精品在线开放课）38门、省级思想政治理论优质建设课程2门。//学校现有教职工796人，在590位专任教师中，副高及以上职称教师301人，其中，博士、博士后275人，“双师素质”教师九成。目前，学校拥有国家级教学团队1个，获国家级教学名师奖1人，获全国五一劳动奖章1人，国家万人计划教学名师1名，广东省教学名师奖3人，广东省“特支计划”教学名师3人，省级教学团队7个，南粤优秀教师7人，广东省“千百十人才培养工程”省级培养对象6人，广东省“珠江学者”特聘教授4人，深圳市“鹏城学者”特聘教授3人，深圳市政府特殊津贴1人，黄炎培职业教育杰出教师奖1人，深圳市高层次专业人才地方级领军人才9名，后备级领军人才21人，博士后创新实践基地在站博士后3人。//学校坚持科研引领、教研创新、突出应用、服务社会。已主持国家自然科学基金等国家级项目26项、省市级科研项目517项，教研课题国家级6项、省市级49项，深圳市首批教育科研专家工作室1个。获得国家级高等学校教学成果一等奖1项、二等奖2项，省级教学成果一等奖6项、二等奖4项，广东省科学技术二等奖2项、三等奖2项，国家教师科研基金“十一五”规划重点课题科研成果一等奖1项，深圳市科技进步奖2项，深圳市科技创新奖2项，深圳市科学技术奖自然科学奖1项，深圳市哲学社会科学优秀成果奖7项，中国人工智能学会进步奖二等奖；拥有发明专利62项，实用新型专利203项，外观设计专利8项。//学校坚持校企合作办学，积极推进产教融合协同育人，创新合作办学机制，探索校企合作模式，在校内构建了“三会两办”的办学机制，并打造了“学院+行业企业”的校企合作模式。学校用2万平米实训场地，引企入校，合作共建实践教学基地、科技创新平台等，基地目前建有2个省级创新平台、1个先进土木研究中心、1个智能制造实训中心、5个校级协同创新中心等创新载体。学校有国家级高等职业教育实训基地2个，省级高等职业教育实训基地11个，省级公共实训中心1个，省级大学生校外实践教学基地12个，深圳市高职教育校外公共实训基地33个。//学校建构高素质高技能人才培养机制，不断提升高就业率、高满意度办学效益。现有全日制在校生15468人，学校坚持产教融合、校企合作、因材施教、特色发展。近三年，学生参加专业技能竞赛共获国家级奖项137个，省级二等奖以上315个。毕业生“下得去、留得住、用得上、干得好”，毕业生总体就业率均在98%以上。毕业生被华为、腾讯、深圳地铁、中国联通等著名企业录用，产生了被《华尔街日报》报道为“中国最年轻90后千万富豪”丁仕源、拥有8家公司的速运邦邦CEO陈家良等创业典型。//学校积极引进国际先进教学资源，不断形成国际化办学特色。2012年，学校成为教育部“中德职教汽车机电合作项目”试点院校；2013年11月学校与西双版纳职业技术学院正式签署合作协议共建“深圳信息/西双版纳国际留学生基地”/并揭牌；2016年9月，由深圳市教育局和德国巴伐利亚州文教部推动，我校与德国巴伐利亚州帕绍技术学校、兰茨胡特应用技术大学合作创办中德学院；2018年5月，学校与芬兰于韦斯屈莱应用科技大学签订战略合作协议全面启动两校战略合作项目；此外，学校还与加拿大谢尔丹理工学院、韩国京畿大学、台湾地区朝阳科技大学、树德科技大学、龙华科技大学、台北城市科技大学、亚太创意技术学院等26所高校开展了师生交流、合作科研等项目。//学校跨越发展，已跻身全国高职院校“第一方阵”。2004年，学校成为“国家示范性软件职业技术学院”建设院校；2007年，以优异成绩通过教育部人才培养工作水平评估；2010年，成为国家骨干高职院校建设单位；2011年，获国家高等职业教育网络技术专业共享型教学资源库建设立项；2012年，入选教育部“中德职教汽车机电合作项目”试点院校；2014年获国家高等职业教育数字媒体专业群教学资源库立项；2015年，深圳市人力资源与社会保障局同意批准我校设立博士后创新实践基地；2016年，学校国家骨干校建设项目以“优秀”等级通过国家验收、获广东省“一流校”建设立项、学校“2188创客空间”被国家科学技术部认定为国家级众创空间，2016年学校又成功召开了第二次党代会，进一步确立了“全力打造有特色国际化一流职业院校”的奋斗目标。//青春深信成新锐，勇向潮头唱大风。学校将继续开拓奋进，勇于不断创新，努力把学校打造成有特色国际化一流职业院校。 | AB19: 学校原名为深圳信息职业技术学院，于2002年4月由深圳教育学院、深圳市工业学校、深圳市财经学校三所学校合并组建；2011年9月，学校从深圳市罗湖区迁至深圳市龙岗区。2012年，学校入选教育部“中德职教汽车机电合作项目”试点院校。2021年，学校获批设立广东省博士工作站。2025年6月，教育部发函广东省，同意以深圳信息职业技术学院为基础设立深圳信息职业技术大学，同时撤销深圳信息职业技术学院的建制。2026年1月，深圳信息职业技术大学正式成立。 | AC19: http://www.sziit.com.cn/ | AD19: http://zhaob.sziit.edu.cn/index.htm | AE19: 075589226360、075589226361 | AF19: 深圳市龙岗区龙翔大道2188号 | AG19: https://www.720yun.com/t/d4528mpguus | AH19: 184 | AI19: https://baike.baidu.com/item/%E6%B7%B1%E5%9C%B3%E4%BF%A1%E6%81%AF%E8%81%8C%E4%B8%9A%E6%8A%80%E6%9C%AF%E5%AD%A6%E9%99%A2 | AJ19: https://gaokao.chsi.com.cn/zsgs/zhangcheng/listZszc//schId/1429.dhtml | AK19: /
A20: 15 | B20: =C20 -> 0 | D20: 依据学考 | E20: 12957 | F20: 深圳信息职业技术大学 | G20: 604 | H20: 541 | I20: 786 | J20: 541 | K20: 786 | L20: 384 | M20: 399 | N20: 15438 | O20: 10324 | P20: =IFERROR(AVERAGE(L20:M20),"/") -> 391.5 | Q20: =IFERROR(AVERAGE(N20:O20),"/") -> 12881 | R20: 广东省 | S20: 深圳市 | T20: 广东省 | U20: 职业本科 | V20: 广东省 | W20: 公办 | X20: 一线城市 | Y20: 双高计划/高水平学校建设单位/国家级骨干/现代学徒制试点学院 | Z20: 第二类高水平学校B档骨干高职现代学徒 | AA20: 深圳信息职业技术学院创办于2002年4月，是经广东省人民政府批准、教育部备案，由深圳市人民政府举办的公办全日制高等院校。//学校现为国家示范（骨干）高职院校、国家示范性软件职业技术学院、教育部“中德职教汽车机电合作项目”试点院校，现拥有3个国家级高等职业教育专业教学资源库（含1个备选项目）。学校拥有现代化、生态型、信息化的校园，占地92.6万平方米（1389亩），建筑面积58.86万平方米。学校现有教学科研仪器设备总值为36786.36万元，图书馆藏书131.33万册。//学校对接深圳支柱产业，打造信息技术特色，共设软件学院、电子与通信学院、计算机学院、数字媒体学院、智能制造与装备学院、交通与环境学院、管理学院、财经学院、应用外语学院、中德学院、马克思主义学院、继续教育学院、创新创业学院、创新教育研究院、公共课教学部、体育部、信息技术研究所等14院2部1所；开设信息类为主的专业44个。现有国家骨干校重点建设专业4个，国家高等职业学校提升专业服务产业发展能力建设专业2个，全国职业院校示范专业点2个，国家高等职业教育教学资源库建设项目3个（含1个备选项目），广东省示范性专业4个，省级重点建设专业6个，省级品牌专业11个；国家级精品资源共享课7门、省级精品资源共享课（含精品在线开放课）38门、省级思想政治理论优质建设课程2门。//学校现有教职工796人，在590位专任教师中，副高及以上职称教师301人，其中，博士、博士后275人，“双师素质”教师九成。目前，学校拥有国家级教学团队1个，获国家级教学名师奖1人，获全国五一劳动奖章1人，国家万人计划教学名师1名，广东省教学名师奖3人，广东省“特支计划”教学名师3人，省级教学团队7个，南粤优秀教师7人，广东省“千百十人才培养工程”省级培养对象6人，广东省“珠江学者”特聘教授4人，深圳市“鹏城学者”特聘教授3人，深圳市政府特殊津贴1人，黄炎培职业教育杰出教师奖1人，深圳市高层次专业人才地方级领军人才9名，后备级领军人才21人，博士后创新实践基地在站博士后3人。//学校坚持科研引领、教研创新、突出应用、服务社会。已主持国家自然科学基金等国家级项目26项、省市级科研项目517项，教研课题国家级6项、省市级49项，深圳市首批教育科研专家工作室1个。获得国家级高等学校教学成果一等奖1项、二等奖2项，省级教学成果一等奖6项、二等奖4项，广东省科学技术二等奖2项、三等奖2项，国家教师科研基金“十一五”规划重点课题科研成果一等奖1项，深圳市科技进步奖2项，深圳市科技创新奖2项，深圳市科学技术奖自然科学奖1项，深圳市哲学社会科学优秀成果奖7项，中国人工智能学会进步奖二等奖；拥有发明专利62项，实用新型专利203项，外观设计专利8项。//学校坚持校企合作办学，积极推进产教融合协同育人，创新合作办学机制，探索校企合作模式，在校内构建了“三会两办”的办学机制，并打造了“学院+行业企业”的校企合作模式。学校用2万平米实训场地，引企入校，合作共建实践教学基地、科技创新平台等，基地目前建有2个省级创新平台、1个先进土木研究中心、1个智能制造实训中心、5个校级协同创新中心等创新载体。学校有国家级高等职业教育实训基地2个，省级高等职业教育实训基地11个，省级公共实训中心1个，省级大学生校外实践教学基地12个，深圳市高职教育校外公共实训基地33个。//学校建构高素质高技能人才培养机制，不断提升高就业率、高满意度办学效益。现有全日制在校生15468人，学校坚持产教融合、校企合作、因材施教、特色发展。近三年，学生参加专业技能竞赛共获国家级奖项137个，省级二等奖以上315个。毕业生“下得去、留得住、用得上、干得好”，毕业生总体就业率均在98%以上。毕业生被华为、腾讯、深圳地铁、中国联通等著名企业录用，产生了被《华尔街日报》报道为“中国最年轻90后千万富豪”丁仕源、拥有8家公司的速运邦邦CEO陈家良等创业典型。//学校积极引进国际先进教学资源，不断形成国际化办学特色。2012年，学校成为教育部“中德职教汽车机电合作项目”试点院校；2013年11月学校与西双版纳职业技术学院正式签署合作协议共建“深圳信息/西双版纳国际留学生基地”/并揭牌；2016年9月，由深圳市教育局和德国巴伐利亚州文教部推动，我校与德国巴伐利亚州帕绍技术学校、兰茨胡特应用技术大学合作创办中德学院；2018年5月，学校与芬兰于韦斯屈莱应用科技大学签订战略合作协议全面启动两校战略合作项目；此外，学校还与加拿大谢尔丹理工学院、韩国京畿大学、台湾地区朝阳科技大学、树德科技大学、龙华科技大学、台北城市科技大学、亚太创意技术学院等26所高校开展了师生交流、合作科研等项目。//学校跨越发展，已跻身全国高职院校“第一方阵”。2004年，学校成为“国家示范性软件职业技术学院”建设院校；2007年，以优异成绩通过教育部人才培养工作水平评估；2010年，成为国家骨干高职院校建设单位；2011年，获国家高等职业教育网络技术专业共享型教学资源库建设立项；2012年，入选教育部“中德职教汽车机电合作项目”试点院校；2014年获国家高等职业教育数字媒体专业群教学资源库立项；2015年，深圳市人力资源与社会保障局同意批准我校设立博士后创新实践基地；2016年，学校国家骨干校建设项目以“优秀”等级通过国家验收、获广东省“一流校”建设立项、学校“2188创客空间”被国家科学技术部认定为国家级众创空间，2016年学校又成功召开了第二次党代会，进一步确立了“全力打造有特色国际化一流职业院校”的奋斗目标。//青春深信成新锐，勇向潮头唱大风。学校将继续开拓奋进，勇于不断创新，努力把学校打造成有特色国际化一流职业院校。 | AB20: 学校原名为深圳信息职业技术学院，于2002年4月由深圳教育学院、深圳市工业学校、深圳市财经学校三所学校合并组建；2011年9月，学校从深圳市罗湖区迁至深圳市龙岗区。2012年，学校入选教育部“中德职教汽车机电合作项目”试点院校。2021年，学校获批设立广东省博士工作站。2025年6月，教育部发函广东省，同意以深圳信息职业技术学院为基础设立深圳信息职业技术大学，同时撤销深圳信息职业技术学院的建制。2026年1月，深圳信息职业技术大学正式成立。 | AC20: http://www.sziit.com.cn/ | AD20: http://zhaob.sziit.edu.cn/index.htm | AE20: 075589226360、075589226361 | AF20: 深圳市龙岗区龙翔大道2188号 | AG20: https://www.720yun.com/t/d4528mpguus | AH20: 184 | AI20: https://baike.baidu.com/item/%E6%B7%B1%E5%9C%B3%E4%BF%A1%E6%81%AF%E8%81%8C%E4%B8%9A%E6%8A%80%E6%9C%AF%E5%AD%A6%E9%99%A2 | AJ20: https://gaokao.chsi.com.cn/zsgs/zhangcheng/listZszc//schId/1429.dhtml | AK20: /
A21: 16 | B21: =C21 -> 0 | D21: 依据学考 | E21: 11113 | F21: 深圳职业技术大学 | G21: 608 | H21: 63 | I21: 70 | J21: 63 | K21: 70 | L21: 384 | M21: 398 | N21: 14791 | O21: 11410 | P21: =IFERROR(AVERAGE(L21:M21),"/") -> 391 | Q21: =IFERROR(AVERAGE(N21:O21),"/") -> 13100.5 | R21: 广东省 | S21: 深圳市 | T21: 广东省 | U21: 职业本科 | V21: 广东省 | W21: 公办 | X21: 一线城市 | Y21: 省属/双高计划/高水平学校建设单位/国家级示范 | Z21: 第一类高水平学校A档示范高职 | AA21: 深圳职业技术学院1993年创建，是国内最早独立举办高等职业技术教育的院校之一。建校以来，深职院人艰苦创业，开拓进取，不断创新教育教学理念、办学体制机制和人才培养模式，创造了中国高职教育的多个第一。学校依托珠三角产业发展，秉承深圳特区改革创新精神，坚持把立德树人作为学校教育的根本任务，立足于职业教育产教融合的办学特色，各项事业取得骄人成绩，被誉为中国高职教育的“一面旗帜”。为紧密契合“中国制造2025”等国家重大战略和深圳创新驱动发展战略，学校在2016年底召开的第三次党代会工作报告中提出“三个服务、五个定位、一个率先”的战略发展目标，始终坚持为党和国家服务、为深圳经济社会发展服务、为学生健康成长成才服务，努力成为职业教育创新发展的先行者、复合式创新型高素质技术技能人才的摇篮、企业家的摇篮、深圳中小微企业技术研发中心、深圳市民终身教育学校与中国职业教育师资培训重要基地，率先建成中国特色、世界一流职业院校，为世界职业教育发展贡献“深圳模式”。////学校现有留仙洞、西丽湖、官龙山、华侨城、凤凰山五个校区，校园总面积212万平方米，学校产权校舍建筑面积57.34万平方米，其中教室10.75万平方米，图书馆5万平方米，体育馆3.34万平方米，实训实习场所10.14万平方米。现有固定资产总值23.66亿元，其中教学仪器设备总值9.58亿元,教学用计算机14525台。图书馆藏有纸质图书261.2万册，电子图书130万册，电子期刊60.54万册，中外文数据库46个，音视频16.07万小时。////全校现有教职员工2380人，其中专任教师1243人，正高217人，副高657人，博士408人，享受国务院特殊津贴专家2名，珠江学者5人、海外高层次人才25人、国家“万人计划”教学名师1人、国家级教学名师3人、省级教学名师8人、国家特支计划教师1人、广东特支计划教学名师4人。学校拥有教育部首批黄大年式教师团队1个；引进美国霍夫曼诺奖团队等一批重量级团队，成立霍夫曼先进材料研究院、智能科学与工程研究院、智能制造研究院、新时代中国职业教育研究院、社会与经济发展研究院等高端平台，为珠三角产业发展提供有力支撑。////学校设有电子与通信工程学院等17个二级学院和体育部、工业中心、国际教育部等教学单位，招生专业80个。全校普通全日制在校生22750人，其中港澳台留学生79人，四年制高职生284人，应用型本科生292人，外国留学生127人。自办专科教育在校生3536人。国家级教学成果奖14项，国家职业教育专业教学资源库3项，国家重点支持建设示范专业12个，中央财政支持实训基地9个，国家级精品教材12部，国家精品课程53门，国家级精品资源共享课43门。////学校一直把人才培养作为中心工作，以培养适应智能时代需要的复合式创新型高素质技术技能人才为目标，更新教育教学理念，探索实施以学生学习成效为导向的OBE（Outcome/Based/Education）人才培养模式改革，深入推进产教融合、职普融合、理实融合、技术与文化融合、教育与生活融合、现代信息技术与教学融合等“六个融合”，提升学生的就业能力、职业生涯拓展能力和幸福生活创造能力。瞄准未来社会和经济发展，紧贴深圳四大支柱产业和新兴产业布局专业，打造品牌专业，与华为、ARM、阿里巴巴、平安、比亚迪、裕同、天健等一流企业紧密合作，共建华为信息与网络技术学院、ARM智能硬件学院、阿里巴巴数字贸易学院、平安金融科技学院、比亚迪应用技术学院、裕同数字图文学院、天健建工学院等7所特色产业学院，校企共同制定专业标准、共同开发课程、共建师资团队、共同培养技术技能人才，在服务一流企业中成就自身一流。开设专业文化课程，大力培育工匠精神，厚植工匠文化，全面推进职业院校文化育人。学校已累计培养11万余名全日制专科毕业生，毕业生初次就业率始终保持在96%以上，多项人才培养质量指标位居全国高职院校前列，深受用人单位欢迎。其中，238人次获CCIE证书，13人获RHCA证书，57人获OCM证书，163人获HCIE证书，13人获RHCE证书。////学校探索实施创新创业教育改革，以“五维一体”的创新创业教育理念（重心在“教育”、路径在“分层”、目标在“万众”、核心在“创新”、关键在“实践”）为引领，打造深圳中小微企业技术研发中心、全球技术技能人才创新创业教育中心，以及创新型人才和企业家培养的成长摇篮。通过系统设计、科学构建，协同推进从启蒙教育、预科教育、专门教育到指导创办企业的进阶式创业人才培养体系，搭建“四会两赛三联盟”双创交流平台和“创新型社团—创客中心—学生创意创业园”双创实践平台，逐步完善跨界融合、产品试制、创业孵化、创业投资的双创服务体系，取得良好的社会效益。近年来获评首批全国创新创业典型经验高校、全国深化创新创业教育改革示范高校、广东省大众创业万众创新示范基地、深圳首批十大创新创业基地等。近四届毕业生毕业一年内自主创业比例达到5%，毕业三年后创业比例12.7%。////学校坚持以“产学研用”一体化的科研导向，重视技术转移和科技成果转化。近年来，学校不断深化科研体制机制改革，大力加强与政府职能部门以及行业企业合作，组建成立了应用技术研发院、文化创意产品研发院、经济与社会发展研究院等三大综合性研发平台，建成43个市区级以上科研平台,抢抓产业发展新机遇，服务地方经济社会和中小企业发展。全校累计承担各级各类科研课题5196项，其中国家级项目84项,年度新增国家自然科学基金项目10项。科研经费到账总经费达到8.06亿元，其中技术转移（横向科研）项目到账经费2.98亿元；出版各类学术专著226部、编著、译著和作品集共199部，61项科研成果获部、省、市级奖励；获国家专利授权1726项，软件著作权登记1136件，发明专利345项。主导或参与制定国际、国家、行业标准74项。////学校重视社会服务，发挥品牌优势，致力于推动现代职业教育培训体系和学习型社会建设。做好高水平师资培训，打造世界级的职业教育培训中心；做好职业培训、职业技能鉴定及职业资格认证工作，服务好地方经济发展需要；联合社区街道组建社区学院、特色学院，开展针对社区居民的健康、养老、旅游等培训项目，服务好地方社会发展需要；以办学理念和教学模式输出为主要内容，构建“理念—教学—师资—管理”四位一体的精准帮扶体系，服务好对口支援地区和院校的发展。全年重点对口帮扶11所职业院校，累计对口支援西藏、新疆、贵州等地11个省、自治区的200余所职业院校。全年举办33个全国高职高专师资培训班，累计为全国680余所职业院校培训骨干教师1.2万人次，连续5年名列全国第一。年均开展各类培训、职业技能鉴定与资格认证12万人次。组建西丽社区学院、大鹏旅游学院等社区学院，与社区共同培养技能人才，打造开放办学、产教融合的“职教特区”；选派核心团队建设管理吉安职业技术学院，开创了特区与老区携手共同发展职业教育的典范。////学校紧扣国家发展战略，加快国际化办学步伐，充分利用区域与自身优势，深化国际教育交流与合作。建校以来，已累计与32个国家和地区的162所高校和教育机构建立了友好合作关系，包括英国、德国、法国、美国等发达国家以及新西兰、马来西亚、保加利亚、土耳其、波兰、匈牙利、缅甸、老挝等14个“一带一路”沿线国家。双方在学生交换、课程合作、科研合作、短期研修等领域开展了全方位、多层次、形式多样的教师和学生国际交流活动，取得了丰硕的成果。近年来，我校年均接待境外来访师生及外宾108批次，658人次；我校赴境外参加国际交流的师生52批次，276人次。开办了国际商务（中澳）、金融管理（中澳）、物流管理（中美）和软件技术（中美）4个中外合作办学专业；与香港专业教育学院黄克竞分校合办电气服务工程高级文凭合作课程，毕业生获得深港两地毕业资格，并成为首批获得招收海外留学生资质的高职院校和首个获批面向港澳台自主招生的高职院校。学校还联合中兴、招商港口等一批世界一流企业“走出去”，服务国家“一带一路”倡议。在马来西亚马六甲应用技术大学设立职业教育与培训中心，推动马来西亚全国各类职业院校全面对接深职院标准。依托在保加利亚成立的职业教育与培训中心，输出学校专业标准。应邀为柬埔寨、蒙古等国家职业教育代表团举行专题培训班，输出职业教育经验。加强与职业教育国际组织的合作，成为联合国教科文组织国际职教全球联系中心之一，获批成立联合国教科文组织职业教育计划亚非研究与培训中心。在提高学校国际知名度与影响力的同时，为推动中国职业教育与语言文化走出去做出了积极贡献。////学校办学成绩显著。2001年首家通过国家示范性高职院校实践教学基地优秀评估，2009年通过国家示范性高等职业院校建设项目验收，成为我国高等职业教育领域首批国家级示范校。近年来，学校先后荣获“全国文明单位”、“全国职业教育先进单位”、“全国一流高职院校建设单位”、“首批全国创新创业典型经验高校”、“全国高校毕业生就业工作先进集体”、“中国十大最具就业力高职院校”、“全国毕业生就业工作典型经验高校”、“全国职业院校就业竞争力示范校”、“中国十大创新型高职院校”、“黄炎培优秀学校奖”、“全国高校实践育人创新创业基地”“广东省文明单位”、“广东省职业技术教育工作先进集体”、“广东省首批大学生创新创业教育示范学校”、“广东省一流高职院校建设单位”“深圳市创新创业基地”等荣誉称号。 | AB21: 深圳职业技术大学于1993年创建，前身为深圳职业技术学院，是中国国内最早独立举办高等职业技术教育的院校之一。2000年、2004年原深圳市职业技术学校、深圳市卫生学校分别并入深圳职业技术学院。2006年深圳职业技术学院被确定为“国家示范性高等职业院校建设计划”首批立项建设院校，2009年学校顺利通过验收成为首批国家示范性高等职业院校。2023年6月，教育部发文同意以深圳职业技术学院为基础整合资源设立深圳职业技术大学，同时撤销深圳职业技术学院的建制。 | AC21: http://www.szpt.edu.cn/ | AD21: https://zhaosheng.szpt.edu.cn/ | AE21: 0755/26731715、26731216 | AF21: 深圳市南山区西丽街道留仙大道7098号 | AG21: https://www.720yun.com/t/d8vksm7e0d9 | AH21: 158 | AI21: https://baike.baidu.com/item/%E6%B7%B1%E5%9C%B3%E8%81%8C%E4%B8%9A%E6%8A%80%E6%9C%AF%E5%A4%A7%E5%AD%A6 | AJ21: https://gaokao.chsi.com.cn/zsgs/zhangcheng/listZszc//schId/734.dhtml | AK21: /
A22: 17 | B22: =C22 -> 0 | D22: 依据学考 | E22: 14845 | F22: 深圳城市职业学院 | G22: 601 | H22: 19 | I22: / | J22: 19 | K22: / | L22: 386 | M22: / | N22: 13137 | O22: / | P22: =IFERROR(AVERAGE(L22:M22),"/") -> 386 | Q22: =IFERROR(AVERAGE(N22:O22),"/") -> 13137 | R22: 广东省 | S22: 深圳市 | T22: 广东省 | U22: 专科（高职） | V22: 广东省 | W22: 公办 | X22: 一线城市 | Y22: / | Z22: / | AA22: 深圳城市职业学院是由深圳市人民政府举办，经广东省人民政府批准、教育部备案，以深圳技师学院为基础设立的公办全日制普通高等职业院校。2024年首批5个专业招生（夏季高考生）。/学校位于深圳市龙岗区中心城，占地555亩，现有中德智造学院、设计学院、信息与通信学院、商贸学院、珠宝学院等13个二级学院。现有专任教师577人，其中博士、硕士418人，高级职称175人。拥有国家级技能大师、全国技术能手/、鹏城工匠等一批高层次人才领衔的双师型师资队伍。最近两届全国人社系统教师职业能力大赛，均获得一等奖。获得第七届广东省青年教师竞赛一等奖1项、三等奖1项。目前建有“深圳市技能型社会研究中心”“龙岗区智能供应链技术重点实验室”等重点研究平台。/与华为、亚马逊、西门子等世界500强企业共建了10家现代产业学院，促进高质量就业。2024届毕业生初次就业平均起薪（6111元）、毕业去向落实率（98.2%）、优质就业率（29.5%）和学生就业满意度（89%），远超全国高职平均水平。学校培养了一批世界拔尖技术技能精英，共获得世界技能大赛奖牌12枚、全国技能大赛奖牌12枚，竞赛成绩名列全国参赛单位前列。/学校遵循高等职业教育规律，以立德树人为根本，以服务“双区”建设为宗旨，坚持“将党的教育方针融入办学治校全领域，将学校发展融入民族复兴大格局，将人才培养融入‘双区’建设大战略，将工匠精神融入教育教学全过程”的办学思路，着力培养应用型、复合型、创新型、数字化、国际化高素质技术技能人才，奋力创建中国特色、世界一流职业院校。 | AB22: / | AC22: https://www.szcp.edu.cn/ | AD22: https://zhaosheng.szcp.edu.cn/ | AE22: 0755-83759856 0755-83759861 | AF22: 深圳市龙岗区龙岗街道五联社区将军帽路1号 | AG22: / | AH22: 2768 | AI22: https://baike.baidu.com/item/%E6%B7%B1%E5%9C%B3%E5%9F%8E%E5%B8%82%E8%81%8C%E4%B8%9A%E5%AD%A6%E9%99%A2 | AJ22: https://gaokao.chsi.com.cn/zsgs/zhangcheng/listZszc--schId-5453828216.dhtml | AK22: /
A23: 18 | B23: =C23 -> 0 | D23: 依据学考 | E23: 10833 | F23: 广东轻工职业技术大学 | G23: 605 | H23: 60 | I23: 290 | J23: 60 | K23: 290 | L23: 386 | M23: 396 | N23: 13260 | O23: 13816 | P23: =IFERROR(AVERAGE(L23:M23),"/") -> 391 | Q23: =IFERROR(AVERAGE(N23:O23),"/") -> 13538 | R23: 广东省 | S23: 广州市 | T23: 广东省 | U23: 职业本科 | V23: 广东省 | W23: 公办 | X23: 一线城市 | Y23: 省属/双高计划/高水平学校建设单位/国家级示范/现代学徒制试点学院 | Z23: 第二类高水平学校B档示范高职现代学徒 | AA23: 广东轻工职业技术学院创建于1933年，是省属唯一国家示范性高等职业院校，全国“双高”高职院校建设单位。前身是“广东省立第一职业学校”，至今已有86年职业教育历史，其中1959/1963年和1978/1983年两段时期，学校开办本科教育，现有全日制在校生21000余人。学校秉承“德能兼备，学以成之”的校训和“自强、敬业、求实、创新”的广轻精神，为珠三角地区乃至全国输送数万名高素质高技能应用型人才。////办学条件好////学校现有广州和南海两个校区，其中广州校区定位为“大文科校区”，文科、艺术类专业面向广州现代服务业；南海校区成为“大工科校区”，工科专业面向珠江西岸高端制造业，校园总面积1700多亩，校舍建筑面积43万多平方米，其中教学科研实训用房近20万平方米，图书馆3万多平方米，学生公寓近16万平方米。固定资产总值15.5亿元，教学仪器设备总值2亿多元，学校图书馆拥有藏书近160万册，电子图书200多万册。网络信息点数2万多个，音视频电子资源1万多小时，学校校园无线网络全覆盖。建有校内实践教学基地近350个、校外实训实习基地900多个。////办学成果优异////学校是广东省唯一拥有7个省级工程技术开发中心的高职院校，是同时拥有省级协同发展中心及协同育人平台的两所高职院校之一，是全国第一批教育信息化试点单位、教育部现代学徒制试点单位、全国高校思政研究会高职高专专业委员会副会长单位（广东省会长单位）、全国跨境电商专业人才培养示范校、全国群众体育先进单位、全国高职“一校一品”示范单位、全国社会实践工作优秀单位、广东省依法治校示范校单位、广东省创新创业示范校单位、广东省安全文明校园示范校单位、广东省示范职业教育集团、广东省集团化办学单位、国防教育特色学校。学校立项“国家标杆党支部”1个，并先后获得全国高等职业院校全国服务贡献50强（连续两年）、全国高等职业院校实习管理50强、全国高等职业院校教学资源50强、全国高等职业院校学生管理50强、全国高等职业院校教学管理50强、全国高等职业院校育人成效50强、亚太职业院校影响力50强、全国示范性高职院校影响力排行榜30强、全国普通高校竞赛评估（高职）20强，全国高职院校思政工作创新优秀示范案例50强。全国高职院校创新创业示范校50强。2019年中国高职高专院校综合竞争力排行榜第9名。////多功能文化食堂、智能垃圾分类系统等创新性后勤改革领先全国。////师资队伍结构合理，业务水平高////学校现有教职工1200余人，其中高级职称教师400余人（二级教授9人），珠江学者9/人，“双师”素质教师70/0余人；国务院特殊津贴专家2人，全国模范教师2人，国家级教学名师2人，国家级教学团队2个，国家“万人计划”教学名师1人，全国技术能手2人，全国青年岗位能手1人，全国高校思想政治理论课教师影响力人物2人，全国轻工行业先进工作者1人，中国轻工职业教育教学名师1人，全国辅导员年度人物1名，广东省高校“千百十工程”国家级培养对象2人，南粤优秀教师11人，南粤优秀教育工作者4人，广东省“特支计划”教学名师、广东省教学名师、专业领军人才等名师专家近70人。建立了一个由企业一线工作的技术人员、能工巧匠、高级经理人等组成的优质兼职教师资源库，兼职教师与专业专任教师数之比达到1:1以上。学校在广东省高职院校教师队伍建设考核中连续三年排名第一。2019年全国高职院校教师教学发展指数排前十名。////教学成果丰硕////学校设有机电技术学院、食品与生物技术学院、轻化工技术学院、信息技术学院、汽车技术学院、生态环境技术学院、艺术设计学院、财贸学院、管理学院、应用外语学院、创业学院、马克思主义学院和继续教育学院，三个协同教学中心（工业机器人协同教学中心、现代信息技术与新工科协同教学中心、应用外语协同教学中心），设20个专业群、69个招生专业。2016年11月，学校成立创业学院，面向全体学生进行创新创业通识教育，面向精英学生进行创新创业定制培养。学校已建成国家示范性专业4个、央财“支持高等职业学校提升专业服务产业发展能力”项目经费支持专业2个、省级示范性专业3个、省级重点（建设）专业13个、省级品牌专业建设项目13个，建有国家级教学资源库1个、国家级精品课程10门、国家级精品资源共享课程9门、全国高校职业发展与就业指导示范课程1门、国家教指委精品课程22门、省级精品课程21门、省级优质课程2门，立项省级精品开放课程4/5门，其中已验收3门，在建省级专业资源库2个。2009年以来，学校共获得国家级优秀教学成果二等奖10项，行业教指会特等奖2个，省级优秀教学成果一等奖9项，省级优秀教学成果二等奖5项。////职教特色明显，人才培养质量高////学校是教育部现代学徒制试点单位，已立项国家级现代学徒制试点项目3项，省级现代学徒制试点项目/9项。学校积极构建职业教育“立交桥”，全面实施“纵向延伸，横向拓展”协同育人模式，开展了“3+2”中高衔接、“2+2”和“4+0”高本联培、“3+2”高本衔接、工程硕士培养等多种形式的协同培养，其中本科专业共1/3个，搭建起“中/高/本/硕”现代职业教育体系框架。连续多年，录取人数和录取分数线均位居省内同类院校前茅，文理类、艺术类高考录取分数线均高于本科省控线。毕业生深受用人单位欢迎，母校的满意度和薪资水平高于全国示范校平均水平，初次就业率高于98%，用人单位满意度99%以上。学生在各级各类技能大赛中获奖数量与质量节节攀升。近三年来，共获得国家级奖项500多个、省部级奖项1000余个。////产教融合，社会服务能力强////学校构建并不断完善政校行企协同促进产教融合长效机制，围绕高水平专业群建设，打造“一群一院一联盟”，搭建了广东轻工职教集团、轻工行业应用技术协同创新发展中心、南海职业教育政校行企协同创新联盟、广东省工业互联网产教联盟、粤港澳数字创意产教联盟、粤港澳跨境电商产教联盟、广东酒店职业教育联盟、全国精准营养食品与果蔬加工产教联盟、国家中小微企业知识产权培训基地等产学研创新、科技研发与转化平台，与华为等世界500强知名企业合作成立了华为ICT学院、瀚蓝环境学院、白天鹅学院、雷诺钟表学院、许鸿飞国际文创学院等10个产业学院，实现校企精准对接，产教深度融合，精准育人。近五年，获国家级科技项目4项、省级36项；国家级、省级科技奖励13项；面向企业开展科技攻关项目200余项。申报专利近430项，授权近300项，专利申请量连续多年位列广州地区高校（含本科）前十名。////坚持对外合作，国际化办学水平高////学校积极广泛开展对外交流与合作，已与国（境）外多所高等院校建立了合作关系，在引进智力与优质教育资源、人才培养、合作办学、汉语言培训等方面开展了实质性的合作。累计已招收来自30多个国家的留学生4/00余名。2017年，学校牵头组建广东省“一带一路”职业教育联盟，输出广轻职教模式，服务“一带一路”沿线国家及地区，国际化办学呈现新气象。////构建终身教育体系，服务广东经济社会////依托“国家中小微企业知识产权培训（南海）基地”“广东轻工培训中心”“职教师资优质省级基地”“广东省专业技术人员继续教育基地”“广东省职业技能鉴定所”等国家级和省级平台，并设有专门和专业性培训机构30多个，面向社会、社区和产业、行业积极开展各级各类培训服务，年培训量超15万人天；与本科院校进行网络远程教育及自学考试合作，并在深圳、佛山、珠海、韶关等地设立12个校外专科继续教育教学点，学校各类学历继续教育在读人数4000余人。////“十三五”期间，学校将遵循“三大一强”院校治理理念，围绕“创新强校工程”及一流高职院校建设，努力把学校建成“国内一流、国际知名”国家优质高职院校，成为高职院校治理的标准与典范，成为高素质技术技能型人才培养的典范。 | AB23: 学校创建于1933年，原名广东省立第一职业学校，学校数易其名，先后更名为广东省立广州农工业职业学校、广东省立广州工业职业学校、广东省立广州高级工业职业学校、广东省广州高级工业技术学校、广东省轻工业学校、广东轻工业学院、广州轻工业学校等 ，1959～1963年和1978～1983年曾开办本科职业教育。 1999年，学校升格为广东轻工职业技术学院。 2020年，广东省轻工职业技术学校、广东省石油化工职业技术学校并入。 2024年6月，教育部正式同意在广东轻工职业技术学院的基础上设立广东轻工职业技术大学。 9月3日，广东轻工职业技术大学正式揭牌。 | AC23: http://www.gdqy.edu.cn/ | AD23: http://gdqyzs.jysd.com/ | AE23: 020/61230198 | AF23: 广州市新港西路152号 | AG23: / | AH23: 369 | AI23: https://baike.baidu.com/item/%E5%B9%BF%E4%B8%9C%E8%BD%BB%E5%B7%A5%E8%81%8C%E4%B8%9A%E6%8A%80%E6%9C%AF%E5%A4%A7%E5%AD%A6 | AJ23: https://gaokao.chsi.com.cn/zsgs/zhangcheng/listZszc//schId/620.dhtml | AK23: /
A24: 19 | B24: =C24 -> 0 | D24: 依据学考 | E24: 13810 | F24: 肇庆医学院 | G24: 602 | H24: 30 | I24: / | J24: 30 | K24: / | L24: 385 | M24: / | N24: 13849 | O24: / | P24: =IFERROR(AVERAGE(L24:M24),"/") -> 385 | Q24: =IFERROR(AVERAGE(N24:O24),"/") -> 13849 | R24: 广东省 | S24: 肇庆市 | T24: 广东省 | U24: 普通本科 | V24: 广东省 | W24: 公办 | X24: 三线城市 | Y24: / | Z24: 省属高等/公立/高等专科学校 | AA24: 一、办学历程肇庆医学高等专科学校是经国家教育部批准成立了一所公立全日制专科层次的普通高等院校。学校地处首批中国优秀旅游城市、国家历史文化名城——肇庆市。学校本着“育人为本、质量立校、人才强校、特色兴校”的办学理念，坚持“立足广东辐射全国、面向基层、服务社会”的办学定位，以服务为宗旨、以就业为导向、以职业能力培养为本位，走“校院合作、医教结合”的发展道路，培养“下得去，用得上、留得住”高素质应用型卫生人才。有效发挥了为区域经济发展提供卫生智力支持和人才保证的教育功能。学校办学历史悠久。1958年建校，前身为中山医学院肇庆分院，后更名为广东省肇庆卫生学校。1994年、2000年学校被国家教委、教育部授予重点中专学校称号。1993年、1999年与广东医学院、中山医科大学联合办学，分别设立广东医学院肇庆教学部和中山医科大学肇庆教学点。2004年5月经教育部批准升格为全日制普通高等专科学校，成为我省唯一一所独立设置的医学专科学校。50多年来，学校为国家输送了50000多名的医疗卫生技术人才，很多毕业生成为了行业的精英骨干。二、校区校貌学校现有三个校区：端州校区、鼎湖校区和北校区。端州坐落在景色宜人的西江畔，鼎湖校区毗邻国家4A级旅游风景区鼎湖山。总占地面积512亩，总建筑面积21万平方米。校园环境幽雅，办学基础设施完善。学校建有8个校内实验实训基地，,拥有各类实验、实训、仿真、模拟技能训练室132个，各实验室配备有现代化的电教设备，充分利用现代信息技术开发虚拟实验，进行综合实验项目训练。学校建有现代化的学术报告厅、图书馆、运动场，室内篮、排球运动场、体操房、乒乓球活动室以及学生公寓，为学生提供了良好的学习生活环境。三、附属医院学校现拥有3所直属附属医院，其中第一附属医院（肇庆市第一人民医院）是一所集医疗、教学、科研、预防、保健和康复功能于一体的大型综合性“三级甲等”医院，1995年通过评审成为“爱婴医院”，1996年、1998年分别被省卫生厅评为“广东省高等医学院校教学医院”、省“百家文明医院”；第二附属医院（肇庆市第二人民医院）是集医疗教学科研预防保健康复为一体的三级综合医院和三级妇幼保健院；肇庆医专附属医院（肇庆市口腔医院）是一所集医疗、预防、保健、康复为一体的具有专科特色的“二级甲等”综合医院。是广东医学院、肇庆医学高等专科学校等医学院校的临床教学和实践基地之一。同时也是肇庆市全国医师资格实践技能考试基地。医院医疗教学仪器设备齐全，拥有口腔科、眼科、甲状腺专科等特色业。目前，学校正在加大非直属医院创建工作，到2015年末，将拥有包括高要市人民医院在内的非直属附属医院8所，学校临床教学实力将进一步增强。此外，学校与广东省人民医院、广东武警总队医院、中山大学第三附属医院等省内外130余所二甲以上优质医院共建校外实习基地。为学生提供了功能齐备，管理规范的校外实训基地。四、师资队伍学校现有专兼职教师700多人，教师队伍以中高级职称为主。学校遵循“立足培养，大力引进”的原则，采取一系列激励措施，加强高学历、高职称教师的引进；重视教学名师、教师骨干的培养；支持鼓励在职教师深造。选拔优秀教师赴境内外的一流院校如台湾中山医学大学、菲律宾马尼拉圣保罗大学、香港理工大学、中山大学等进行学习培训。坚持“医教结合”的发展道路，培养出一支“双师型”的师资队伍，在教学、医疗和科研上发挥了重要作用。通过院校（企）合作，构建动态的兼职教师资源库，完善兼职教师聘任制度，初步形成一支数量适宜、结构合理、专兼结合的师资队伍。拥有省市级教学名师、拔尖人才、专业带头人22人。143人次担任教育部高职高专医学类、相关医学类教学指导委员会、全国卫生职业教育教学指导委员会、省、市各学会委员及行业专家。学校教师认真投身于科教研工作，积极参与教材编写及论文发表，教科研项目屡屡在各级成果评比中获奖。五、专业教学学校设有临床医学系、医技系、药学系、护理系、中医系、口腔系、医学基础部、公共基础部、思想政治理论课教学部。学校现开设临床医学、口腔医学、中医学、护理、涉外护理、助产、药学、中药、药品经营与管理、医学影像技术、医学检验技术、卫生检验与检疫技术、卫生财会统计等13个专业；设有康复类学科，开设针灸推拿、康复治疗技术、中医康复技术、健康管理等4个专业，形成了应用医学类和健康管理类学科专业体系。专业设置以市场经济为导向，紧盯社会经济的发展需求，省重点专业有护理专业、临床医学专业、助产专业，其中护理专业是省示范性专业、临床医学和助产专业也是中央财政支持的重点专业；口腔医学专业、中医学专业、药学专业、医学检验技术专业为省“十二五”重点建设专业。康复治疗技术专业、医学影像技术专业为校级重点建设专业。学校是教育部、卫生部等六部委发文确定的《我国护理紧缺人才培养培训基地》。护理和临床医学专业的实训基地得到中央和省级财政的重点扶持。学校口腔医学是与中山大学光华口腔医学院联合办学的重点专业。学校附属医院（肇庆市口腔医院）也得到中山医光华口腔医学院的大力扶持。学校的医学影像、康复治疗技术、社区护理是香港华夏基金会项目资助的项目，具有较强的办学实力。六、办学特色学校人才培养坚持以职业能力为核心，以知识、能力、素质为培养内涵，构建人文素质、理论与实践一体教学体系。一是以德育为载体，注重医学生“做人”教育。依托现代人文，实施素质教育贯穿人才培养全过程。重视学生“学会做人”的道德修养教育，使学生懂得“敬畏生命、关爱病人”，建立社会责任意识和服务意识，乐于为社会为他人奉献。二是以就业为导向，强化技能培养。依托学校与医院行业的紧密合作，做到“三早三突出”，即“早接触社会、早接触专业、早接触临床和突出实验、实训、实习三个关键环节”，帮助学生尽早了解和树立起职业思想。三是以能力为中心，鼓励特长发展。在提高学生专业技能的基础上，创造各种条件培养学生的特长和爱好，进一步提高了学生的综合素质和就业竞争力，为学生走向社会、更好地生活奠定基础。学校个人、团体在省市的艺术文化比赛中屡获殊荣。七、对外交流学校积极开展多种形式的对外交流与合作，逐步树立与国际教育接轨的教育意识，发展特色优势专业教育、拓宽教学思路，提高师生的国际交往能力。与菲律宾马尼拉圣堡罗大学，圣虔诚大学签订交流协议，每年互派师生进行文化交流。与香港理工大学护理学院合作，引进先进的护理教育改革思路；香港理工大学派遣师生到学校进行交流，并共同深入到农村，为少年儿童进行健康知识教育与指导。与台湾中山医学大学合作，邀请台湾的专家学者来校讲学，同时我校输送教师赴台进修学习。与澳门镜湖护理学院合作，选拔优秀应届毕业生赴澳门的医院进行临床实习。学校还与美国、加拿大、日本等国外多家院校和教育机构进行教育、学术、培训合作与交流。八、“十三五”规划发展目标：按照构建职业教育体系要求，引领职业教育科学发展，通过深化改革，以内涵建设为着力点，不断提高办学质量、办学水平、彰显办学特色，实现提升办学层次的目标。将学校创建成省内有地位、国内有影响，特色鲜明，集学历教育、短期培训和社会服务为一体的应用型医学本科院校。 | AB24: / | AC24: http://www.zqmc.net/ | AD24: http://zhaosheng.zqmc.edu.cn/ | AE24: 0758/2857067 | AF24: 校本部：广东省肇庆市端州区西江南路6号；鼎湖校区：广东省肇庆市鼎湖区新城北18区团结路1号；新区校区：广东省肇庆市新区丰乐路12号； | AG24: / | AH24: 662 | AI24: https://baike.baidu.com/item/%E8%82%87%E5%BA%86%E5%8C%BB%E5%AD%A6%E9%99%A2 | AJ24: https://gaokao.chsi.com.cn/zsgs/zhangcheng/listZszc//schId/2049.dhtml | AK24: /
A25: 20 | B25: =C25 -> 0 | D25: 依据学考 | E25: 12957 | F25: 深圳信息职业技术大学 | G25: 607 | H25: 86 | I25: / | J25: 86 | K25: / | L25: 385 | M25: / | N25: 14218 | O25: / | P25: =IFERROR(AVERAGE(L25:M25),"/") -> 385 | Q25: =IFERROR(AVERAGE(N25:O25),"/") -> 14218 | R25: 广东省 | S25: 深圳市 | T25: 广东省 | U25: 职业本科 | V25: 广东省 | W25: 公办 | X25: 一线城市 | Y25: 双高计划/高水平学校建设单位/国家级骨干/现代学徒制试点学院 | Z25: 第二类高水平学校B档骨干高职现代学徒 | AA25: 深圳信息职业技术学院创办于2002年4月，是经广东省人民政府批准、教育部备案，由深圳市人民政府举办的公办全日制高等院校。//学校现为国家示范（骨干）高职院校、国家示范性软件职业技术学院、教育部“中德职教汽车机电合作项目”试点院校，现拥有3个国家级高等职业教育专业教学资源库（含1个备选项目）。学校拥有现代化、生态型、信息化的校园，占地92.6万平方米（1389亩），建筑面积58.86万平方米。学校现有教学科研仪器设备总值为36786.36万元，图书馆藏书131.33万册。//学校对接深圳支柱产业，打造信息技术特色，共设软件学院、电子与通信学院、计算机学院、数字媒体学院、智能制造与装备学院、交通与环境学院、管理学院、财经学院、应用外语学院、中德学院、马克思主义学院、继续教育学院、创新创业学院、创新教育研究院、公共课教学部、体育部、信息技术研究所等14院2部1所；开设信息类为主的专业44个。现有国家骨干校重点建设专业4个，国家高等职业学校提升专业服务产业发展能力建设专业2个，全国职业院校示范专业点2个，国家高等职业教育教学资源库建设项目3个（含1个备选项目），广东省示范性专业4个，省级重点建设专业6个，省级品牌专业11个；国家级精品资源共享课7门、省级精品资源共享课（含精品在线开放课）38门、省级思想政治理论优质建设课程2门。//学校现有教职工796人，在590位专任教师中，副高及以上职称教师301人，其中，博士、博士后275人，“双师素质”教师九成。目前，学校拥有国家级教学团队1个，获国家级教学名师奖1人，获全国五一劳动奖章1人，国家万人计划教学名师1名，广东省教学名师奖3人，广东省“特支计划”教学名师3人，省级教学团队7个，南粤优秀教师7人，广东省“千百十人才培养工程”省级培养对象6人，广东省“珠江学者”特聘教授4人，深圳市“鹏城学者”特聘教授3人，深圳市政府特殊津贴1人，黄炎培职业教育杰出教师奖1人，深圳市高层次专业人才地方级领军人才9名，后备级领军人才21人，博士后创新实践基地在站博士后3人。//学校坚持科研引领、教研创新、突出应用、服务社会。已主持国家自然科学基金等国家级项目26项、省市级科研项目517项，教研课题国家级6项、省市级49项，深圳市首批教育科研专家工作室1个。获得国家级高等学校教学成果一等奖1项、二等奖2项，省级教学成果一等奖6项、二等奖4项，广东省科学技术二等奖2项、三等奖2项，国家教师科研基金“十一五”规划重点课题科研成果一等奖1项，深圳市科技进步奖2项，深圳市科技创新奖2项，深圳市科学技术奖自然科学奖1项，深圳市哲学社会科学优秀成果奖7项，中国人工智能学会进步奖二等奖；拥有发明专利62项，实用新型专利203项，外观设计专利8项。//学校坚持校企合作办学，积极推进产教融合协同育人，创新合作办学机制，探索校企合作模式，在校内构建了“三会两办”的办学机制，并打造了“学院+行业企业”的校企合作模式。学校用2万平米实训场地，引企入校，合作共建实践教学基地、科技创新平台等，基地目前建有2个省级创新平台、1个先进土木研究中心、1个智能制造实训中心、5个校级协同创新中心等创新载体。学校有国家级高等职业教育实训基地2个，省级高等职业教育实训基地11个，省级公共实训中心1个，省级大学生校外实践教学基地12个，深圳市高职教育校外公共实训基地33个。//学校建构高素质高技能人才培养机制，不断提升高就业率、高满意度办学效益。现有全日制在校生15468人，学校坚持产教融合、校企合作、因材施教、特色发展。近三年，学生参加专业技能竞赛共获国家级奖项137个，省级二等奖以上315个。毕业生“下得去、留得住、用得上、干得好”，毕业生总体就业率均在98%以上。毕业生被华为、腾讯、深圳地铁、中国联通等著名企业录用，产生了被《华尔街日报》报道为“中国最年轻90后千万富豪”丁仕源、拥有8家公司的速运邦邦CEO陈家良等创业典型。//学校积极引进国际先进教学资源，不断形成国际化办学特色。2012年，学校成为教育部“中德职教汽车机电合作项目”试点院校；2013年11月学校与西双版纳职业技术学院正式签署合作协议共建“深圳信息/西双版纳国际留学生基地”/并揭牌；2016年9月，由深圳市教育局和德国巴伐利亚州文教部推动，我校与德国巴伐利亚州帕绍技术学校、兰茨胡特应用技术大学合作创办中德学院；2018年5月，学校与芬兰于韦斯屈莱应用科技大学签订战略合作协议全面启动两校战略合作项目；此外，学校还与加拿大谢尔丹理工学院、韩国京畿大学、台湾地区朝阳科技大学、树德科技大学、龙华科技大学、台北城市科技大学、亚太创意技术学院等26所高校开展了师生交流、合作科研等项目。//学校跨越发展，已跻身全国高职院校“第一方阵”。2004年，学校成为“国家示范性软件职业技术学院”建设院校；2007年，以优异成绩通过教育部人才培养工作水平评估；2010年，成为国家骨干高职院校建设单位；2011年，获国家高等职业教育网络技术专业共享型教学资源库建设立项；2012年，入选教育部“中德职教汽车机电合作项目”试点院校；2014年获国家高等职业教育数字媒体专业群教学资源库立项；2015年，深圳市人力资源与社会保障局同意批准我校设立博士后创新实践基地；2016年，学校国家骨干校建设项目以“优秀”等级通过国家验收、获广东省“一流校”建设立项、学校“2188创客空间”被国家科学技术部认定为国家级众创空间，2016年学校又成功召开了第二次党代会，进一步确立了“全力打造有特色国际化一流职业院校”的奋斗目标。//青春深信成新锐，勇向潮头唱大风。学校将继续开拓奋进，勇于不断创新，努力把学校打造成有特色国际化一流职业院校。 | AB25: 学校原名为深圳信息职业技术学院，于2002年4月由深圳教育学院、深圳市工业学校、深圳市财经学校三所学校合并组建；2011年9月，学校从深圳市罗湖区迁至深圳市龙岗区。2012年，学校入选教育部“中德职教汽车机电合作项目”试点院校。2021年，学校获批设立广东省博士工作站。2025年6月，教育部发函广东省，同意以深圳信息职业技术学院为基础设立深圳信息职业技术大学，同时撤销深圳信息职业技术学院的建制。2026年1月，深圳信息职业技术大学正式成立。 | AC25: http://www.sziit.com.cn/ | AD25: http://zhaob.sziit.edu.cn/index.htm | AE25: 075589226360、075589226361 | AF25: 深圳市龙岗区龙翔大道2188号 | AG25: https://www.720yun.com/t/d4528mpguus | AH25: 184 | AI25: https://baike.baidu.com/item/%E6%B7%B1%E5%9C%B3%E4%BF%A1%E6%81%AF%E8%81%8C%E4%B8%9A%E6%8A%80%E6%9C%AF%E5%AD%A6%E9%99%A2 | AJ25: https://gaokao.chsi.com.cn/zsgs/zhangcheng/listZszc//schId/1429.dhtml | AK25: /
A26: 21 | B26: =C26 -> 0 | D26: 依据学考 | E26: 10833 | F26: 广东轻工职业技术大学 | G26: 604 | H26: 175 | I26: 120 | J26: 175 | K26: 120 | L26: 382 | M26: 397 | N26: 16982 | O26: 11595 | P26: =IFERROR(AVERAGE(L26:M26),"/") -> 389.5 | Q26: =IFERROR(AVERAGE(N26:O26),"/") -> 14288.5 | R26: 广东省 | S26: 广州市 | T26: 广东省 | U26: 职业本科 | V26: 广东省 | W26: 公办 | X26: 一线城市 | Y26: 省属/双高计划/高水平学校建设单位/国家级示范/现代学徒制试点学院 | Z26: 第二类高水平学校B档示范高职现代学徒 | AA26: 广东轻工职业技术学院创建于1933年，是省属唯一国家示范性高等职业院校，全国“双高”高职院校建设单位。前身是“广东省立第一职业学校”，至今已有86年职业教育历史，其中1959/1963年和1978/1983年两段时期，学校开办本科教育，现有全日制在校生21000余人。学校秉承“德能兼备，学以成之”的校训和“自强、敬业、求实、创新”的广轻精神，为珠三角地区乃至全国输送数万名高素质高技能应用型人才。////办学条件好////学校现有广州和南海两个校区，其中广州校区定位为“大文科校区”，文科、艺术类专业面向广州现代服务业；南海校区成为“大工科校区”，工科专业面向珠江西岸高端制造业，校园总面积1700多亩，校舍建筑面积43万多平方米，其中教学科研实训用房近20万平方米，图书馆3万多平方米，学生公寓近16万平方米。固定资产总值15.5亿元，教学仪器设备总值2亿多元，学校图书馆拥有藏书近160万册，电子图书200多万册。网络信息点数2万多个，音视频电子资源1万多小时，学校校园无线网络全覆盖。建有校内实践教学基地近350个、校外实训实习基地900多个。////办学成果优异////学校是广东省唯一拥有7个省级工程技术开发中心的高职院校，是同时拥有省级协同发展中心及协同育人平台的两所高职院校之一，是全国第一批教育信息化试点单位、教育部现代学徒制试点单位、全国高校思政研究会高职高专专业委员会副会长单位（广东省会长单位）、全国跨境电商专业人才培养示范校、全国群众体育先进单位、全国高职“一校一品”示范单位、全国社会实践工作优秀单位、广东省依法治校示范校单位、广东省创新创业示范校单位、广东省安全文明校园示范校单位、广东省示范职业教育集团、广东省集团化办学单位、国防教育特色学校。学校立项“国家标杆党支部”1个，并先后获得全国高等职业院校全国服务贡献50强（连续两年）、全国高等职业院校实习管理50强、全国高等职业院校教学资源50强、全国高等职业院校学生管理50强、全国高等职业院校教学管理50强、全国高等职业院校育人成效50强、亚太职业院校影响力50强、全国示范性高职院校影响力排行榜30强、全国普通高校竞赛评估（高职）20强，全国高职院校思政工作创新优秀示范案例50强。全国高职院校创新创业示范校50强。2019年中国高职高专院校综合竞争力排行榜第9名。////多功能文化食堂、智能垃圾分类系统等创新性后勤改革领先全国。////师资队伍结构合理，业务水平高////学校现有教职工1200余人，其中高级职称教师400余人（二级教授9人），珠江学者9/人，“双师”素质教师70/0余人；国务院特殊津贴专家2人，全国模范教师2人，国家级教学名师2人，国家级教学团队2个，国家“万人计划”教学名师1人，全国技术能手2人，全国青年岗位能手1人，全国高校思想政治理论课教师影响力人物2人，全国轻工行业先进工作者1人，中国轻工职业教育教学名师1人，全国辅导员年度人物1名，广东省高校“千百十工程”国家级培养对象2人，南粤优秀教师11人，南粤优秀教育工作者4人，广东省“特支计划”教学名师、广东省教学名师、专业领军人才等名师专家近70人。建立了一个由企业一线工作的技术人员、能工巧匠、高级经理人等组成的优质兼职教师资源库，兼职教师与专业专任教师数之比达到1:1以上。学校在广东省高职院校教师队伍建设考核中连续三年排名第一。2019年全国高职院校教师教学发展指数排前十名。////教学成果丰硕////学校设有机电技术学院、食品与生物技术学院、轻化工技术学院、信息技术学院、汽车技术学院、生态环境技术学院、艺术设计学院、财贸学院、管理学院、应用外语学院、创业学院、马克思主义学院和继续教育学院，三个协同教学中心（工业机器人协同教学中心、现代信息技术与新工科协同教学中心、应用外语协同教学中心），设20个专业群、69个招生专业。2016年11月，学校成立创业学院，面向全体学生进行创新创业通识教育，面向精英学生进行创新创业定制培养。学校已建成国家示范性专业4个、央财“支持高等职业学校提升专业服务产业发展能力”项目经费支持专业2个、省级示范性专业3个、省级重点（建设）专业13个、省级品牌专业建设项目13个，建有国家级教学资源库1个、国家级精品课程10门、国家级精品资源共享课程9门、全国高校职业发展与就业指导示范课程1门、国家教指委精品课程22门、省级精品课程21门、省级优质课程2门，立项省级精品开放课程4/5门，其中已验收3门，在建省级专业资源库2个。2009年以来，学校共获得国家级优秀教学成果二等奖10项，行业教指会特等奖2个，省级优秀教学成果一等奖9项，省级优秀教学成果二等奖5项。////职教特色明显，人才培养质量高////学校是教育部现代学徒制试点单位，已立项国家级现代学徒制试点项目3项，省级现代学徒制试点项目/9项。学校积极构建职业教育“立交桥”，全面实施“纵向延伸，横向拓展”协同育人模式，开展了“3+2”中高衔接、“2+2”和“4+0”高本联培、“3+2”高本衔接、工程硕士培养等多种形式的协同培养，其中本科专业共1/3个，搭建起“中/高/本/硕”现代职业教育体系框架。连续多年，录取人数和录取分数线均位居省内同类院校前茅，文理类、艺术类高考录取分数线均高于本科省控线。毕业生深受用人单位欢迎，母校的满意度和薪资水平高于全国示范校平均水平，初次就业率高于98%，用人单位满意度99%以上。学生在各级各类技能大赛中获奖数量与质量节节攀升。近三年来，共获得国家级奖项500多个、省部级奖项1000余个。////产教融合，社会服务能力强////学校构建并不断完善政校行企协同促进产教融合长效机制，围绕高水平专业群建设，打造“一群一院一联盟”，搭建了广东轻工职教集团、轻工行业应用技术协同创新发展中心、南海职业教育政校行企协同创新联盟、广东省工业互联网产教联盟、粤港澳数字创意产教联盟、粤港澳跨境电商产教联盟、广东酒店职业教育联盟、全国精准营养食品与果蔬加工产教联盟、国家中小微企业知识产权培训基地等产学研创新、科技研发与转化平台，与华为等世界500强知名企业合作成立了华为ICT学院、瀚蓝环境学院、白天鹅学院、雷诺钟表学院、许鸿飞国际文创学院等10个产业学院，实现校企精准对接，产教深度融合，精准育人。近五年，获国家级科技项目4项、省级36项；国家级、省级科技奖励13项；面向企业开展科技攻关项目200余项。申报专利近430项，授权近300项，专利申请量连续多年位列广州地区高校（含本科）前十名。////坚持对外合作，国际化办学水平高////学校积极广泛开展对外交流与合作，已与国（境）外多所高等院校建立了合作关系，在引进智力与优质教育资源、人才培养、合作办学、汉语言培训等方面开展了实质性的合作。累计已招收来自30多个国家的留学生4/00余名。2017年，学校牵头组建广东省“一带一路”职业教育联盟，输出广轻职教模式，服务“一带一路”沿线国家及地区，国际化办学呈现新气象。////构建终身教育体系，服务广东经济社会////依托“国家中小微企业知识产权培训（南海）基地”“广东轻工培训中心”“职教师资优质省级基地”“广东省专业技术人员继续教育基地”“广东省职业技能鉴定所”等国家级和省级平台，并设有专门和专业性培训机构30多个，面向社会、社区和产业、行业积极开展各级各类培训服务，年培训量超15万人天；与本科院校进行网络远程教育及自学考试合作，并在深圳、佛山、珠海、韶关等地设立12个校外专科继续教育教学点，学校各类学历继续教育在读人数4000余人。////“十三五”期间，学校将遵循“三大一强”院校治理理念，围绕“创新强校工程”及一流高职院校建设，努力把学校建成“国内一流、国际知名”国家优质高职院校，成为高职院校治理的标准与典范，成为高素质技术技能型人才培养的典范。 | AB26: 学校创建于1933年，原名广东省立第一职业学校，学校数易其名，先后更名为广东省立广州农工业职业学校、广东省立广州工业职业学校、广东省立广州高级工业职业学校、广东省广州高级工业技术学校、广东省轻工业学校、广东轻工业学院、广州轻工业学校等 ，1959～1963年和1978～1983年曾开办本科职业教育。 1999年，学校升格为广东轻工职业技术学院。 2020年，广东省轻工职业技术学校、广东省石油化工职业技术学校并入。 2024年6月，教育部正式同意在广东轻工职业技术学院的基础上设立广东轻工职业技术大学。 9月3日，广东轻工职业技术大学正式揭牌。 | AC26: http://www.gdqy.edu.cn/ | AD26: http://gdqyzs.jysd.com/ | AE26: 020/61230198 | AF26: 广州市新港西路152号 | AG26: / | AH26: 369 | AI26: https://baike.baidu.com/item/%E5%B9%BF%E4%B8%9C%E8%BD%BB%E5%B7%A5%E8%81%8C%E4%B8%9A%E6%8A%80%E6%9C%AF%E5%A4%A7%E5%AD%A6 | AJ26: https://gaokao.chsi.com.cn/zsgs/zhangcheng/listZszc//schId/620.dhtml | AK26: /
A27: 22 | B27: =C27 -> 0 | D27: 依据学考 | E27: 10833 | F27: 广东轻工职业技术大学 | G27: 610 | H27: 200 | I27: 60 | J27: 200 | K27: 60 | L27: 381 | M27: 398 | N27: 18320 | O27: 10849 | P27: =IFERROR(AVERAGE(L27:M27),"/") -> 389.5 | Q27: =IFERROR(AVERAGE(N27:O27),"/") -> 14584.5 | R27: 广东省 | S27: 广州市 | T27: 广东省 | U27: 职业本科 | V27: 广东省 | W27: 公办 | X27: 一线城市 | Y27: 省属/双高计划/高水平学校建设单位/国家级示范/现代学徒制试点学院 | Z27: 第二类高水平学校B档示范高职现代学徒 | AA27: 广东轻工职业技术学院创建于1933年，是省属唯一国家示范性高等职业院校，全国“双高”高职院校建设单位。前身是“广东省立第一职业学校”，至今已有86年职业教育历史，其中1959/1963年和1978/1983年两段时期，学校开办本科教育，现有全日制在校生21000余人。学校秉承“德能兼备，学以成之”的校训和“自强、敬业、求实、创新”的广轻精神，为珠三角地区乃至全国输送数万名高素质高技能应用型人才。////办学条件好////学校现有广州和南海两个校区，其中广州校区定位为“大文科校区”，文科、艺术类专业面向广州现代服务业；南海校区成为“大工科校区”，工科专业面向珠江西岸高端制造业，校园总面积1700多亩，校舍建筑面积43万多平方米，其中教学科研实训用房近20万平方米，图书馆3万多平方米，学生公寓近16万平方米。固定资产总值15.5亿元，教学仪器设备总值2亿多元，学校图书馆拥有藏书近160万册，电子图书200多万册。网络信息点数2万多个，音视频电子资源1万多小时，学校校园无线网络全覆盖。建有校内实践教学基地近350个、校外实训实习基地900多个。////办学成果优异////学校是广东省唯一拥有7个省级工程技术开发中心的高职院校，是同时拥有省级协同发展中心及协同育人平台的两所高职院校之一，是全国第一批教育信息化试点单位、教育部现代学徒制试点单位、全国高校思政研究会高职高专专业委员会副会长单位（广东省会长单位）、全国跨境电商专业人才培养示范校、全国群众体育先进单位、全国高职“一校一品”示范单位、全国社会实践工作优秀单位、广东省依法治校示范校单位、广东省创新创业示范校单位、广东省安全文明校园示范校单位、广东省示范职业教育集团、广东省集团化办学单位、国防教育特色学校。学校立项“国家标杆党支部”1个，并先后获得全国高等职业院校全国服务贡献50强（连续两年）、全国高等职业院校实习管理50强、全国高等职业院校教学资源50强、全国高等职业院校学生管理50强、全国高等职业院校教学管理50强、全国高等职业院校育人成效50强、亚太职业院校影响力50强、全国示范性高职院校影响力排行榜30强、全国普通高校竞赛评估（高职）20强，全国高职院校思政工作创新优秀示范案例50强。全国高职院校创新创业示范校50强。2019年中国高职高专院校综合竞争力排行榜第9名。////多功能文化食堂、智能垃圾分类系统等创新性后勤改革领先全国。////师资队伍结构合理，业务水平高////学校现有教职工1200余人，其中高级职称教师400余人（二级教授9人），珠江学者9/人，“双师”素质教师70/0余人；国务院特殊津贴专家2人，全国模范教师2人，国家级教学名师2人，国家级教学团队2个，国家“万人计划”教学名师1人，全国技术能手2人，全国青年岗位能手1人，全国高校思想政治理论课教师影响力人物2人，全国轻工行业先进工作者1人，中国轻工职业教育教学名师1人，全国辅导员年度人物1名，广东省高校“千百十工程”国家级培养对象2人，南粤优秀教师11人，南粤优秀教育工作者4人，广东省“特支计划”教学名师、广东省教学名师、专业领军人才等名师专家近70人。建立了一个由企业一线工作的技术人员、能工巧匠、高级经理人等组成的优质兼职教师资源库，兼职教师与专业专任教师数之比达到1:1以上。学校在广东省高职院校教师队伍建设考核中连续三年排名第一。2019年全国高职院校教师教学发展指数排前十名。////教学成果丰硕////学校设有机电技术学院、食品与生物技术学院、轻化工技术学院、信息技术学院、汽车技术学院、生态环境技术学院、艺术设计学院、财贸学院、管理学院、应用外语学院、创业学院、马克思主义学院和继续教育学院，三个协同教学中心（工业机器人协同教学中心、现代信息技术与新工科协同教学中心、应用外语协同教学中心），设20个专业群、69个招生专业。2016年11月，学校成立创业学院，面向全体学生进行创新创业通识教育，面向精英学生进行创新创业定制培养。学校已建成国家示范性专业4个、央财“支持高等职业学校提升专业服务产业发展能力”项目经费支持专业2个、省级示范性专业3个、省级重点（建设）专业13个、省级品牌专业建设项目13个，建有国家级教学资源库1个、国家级精品课程10门、国家级精品资源共享课程9门、全国高校职业发展与就业指导示范课程1门、国家教指委精品课程22门、省级精品课程21门、省级优质课程2门，立项省级精品开放课程4/5门，其中已验收3门，在建省级专业资源库2个。2009年以来，学校共获得国家级优秀教学成果二等奖10项，行业教指会特等奖2个，省级优秀教学成果一等奖9项，省级优秀教学成果二等奖5项。////职教特色明显，人才培养质量高////学校是教育部现代学徒制试点单位，已立项国家级现代学徒制试点项目3项，省级现代学徒制试点项目/9项。学校积极构建职业教育“立交桥”，全面实施“纵向延伸，横向拓展”协同育人模式，开展了“3+2”中高衔接、“2+2”和“4+0”高本联培、“3+2”高本衔接、工程硕士培养等多种形式的协同培养，其中本科专业共1/3个，搭建起“中/高/本/硕”现代职业教育体系框架。连续多年，录取人数和录取分数线均位居省内同类院校前茅，文理类、艺术类高考录取分数线均高于本科省控线。毕业生深受用人单位欢迎，母校的满意度和薪资水平高于全国示范校平均水平，初次就业率高于98%，用人单位满意度99%以上。学生在各级各类技能大赛中获奖数量与质量节节攀升。近三年来，共获得国家级奖项500多个、省部级奖项1000余个。////产教融合，社会服务能力强////学校构建并不断完善政校行企协同促进产教融合长效机制，围绕高水平专业群建设，打造“一群一院一联盟”，搭建了广东轻工职教集团、轻工行业应用技术协同创新发展中心、南海职业教育政校行企协同创新联盟、广东省工业互联网产教联盟、粤港澳数字创意产教联盟、粤港澳跨境电商产教联盟、广东酒店职业教育联盟、全国精准营养食品与果蔬加工产教联盟、国家中小微企业知识产权培训基地等产学研创新、科技研发与转化平台，与华为等世界500强知名企业合作成立了华为ICT学院、瀚蓝环境学院、白天鹅学院、雷诺钟表学院、许鸿飞国际文创学院等10个产业学院，实现校企精准对接，产教深度融合，精准育人。近五年，获国家级科技项目4项、省级36项；国家级、省级科技奖励13项；面向企业开展科技攻关项目200余项。申报专利近430项，授权近300项，专利申请量连续多年位列广州地区高校（含本科）前十名。////坚持对外合作，国际化办学水平高////学校积极广泛开展对外交流与合作，已与国（境）外多所高等院校建立了合作关系，在引进智力与优质教育资源、人才培养、合作办学、汉语言培训等方面开展了实质性的合作。累计已招收来自30多个国家的留学生4/00余名。2017年，学校牵头组建广东省“一带一路”职业教育联盟，输出广轻职教模式，服务“一带一路”沿线国家及地区，国际化办学呈现新气象。////构建终身教育体系，服务广东经济社会////依托“国家中小微企业知识产权培训（南海）基地”“广东轻工培训中心”“职教师资优质省级基地”“广东省专业技术人员继续教育基地”“广东省职业技能鉴定所”等国家级和省级平台，并设有专门和专业性培训机构30多个，面向社会、社区和产业、行业积极开展各级各类培训服务，年培训量超15万人天；与本科院校进行网络远程教育及自学考试合作，并在深圳、佛山、珠海、韶关等地设立12个校外专科继续教育教学点，学校各类学历继续教育在读人数4000余人。////“十三五”期间，学校将遵循“三大一强”院校治理理念，围绕“创新强校工程”及一流高职院校建设，努力把学校建成“国内一流、国际知名”国家优质高职院校，成为高职院校治理的标准与典范，成为高素质技术技能型人才培养的典范。 | AB27: 学校创建于1933年，原名广东省立第一职业学校，学校数易其名，先后更名为广东省立广州农工业职业学校、广东省立广州工业职业学校、广东省立广州高级工业职业学校、广东省广州高级工业技术学校、广东省轻工业学校、广东轻工业学院、广州轻工业学校等 ，1959～1963年和1978～1983年曾开办本科职业教育。 1999年，学校升格为广东轻工职业技术学院。 2020年，广东省轻工职业技术学校、广东省石油化工职业技术学校并入。 2024年6月，教育部正式同意在广东轻工职业技术学院的基础上设立广东轻工职业技术大学。 9月3日，广东轻工职业技术大学正式揭牌。 | AC27: http://www.gdqy.edu.cn/ | AD27: http://gdqyzs.jysd.com/ | AE27: 020/61230198 | AF27: 广州市新港西路152号 | AG27: / | AH27: 369 | AI27: https://baike.baidu.com/item/%E5%B9%BF%E4%B8%9C%E8%BD%BB%E5%B7%A5%E8%81%8C%E4%B8%9A%E6%8A%80%E6%9C%AF%E5%A4%A7%E5%AD%A6 | AJ27: https://gaokao.chsi.com.cn/zsgs/zhangcheng/listZszc//schId/620.dhtml | AK27: /
A28: 23 | B28: =C28 -> 0 | D28: 依据学考 | E28: 12046 | F28: 广州职业技术大学 | G28: 603 | H28: 85 | I28: / | J28: 85 | K28: / | L28: 384 | M28: / | N28: 15543 | O28: / | P28: =IFERROR(AVERAGE(L28:M28),"/") -> 384 | Q28: =IFERROR(AVERAGE(N28:O28),"/") -> 15543 | R28: 广东省 | S28: 广州市 | T28: 广东省 | U28: 职业本科 | V28: 广东省 | W28: 公办 | X28: 一线城市 | Y28: 双高计划/高水平学校建设单位/国家级示范/现代学徒制试点学院 | Z28: 第二类高水平学校B档示范高职现代学徒 | AA28: 广州番禺职业技术学院(原名番禺理工学院、番禺职业技术学院)1993年筹建,1997年9月教育部正式批准备案,是全国首批、广州市属第一所公办全日制普通高等职业院校。2003年被广州市政府确定为市属高等职业教育龙头院校。2005年4月以“优秀”成绩通过教育部人才培养工作水平评估。2006年12月被教育部、财政部确定为“国家示范性高等职业院校建设计划”首批28所立项建设院校之一。2009年12月通过教育部、财政部的验收,被正式批准为首批国家示范性高等职业院校。2010年11月被广东省人民政府授予“广东省职业技术教育工作先进集体”称号。2014年5月荣获我国职业教育界的最高奖项——第四届黄炎培职业教育奖“优秀学校奖”。2014年7月被教育部评为“全国毕业生就业典型经验高校50强”。2016年11月成为广东省一流高职院校建设计划立项建设单位。2017年7月荣登“全国高职院校国际影响力50强”和“全国高职院校服务贡献50强”榜单。学校地处珠江三角洲腹地的广州市番禺区,占地2067亩,校舍建筑面积32.98万平方米,固定资产总值超过10.06亿元,其中教学科研仪器设备总值超过2.98亿元,图书馆面积3.07万平方米,馆内阅览座位4300多个,馆藏纸质图书123余万册、电子图书约2900GB、纸质期刊近880种、电子期刊8360余种,建有41个校内实训基地和176个校外实训基地,现有全日制在校生11769人,生源地分布于全国13个省(区)。校园峰峦起伏,碧波粼粼,繁花似锦,绿草如茵,是广州市花园式单位,2012年获评“全国职业院校魅力校园”,被誉为国内最美丽的大学之一。学校以高等职业技术教育为主,设有财经学院、管理学院、机电工程学院、建筑工程学院、人文社科学院、外语外贸学院、信息工程学院、艺术设计学院、珠宝学院、马克思主义学院、继续教育学院等十一个学院,开设44个紧贴珠三角地区产业结构和社会发展需求的专业。目前,学校拥有玩具设计与制造、计算机网络技术、金融管理、视觉传播设计与制作、酒店管理、珠宝首饰工艺及鉴定等6个国家示范性高职院校重点建设专业、1个全国职业院校国家级示范专业点、2个中央财政支持提升专业服务产业发展能力专业、2个省级协同育人平台、9个省级示范性专业、8个省级重点建设专业、12个省级品牌建设专业、8个市级特色专业学院、2个市级校企合作示范学院、2个产业学院、6个市级示范性专业、6个市级重点建设专业;15门国家级精品课程、25门省级精品课程和40门市级精品课程;14门国家级精品资源共享课程、31门省级精品开放(建设)课程和5门省级精品在线开放(建设)课程;1门国家精品视频公开课程、2门省级精品视频公开课;1个国家级校内实训基地、7个省级校内实训基地、9个市级校内实训基地和2个省级大学生校外实践教学基地、10个省级大学生校外实践教学基地(建设)项目、2个市级校外示范性实训基地。学校积极与企业、科研院所开展产学研合作,搭建应用技术研发平台,建有包括广东高校珠宝首饰工程技术开发中心、广东省珠宝首饰工程技术研究中心、广东省智慧职业教育大数据工程技术研究中心、广东省皮革智能产品3D打印应用工程技术研究中心、广东省绿色建造和检测工程技术研究中心等工程中心，以及广州市人文社科研究基地、广州市技术转移示范机构（中心）在内的39个科学研究机构（应用技术协同创新中心、研究基地等）。产出了一批以专利为代表的科技创新成果,专利申请、专利授权、有效专利、专利竞争力全部进入2017年中国大学专利排行榜500强,获2013年广州市专利创造贡献奖。承担了国家自然科学基金项目、国家社会科学基金项目(教育学)、全国教育规划项目、教育部人文社科项目等一批高层级的科研项目,公开发表一批有影响的科研教研论文,论文最高他引次数达604次。学校面向全国公开招聘优秀教师,拥有一支人员精干、结构合理、水平较高的师资队伍。现有教职工934人,专任教师545人,专任教师中具有高级职称者占30.09%,具有研究生学位者占70.46%,“双师”素质专任教师比例达70.28%。现有全国教育系统先进集体1个、全国职业教育先进单位1个,国家级教学团队2个、省级教学团队6个,有享受国务院政府特殊津贴专家3人、国家级教学名师5人、省级教学名师12人、市级教学名师6人。学校坚持走质量、规模、效益协调发展的内涵式发展之路,强化质量意识,以教师为主导,以学生为主体,以培养学生创新精神和职业能力为目标,积极探索教学改革,2001年以来,共有66项教学成果获得国家、省、市教学成果奖,其中,国家级教学成果一等奖1项、二等奖10项,广东省教学成果特等奖1项、一等奖11项、二等奖15项,广州市教学成果特等奖4项、一等奖12项。学校坚持以服务为宗旨,是国家计算机应用与软件技术专业领域技能型紧缺人才培养培训基地,中国玩具行业人才培训基地,广东省首批省级示范性软件学院建设学校,广东省高职高专师资培训基地、广东省中等职业学校师资培训基地、广州市专业技术人员继续教育基地、广州市中等职业学校教师(校长)培训中心,已成立国家职业技能鉴定所,可以开展19个工种的职业资格鉴定。学校广泛开展对外交流与合作,加强与海内外知名大学、同类职业技术学院及培训机构的联系,已与英国、美国、加拿大、芬兰、荷兰、意大利、新加坡、日本等国外高等教育机构和港澳台地区的教育机构及科技大学建立了教育交流与合作关系，同时积极拓展与“一带一路”沿线国家的教育交流合作。在设立海外研习基地、联合培养、专业及课程共建、学分互认、中外合作办学、质量管理体系建设、师资培训等方面开展了富有成效的交流与合作,促进了人才培养质量和国际化程度的提升。同时,学校发挥品牌专业和特色课程优势,吸引国际学生来校短期交换和修读课程,形成了较高的知名度和美誉度。2018年我校与新加坡南洋理工学院学生海外研习基地合作项目入选全国首批20个“中国—东盟高职院校特色合作项目”。学校围绕培养“一技之长+综合素质”的高素质、创新性技术技能人才的目标,实行以素质为基础,以能力为核心,以就业为导向,产学研结合的人才培养模式,积极实施“双证书”制度,大力培养学生的职业技能,毕业生以其适应性强、动手能力强、综合素质高而受到用人单位普遍欢迎。自2001年广东省首次公布高校毕业生就业率以来,学校毕业生就业率一直稳居全省高校前列,2004年、2005年和2008年三年位居全省所有本专科院校第一位。2010年,学校模具设计与制造专业2001届毕业生黄德智喜获“全国劳动模范”崇高荣誉,在北京人民大会堂受到党中央和国务院的隆重表彰。2018年，学校涉外文秘专业2002届毕业生王俊文荣获广东省五一劳动奖章。2018年,毕业生就业率达98.79%。番禺籍的原全国政协副主席霍英东,全国政协副主席、澳门特别行政区首任行政长官何厚铧,全国政协委员陈瑞球,以及何添、何善衡等港澳同胞和社会各界有识之士对学校的建设给予极大的关注和有力的资助,捐资兴建了霍英东学术交流中心、何厚铧大楼等一批教学、实训用房和学生宿舍,极大地促进了学校的发展。功崇惟志,天道酬勤。学校以习近平新时代中国特色社会义思想为指导，积极对接国家“一带一路”和粤港澳大湾区发展战略，坚持走以质量为核心的内涵式发展道路，以建设“中国特色、国际水准”的高职院校为目标，不断深化校企合作、产教融合体制机制改革，致力于为大湾区经济社会发展培养具有“一技之长+综合素质”的高素质、创新型技术技能人才。 | AB28: 学校的前身是1996年4月经广东省人民政府批准成立的番禺理工学院，于1993年筹建；1997年6月更名为番禺职业技术学院；1997年9月经国家教育委员会正式备案，由广州市和番禺市人民政府共同领导、番禺市直接管理；2006年起实行“市区共建，以区为主”的管理体制；2008年7月更名为广州番禺职业技术学院；2010年起实行“市区共建，以市为主”的管理体制；2006年12月被教育部、财政部确定为“国家示范性高等职业院校建设计划”首批立项建设院校，2009年12月通过验收，成为国家示范性高等职业院校；2019年12月入选中国特色高水平高职学校和专业建设单位。2025年6月中华人民共和国教育部同意以广州番禺职业技术学院为基础设立广州职业技术大学。 | AC28: http://www.gzpyp.edu.cn/ | AD28: http://zs.gzpyp.edu.cn/ | AE28: 020/34874086、84731206 | AF28: 广东省广州市番禺区市良路1342号 | AG28: https://www.720yun.com/t/f10jz0yavf3 | AH28: 426 | AI28: https://baike.baidu.com/item/%E5%B9%BF%E5%B7%9E%E7%95%AA%E7%A6%BA%E8%81%8C%E4%B8%9A%E6%8A%80%E6%9C%AF%E5%AD%A6%E9%99%A2 | AJ28: https://gaokao.chsi.com.cn/zsgs/zhangcheng/listZszc//schId/954.dhtml | AK28: /
A29: 24 | B29: =C29 -> 0 | D29: 依据学考 | E29: 14845 | F29: 深圳城市职业学院 | G29: 602 | H29: 19 | I29: / | J29: 19 | K29: / | L29: 384 | M29: / | N29: 15839 | O29: / | P29: =IFERROR(AVERAGE(L29:M29),"/") -> 384 | Q29: =IFERROR(AVERAGE(N29:O29),"/") -> 15839 | R29: 广东省 | S29: 深圳市 | T29: 广东省 | U29: 专科（高职） | V29: 广东省 | W29: 公办 | X29: 一线城市 | Y29: / | Z29: / | AA29: 深圳城市职业学院是由深圳市人民政府举办，经广东省人民政府批准、教育部备案，以深圳技师学院为基础设立的公办全日制普通高等职业院校。2024年首批5个专业招生（夏季高考生）。/学校位于深圳市龙岗区中心城，占地555亩，现有中德智造学院、设计学院、信息与通信学院、商贸学院、珠宝学院等13个二级学院。现有专任教师577人，其中博士、硕士418人，高级职称175人。拥有国家级技能大师、全国技术能手/、鹏城工匠等一批高层次人才领衔的双师型师资队伍。最近两届全国人社系统教师职业能力大赛，均获得一等奖。获得第七届广东省青年教师竞赛一等奖1项、三等奖1项。目前建有“深圳市技能型社会研究中心”“龙岗区智能供应链技术重点实验室”等重点研究平台。/与华为、亚马逊、西门子等世界500强企业共建了10家现代产业学院，促进高质量就业。2024届毕业生初次就业平均起薪（6111元）、毕业去向落实率（98.2%）、优质就业率（29.5%）和学生就业满意度（89%），远超全国高职平均水平。学校培养了一批世界拔尖技术技能精英，共获得世界技能大赛奖牌12枚、全国技能大赛奖牌12枚，竞赛成绩名列全国参赛单位前列。/学校遵循高等职业教育规律，以立德树人为根本，以服务“双区”建设为宗旨，坚持“将党的教育方针融入办学治校全领域，将学校发展融入民族复兴大格局，将人才培养融入‘双区’建设大战略，将工匠精神融入教育教学全过程”的办学思路，着力培养应用型、复合型、创新型、数字化、国际化高素质技术技能人才，奋力创建中国特色、世界一流职业院校。 | AB29: / | AC29: https://www.szcp.edu.cn/ | AD29: https://zhaosheng.szcp.edu.cn/ | AE29: 0755-83759856 0755-83759861 | AF29: 深圳市龙岗区龙岗街道五联社区将军帽路1号 | AG29: / | AH29: 2768 | AI29: https://baike.baidu.com/item/%E6%B7%B1%E5%9C%B3%E5%9F%8E%E5%B8%82%E8%81%8C%E4%B8%9A%E5%AD%A6%E9%99%A2 | AJ29: https://gaokao.chsi.com.cn/zsgs/zhangcheng/listZszc--schId-5453828216.dhtml | AK29: /
A30: 25 | B30: =C30 -> 0 | D30: 依据学考 | E30: 10833 | F30: 广东轻工职业技术大学 | G30: 608 | H30: 235 | I30: 280 | J30: 235 | K30: 282 | L30: 383 | M30: 395 | N30: 16943 | O30: 15058 | P30: =IFERROR(AVERAGE(L30:M30),"/") -> 389 | Q30: =IFERROR(AVERAGE(N30:O30),"/") -> 16000.5 | R30: 广东省 | S30: 广州市 | T30: 广东省 | U30: 职业本科 | V30: 广东省 | W30: 公办 | X30: 一线城市 | Y30: 省属/双高计划/高水平学校建设单位/国家级示范/现代学徒制试点学院 | Z30: 第二类高水平学校B档示范高职现代学徒 | AA30: 广东轻工职业技术学院创建于1933年，是省属唯一国家示范性高等职业院校，全国“双高”高职院校建设单位。前身是“广东省立第一职业学校”，至今已有86年职业教育历史，其中1959/1963年和1978/1983年两段时期，学校开办本科教育，现有全日制在校生21000余人。学校秉承“德能兼备，学以成之”的校训和“自强、敬业、求实、创新”的广轻精神，为珠三角地区乃至全国输送数万名高素质高技能应用型人才。////办学条件好////学校现有广州和南海两个校区，其中广州校区定位为“大文科校区”，文科、艺术类专业面向广州现代服务业；南海校区成为“大工科校区”，工科专业面向珠江西岸高端制造业，校园总面积1700多亩，校舍建筑面积43万多平方米，其中教学科研实训用房近20万平方米，图书馆3万多平方米，学生公寓近16万平方米。固定资产总值15.5亿元，教学仪器设备总值2亿多元，学校图书馆拥有藏书近160万册，电子图书200多万册。网络信息点数2万多个，音视频电子资源1万多小时，学校校园无线网络全覆盖。建有校内实践教学基地近350个、校外实训实习基地900多个。////办学成果优异////学校是广东省唯一拥有7个省级工程技术开发中心的高职院校，是同时拥有省级协同发展中心及协同育人平台的两所高职院校之一，是全国第一批教育信息化试点单位、教育部现代学徒制试点单位、全国高校思政研究会高职高专专业委员会副会长单位（广东省会长单位）、全国跨境电商专业人才培养示范校、全国群众体育先进单位、全国高职“一校一品”示范单位、全国社会实践工作优秀单位、广东省依法治校示范校单位、广东省创新创业示范校单位、广东省安全文明校园示范校单位、广东省示范职业教育集团、广东省集团化办学单位、国防教育特色学校。学校立项“国家标杆党支部”1个，并先后获得全国高等职业院校全国服务贡献50强（连续两年）、全国高等职业院校实习管理50强、全国高等职业院校教学资源50强、全国高等职业院校学生管理50强、全国高等职业院校教学管理50强、全国高等职业院校育人成效50强、亚太职业院校影响力50强、全国示范性高职院校影响力排行榜30强、全国普通高校竞赛评估（高职）20强，全国高职院校思政工作创新优秀示范案例50强。全国高职院校创新创业示范校50强。2019年中国高职高专院校综合竞争力排行榜第9名。////多功能文化食堂、智能垃圾分类系统等创新性后勤改革领先全国。////师资队伍结构合理，业务水平高////学校现有教职工1200余人，其中高级职称教师400余人（二级教授9人），珠江学者9/人，“双师”素质教师70/0余人；国务院特殊津贴专家2人，全国模范教师2人，国家级教学名师2人，国家级教学团队2个，国家“万人计划”教学名师1人，全国技术能手2人，全国青年岗位能手1人，全国高校思想政治理论课教师影响力人物2人，全国轻工行业先进工作者1人，中国轻工职业教育教学名师1人，全国辅导员年度人物1名，广东省高校“千百十工程”国家级培养对象2人，南粤优秀教师11人，南粤优秀教育工作者4人，广东省“特支计划”教学名师、广东省教学名师、专业领军人才等名师专家近70人。建立了一个由企业一线工作的技术人员、能工巧匠、高级经理人等组成的优质兼职教师资源库，兼职教师与专业专任教师数之比达到1:1以上。学校在广东省高职院校教师队伍建设考核中连续三年排名第一。2019年全国高职院校教师教学发展指数排前十名。////教学成果丰硕////学校设有机电技术学院、食品与生物技术学院、轻化工技术学院、信息技术学院、汽车技术学院、生态环境技术学院、艺术设计学院、财贸学院、管理学院、应用外语学院、创业学院、马克思主义学院和继续教育学院，三个协同教学中心（工业机器人协同教学中心、现代信息技术与新工科协同教学中心、应用外语协同教学中心），设20个专业群、69个招生专业。2016年11月，学校成立创业学院，面向全体学生进行创新创业通识教育，面向精英学生进行创新创业定制培养。学校已建成国家示范性专业4个、央财“支持高等职业学校提升专业服务产业发展能力”项目经费支持专业2个、省级示范性专业3个、省级重点（建设）专业13个、省级品牌专业建设项目13个，建有国家级教学资源库1个、国家级精品课程10门、国家级精品资源共享课程9门、全国高校职业发展与就业指导示范课程1门、国家教指委精品课程22门、省级精品课程21门、省级优质课程2门，立项省级精品开放课程4/5门，其中已验收3门，在建省级专业资源库2个。2009年以来，学校共获得国家级优秀教学成果二等奖10项，行业教指会特等奖2个，省级优秀教学成果一等奖9项，省级优秀教学成果二等奖5项。////职教特色明显，人才培养质量高////学校是教育部现代学徒制试点单位，已立项国家级现代学徒制试点项目3项，省级现代学徒制试点项目/9项。学校积极构建职业教育“立交桥”，全面实施“纵向延伸，横向拓展”协同育人模式，开展了“3+2”中高衔接、“2+2”和“4+0”高本联培、“3+2”高本衔接、工程硕士培养等多种形式的协同培养，其中本科专业共1/3个，搭建起“中/高/本/硕”现代职业教育体系框架。连续多年，录取人数和录取分数线均位居省内同类院校前茅，文理类、艺术类高考录取分数线均高于本科省控线。毕业生深受用人单位欢迎，母校的满意度和薪资水平高于全国示范校平均水平，初次就业率高于98%，用人单位满意度99%以上。学生在各级各类技能大赛中获奖数量与质量节节攀升。近三年来，共获得国家级奖项500多个、省部级奖项1000余个。////产教融合，社会服务能力强////学校构建并不断完善政校行企协同促进产教融合长效机制，围绕高水平专业群建设，打造“一群一院一联盟”，搭建了广东轻工职教集团、轻工行业应用技术协同创新发展中心、南海职业教育政校行企协同创新联盟、广东省工业互联网产教联盟、粤港澳数字创意产教联盟、粤港澳跨境电商产教联盟、广东酒店职业教育联盟、全国精准营养食品与果蔬加工产教联盟、国家中小微企业知识产权培训基地等产学研创新、科技研发与转化平台，与华为等世界500强知名企业合作成立了华为ICT学院、瀚蓝环境学院、白天鹅学院、雷诺钟表学院、许鸿飞国际文创学院等10个产业学院，实现校企精准对接，产教深度融合，精准育人。近五年，获国家级科技项目4项、省级36项；国家级、省级科技奖励13项；面向企业开展科技攻关项目200余项。申报专利近430项，授权近300项，专利申请量连续多年位列广州地区高校（含本科）前十名。////坚持对外合作，国际化办学水平高////学校积极广泛开展对外交流与合作，已与国（境）外多所高等院校建立了合作关系，在引进智力与优质教育资源、人才培养、合作办学、汉语言培训等方面开展了实质性的合作。累计已招收来自30多个国家的留学生4/00余名。2017年，学校牵头组建广东省“一带一路”职业教育联盟，输出广轻职教模式，服务“一带一路”沿线国家及地区，国际化办学呈现新气象。////构建终身教育体系，服务广东经济社会////依托“国家中小微企业知识产权培训（南海）基地”“广东轻工培训中心”“职教师资优质省级基地”“广东省专业技术人员继续教育基地”“广东省职业技能鉴定所”等国家级和省级平台，并设有专门和专业性培训机构30多个，面向社会、社区和产业、行业积极开展各级各类培训服务，年培训量超15万人天；与本科院校进行网络远程教育及自学考试合作，并在深圳、佛山、珠海、韶关等地设立12个校外专科继续教育教学点，学校各类学历继续教育在读人数4000余人。////“十三五”期间，学校将遵循“三大一强”院校治理理念，围绕“创新强校工程”及一流高职院校建设，努力把学校建成“国内一流、国际知名”国家优质高职院校，成为高职院校治理的标准与典范，成为高素质技术技能型人才培养的典范。 | AB30: 学校创建于1933年，原名广东省立第一职业学校，学校数易其名，先后更名为广东省立广州农工业职业学校、广东省立广州工业职业学校、广东省立广州高级工业职业学校、广东省广州高级工业技术学校、广东省轻工业学校、广东轻工业学院、广州轻工业学校等 ，1959～1963年和1978～1983年曾开办本科职业教育。 1999年，学校升格为广东轻工职业技术学院。 2020年，广东省轻工职业技术学校、广东省石油化工职业技术学校并入。 2024年6月，教育部正式同意在广东轻工职业技术学院的基础上设立广东轻工职业技术大学。 9月3日，广东轻工职业技术大学正式揭牌。 | AC30: http://www.gdqy.edu.cn/ | AD30: http://gdqyzs.jysd.com/ | AE30: 020/61230198 | AF30: 广州市新港西路152号 | AG30: / | AH30: 369 | AI30: https://baike.baidu.com/item/%E5%B9%BF%E4%B8%9C%E8%BD%BB%E5%B7%A5%E8%81%8C%E4%B8%9A%E6%8A%80%E6%9C%AF%E5%A4%A7%E5%AD%A6 | AJ30: https://gaokao.chsi.com.cn/zsgs/zhangcheng/listZszc//schId/620.dhtml | AK30: /
A31: 26 | B31: =C31 -> 0 | D31: 依据学考 | E31: 10833 | F31: 广东轻工职业技术大学 | G31: 607 | H31: 120 | I31: 110 | J31: 120 | K31: 110 | L31: 384 | M31: 394 | N31: 15402 | O31: 16635 | P31: =IFERROR(AVERAGE(L31:M31),"/") -> 389 | Q31: =IFERROR(AVERAGE(N31:O31),"/") -> 16018.5 | R31: 广东省 | S31: 广州市 | T31: 广东省 | U31: 职业本科 | V31: 广东省 | W31: 公办 | X31: 一线城市 | Y31: 省属/双高计划/高水平学校建设单位/国家级示范/现代学徒制试点学院 | Z31: 第二类高水平学校B档示范高职现代学徒 | AA31: 广东轻工职业技术学院创建于1933年，是省属唯一国家示范性高等职业院校，全国“双高”高职院校建设单位。前身是“广东省立第一职业学校”，至今已有86年职业教育历史，其中1959/1963年和1978/1983年两段时期，学校开办本科教育，现有全日制在校生21000余人。学校秉承“德能兼备，学以成之”的校训和“自强、敬业、求实、创新”的广轻精神，为珠三角地区乃至全国输送数万名高素质高技能应用型人才。////办学条件好////学校现有广州和南海两个校区，其中广州校区定位为“大文科校区”，文科、艺术类专业面向广州现代服务业；南海校区成为“大工科校区”，工科专业面向珠江西岸高端制造业，校园总面积1700多亩，校舍建筑面积43万多平方米，其中教学科研实训用房近20万平方米，图书馆3万多平方米，学生公寓近16万平方米。固定资产总值15.5亿元，教学仪器设备总值2亿多元，学校图书馆拥有藏书近160万册，电子图书200多万册。网络信息点数2万多个，音视频电子资源1万多小时，学校校园无线网络全覆盖。建有校内实践教学基地近350个、校外实训实习基地900多个。////办学成果优异////学校是广东省唯一拥有7个省级工程技术开发中心的高职院校，是同时拥有省级协同发展中心及协同育人平台的两所高职院校之一，是全国第一批教育信息化试点单位、教育部现代学徒制试点单位、全国高校思政研究会高职高专专业委员会副会长单位（广东省会长单位）、全国跨境电商专业人才培养示范校、全国群众体育先进单位、全国高职“一校一品”示范单位、全国社会实践工作优秀单位、广东省依法治校示范校单位、广东省创新创业示范校单位、广东省安全文明校园示范校单位、广东省示范职业教育集团、广东省集团化办学单位、国防教育特色学校。学校立项“国家标杆党支部”1个，并先后获得全国高等职业院校全国服务贡献50强（连续两年）、全国高等职业院校实习管理50强、全国高等职业院校教学资源50强、全国高等职业院校学生管理50强、全国高等职业院校教学管理50强、全国高等职业院校育人成效50强、亚太职业院校影响力50强、全国示范性高职院校影响力排行榜30强、全国普通高校竞赛评估（高职）20强，全国高职院校思政工作创新优秀示范案例50强。全国高职院校创新创业示范校50强。2019年中国高职高专院校综合竞争力排行榜第9名。////多功能文化食堂、智能垃圾分类系统等创新性后勤改革领先全国。////师资队伍结构合理，业务水平高////学校现有教职工1200余人，其中高级职称教师400余人（二级教授9人），珠江学者9/人，“双师”素质教师70/0余人；国务院特殊津贴专家2人，全国模范教师2人，国家级教学名师2人，国家级教学团队2个，国家“万人计划”教学名师1人，全国技术能手2人，全国青年岗位能手1人，全国高校思想政治理论课教师影响力人物2人，全国轻工行业先进工作者1人，中国轻工职业教育教学名师1人，全国辅导员年度人物1名，广东省高校“千百十工程”国家级培养对象2人，南粤优秀教师11人，南粤优秀教育工作者4人，广东省“特支计划”教学名师、广东省教学名师、专业领军人才等名师专家近70人。建立了一个由企业一线工作的技术人员、能工巧匠、高级经理人等组成的优质兼职教师资源库，兼职教师与专业专任教师数之比达到1:1以上。学校在广东省高职院校教师队伍建设考核中连续三年排名第一。2019年全国高职院校教师教学发展指数排前十名。////教学成果丰硕////学校设有机电技术学院、食品与生物技术学院、轻化工技术学院、信息技术学院、汽车技术学院、生态环境技术学院、艺术设计学院、财贸学院、管理学院、应用外语学院、创业学院、马克思主义学院和继续教育学院，三个协同教学中心（工业机器人协同教学中心、现代信息技术与新工科协同教学中心、应用外语协同教学中心），设20个专业群、69个招生专业。2016年11月，学校成立创业学院，面向全体学生进行创新创业通识教育，面向精英学生进行创新创业定制培养。学校已建成国家示范性专业4个、央财“支持高等职业学校提升专业服务产业发展能力”项目经费支持专业2个、省级示范性专业3个、省级重点（建设）专业13个、省级品牌专业建设项目13个，建有国家级教学资源库1个、国家级精品课程10门、国家级精品资源共享课程9门、全国高校职业发展与就业指导示范课程1门、国家教指委精品课程22门、省级精品课程21门、省级优质课程2门，立项省级精品开放课程4/5门，其中已验收3门，在建省级专业资源库2个。2009年以来，学校共获得国家级优秀教学成果二等奖10项，行业教指会特等奖2个，省级优秀教学成果一等奖9项，省级优秀教学成果二等奖5项。////职教特色明显，人才培养质量高////学校是教育部现代学徒制试点单位，已立项国家级现代学徒制试点项目3项，省级现代学徒制试点项目/9项。学校积极构建职业教育“立交桥”，全面实施“纵向延伸，横向拓展”协同育人模式，开展了“3+2”中高衔接、“2+2”和“4+0”高本联培、“3+2”高本衔接、工程硕士培养等多种形式的协同培养，其中本科专业共1/3个，搭建起“中/高/本/硕”现代职业教育体系框架。连续多年，录取人数和录取分数线均位居省内同类院校前茅，文理类、艺术类高考录取分数线均高于本科省控线。毕业生深受用人单位欢迎，母校的满意度和薪资水平高于全国示范校平均水平，初次就业率高于98%，用人单位满意度99%以上。学生在各级各类技能大赛中获奖数量与质量节节攀升。近三年来，共获得国家级奖项500多个、省部级奖项1000余个。////产教融合，社会服务能力强////学校构建并不断完善政校行企协同促进产教融合长效机制，围绕高水平专业群建设，打造“一群一院一联盟”，搭建了广东轻工职教集团、轻工行业应用技术协同创新发展中心、南海职业教育政校行企协同创新联盟、广东省工业互联网产教联盟、粤港澳数字创意产教联盟、粤港澳跨境电商产教联盟、广东酒店职业教育联盟、全国精准营养食品与果蔬加工产教联盟、国家中小微企业知识产权培训基地等产学研创新、科技研发与转化平台，与华为等世界500强知名企业合作成立了华为ICT学院、瀚蓝环境学院、白天鹅学院、雷诺钟表学院、许鸿飞国际文创学院等10个产业学院，实现校企精准对接，产教深度融合，精准育人。近五年，获国家级科技项目4项、省级36项；国家级、省级科技奖励13项；面向企业开展科技攻关项目200余项。申报专利近430项，授权近300项，专利申请量连续多年位列广州地区高校（含本科）前十名。////坚持对外合作，国际化办学水平高////学校积极广泛开展对外交流与合作，已与国（境）外多所高等院校建立了合作关系，在引进智力与优质教育资源、人才培养、合作办学、汉语言培训等方面开展了实质性的合作。累计已招收来自30多个国家的留学生4/00余名。2017年，学校牵头组建广东省“一带一路”职业教育联盟，输出广轻职教模式，服务“一带一路”沿线国家及地区，国际化办学呈现新气象。////构建终身教育体系，服务广东经济社会////依托“国家中小微企业知识产权培训（南海）基地”“广东轻工培训中心”“职教师资优质省级基地”“广东省专业技术人员继续教育基地”“广东省职业技能鉴定所”等国家级和省级平台，并设有专门和专业性培训机构30多个，面向社会、社区和产业、行业积极开展各级各类培训服务，年培训量超15万人天；与本科院校进行网络远程教育及自学考试合作，并在深圳、佛山、珠海、韶关等地设立12个校外专科继续教育教学点，学校各类学历继续教育在读人数4000余人。////“十三五”期间，学校将遵循“三大一强”院校治理理念，围绕“创新强校工程”及一流高职院校建设，努力把学校建成“国内一流、国际知名”国家优质高职院校，成为高职院校治理的标准与典范，成为高素质技术技能型人才培养的典范。 | AB31: 学校创建于1933年，原名广东省立第一职业学校，学校数易其名，先后更名为广东省立广州农工业职业学校、广东省立广州工业职业学校、广东省立广州高级工业职业学校、广东省广州高级工业技术学校、广东省轻工业学校、广东轻工业学院、广州轻工业学校等 ，1959～1963年和1978～1983年曾开办本科职业教育。 1999年，学校升格为广东轻工职业技术学院。 2020年，广东省轻工职业技术学校、广东省石油化工职业技术学校并入。 2024年6月，教育部正式同意在广东轻工职业技术学院的基础上设立广东轻工职业技术大学。 9月3日，广东轻工职业技术大学正式揭牌。 | AC31: http://www.gdqy.edu.cn/ | AD31: http://gdqyzs.jysd.com/ | AE31: 020/61230198 | AF31: 广州市新港西路152号 | AG31: / | AH31: 369 | AI31: https://baike.baidu.com/item/%E5%B9%BF%E4%B8%9C%E8%BD%BB%E5%B7%A5%E8%81%8C%E4%B8%9A%E6%8A%80%E6%9C%AF%E5%A4%A7%E5%AD%A6 | AJ31: https://gaokao.chsi.com.cn/zsgs/zhangcheng/listZszc//schId/620.dhtml | AK31: /
A32: 27 | B32: =C32 -> 0 | D32: 依据学考 | E32: 10831 | F32: 顺德职业技术大学 | G32: 601 | H32: 191 | I32: 193 | J32: 191 | K32: 193 | L32: 382 | M32: 395 | N32: 17684 | O32: 15092 | P32: =IFERROR(AVERAGE(L32:M32),"/") -> 388.5 | Q32: =IFERROR(AVERAGE(N32:O32),"/") -> 16388 | R32: 广东省 | S32: 佛山市 | T32: 广东省 | U32: 职业本科 | V32: 广东省 | W32: 公办 | X32: 新一线城市 | Y32: 双高计划/高水平学校建设单位/国家级骨干/现代学徒制试点学院 | Z32: 第二类高水平学校B档骨干高职现代学徒 | AA32: 顺德职业技术学院成立于1999年3月，是经国家教育部批准成立、广东省人民政府领导管理、省市共建、顺德区政府投资兴建的地方高职院校。经过多年的建设发展，学校已成为国家示范（骨干）高等职业院校、广东省示范性高等职业院校、广东省一流高职院校建设单位。学校环境优美、设施良好、制度健全、管理科学，是莘莘学子求学成才的理想之地。先后获得“全国职业教育先进单位”、“全国绿化模范单位”、“全国节能型公共机构示范单位”、“广东省安全文明校园”、“广东省依法治校示范学校”等荣誉称号或奖励，为区域经济社会发展培养一大批高素质技术技能人才做出了积极贡献。//学校的前身是1994年12月成立的顺德永强成人学院。2002年7月，顺德师范学校（1924年成立）和顺德成人卫生中等专业学校（1958年成立）合并到顺德职业技术学院。2002年，学校迁入位于德胜东路的新校园。//2005年12月，学校以优秀成绩通过国家教育部高职高专人才培养工作水平评估。2008年7月，学校被教育部财政部确定为国家重点培育高等职业院校立项进行建设，并于2010年通过验收。2009年9月，学校被广东省教育厅财政厅确定为广东省示范性高等职业院校建设项目立项建设单位。2010年12月学校被教育部财政部确定为“国家示范性高等职业院校建设计划”骨干高职院校第一批立项建设单位，并于2013年11月以优秀成绩通过验收。2016年，学校被广东省教育厅确定为广东省一流高职院校建设单位。//学校现设有10个二级学院（机电工程学院、电子与信息工程学院、应用化工技术学院、医药卫生学院、设计学院、经济管理学院、酒店与旅游管理学院、人文社科学院、外语学院、马克思主义学院）。学校共有专业49个，其中国家教育改革试点专业2个（制冷与空调技术、家具艺术设计）、中央财政支持重点专业2个（工业设计、烹饪工艺与营养）、广东省示范性专业8个（数控技术、汽车检测与维修技术、制冷与空调技术、电子信息工程技术、应用化工技术、家具艺术设计、会计、工商企业管理）、广东省重点专业3个（物流管理、酒店管理、应用英语）、广东省重点建设专业3个（园林技术、工业分析技术、机电一体化技术）、第一批省级一类品牌建设专业2个（制冷与空调技术、家具艺术设计）、第二批省级二类品牌建设专业5个（计算机应用技术、药学、金融管理、展示艺术设计、数字媒体艺术设计）。//学校获国家高等教育教学成果奖4项，广东省高等教育教学成果奖23项。共建有国家级精品课程12门，国家精品资源共享课立项建设项目9门；省级精品课程22门，广东省高职教育精品开放课程5门，广东省高职教育精品在线开放课程4门，广东省精品视频公开课1门，广东省精品资源共享课19门。//学校办学条件良好，教学环境优良。学校建筑面积超过57万平方米，固定资产总额超过12.36亿元人民币，/教学、科研仪器设备总值3.12亿元。拥有校内实训基地19个，实验实训室197个，其中中央财政支持实训基地1个，省级重点实训基地9个。学校有校外实训基地541个，其中省级大学生校外实践教学基地13个。学生文化体育设施齐全，建有高标准的田径场、篮球场等各类场馆。//学校共有21个科研平台，4个技术服务平台。科研平台中以学校为第一申报的平台有16个，其中省部级6个，市厅级12个。获国家自然科研基金项目11项（含主持7项）、主持获得教育部人文社科项目9项、省自然科学基金项目12项，省哲学社会科学项目20项。横向项目累计到账经费达到了4475.32万元。省部级及以上的科研奖7项。获专利授权388件，其中发明专利授权85件，实用新型专利247件，累计有34项发明专利实现了转化。//全校教职工总数924人，其中高级职称263人。现有专任教师730人。有国家级教学团队1个、省级教学团队6个，国家级教学名师2人、省级教学名师5人、广东省“特支计划”教学名师4人，南粤优秀教师6人，广东省“千百十工程”省级培养对象7人，广东省高等学校优秀青年教师培养计划培养对象6人，广东省高等职业教育专业领军人才培养对象5人。//学校全日制在校生15703人，成人教育在读学员2915人。获国际奖项德国红点奖1项；国家级教学成果奖4项，省级教学成果奖23项；全国性职业技能竞赛一等奖120个、二等奖198个，位居全国全省前列。2016年，获评全国高职院校创新创业示范校50强。2017年高考招生，我校在顺德区以外录取的新生，高考成绩100%高于全省二本分数线，顺德区内考生分数线也接近全省二本分数线。学校每年毕业生供不应求，初次就业率连续多年高于98%。2014年，获评全国职业院校就业竞争力示范校。//学校国际化发展坚持“引进来”与“走出去”相结合，与英国、美国、澳大利亚、德国、台湾、香港等国家和地区的40多所高校和机构保持了友好合作关系。与马来西亚UCSI大学合作共建的马来西亚UCSI大学顺峰烹饪学院，是中国高等教育在海外建立的第一个烹饪学院，开创了中国烹饪高等教育走向世界的先河。与世界酒店管理知名学府——香港理工大学酒店及旅游业管理学院合作，联合培养高水平酒店管理专业人才。2017年，国务院侨办批准在我校设立“海外惠侨工程—中餐繁荣基地”（国内仅有3家），这是对我校近年来餐饮教学及面向国内外的餐饮文化交流活动成效和影响的充分肯定，为我校烹饪专业教学及中国烹饪学院建设赢来了更大国际化发展空间和机遇。与德国亚琛工业大学达成合作协议，共建广东—亚琛工业4.0应用研究中心。中心建成后，将以德国工业4.0技术与理念为指引，通过工业4.0示范工厂和示范线建设、展览展示、技术实施与服务等开展高端技术研究、技术推广与服务等活动，以高水平的国际合作带动人才培养、校企合作的良性发展，形成示范引领带动作用；推动顺德以及珠三角地区装备制造产业、智能制造与工业机器人产业、工厂自动化与智慧工厂等产业优化升级。//上级领导高度肯定学校办学成果。2011年7月14日，时任中共中央政治局委员、广东省委书记汪洋，省委常委、副省长肖志恒，省委常委、秘书长徐少华，佛山市委书记陈云贤，广东省教育厅厅长罗伟其等领导到学校进行专题调研，汪洋书记充分肯定我校为区域经济转型升级提供的人力支持。2009年11月18日，国家教育部副部长鲁昕率领职成司司长葛道凯、原高教司高职高专处处长范唯等到我校调研，鲁副部长认为我校走出了一条能引领全国职业教育改革的新路子。//在新的发展时期，学校瞄准“国内一流、国际有影响”的一流高职建设目标，坚持“以贡献求支持，以服务求发展”，以智慧化、国际化、法治化、市场化为重点全面推进内涵建设，争取成为第一批中国特色高水平高职院校。 | AB32: 学校前身是成立于1994年的顺德永强成人学院；1999年，教育部批准成立顺德职业技术学院。2002年，顺德师范学校和顺德成人卫生中等专业学校并入学校，同年，学校迁至佛山市顺德区德胜东路现址。2019年，学校入选中国特色高水平高职学校和专业建设计划建设单位。2025年6月，经教育部批准，以顺德职业技术学院为基础设立顺德职业技术大学。 | AC32: http://www.sdpt.com.cn/ | AD32: http://zs.sdpt.edu.cn | AE32: 0757/22327131、22327132、22323732、22327270 | AF32: 校本部：广东省佛山市顺德区大良街道德胜东路； | AG32: https://www.720yun.com/t/a4c2ejrkxer | AH32: 372 | AI32: https://baike.baidu.com/item/%E9%A1%BA%E5%BE%B7%E8%81%8C%E4%B8%9A%E6%8A%80%E6%9C%AF%E5%AD%A6%E9%99%A2 | AJ32: https://gaokao.chsi.com.cn/zsgs/zhangcheng/listZszc//schId/618.dhtml | AK32: /
A33: 28 | B33: =C33 -> 0 | D33: 依据学考 | E33: 10833 | F33: 广东轻工职业技术大学 | G33: 606 | H33: 55 | I33: 80 | J33: 55 | K33: 80 | L33: 381 | M33: 395 | N33: 18492 | O33: 14572 | P33: =IFERROR(AVERAGE(L33:M33),"/") -> 388 | Q33: =IFERROR(AVERAGE(N33:O33),"/") -> 16532 | R33: 广东省 | S33: 广州市 | T33: 广东省 | U33: 职业本科 | V33: 广东省 | W33: 公办 | X33: 一线城市 | Y33: 省属/双高计划/高水平学校建设单位/国家级示范/现代学徒制试点学院 | Z33: 第二类高水平学校B档示范高职现代学徒 | AA33: 广东轻工职业技术学院创建于1933年，是省属唯一国家示范性高等职业院校，全国“双高”高职院校建设单位。前身是“广东省立第一职业学校”，至今已有86年职业教育历史，其中1959/1963年和1978/1983年两段时期，学校开办本科教育，现有全日制在校生21000余人。学校秉承“德能兼备，学以成之”的校训和“自强、敬业、求实、创新”的广轻精神，为珠三角地区乃至全国输送数万名高素质高技能应用型人才。////办学条件好////学校现有广州和南海两个校区，其中广州校区定位为“大文科校区”，文科、艺术类专业面向广州现代服务业；南海校区成为“大工科校区”，工科专业面向珠江西岸高端制造业，校园总面积1700多亩，校舍建筑面积43万多平方米，其中教学科研实训用房近20万平方米，图书馆3万多平方米，学生公寓近16万平方米。固定资产总值15.5亿元，教学仪器设备总值2亿多元，学校图书馆拥有藏书近160万册，电子图书200多万册。网络信息点数2万多个，音视频电子资源1万多小时，学校校园无线网络全覆盖。建有校内实践教学基地近350个、校外实训实习基地900多个。////办学成果优异////学校是广东省唯一拥有7个省级工程技术开发中心的高职院校，是同时拥有省级协同发展中心及协同育人平台的两所高职院校之一，是全国第一批教育信息化试点单位、教育部现代学徒制试点单位、全国高校思政研究会高职高专专业委员会副会长单位（广东省会长单位）、全国跨境电商专业人才培养示范校、全国群众体育先进单位、全国高职“一校一品”示范单位、全国社会实践工作优秀单位、广东省依法治校示范校单位、广东省创新创业示范校单位、广东省安全文明校园示范校单位、广东省示范职业教育集团、广东省集团化办学单位、国防教育特色学校。学校立项“国家标杆党支部”1个，并先后获得全国高等职业院校全国服务贡献50强（连续两年）、全国高等职业院校实习管理50强、全国高等职业院校教学资源50强、全国高等职业院校学生管理50强、全国高等职业院校教学管理50强、全国高等职业院校育人成效50强、亚太职业院校影响力50强、全国示范性高职院校影响力排行榜30强、全国普通高校竞赛评估（高职）20强，全国高职院校思政工作创新优秀示范案例50强。全国高职院校创新创业示范校50强。2019年中国高职高专院校综合竞争力排行榜第9名。////多功能文化食堂、智能垃圾分类系统等创新性后勤改革领先全国。////师资队伍结构合理，业务水平高////学校现有教职工1200余人，其中高级职称教师400余人（二级教授9人），珠江学者9/人，“双师”素质教师70/0余人；国务院特殊津贴专家2人，全国模范教师2人，国家级教学名师2人，国家级教学团队2个，国家“万人计划”教学名师1人，全国技术能手2人，全国青年岗位能手1人，全国高校思想政治理论课教师影响力人物2人，全国轻工行业先进工作者1人，中国轻工职业教育教学名师1人，全国辅导员年度人物1名，广东省高校“千百十工程”国家级培养对象2人，南粤优秀教师11人，南粤优秀教育工作者4人，广东省“特支计划”教学名师、广东省教学名师、专业领军人才等名师专家近70人。建立了一个由企业一线工作的技术人员、能工巧匠、高级经理人等组成的优质兼职教师资源库，兼职教师与专业专任教师数之比达到1:1以上。学校在广东省高职院校教师队伍建设考核中连续三年排名第一。2019年全国高职院校教师教学发展指数排前十名。////教学成果丰硕////学校设有机电技术学院、食品与生物技术学院、轻化工技术学院、信息技术学院、汽车技术学院、生态环境技术学院、艺术设计学院、财贸学院、管理学院、应用外语学院、创业学院、马克思主义学院和继续教育学院，三个协同教学中心（工业机器人协同教学中心、现代信息技术与新工科协同教学中心、应用外语协同教学中心），设20个专业群、69个招生专业。2016年11月，学校成立创业学院，面向全体学生进行创新创业通识教育，面向精英学生进行创新创业定制培养。学校已建成国家示范性专业4个、央财“支持高等职业学校提升专业服务产业发展能力”项目经费支持专业2个、省级示范性专业3个、省级重点（建设）专业13个、省级品牌专业建设项目13个，建有国家级教学资源库1个、国家级精品课程10门、国家级精品资源共享课程9门、全国高校职业发展与就业指导示范课程1门、国家教指委精品课程22门、省级精品课程21门、省级优质课程2门，立项省级精品开放课程4/5门，其中已验收3门，在建省级专业资源库2个。2009年以来，学校共获得国家级优秀教学成果二等奖10项，行业教指会特等奖2个，省级优秀教学成果一等奖9项，省级优秀教学成果二等奖5项。////职教特色明显，人才培养质量高////学校是教育部现代学徒制试点单位，已立项国家级现代学徒制试点项目3项，省级现代学徒制试点项目/9项。学校积极构建职业教育“立交桥”，全面实施“纵向延伸，横向拓展”协同育人模式，开展了“3+2”中高衔接、“2+2”和“4+0”高本联培、“3+2”高本衔接、工程硕士培养等多种形式的协同培养，其中本科专业共1/3个，搭建起“中/高/本/硕”现代职业教育体系框架。连续多年，录取人数和录取分数线均位居省内同类院校前茅，文理类、艺术类高考录取分数线均高于本科省控线。毕业生深受用人单位欢迎，母校的满意度和薪资水平高于全国示范校平均水平，初次就业率高于98%，用人单位满意度99%以上。学生在各级各类技能大赛中获奖数量与质量节节攀升。近三年来，共获得国家级奖项500多个、省部级奖项1000余个。////产教融合，社会服务能力强////学校构建并不断完善政校行企协同促进产教融合长效机制，围绕高水平专业群建设，打造“一群一院一联盟”，搭建了广东轻工职教集团、轻工行业应用技术协同创新发展中心、南海职业教育政校行企协同创新联盟、广东省工业互联网产教联盟、粤港澳数字创意产教联盟、粤港澳跨境电商产教联盟、广东酒店职业教育联盟、全国精准营养食品与果蔬加工产教联盟、国家中小微企业知识产权培训基地等产学研创新、科技研发与转化平台，与华为等世界500强知名企业合作成立了华为ICT学院、瀚蓝环境学院、白天鹅学院、雷诺钟表学院、许鸿飞国际文创学院等10个产业学院，实现校企精准对接，产教深度融合，精准育人。近五年，获国家级科技项目4项、省级36项；国家级、省级科技奖励13项；面向企业开展科技攻关项目200余项。申报专利近430项，授权近300项，专利申请量连续多年位列广州地区高校（含本科）前十名。////坚持对外合作，国际化办学水平高////学校积极广泛开展对外交流与合作，已与国（境）外多所高等院校建立了合作关系，在引进智力与优质教育资源、人才培养、合作办学、汉语言培训等方面开展了实质性的合作。累计已招收来自30多个国家的留学生4/00余名。2017年，学校牵头组建广东省“一带一路”职业教育联盟，输出广轻职教模式，服务“一带一路”沿线国家及地区，国际化办学呈现新气象。////构建终身教育体系，服务广东经济社会////依托“国家中小微企业知识产权培训（南海）基地”“广东轻工培训中心”“职教师资优质省级基地”“广东省专业技术人员继续教育基地”“广东省职业技能鉴定所”等国家级和省级平台，并设有专门和专业性培训机构30多个，面向社会、社区和产业、行业积极开展各级各类培训服务，年培训量超15万人天；与本科院校进行网络远程教育及自学考试合作，并在深圳、佛山、珠海、韶关等地设立12个校外专科继续教育教学点，学校各类学历继续教育在读人数4000余人。////“十三五”期间，学校将遵循“三大一强”院校治理理念，围绕“创新强校工程”及一流高职院校建设，努力把学校建成“国内一流、国际知名”国家优质高职院校，成为高职院校治理的标准与典范，成为高素质技术技能型人才培养的典范。 | AB33: 学校创建于1933年，原名广东省立第一职业学校，学校数易其名，先后更名为广东省立广州农工业职业学校、广东省立广州工业职业学校、广东省立广州高级工业职业学校、广东省广州高级工业技术学校、广东省轻工业学校、广东轻工业学院、广州轻工业学校等 ，1959～1963年和1978～1983年曾开办本科职业教育。 1999年，学校升格为广东轻工职业技术学院。 2020年，广东省轻工职业技术学校、广东省石油化工职业技术学校并入。 2024年6月，教育部正式同意在广东轻工职业技术学院的基础上设立广东轻工职业技术大学。 9月3日，广东轻工职业技术大学正式揭牌。 | AC33: http://www.gdqy.edu.cn/ | AD33: http://gdqyzs.jysd.com/ | AE33: 020/61230198 | AF33: 广州市新港西路152号 | AG33: / | AH33: 369 | AI33: https://baike.baidu.com/item/%E5%B9%BF%E4%B8%9C%E8%BD%BB%E5%B7%A5%E8%81%8C%E4%B8%9A%E6%8A%80%E6%9C%AF%E5%A4%A7%E5%AD%A6 | AJ33: https://gaokao.chsi.com.cn/zsgs/zhangcheng/listZszc//schId/620.dhtml | AK33: /
A34: 29 | B34: =C34 -> 0 | D34: 依据学考 | E34: 14845 | F34: 深圳城市职业学院 | G34: 603 | H34: 19 | I34: / | J34: 19 | K34: / | L34: 383 | M34: / | N34: 16653 | O34: / | P34: =IFERROR(AVERAGE(L34:M34),"/") -> 383 | Q34: =IFERROR(AVERAGE(N34:O34),"/") -> 16653 | R34: 广东省 | S34: 深圳市 | T34: 广东省 | U34: 专科（高职） | V34: 广东省 | W34: 公办 | X34: 一线城市 | Y34: / | Z34: / | AA34: 深圳城市职业学院是由深圳市人民政府举办，经广东省人民政府批准、教育部备案，以深圳技师学院为基础设立的公办全日制普通高等职业院校。2024年首批5个专业招生（夏季高考生）。/学校位于深圳市龙岗区中心城，占地555亩，现有中德智造学院、设计学院、信息与通信学院、商贸学院、珠宝学院等13个二级学院。现有专任教师577人，其中博士、硕士418人，高级职称175人。拥有国家级技能大师、全国技术能手/、鹏城工匠等一批高层次人才领衔的双师型师资队伍。最近两届全国人社系统教师职业能力大赛，均获得一等奖。获得第七届广东省青年教师竞赛一等奖1项、三等奖1项。目前建有“深圳市技能型社会研究中心”“龙岗区智能供应链技术重点实验室”等重点研究平台。/与华为、亚马逊、西门子等世界500强企业共建了10家现代产业学院，促进高质量就业。2024届毕业生初次就业平均起薪（6111元）、毕业去向落实率（98.2%）、优质就业率（29.5%）和学生就业满意度（89%），远超全国高职平均水平。学校培养了一批世界拔尖技术技能精英，共获得世界技能大赛奖牌12枚、全国技能大赛奖牌12枚，竞赛成绩名列全国参赛单位前列。/学校遵循高等职业教育规律，以立德树人为根本，以服务“双区”建设为宗旨，坚持“将党的教育方针融入办学治校全领域，将学校发展融入民族复兴大格局，将人才培养融入‘双区’建设大战略，将工匠精神融入教育教学全过程”的办学思路，着力培养应用型、复合型、创新型、数字化、国际化高素质技术技能人才，奋力创建中国特色、世界一流职业院校。 | AB34: / | AC34: https://www.szcp.edu.cn/ | AD34: https://zhaosheng.szcp.edu.cn/ | AE34: 0755-83759856 0755-83759861 | AF34: 深圳市龙岗区龙岗街道五联社区将军帽路1号 | AG34: / | AH34: 2768 | AI34: https://baike.baidu.com/item/%E6%B7%B1%E5%9C%B3%E5%9F%8E%E5%B8%82%E8%81%8C%E4%B8%9A%E5%AD%A6%E9%99%A2 | AJ34: https://gaokao.chsi.com.cn/zsgs/zhangcheng/listZszc--schId-5453828216.dhtml | AK34: /
A35: 30 | B35: =C35 -> 0 | D35: 依据学考 | E35: 12957 | F35: 深圳信息职业技术大学 | G35: 608 | H35: 13 | I35: / | J35: 13 | K35: / | L35: 383 | M35: / | N35: 16717 | O35: / | P35: =IFERROR(AVERAGE(L35:M35),"/") -> 383 | Q35: =IFERROR(AVERAGE(N35:O35),"/") -> 16717 | R35: 广东省 | S35: 深圳市 | T35: 广东省 | U35: 职业本科 | V35: 广东省 | W35: 公办 | X35: 一线城市 | Y35: 双高计划/高水平学校建设单位/国家级骨干/现代学徒制试点学院 | Z35: 第二类高水平学校B档骨干高职现代学徒 | AA35: 深圳信息职业技术学院创办于2002年4月，是经广东省人民政府批准、教育部备案，由深圳市人民政府举办的公办全日制高等院校。//学校现为国家示范（骨干）高职院校、国家示范性软件职业技术学院、教育部“中德职教汽车机电合作项目”试点院校，现拥有3个国家级高等职业教育专业教学资源库（含1个备选项目）。学校拥有现代化、生态型、信息化的校园，占地92.6万平方米（1389亩），建筑面积58.86万平方米。学校现有教学科研仪器设备总值为36786.36万元，图书馆藏书131.33万册。//学校对接深圳支柱产业，打造信息技术特色，共设软件学院、电子与通信学院、计算机学院、数字媒体学院、智能制造与装备学院、交通与环境学院、管理学院、财经学院、应用外语学院、中德学院、马克思主义学院、继续教育学院、创新创业学院、创新教育研究院、公共课教学部、体育部、信息技术研究所等14院2部1所；开设信息类为主的专业44个。现有国家骨干校重点建设专业4个，国家高等职业学校提升专业服务产业发展能力建设专业2个，全国职业院校示范专业点2个，国家高等职业教育教学资源库建设项目3个（含1个备选项目），广东省示范性专业4个，省级重点建设专业6个，省级品牌专业11个；国家级精品资源共享课7门、省级精品资源共享课（含精品在线开放课）38门、省级思想政治理论优质建设课程2门。//学校现有教职工796人，在590位专任教师中，副高及以上职称教师301人，其中，博士、博士后275人，“双师素质”教师九成。目前，学校拥有国家级教学团队1个，获国家级教学名师奖1人，获全国五一劳动奖章1人，国家万人计划教学名师1名，广东省教学名师奖3人，广东省“特支计划”教学名师3人，省级教学团队7个，南粤优秀教师7人，广东省“千百十人才培养工程”省级培养对象6人，广东省“珠江学者”特聘教授4人，深圳市“鹏城学者”特聘教授3人，深圳市政府特殊津贴1人，黄炎培职业教育杰出教师奖1人，深圳市高层次专业人才地方级领军人才9名，后备级领军人才21人，博士后创新实践基地在站博士后3人。//学校坚持科研引领、教研创新、突出应用、服务社会。已主持国家自然科学基金等国家级项目26项、省市级科研项目517项，教研课题国家级6项、省市级49项，深圳市首批教育科研专家工作室1个。获得国家级高等学校教学成果一等奖1项、二等奖2项，省级教学成果一等奖6项、二等奖4项，广东省科学技术二等奖2项、三等奖2项，国家教师科研基金“十一五”规划重点课题科研成果一等奖1项，深圳市科技进步奖2项，深圳市科技创新奖2项，深圳市科学技术奖自然科学奖1项，深圳市哲学社会科学优秀成果奖7项，中国人工智能学会进步奖二等奖；拥有发明专利62项，实用新型专利203项，外观设计专利8项。//学校坚持校企合作办学，积极推进产教融合协同育人，创新合作办学机制，探索校企合作模式，在校内构建了“三会两办”的办学机制，并打造了“学院+行业企业”的校企合作模式。学校用2万平米实训场地，引企入校，合作共建实践教学基地、科技创新平台等，基地目前建有2个省级创新平台、1个先进土木研究中心、1个智能制造实训中心、5个校级协同创新中心等创新载体。学校有国家级高等职业教育实训基地2个，省级高等职业教育实训基地11个，省级公共实训中心1个，省级大学生校外实践教学基地12个，深圳市高职教育校外公共实训基地33个。//学校建构高素质高技能人才培养机制，不断提升高就业率、高满意度办学效益。现有全日制在校生15468人，学校坚持产教融合、校企合作、因材施教、特色发展。近三年，学生参加专业技能竞赛共获国家级奖项137个，省级二等奖以上315个。毕业生“下得去、留得住、用得上、干得好”，毕业生总体就业率均在98%以上。毕业生被华为、腾讯、深圳地铁、中国联通等著名企业录用，产生了被《华尔街日报》报道为“中国最年轻90后千万富豪”丁仕源、拥有8家公司的速运邦邦CEO陈家良等创业典型。//学校积极引进国际先进教学资源，不断形成国际化办学特色。2012年，学校成为教育部“中德职教汽车机电合作项目”试点院校；2013年11月学校与西双版纳职业技术学院正式签署合作协议共建“深圳信息/西双版纳国际留学生基地”/并揭牌；2016年9月，由深圳市教育局和德国巴伐利亚州文教部推动，我校与德国巴伐利亚州帕绍技术学校、兰茨胡特应用技术大学合作创办中德学院；2018年5月，学校与芬兰于韦斯屈莱应用科技大学签订战略合作协议全面启动两校战略合作项目；此外，学校还与加拿大谢尔丹理工学院、韩国京畿大学、台湾地区朝阳科技大学、树德科技大学、龙华科技大学、台北城市科技大学、亚太创意技术学院等26所高校开展了师生交流、合作科研等项目。//学校跨越发展，已跻身全国高职院校“第一方阵”。2004年，学校成为“国家示范性软件职业技术学院”建设院校；2007年，以优异成绩通过教育部人才培养工作水平评估；2010年，成为国家骨干高职院校建设单位；2011年，获国家高等职业教育网络技术专业共享型教学资源库建设立项；2012年，入选教育部“中德职教汽车机电合作项目”试点院校；2014年获国家高等职业教育数字媒体专业群教学资源库立项；2015年，深圳市人力资源与社会保障局同意批准我校设立博士后创新实践基地；2016年，学校国家骨干校建设项目以“优秀”等级通过国家验收、获广东省“一流校”建设立项、学校“2188创客空间”被国家科学技术部认定为国家级众创空间，2016年学校又成功召开了第二次党代会，进一步确立了“全力打造有特色国际化一流职业院校”的奋斗目标。//青春深信成新锐，勇向潮头唱大风。学校将继续开拓奋进，勇于不断创新，努力把学校打造成有特色国际化一流职业院校。 | AB35: 学校原名为深圳信息职业技术学院，于2002年4月由深圳教育学院、深圳市工业学校、深圳市财经学校三所学校合并组建；2011年9月，学校从深圳市罗湖区迁至深圳市龙岗区。2012年，学校入选教育部“中德职教汽车机电合作项目”试点院校。2021年，学校获批设立广东省博士工作站。2025年6月，教育部发函广东省，同意以深圳信息职业技术学院为基础设立深圳信息职业技术大学，同时撤销深圳信息职业技术学院的建制。2026年1月，深圳信息职业技术大学正式成立。 | AC35: http://www.sziit.com.cn/ | AD35: http://zhaob.sziit.edu.cn/index.htm | AE35: 075589226360、075589226361 | AF35: 深圳市龙岗区龙翔大道2188号 | AG35: https://www.720yun.com/t/d4528mpguus | AH35: 184 | AI35: https://baike.baidu.com/item/%E6%B7%B1%E5%9C%B3%E4%BF%A1%E6%81%AF%E8%81%8C%E4%B8%9A%E6%8A%80%E6%9C%AF%E5%AD%A6%E9%99%A2 | AJ35: https://gaokao.chsi.com.cn/zsgs/zhangcheng/listZszc//schId/1429.dhtml | AK35: /
A36: 31 | B36: =C36 -> 0 | D36: 依据学考 | E36: 10831 | F36: 顺德职业技术大学 | G36: 603 | H36: 728 | I36: 742 | J36: 728 | K36: 742 | L36: 380 | M36: 395 | N36: 19355 | O36: 15110 | P36: =IFERROR(AVERAGE(L36:M36),"/") -> 387.5 | Q36: =IFERROR(AVERAGE(N36:O36),"/") -> 17232.5 | R36: 广东省 | S36: 佛山市 | T36: 广东省 | U36: 职业本科 | V36: 广东省 | W36: 公办 | X36: 新一线城市 | Y36: 双高计划/高水平学校建设单位/国家级骨干/现代学徒制试点学院 | Z36: 第二类高水平学校B档骨干高职现代学徒 | AA36: 顺德职业技术学院成立于1999年3月，是经国家教育部批准成立、广东省人民政府领导管理、省市共建、顺德区政府投资兴建的地方高职院校。经过多年的建设发展，学校已成为国家示范（骨干）高等职业院校、广东省示范性高等职业院校、广东省一流高职院校建设单位。学校环境优美、设施良好、制度健全、管理科学，是莘莘学子求学成才的理想之地。先后获得“全国职业教育先进单位”、“全国绿化模范单位”、“全国节能型公共机构示范单位”、“广东省安全文明校园”、“广东省依法治校示范学校”等荣誉称号或奖励，为区域经济社会发展培养一大批高素质技术技能人才做出了积极贡献。//学校的前身是1994年12月成立的顺德永强成人学院。2002年7月，顺德师范学校（1924年成立）和顺德成人卫生中等专业学校（1958年成立）合并到顺德职业技术学院。2002年，学校迁入位于德胜东路的新校园。//2005年12月，学校以优秀成绩通过国家教育部高职高专人才培养工作水平评估。2008年7月，学校被教育部财政部确定为国家重点培育高等职业院校立项进行建设，并于2010年通过验收。2009年9月，学校被广东省教育厅财政厅确定为广东省示范性高等职业院校建设项目立项建设单位。2010年12月学校被教育部财政部确定为“国家示范性高等职业院校建设计划”骨干高职院校第一批立项建设单位，并于2013年11月以优秀成绩通过验收。2016年，学校被广东省教育厅确定为广东省一流高职院校建设单位。//学校现设有10个二级学院（机电工程学院、电子与信息工程学院、应用化工技术学院、医药卫生学院、设计学院、经济管理学院、酒店与旅游管理学院、人文社科学院、外语学院、马克思主义学院）。学校共有专业49个，其中国家教育改革试点专业2个（制冷与空调技术、家具艺术设计）、中央财政支持重点专业2个（工业设计、烹饪工艺与营养）、广东省示范性专业8个（数控技术、汽车检测与维修技术、制冷与空调技术、电子信息工程技术、应用化工技术、家具艺术设计、会计、工商企业管理）、广东省重点专业3个（物流管理、酒店管理、应用英语）、广东省重点建设专业3个（园林技术、工业分析技术、机电一体化技术）、第一批省级一类品牌建设专业2个（制冷与空调技术、家具艺术设计）、第二批省级二类品牌建设专业5个（计算机应用技术、药学、金融管理、展示艺术设计、数字媒体艺术设计）。//学校获国家高等教育教学成果奖4项，广东省高等教育教学成果奖23项。共建有国家级精品课程12门，国家精品资源共享课立项建设项目9门；省级精品课程22门，广东省高职教育精品开放课程5门，广东省高职教育精品在线开放课程4门，广东省精品视频公开课1门，广东省精品资源共享课19门。//学校办学条件良好，教学环境优良。学校建筑面积超过57万平方米，固定资产总额超过12.36亿元人民币，/教学、科研仪器设备总值3.12亿元。拥有校内实训基地19个，实验实训室197个，其中中央财政支持实训基地1个，省级重点实训基地9个。学校有校外实训基地541个，其中省级大学生校外实践教学基地13个。学生文化体育设施齐全，建有高标准的田径场、篮球场等各类场馆。//学校共有21个科研平台，4个技术服务平台。科研平台中以学校为第一申报的平台有16个，其中省部级6个，市厅级12个。获国家自然科研基金项目11项（含主持7项）、主持获得教育部人文社科项目9项、省自然科学基金项目12项，省哲学社会科学项目20项。横向项目累计到账经费达到了4475.32万元。省部级及以上的科研奖7项。获专利授权388件，其中发明专利授权85件，实用新型专利247件，累计有34项发明专利实现了转化。//全校教职工总数924人，其中高级职称263人。现有专任教师730人。有国家级教学团队1个、省级教学团队6个，国家级教学名师2人、省级教学名师5人、广东省“特支计划”教学名师4人，南粤优秀教师6人，广东省“千百十工程”省级培养对象7人，广东省高等学校优秀青年教师培养计划培养对象6人，广东省高等职业教育专业领军人才培养对象5人。//学校全日制在校生15703人，成人教育在读学员2915人。获国际奖项德国红点奖1项；国家级教学成果奖4项，省级教学成果奖23项；全国性职业技能竞赛一等奖120个、二等奖198个，位居全国全省前列。2016年，获评全国高职院校创新创业示范校50强。2017年高考招生，我校在顺德区以外录取的新生，高考成绩100%高于全省二本分数线，顺德区内考生分数线也接近全省二本分数线。学校每年毕业生供不应求，初次就业率连续多年高于98%。2014年，获评全国职业院校就业竞争力示范校。//学校国际化发展坚持“引进来”与“走出去”相结合，与英国、美国、澳大利亚、德国、台湾、香港等国家和地区的40多所高校和机构保持了友好合作关系。与马来西亚UCSI大学合作共建的马来西亚UCSI大学顺峰烹饪学院，是中国高等教育在海外建立的第一个烹饪学院，开创了中国烹饪高等教育走向世界的先河。与世界酒店管理知名学府——香港理工大学酒店及旅游业管理学院合作，联合培养高水平酒店管理专业人才。2017年，国务院侨办批准在我校设立“海外惠侨工程—中餐繁荣基地”（国内仅有3家），这是对我校近年来餐饮教学及面向国内外的餐饮文化交流活动成效和影响的充分肯定，为我校烹饪专业教学及中国烹饪学院建设赢来了更大国际化发展空间和机遇。与德国亚琛工业大学达成合作协议，共建广东—亚琛工业4.0应用研究中心。中心建成后，将以德国工业4.0技术与理念为指引，通过工业4.0示范工厂和示范线建设、展览展示、技术实施与服务等开展高端技术研究、技术推广与服务等活动，以高水平的国际合作带动人才培养、校企合作的良性发展，形成示范引领带动作用；推动顺德以及珠三角地区装备制造产业、智能制造与工业机器人产业、工厂自动化与智慧工厂等产业优化升级。//上级领导高度肯定学校办学成果。2011年7月14日，时任中共中央政治局委员、广东省委书记汪洋，省委常委、副省长肖志恒，省委常委、秘书长徐少华，佛山市委书记陈云贤，广东省教育厅厅长罗伟其等领导到学校进行专题调研，汪洋书记充分肯定我校为区域经济转型升级提供的人力支持。2009年11月18日，国家教育部副部长鲁昕率领职成司司长葛道凯、原高教司高职高专处处长范唯等到我校调研，鲁副部长认为我校走出了一条能引领全国职业教育改革的新路子。//在新的发展时期，学校瞄准“国内一流、国际有影响”的一流高职建设目标，坚持“以贡献求支持，以服务求发展”，以智慧化、国际化、法治化、市场化为重点全面推进内涵建设，争取成为第一批中国特色高水平高职院校。 | AB36: 学校前身是成立于1994年的顺德永强成人学院；1999年，教育部批准成立顺德职业技术学院。2002年，顺德师范学校和顺德成人卫生中等专业学校并入学校，同年，学校迁至佛山市顺德区德胜东路现址。2019年，学校入选中国特色高水平高职学校和专业建设计划建设单位。2025年6月，经教育部批准，以顺德职业技术学院为基础设立顺德职业技术大学。 | AC36: http://www.sdpt.com.cn/ | AD36: http://zs.sdpt.edu.cn | AE36: 0757/22327131、22327132、22323732、22327270 | AF36: 校本部：广东省佛山市顺德区大良街道德胜东路； | AG36: https://www.720yun.com/t/a4c2ejrkxer | AH36: 372 | AI36: https://baike.baidu.com/item/%E9%A1%BA%E5%BE%B7%E8%81%8C%E4%B8%9A%E6%8A%80%E6%9C%AF%E5%AD%A6%E9%99%A2 | AJ36: https://gaokao.chsi.com.cn/zsgs/zhangcheng/listZszc//schId/618.dhtml | AK36: /
A37: 32 | B37: =C37 -> 0 | D37: 依据学考 | E37: 12046 | F37: 广州职业技术大学 | G37: 607 | H37: 42 | I37: 20 | J37: 42 | K37: 20 | L37: 382 | M37: 392 | N37: 17547 | O37: 19495 | P37: =IFERROR(AVERAGE(L37:M37),"/") -> 387 | Q37: =IFERROR(AVERAGE(N37:O37),"/") -> 18521 | R37: 广东省 | S37: 广州市 | T37: 广东省 | U37: 职业本科 | V37: 广东省 | W37: 公办 | X37: 一线城市 | Y37: 双高计划/高水平学校建设单位/国家级示范/现代学徒制试点学院 | Z37: 第二类高水平学校B档示范高职现代学徒 | AA37: 广州番禺职业技术学院(原名番禺理工学院、番禺职业技术学院)1993年筹建,1997年9月教育部正式批准备案,是全国首批、广州市属第一所公办全日制普通高等职业院校。2003年被广州市政府确定为市属高等职业教育龙头院校。2005年4月以“优秀”成绩通过教育部人才培养工作水平评估。2006年12月被教育部、财政部确定为“国家示范性高等职业院校建设计划”首批28所立项建设院校之一。2009年12月通过教育部、财政部的验收,被正式批准为首批国家示范性高等职业院校。2010年11月被广东省人民政府授予“广东省职业技术教育工作先进集体”称号。2014年5月荣获我国职业教育界的最高奖项——第四届黄炎培职业教育奖“优秀学校奖”。2014年7月被教育部评为“全国毕业生就业典型经验高校50强”。2016年11月成为广东省一流高职院校建设计划立项建设单位。2017年7月荣登“全国高职院校国际影响力50强”和“全国高职院校服务贡献50强”榜单。学校地处珠江三角洲腹地的广州市番禺区,占地2067亩,校舍建筑面积32.98万平方米,固定资产总值超过10.06亿元,其中教学科研仪器设备总值超过2.98亿元,图书馆面积3.07万平方米,馆内阅览座位4300多个,馆藏纸质图书123余万册、电子图书约2900GB、纸质期刊近880种、电子期刊8360余种,建有41个校内实训基地和176个校外实训基地,现有全日制在校生11769人,生源地分布于全国13个省(区)。校园峰峦起伏,碧波粼粼,繁花似锦,绿草如茵,是广州市花园式单位,2012年获评“全国职业院校魅力校园”,被誉为国内最美丽的大学之一。学校以高等职业技术教育为主,设有财经学院、管理学院、机电工程学院、建筑工程学院、人文社科学院、外语外贸学院、信息工程学院、艺术设计学院、珠宝学院、马克思主义学院、继续教育学院等十一个学院,开设44个紧贴珠三角地区产业结构和社会发展需求的专业。目前,学校拥有玩具设计与制造、计算机网络技术、金融管理、视觉传播设计与制作、酒店管理、珠宝首饰工艺及鉴定等6个国家示范性高职院校重点建设专业、1个全国职业院校国家级示范专业点、2个中央财政支持提升专业服务产业发展能力专业、2个省级协同育人平台、9个省级示范性专业、8个省级重点建设专业、12个省级品牌建设专业、8个市级特色专业学院、2个市级校企合作示范学院、2个产业学院、6个市级示范性专业、6个市级重点建设专业;15门国家级精品课程、25门省级精品课程和40门市级精品课程;14门国家级精品资源共享课程、31门省级精品开放(建设)课程和5门省级精品在线开放(建设)课程;1门国家精品视频公开课程、2门省级精品视频公开课;1个国家级校内实训基地、7个省级校内实训基地、9个市级校内实训基地和2个省级大学生校外实践教学基地、10个省级大学生校外实践教学基地(建设)项目、2个市级校外示范性实训基地。学校积极与企业、科研院所开展产学研合作,搭建应用技术研发平台,建有包括广东高校珠宝首饰工程技术开发中心、广东省珠宝首饰工程技术研究中心、广东省智慧职业教育大数据工程技术研究中心、广东省皮革智能产品3D打印应用工程技术研究中心、广东省绿色建造和检测工程技术研究中心等工程中心，以及广州市人文社科研究基地、广州市技术转移示范机构（中心）在内的39个科学研究机构（应用技术协同创新中心、研究基地等）。产出了一批以专利为代表的科技创新成果,专利申请、专利授权、有效专利、专利竞争力全部进入2017年中国大学专利排行榜500强,获2013年广州市专利创造贡献奖。承担了国家自然科学基金项目、国家社会科学基金项目(教育学)、全国教育规划项目、教育部人文社科项目等一批高层级的科研项目,公开发表一批有影响的科研教研论文,论文最高他引次数达604次。学校面向全国公开招聘优秀教师,拥有一支人员精干、结构合理、水平较高的师资队伍。现有教职工934人,专任教师545人,专任教师中具有高级职称者占30.09%,具有研究生学位者占70.46%,“双师”素质专任教师比例达70.28%。现有全国教育系统先进集体1个、全国职业教育先进单位1个,国家级教学团队2个、省级教学团队6个,有享受国务院政府特殊津贴专家3人、国家级教学名师5人、省级教学名师12人、市级教学名师6人。学校坚持走质量、规模、效益协调发展的内涵式发展之路,强化质量意识,以教师为主导,以学生为主体,以培养学生创新精神和职业能力为目标,积极探索教学改革,2001年以来,共有66项教学成果获得国家、省、市教学成果奖,其中,国家级教学成果一等奖1项、二等奖10项,广东省教学成果特等奖1项、一等奖11项、二等奖15项,广州市教学成果特等奖4项、一等奖12项。学校坚持以服务为宗旨,是国家计算机应用与软件技术专业领域技能型紧缺人才培养培训基地,中国玩具行业人才培训基地,广东省首批省级示范性软件学院建设学校,广东省高职高专师资培训基地、广东省中等职业学校师资培训基地、广州市专业技术人员继续教育基地、广州市中等职业学校教师(校长)培训中心,已成立国家职业技能鉴定所,可以开展19个工种的职业资格鉴定。学校广泛开展对外交流与合作,加强与海内外知名大学、同类职业技术学院及培训机构的联系,已与英国、美国、加拿大、芬兰、荷兰、意大利、新加坡、日本等国外高等教育机构和港澳台地区的教育机构及科技大学建立了教育交流与合作关系，同时积极拓展与“一带一路”沿线国家的教育交流合作。在设立海外研习基地、联合培养、专业及课程共建、学分互认、中外合作办学、质量管理体系建设、师资培训等方面开展了富有成效的交流与合作,促进了人才培养质量和国际化程度的提升。同时,学校发挥品牌专业和特色课程优势,吸引国际学生来校短期交换和修读课程,形成了较高的知名度和美誉度。2018年我校与新加坡南洋理工学院学生海外研习基地合作项目入选全国首批20个“中国—东盟高职院校特色合作项目”。学校围绕培养“一技之长+综合素质”的高素质、创新性技术技能人才的目标,实行以素质为基础,以能力为核心,以就业为导向,产学研结合的人才培养模式,积极实施“双证书”制度,大力培养学生的职业技能,毕业生以其适应性强、动手能力强、综合素质高而受到用人单位普遍欢迎。自2001年广东省首次公布高校毕业生就业率以来,学校毕业生就业率一直稳居全省高校前列,2004年、2005年和2008年三年位居全省所有本专科院校第一位。2010年,学校模具设计与制造专业2001届毕业生黄德智喜获“全国劳动模范”崇高荣誉,在北京人民大会堂受到党中央和国务院的隆重表彰。2018年，学校涉外文秘专业2002届毕业生王俊文荣获广东省五一劳动奖章。2018年,毕业生就业率达98.79%。番禺籍的原全国政协副主席霍英东,全国政协副主席、澳门特别行政区首任行政长官何厚铧,全国政协委员陈瑞球,以及何添、何善衡等港澳同胞和社会各界有识之士对学校的建设给予极大的关注和有力的资助,捐资兴建了霍英东学术交流中心、何厚铧大楼等一批教学、实训用房和学生宿舍,极大地促进了学校的发展。功崇惟志,天道酬勤。学校以习近平新时代中国特色社会义思想为指导，积极对接国家“一带一路”和粤港澳大湾区发展战略，坚持走以质量为核心的内涵式发展道路，以建设“中国特色、国际水准”的高职院校为目标，不断深化校企合作、产教融合体制机制改革，致力于为大湾区经济社会发展培养具有“一技之长+综合素质”的高素质、创新型技术技能人才。 | AB37: 学校的前身是1996年4月经广东省人民政府批准成立的番禺理工学院，于1993年筹建；1997年6月更名为番禺职业技术学院；1997年9月经国家教育委员会正式备案，由广州市和番禺市人民政府共同领导、番禺市直接管理；2006年起实行“市区共建，以区为主”的管理体制；2008年7月更名为广州番禺职业技术学院；2010年起实行“市区共建，以市为主”的管理体制；2006年12月被教育部、财政部确定为“国家示范性高等职业院校建设计划”首批立项建设院校，2009年12月通过验收，成为国家示范性高等职业院校；2019年12月入选中国特色高水平高职学校和专业建设单位。2025年6月中华人民共和国教育部同意以广州番禺职业技术学院为基础设立广州职业技术大学。 | AC37: http://www.gzpyp.edu.cn/ | AD37: http://zs.gzpyp.edu.cn/ | AE37: 020/34874086、84731206 | AF37: 广东省广州市番禺区市良路1342号 | AG37: https://www.720yun.com/t/f10jz0yavf3 | AH37: 426 | AI37: https://baike.baidu.com/item/%E5%B9%BF%E5%B7%9E%E7%95%AA%E7%A6%BA%E8%81%8C%E4%B8%9A%E6%8A%80%E6%9C%AF%E5%AD%A6%E9%99%A2 | AJ37: https://gaokao.chsi.com.cn/zsgs/zhangcheng/listZszc//schId/954.dhtml | AK37: /
A38: 33 | B38: =C38 -> 0 | D38: 依据学考 | E38: 12040 | F38: 广州民航职业技术学院 | G38: 602 | H38: 65 | I38: 40 | J38: 65 | K38: 40 | L38: 381 | M38: 392 | N38: 18771 | O38: 20123 | P38: =IFERROR(AVERAGE(L38:M38),"/") -> 386.5 | Q38: =IFERROR(AVERAGE(N38:O38),"/") -> 19447 | R38: 广东省 | S38: 广州市 | T38: 广东省 | U38: 专科（高职） | V38: 交通运输部（中国民用航空局） | W38: 公办 | X38: 一线城市 | Y38: 部委院校/省部共建/双高计划/高水平专业群建设单位/国家级示范/现代学徒制试点学院 | Z38: 示范高职/第四类高水平专业群C档 | AA38: 广州民航职业技术学院直属中国民用航空局，是民航内最早一所独立设置实施高等职业教育的全日制公办普通高校。学校1994年被国家教育部确定为全国首批十所试办五年制高职教育的学校之一；1999年经教育部、民航局批准成立；2010年被教育部、财政部确定为国家示范性高等职业院校，是全国百所、广东省四所之一，民航唯一一所国家示范性高等职业院校；2013年正式成为民航局与广东省“省部共建”院校；2016年被广东省教育厅、财政厅确定为“广东省一流高职院校建设计划立项建设单位”。//学校“立足民航，服务地方，面向世界”，坚持职业教育类型的办学定位，在全国率先提出并实施了基于行业标准的技术技能人才培养模式，形成了“依托行业、产学合作、双师双证、国际通用”的办学特色。//学校现有机场路校区、白云机场校区、花都赤坭校区三个校区，共占地1112亩。现有固定资产总值约10.05亿元，其中，教学、科研仪器设备资产值约2.39亿元，33架大中小型教学用飞机，140台飞机发动机，5万多台（件）飞机零部件和一大批专业设备。//学校教职工规模689人，其中，专任教师549人，具有硕士以上学位的教师425人，占专任教师比例为77%；具有双师素质的专业教师224人，占专业课教师数的比例为64%；具有行业企业一线工作经历的教师比例为44.8%；具有民航行业特有工种职业资格证书、职业技能鉴定考评员及教员证书、其他工种职业资格证书的教师比例为41%。//学校下设飞机维修工程学院、航空港管理学院、民航经营管理学院、人文社科学院、继续教育学院五个二级学院。面向31个省、市、自治区招生，现有21个专业26个专业方向，覆盖了民航维修和服务的关键岗位，在校生1.2余万人。新生报到率、毕业生就业率、专业对口率等方面均走在同类院校前列，其中，飞机机电设备维修、飞机结构修理、航空电子设备维修、航空地面设备维修、通用航空器维修等民航特有专业对口率均超过90%，优秀毕业生已成为技术骨干与管理人才。//学校以现代民用航空体系和航空产业链建设需求为导向，以飞机维修、民航运输等民航特有专业岗位（群）核心能力培养为主线，创新了“课证一体、中外融通、校企融合”的民航特有专业人才培养模式。制定了基于行业标准的民航特有专业课程教学标准，做到“行业标准入体系、职业标准入课程”，与民航行业企业合作共建民航飞机维修工程、航空港安全检查、航空服务、通用航空等民航特有专业的校企共享型“公共实训平台”，为全国其他院校的民航专业教学起到引领作用。//学校不断加强与美国、英国、加拿大、新加坡、香港等境外院校和航空企业合作，提升办学国际化水平；与斯里兰卡等“一带一路”沿线国家开展民航职业教育合作，实现教育资源对外输出；先后与美国西敏学院、马来西亚建设大学、台湾中华科技大学开展本科层次职业教育合作，搭建人才成长“立交桥”，实现民航职业教育体系中外衔接；通过国际合作与对外交流，促进了人才培养标准、师资、教材和管理国际化，实现了学校教育与国际接轨，提升了民航职业教育软实力。 | AB38: 学校源自1980年由原中国民航广州管理局举办的技工学校。1984年在此基础上成立“中国民航广州中等专业学校”，由民航广州地区管理局领导管理。1999年经教育部批准成立“广州民航职业技术学院”。2013年成为民航局与广东省“省部共建”院校，2019年被列入第四类高水平专业群建设单位（C档）。 2021年现代学徒制第三批试点验收暂缓通过。 | AC38: http://www.caac.net/ | AD38: https://www.gcac.edu.cn/sites/zsb/index.html | AE38: 020/86123135、86121941 | AF38: 机场路校区：广东省广州市白云区机场路向云西街10号,白云机场校区：广州市白云国际机场空港北横六路 | AG38: / | AH38: 2377 | AI38: https://baike.baidu.com/item/%E5%B9%BF%E5%B7%9E%E6%B0%91%E8%88%AA%E8%81%8C%E4%B8%9A%E6%8A%80%E6%9C%AF%E5%AD%A6%E9%99%A2 | AJ38: https://gaokao.chsi.com.cn/zsgs/zhangcheng/listZszc//schId/952.dhtml | AK38: /
A39: 34 | B39: =C39 -> 0 | D39: 依据学考 | E39: 12046 | F39: 广州职业技术大学 | G39: 604 | H39: 133 | I39: / | J39: 133 | K39: / | L39: 380 | M39: / | N39: 19461 | O39: / | P39: =IFERROR(AVERAGE(L39:M39),"/") -> 380 | Q39: =IFERROR(AVERAGE(N39:O39),"/") -> 19461 | R39: 广东省 | S39: 广州市 | T39: 广东省 | U39: 职业本科 | V39: 广东省 | W39: 公办 | X39: 一线城市 | Y39: 双高计划/高水平学校建设单位/国家级示范/现代学徒制试点学院 | Z39: 第二类高水平学校B档示范高职现代学徒 | AA39: 广州番禺职业技术学院(原名番禺理工学院、番禺职业技术学院)1993年筹建,1997年9月教育部正式批准备案,是全国首批、广州市属第一所公办全日制普通高等职业院校。2003年被广州市政府确定为市属高等职业教育龙头院校。2005年4月以“优秀”成绩通过教育部人才培养工作水平评估。2006年12月被教育部、财政部确定为“国家示范性高等职业院校建设计划”首批28所立项建设院校之一。2009年12月通过教育部、财政部的验收,被正式批准为首批国家示范性高等职业院校。2010年11月被广东省人民政府授予“广东省职业技术教育工作先进集体”称号。2014年5月荣获我国职业教育界的最高奖项——第四届黄炎培职业教育奖“优秀学校奖”。2014年7月被教育部评为“全国毕业生就业典型经验高校50强”。2016年11月成为广东省一流高职院校建设计划立项建设单位。2017年7月荣登“全国高职院校国际影响力50强”和“全国高职院校服务贡献50强”榜单。学校地处珠江三角洲腹地的广州市番禺区,占地2067亩,校舍建筑面积32.98万平方米,固定资产总值超过10.06亿元,其中教学科研仪器设备总值超过2.98亿元,图书馆面积3.07万平方米,馆内阅览座位4300多个,馆藏纸质图书123余万册、电子图书约2900GB、纸质期刊近880种、电子期刊8360余种,建有41个校内实训基地和176个校外实训基地,现有全日制在校生11769人,生源地分布于全国13个省(区)。校园峰峦起伏,碧波粼粼,繁花似锦,绿草如茵,是广州市花园式单位,2012年获评“全国职业院校魅力校园”,被誉为国内最美丽的大学之一。学校以高等职业技术教育为主,设有财经学院、管理学院、机电工程学院、建筑工程学院、人文社科学院、外语外贸学院、信息工程学院、艺术设计学院、珠宝学院、马克思主义学院、继续教育学院等十一个学院,开设44个紧贴珠三角地区产业结构和社会发展需求的专业。目前,学校拥有玩具设计与制造、计算机网络技术、金融管理、视觉传播设计与制作、酒店管理、珠宝首饰工艺及鉴定等6个国家示范性高职院校重点建设专业、1个全国职业院校国家级示范专业点、2个中央财政支持提升专业服务产业发展能力专业、2个省级协同育人平台、9个省级示范性专业、8个省级重点建设专业、12个省级品牌建设专业、8个市级特色专业学院、2个市级校企合作示范学院、2个产业学院、6个市级示范性专业、6个市级重点建设专业;15门国家级精品课程、25门省级精品课程和40门市级精品课程;14门国家级精品资源共享课程、31门省级精品开放(建设)课程和5门省级精品在线开放(建设)课程;1门国家精品视频公开课程、2门省级精品视频公开课;1个国家级校内实训基地、7个省级校内实训基地、9个市级校内实训基地和2个省级大学生校外实践教学基地、10个省级大学生校外实践教学基地(建设)项目、2个市级校外示范性实训基地。学校积极与企业、科研院所开展产学研合作,搭建应用技术研发平台,建有包括广东高校珠宝首饰工程技术开发中心、广东省珠宝首饰工程技术研究中心、广东省智慧职业教育大数据工程技术研究中心、广东省皮革智能产品3D打印应用工程技术研究中心、广东省绿色建造和检测工程技术研究中心等工程中心，以及广州市人文社科研究基地、广州市技术转移示范机构（中心）在内的39个科学研究机构（应用技术协同创新中心、研究基地等）。产出了一批以专利为代表的科技创新成果,专利申请、专利授权、有效专利、专利竞争力全部进入2017年中国大学专利排行榜500强,获2013年广州市专利创造贡献奖。承担了国家自然科学基金项目、国家社会科学基金项目(教育学)、全国教育规划项目、教育部人文社科项目等一批高层级的科研项目,公开发表一批有影响的科研教研论文,论文最高他引次数达604次。学校面向全国公开招聘优秀教师,拥有一支人员精干、结构合理、水平较高的师资队伍。现有教职工934人,专任教师545人,专任教师中具有高级职称者占30.09%,具有研究生学位者占70.46%,“双师”素质专任教师比例达70.28%。现有全国教育系统先进集体1个、全国职业教育先进单位1个,国家级教学团队2个、省级教学团队6个,有享受国务院政府特殊津贴专家3人、国家级教学名师5人、省级教学名师12人、市级教学名师6人。学校坚持走质量、规模、效益协调发展的内涵式发展之路,强化质量意识,以教师为主导,以学生为主体,以培养学生创新精神和职业能力为目标,积极探索教学改革,2001年以来,共有66项教学成果获得国家、省、市教学成果奖,其中,国家级教学成果一等奖1项、二等奖10项,广东省教学成果特等奖1项、一等奖11项、二等奖15项,广州市教学成果特等奖4项、一等奖12项。学校坚持以服务为宗旨,是国家计算机应用与软件技术专业领域技能型紧缺人才培养培训基地,中国玩具行业人才培训基地,广东省首批省级示范性软件学院建设学校,广东省高职高专师资培训基地、广东省中等职业学校师资培训基地、广州市专业技术人员继续教育基地、广州市中等职业学校教师(校长)培训中心,已成立国家职业技能鉴定所,可以开展19个工种的职业资格鉴定。学校广泛开展对外交流与合作,加强与海内外知名大学、同类职业技术学院及培训机构的联系,已与英国、美国、加拿大、芬兰、荷兰、意大利、新加坡、日本等国外高等教育机构和港澳台地区的教育机构及科技大学建立了教育交流与合作关系，同时积极拓展与“一带一路”沿线国家的教育交流合作。在设立海外研习基地、联合培养、专业及课程共建、学分互认、中外合作办学、质量管理体系建设、师资培训等方面开展了富有成效的交流与合作,促进了人才培养质量和国际化程度的提升。同时,学校发挥品牌专业和特色课程优势,吸引国际学生来校短期交换和修读课程,形成了较高的知名度和美誉度。2018年我校与新加坡南洋理工学院学生海外研习基地合作项目入选全国首批20个“中国—东盟高职院校特色合作项目”。学校围绕培养“一技之长+综合素质”的高素质、创新性技术技能人才的目标,实行以素质为基础,以能力为核心,以就业为导向,产学研结合的人才培养模式,积极实施“双证书”制度,大力培养学生的职业技能,毕业生以其适应性强、动手能力强、综合素质高而受到用人单位普遍欢迎。自2001年广东省首次公布高校毕业生就业率以来,学校毕业生就业率一直稳居全省高校前列,2004年、2005年和2008年三年位居全省所有本专科院校第一位。2010年,学校模具设计与制造专业2001届毕业生黄德智喜获“全国劳动模范”崇高荣誉,在北京人民大会堂受到党中央和国务院的隆重表彰。2018年，学校涉外文秘专业2002届毕业生王俊文荣获广东省五一劳动奖章。2018年,毕业生就业率达98.79%。番禺籍的原全国政协副主席霍英东,全国政协副主席、澳门特别行政区首任行政长官何厚铧,全国政协委员陈瑞球,以及何添、何善衡等港澳同胞和社会各界有识之士对学校的建设给予极大的关注和有力的资助,捐资兴建了霍英东学术交流中心、何厚铧大楼等一批教学、实训用房和学生宿舍,极大地促进了学校的发展。功崇惟志,天道酬勤。学校以习近平新时代中国特色社会义思想为指导，积极对接国家“一带一路”和粤港澳大湾区发展战略，坚持走以质量为核心的内涵式发展道路，以建设“中国特色、国际水准”的高职院校为目标，不断深化校企合作、产教融合体制机制改革，致力于为大湾区经济社会发展培养具有“一技之长+综合素质”的高素质、创新型技术技能人才。 | AB39: 学校的前身是1996年4月经广东省人民政府批准成立的番禺理工学院，于1993年筹建；1997年6月更名为番禺职业技术学院；1997年9月经国家教育委员会正式备案，由广州市和番禺市人民政府共同领导、番禺市直接管理；2006年起实行“市区共建，以区为主”的管理体制；2008年7月更名为广州番禺职业技术学院；2010年起实行“市区共建，以市为主”的管理体制；2006年12月被教育部、财政部确定为“国家示范性高等职业院校建设计划”首批立项建设院校，2009年12月通过验收，成为国家示范性高等职业院校；2019年12月入选中国特色高水平高职学校和专业建设单位。2025年6月中华人民共和国教育部同意以广州番禺职业技术学院为基础设立广州职业技术大学。 | AC39: http://www.gzpyp.edu.cn/ | AD39: http://zs.gzpyp.edu.cn/ | AE39: 020/34874086、84731206 | AF39: 广东省广州市番禺区市良路1342号 | AG39: https://www.720yun.com/t/f10jz0yavf3 | AH39: 426 | AI39: https://baike.baidu.com/item/%E5%B9%BF%E5%B7%9E%E7%95%AA%E7%A6%BA%E8%81%8C%E4%B8%9A%E6%8A%80%E6%9C%AF%E5%AD%A6%E9%99%A2 | AJ39: https://gaokao.chsi.com.cn/zsgs/zhangcheng/listZszc//schId/954.dhtml | AK39: /
A40: 35 | B40: =C40 -> 0 | D40: 依据学考 | E40: 12046 | F40: 广州职业技术大学 | G40: 605 | H40: 67 | I40: / | J40: 67 | K40: / | L40: 379 | M40: / | N40: 20725 | O40: / | P40: =IFERROR(AVERAGE(L40:M40),"/") -> 379 | Q40: =IFERROR(AVERAGE(N40:O40),"/") -> 20725 | R40: 广东省 | S40: 广州市 | T40: 广东省 | U40: 职业本科 | V40: 广东省 | W40: 公办 | X40: 一线城市 | Y40: 双高计划/高水平学校建设单位/国家级示范/现代学徒制试点学院 | Z40: 第二类高水平学校B档示范高职现代学徒 | AA40: 广州番禺职业技术学院(原名番禺理工学院、番禺职业技术学院)1993年筹建,1997年9月教育部正式批准备案,是全国首批、广州市属第一所公办全日制普通高等职业院校。2003年被广州市政府确定为市属高等职业教育龙头院校。2005年4月以“优秀”成绩通过教育部人才培养工作水平评估。2006年12月被教育部、财政部确定为“国家示范性高等职业院校建设计划”首批28所立项建设院校之一。2009年12月通过教育部、财政部的验收,被正式批准为首批国家示范性高等职业院校。2010年11月被广东省人民政府授予“广东省职业技术教育工作先进集体”称号。2014年5月荣获我国职业教育界的最高奖项——第四届黄炎培职业教育奖“优秀学校奖”。2014年7月被教育部评为“全国毕业生就业典型经验高校50强”。2016年11月成为广东省一流高职院校建设计划立项建设单位。2017年7月荣登“全国高职院校国际影响力50强”和“全国高职院校服务贡献50强”榜单。学校地处珠江三角洲腹地的广州市番禺区,占地2067亩,校舍建筑面积32.98万平方米,固定资产总值超过10.06亿元,其中教学科研仪器设备总值超过2.98亿元,图书馆面积3.07万平方米,馆内阅览座位4300多个,馆藏纸质图书123余万册、电子图书约2900GB、纸质期刊近880种、电子期刊8360余种,建有41个校内实训基地和176个校外实训基地,现有全日制在校生11769人,生源地分布于全国13个省(区)。校园峰峦起伏,碧波粼粼,繁花似锦,绿草如茵,是广州市花园式单位,2012年获评“全国职业院校魅力校园”,被誉为国内最美丽的大学之一。学校以高等职业技术教育为主,设有财经学院、管理学院、机电工程学院、建筑工程学院、人文社科学院、外语外贸学院、信息工程学院、艺术设计学院、珠宝学院、马克思主义学院、继续教育学院等十一个学院,开设44个紧贴珠三角地区产业结构和社会发展需求的专业。目前,学校拥有玩具设计与制造、计算机网络技术、金融管理、视觉传播设计与制作、酒店管理、珠宝首饰工艺及鉴定等6个国家示范性高职院校重点建设专业、1个全国职业院校国家级示范专业点、2个中央财政支持提升专业服务产业发展能力专业、2个省级协同育人平台、9个省级示范性专业、8个省级重点建设专业、12个省级品牌建设专业、8个市级特色专业学院、2个市级校企合作示范学院、2个产业学院、6个市级示范性专业、6个市级重点建设专业;15门国家级精品课程、25门省级精品课程和40门市级精品课程;14门国家级精品资源共享课程、31门省级精品开放(建设)课程和5门省级精品在线开放(建设)课程;1门国家精品视频公开课程、2门省级精品视频公开课;1个国家级校内实训基地、7个省级校内实训基地、9个市级校内实训基地和2个省级大学生校外实践教学基地、10个省级大学生校外实践教学基地(建设)项目、2个市级校外示范性实训基地。学校积极与企业、科研院所开展产学研合作,搭建应用技术研发平台,建有包括广东高校珠宝首饰工程技术开发中心、广东省珠宝首饰工程技术研究中心、广东省智慧职业教育大数据工程技术研究中心、广东省皮革智能产品3D打印应用工程技术研究中心、广东省绿色建造和检测工程技术研究中心等工程中心，以及广州市人文社科研究基地、广州市技术转移示范机构（中心）在内的39个科学研究机构（应用技术协同创新中心、研究基地等）。产出了一批以专利为代表的科技创新成果,专利申请、专利授权、有效专利、专利竞争力全部进入2017年中国大学专利排行榜500强,获2013年广州市专利创造贡献奖。承担了国家自然科学基金项目、国家社会科学基金项目(教育学)、全国教育规划项目、教育部人文社科项目等一批高层级的科研项目,公开发表一批有影响的科研教研论文,论文最高他引次数达604次。学校面向全国公开招聘优秀教师,拥有一支人员精干、结构合理、水平较高的师资队伍。现有教职工934人,专任教师545人,专任教师中具有高级职称者占30.09%,具有研究生学位者占70.46%,“双师”素质专任教师比例达70.28%。现有全国教育系统先进集体1个、全国职业教育先进单位1个,国家级教学团队2个、省级教学团队6个,有享受国务院政府特殊津贴专家3人、国家级教学名师5人、省级教学名师12人、市级教学名师6人。学校坚持走质量、规模、效益协调发展的内涵式发展之路,强化质量意识,以教师为主导,以学生为主体,以培养学生创新精神和职业能力为目标,积极探索教学改革,2001年以来,共有66项教学成果获得国家、省、市教学成果奖,其中,国家级教学成果一等奖1项、二等奖10项,广东省教学成果特等奖1项、一等奖11项、二等奖15项,广州市教学成果特等奖4项、一等奖12项。学校坚持以服务为宗旨,是国家计算机应用与软件技术专业领域技能型紧缺人才培养培训基地,中国玩具行业人才培训基地,广东省首批省级示范性软件学院建设学校,广东省高职高专师资培训基地、广东省中等职业学校师资培训基地、广州市专业技术人员继续教育基地、广州市中等职业学校教师(校长)培训中心,已成立国家职业技能鉴定所,可以开展19个工种的职业资格鉴定。学校广泛开展对外交流与合作,加强与海内外知名大学、同类职业技术学院及培训机构的联系,已与英国、美国、加拿大、芬兰、荷兰、意大利、新加坡、日本等国外高等教育机构和港澳台地区的教育机构及科技大学建立了教育交流与合作关系，同时积极拓展与“一带一路”沿线国家的教育交流合作。在设立海外研习基地、联合培养、专业及课程共建、学分互认、中外合作办学、质量管理体系建设、师资培训等方面开展了富有成效的交流与合作,促进了人才培养质量和国际化程度的提升。同时,学校发挥品牌专业和特色课程优势,吸引国际学生来校短期交换和修读课程,形成了较高的知名度和美誉度。2018年我校与新加坡南洋理工学院学生海外研习基地合作项目入选全国首批20个“中国—东盟高职院校特色合作项目”。学校围绕培养“一技之长+综合素质”的高素质、创新性技术技能人才的目标,实行以素质为基础,以能力为核心,以就业为导向,产学研结合的人才培养模式,积极实施“双证书”制度,大力培养学生的职业技能,毕业生以其适应性强、动手能力强、综合素质高而受到用人单位普遍欢迎。自2001年广东省首次公布高校毕业生就业率以来,学校毕业生就业率一直稳居全省高校前列,2004年、2005年和2008年三年位居全省所有本专科院校第一位。2010年,学校模具设计与制造专业2001届毕业生黄德智喜获“全国劳动模范”崇高荣誉,在北京人民大会堂受到党中央和国务院的隆重表彰。2018年，学校涉外文秘专业2002届毕业生王俊文荣获广东省五一劳动奖章。2018年,毕业生就业率达98.79%。番禺籍的原全国政协副主席霍英东,全国政协副主席、澳门特别行政区首任行政长官何厚铧,全国政协委员陈瑞球,以及何添、何善衡等港澳同胞和社会各界有识之士对学校的建设给予极大的关注和有力的资助,捐资兴建了霍英东学术交流中心、何厚铧大楼等一批教学、实训用房和学生宿舍,极大地促进了学校的发展。功崇惟志,天道酬勤。学校以习近平新时代中国特色社会义思想为指导，积极对接国家“一带一路”和粤港澳大湾区发展战略，坚持走以质量为核心的内涵式发展道路，以建设“中国特色、国际水准”的高职院校为目标，不断深化校企合作、产教融合体制机制改革，致力于为大湾区经济社会发展培养具有“一技之长+综合素质”的高素质、创新型技术技能人才。 | AB40: 学校的前身是1996年4月经广东省人民政府批准成立的番禺理工学院，于1993年筹建；1997年6月更名为番禺职业技术学院；1997年9月经国家教育委员会正式备案，由广州市和番禺市人民政府共同领导、番禺市直接管理；2006年起实行“市区共建，以区为主”的管理体制；2008年7月更名为广州番禺职业技术学院；2010年起实行“市区共建，以市为主”的管理体制；2006年12月被教育部、财政部确定为“国家示范性高等职业院校建设计划”首批立项建设院校，2009年12月通过验收，成为国家示范性高等职业院校；2019年12月入选中国特色高水平高职学校和专业建设单位。2025年6月中华人民共和国教育部同意以广州番禺职业技术学院为基础设立广州职业技术大学。 | AC40: http://www.gzpyp.edu.cn/ | AD40: http://zs.gzpyp.edu.cn/ | AE40: 020/34874086、84731206 | AF40: 广东省广州市番禺区市良路1342号 | AG40: https://www.720yun.com/t/f10jz0yavf3 | AH40: 426 | AI40: https://baike.baidu.com/item/%E5%B9%BF%E5%B7%9E%E7%95%AA%E7%A6%BA%E8%81%8C%E4%B8%9A%E6%8A%80%E6%9C%AF%E5%AD%A6%E9%99%A2 | AJ40: https://gaokao.chsi.com.cn/zsgs/zhangcheng/listZszc//schId/954.dhtml | AK40: /
A41: 36 | B41: =C41 -> 0 | D41: 依据学考 | E41: 10831 | F41: 顺德职业技术大学 | G41: 602 | H41: 8 | I41: 19 | J41: 8 | K41: 19 | L41: 380 | M41: 391 | N41: 20476 | O41: 21355 | P41: =IFERROR(AVERAGE(L41:M41),"/") -> 385.5 | Q41: =IFERROR(AVERAGE(N41:O41),"/") -> 20915.5 | R41: 广东省 | S41: 佛山市 | T41: 广东省 | U41: 职业本科 | V41: 广东省 | W41: 公办 | X41: 新一线城市 | Y41: 双高计划/高水平学校建设单位/国家级骨干/现代学徒制试点学院 | Z41: 第二类高水平学校B档骨干高职现代学徒 | AA41: 顺德职业技术学院成立于1999年3月，是经国家教育部批准成立、广东省人民政府领导管理、省市共建、顺德区政府投资兴建的地方高职院校。经过多年的建设发展，学校已成为国家示范（骨干）高等职业院校、广东省示范性高等职业院校、广东省一流高职院校建设单位。学校环境优美、设施良好、制度健全、管理科学，是莘莘学子求学成才的理想之地。先后获得“全国职业教育先进单位”、“全国绿化模范单位”、“全国节能型公共机构示范单位”、“广东省安全文明校园”、“广东省依法治校示范学校”等荣誉称号或奖励，为区域经济社会发展培养一大批高素质技术技能人才做出了积极贡献。//学校的前身是1994年12月成立的顺德永强成人学院。2002年7月，顺德师范学校（1924年成立）和顺德成人卫生中等专业学校（1958年成立）合并到顺德职业技术学院。2002年，学校迁入位于德胜东路的新校园。//2005年12月，学校以优秀成绩通过国家教育部高职高专人才培养工作水平评估。2008年7月，学校被教育部财政部确定为国家重点培育高等职业院校立项进行建设，并于2010年通过验收。2009年9月，学校被广东省教育厅财政厅确定为广东省示范性高等职业院校建设项目立项建设单位。2010年12月学校被教育部财政部确定为“国家示范性高等职业院校建设计划”骨干高职院校第一批立项建设单位，并于2013年11月以优秀成绩通过验收。2016年，学校被广东省教育厅确定为广东省一流高职院校建设单位。//学校现设有10个二级学院（机电工程学院、电子与信息工程学院、应用化工技术学院、医药卫生学院、设计学院、经济管理学院、酒店与旅游管理学院、人文社科学院、外语学院、马克思主义学院）。学校共有专业49个，其中国家教育改革试点专业2个（制冷与空调技术、家具艺术设计）、中央财政支持重点专业2个（工业设计、烹饪工艺与营养）、广东省示范性专业8个（数控技术、汽车检测与维修技术、制冷与空调技术、电子信息工程技术、应用化工技术、家具艺术设计、会计、工商企业管理）、广东省重点专业3个（物流管理、酒店管理、应用英语）、广东省重点建设专业3个（园林技术、工业分析技术、机电一体化技术）、第一批省级一类品牌建设专业2个（制冷与空调技术、家具艺术设计）、第二批省级二类品牌建设专业5个（计算机应用技术、药学、金融管理、展示艺术设计、数字媒体艺术设计）。//学校获国家高等教育教学成果奖4项，广东省高等教育教学成果奖23项。共建有国家级精品课程12门，国家精品资源共享课立项建设项目9门；省级精品课程22门，广东省高职教育精品开放课程5门，广东省高职教育精品在线开放课程4门，广东省精品视频公开课1门，广东省精品资源共享课19门。//学校办学条件良好，教学环境优良。学校建筑面积超过57万平方米，固定资产总额超过12.36亿元人民币，/教学、科研仪器设备总值3.12亿元。拥有校内实训基地19个，实验实训室197个，其中中央财政支持实训基地1个，省级重点实训基地9个。学校有校外实训基地541个，其中省级大学生校外实践教学基地13个。学生文化体育设施齐全，建有高标准的田径场、篮球场等各类场馆。//学校共有21个科研平台，4个技术服务平台。科研平台中以学校为第一申报的平台有16个，其中省部级6个，市厅级12个。获国家自然科研基金项目11项（含主持7项）、主持获得教育部人文社科项目9项、省自然科学基金项目12项，省哲学社会科学项目20项。横向项目累计到账经费达到了4475.32万元。省部级及以上的科研奖7项。获专利授权388件，其中发明专利授权85件，实用新型专利247件，累计有34项发明专利实现了转化。//全校教职工总数924人，其中高级职称263人。现有专任教师730人。有国家级教学团队1个、省级教学团队6个，国家级教学名师2人、省级教学名师5人、广东省“特支计划”教学名师4人，南粤优秀教师6人，广东省“千百十工程”省级培养对象7人，广东省高等学校优秀青年教师培养计划培养对象6人，广东省高等职业教育专业领军人才培养对象5人。//学校全日制在校生15703人，成人教育在读学员2915人。获国际奖项德国红点奖1项；国家级教学成果奖4项，省级教学成果奖23项；全国性职业技能竞赛一等奖120个、二等奖198个，位居全国全省前列。2016年，获评全国高职院校创新创业示范校50强。2017年高考招生，我校在顺德区以外录取的新生，高考成绩100%高于全省二本分数线，顺德区内考生分数线也接近全省二本分数线。学校每年毕业生供不应求，初次就业率连续多年高于98%。2014年，获评全国职业院校就业竞争力示范校。//学校国际化发展坚持“引进来”与“走出去”相结合，与英国、美国、澳大利亚、德国、台湾、香港等国家和地区的40多所高校和机构保持了友好合作关系。与马来西亚UCSI大学合作共建的马来西亚UCSI大学顺峰烹饪学院，是中国高等教育在海外建立的第一个烹饪学院，开创了中国烹饪高等教育走向世界的先河。与世界酒店管理知名学府——香港理工大学酒店及旅游业管理学院合作，联合培养高水平酒店管理专业人才。2017年，国务院侨办批准在我校设立“海外惠侨工程—中餐繁荣基地”（国内仅有3家），这是对我校近年来餐饮教学及面向国内外的餐饮文化交流活动成效和影响的充分肯定，为我校烹饪专业教学及中国烹饪学院建设赢来了更大国际化发展空间和机遇。与德国亚琛工业大学达成合作协议，共建广东—亚琛工业4.0应用研究中心。中心建成后，将以德国工业4.0技术与理念为指引，通过工业4.0示范工厂和示范线建设、展览展示、技术实施与服务等开展高端技术研究、技术推广与服务等活动，以高水平的国际合作带动人才培养、校企合作的良性发展，形成示范引领带动作用；推动顺德以及珠三角地区装备制造产业、智能制造与工业机器人产业、工厂自动化与智慧工厂等产业优化升级。//上级领导高度肯定学校办学成果。2011年7月14日，时任中共中央政治局委员、广东省委书记汪洋，省委常委、副省长肖志恒，省委常委、秘书长徐少华，佛山市委书记陈云贤，广东省教育厅厅长罗伟其等领导到学校进行专题调研，汪洋书记充分肯定我校为区域经济转型升级提供的人力支持。2009年11月18日，国家教育部副部长鲁昕率领职成司司长葛道凯、原高教司高职高专处处长范唯等到我校调研，鲁副部长认为我校走出了一条能引领全国职业教育改革的新路子。//在新的发展时期，学校瞄准“国内一流、国际有影响”的一流高职建设目标，坚持“以贡献求支持，以服务求发展”，以智慧化、国际化、法治化、市场化为重点全面推进内涵建设，争取成为第一批中国特色高水平高职院校。 | AB41: 学校前身是成立于1994年的顺德永强成人学院；1999年，教育部批准成立顺德职业技术学院。2002年，顺德师范学校和顺德成人卫生中等专业学校并入学校，同年，学校迁至佛山市顺德区德胜东路现址。2019年，学校入选中国特色高水平高职学校和专业建设计划建设单位。2025年6月，经教育部批准，以顺德职业技术学院为基础设立顺德职业技术大学。 | AC41: http://www.sdpt.com.cn/ | AD41: http://zs.sdpt.edu.cn | AE41: 0757/22327131、22327132、22323732、22327270 | AF41: 校本部：广东省佛山市顺德区大良街道德胜东路； | AG41: https://www.720yun.com/t/a4c2ejrkxer | AH41: 372 | AI41: https://baike.baidu.com/item/%E9%A1%BA%E5%BE%B7%E8%81%8C%E4%B8%9A%E6%8A%80%E6%9C%AF%E5%AD%A6%E9%99%A2 | AJ41: https://gaokao.chsi.com.cn/zsgs/zhangcheng/listZszc//schId/618.dhtml | AK41: /
A42: 37 | B42: =C42 -> 0 | D42: 依据学考 | E42: 13810 | F42: 肇庆医学院 | G42: 601 | H42: 80 | I42: 2100 | J42: 80 | K42: 2100 | L42: 382 | M42: 389 | N42: 17879 | O42: 24265 | P42: =IFERROR(AVERAGE(L42:M42),"/") -> 385.5 | Q42: =IFERROR(AVERAGE(N42:O42),"/") -> 21072 | R42: 广东省 | S42: 肇庆市 | T42: 广东省 | U42: 普通本科 | V42: 广东省 | W42: 公办 | X42: 三线城市 | Y42: / | Z42: 省属高等/公立/高等专科学校 | AA42: 一、办学历程肇庆医学高等专科学校是经国家教育部批准成立了一所公立全日制专科层次的普通高等院校。学校地处首批中国优秀旅游城市、国家历史文化名城——肇庆市。学校本着“育人为本、质量立校、人才强校、特色兴校”的办学理念，坚持“立足广东辐射全国、面向基层、服务社会”的办学定位，以服务为宗旨、以就业为导向、以职业能力培养为本位，走“校院合作、医教结合”的发展道路，培养“下得去，用得上、留得住”高素质应用型卫生人才。有效发挥了为区域经济发展提供卫生智力支持和人才保证的教育功能。学校办学历史悠久。1958年建校，前身为中山医学院肇庆分院，后更名为广东省肇庆卫生学校。1994年、2000年学校被国家教委、教育部授予重点中专学校称号。1993年、1999年与广东医学院、中山医科大学联合办学，分别设立广东医学院肇庆教学部和中山医科大学肇庆教学点。2004年5月经教育部批准升格为全日制普通高等专科学校，成为我省唯一一所独立设置的医学专科学校。50多年来，学校为国家输送了50000多名的医疗卫生技术人才，很多毕业生成为了行业的精英骨干。二、校区校貌学校现有三个校区：端州校区、鼎湖校区和北校区。端州坐落在景色宜人的西江畔，鼎湖校区毗邻国家4A级旅游风景区鼎湖山。总占地面积512亩，总建筑面积21万平方米。校园环境幽雅，办学基础设施完善。学校建有8个校内实验实训基地，,拥有各类实验、实训、仿真、模拟技能训练室132个，各实验室配备有现代化的电教设备，充分利用现代信息技术开发虚拟实验，进行综合实验项目训练。学校建有现代化的学术报告厅、图书馆、运动场，室内篮、排球运动场、体操房、乒乓球活动室以及学生公寓，为学生提供了良好的学习生活环境。三、附属医院学校现拥有3所直属附属医院，其中第一附属医院（肇庆市第一人民医院）是一所集医疗、教学、科研、预防、保健和康复功能于一体的大型综合性“三级甲等”医院，1995年通过评审成为“爱婴医院”，1996年、1998年分别被省卫生厅评为“广东省高等医学院校教学医院”、省“百家文明医院”；第二附属医院（肇庆市第二人民医院）是集医疗教学科研预防保健康复为一体的三级综合医院和三级妇幼保健院；肇庆医专附属医院（肇庆市口腔医院）是一所集医疗、预防、保健、康复为一体的具有专科特色的“二级甲等”综合医院。是广东医学院、肇庆医学高等专科学校等医学院校的临床教学和实践基地之一。同时也是肇庆市全国医师资格实践技能考试基地。医院医疗教学仪器设备齐全，拥有口腔科、眼科、甲状腺专科等特色业。目前，学校正在加大非直属医院创建工作，到2015年末，将拥有包括高要市人民医院在内的非直属附属医院8所，学校临床教学实力将进一步增强。此外，学校与广东省人民医院、广东武警总队医院、中山大学第三附属医院等省内外130余所二甲以上优质医院共建校外实习基地。为学生提供了功能齐备，管理规范的校外实训基地。四、师资队伍学校现有专兼职教师700多人，教师队伍以中高级职称为主。学校遵循“立足培养，大力引进”的原则，采取一系列激励措施，加强高学历、高职称教师的引进；重视教学名师、教师骨干的培养；支持鼓励在职教师深造。选拔优秀教师赴境内外的一流院校如台湾中山医学大学、菲律宾马尼拉圣保罗大学、香港理工大学、中山大学等进行学习培训。坚持“医教结合”的发展道路，培养出一支“双师型”的师资队伍，在教学、医疗和科研上发挥了重要作用。通过院校（企）合作，构建动态的兼职教师资源库，完善兼职教师聘任制度，初步形成一支数量适宜、结构合理、专兼结合的师资队伍。拥有省市级教学名师、拔尖人才、专业带头人22人。143人次担任教育部高职高专医学类、相关医学类教学指导委员会、全国卫生职业教育教学指导委员会、省、市各学会委员及行业专家。学校教师认真投身于科教研工作，积极参与教材编写及论文发表，教科研项目屡屡在各级成果评比中获奖。五、专业教学学校设有临床医学系、医技系、药学系、护理系、中医系、口腔系、医学基础部、公共基础部、思想政治理论课教学部。学校现开设临床医学、口腔医学、中医学、护理、涉外护理、助产、药学、中药、药品经营与管理、医学影像技术、医学检验技术、卫生检验与检疫技术、卫生财会统计等13个专业；设有康复类学科，开设针灸推拿、康复治疗技术、中医康复技术、健康管理等4个专业，形成了应用医学类和健康管理类学科专业体系。专业设置以市场经济为导向，紧盯社会经济的发展需求，省重点专业有护理专业、临床医学专业、助产专业，其中护理专业是省示范性专业、临床医学和助产专业也是中央财政支持的重点专业；口腔医学专业、中医学专业、药学专业、医学检验技术专业为省“十二五”重点建设专业。康复治疗技术专业、医学影像技术专业为校级重点建设专业。学校是教育部、卫生部等六部委发文确定的《我国护理紧缺人才培养培训基地》。护理和临床医学专业的实训基地得到中央和省级财政的重点扶持。学校口腔医学是与中山大学光华口腔医学院联合办学的重点专业。学校附属医院（肇庆市口腔医院）也得到中山医光华口腔医学院的大力扶持。学校的医学影像、康复治疗技术、社区护理是香港华夏基金会项目资助的项目，具有较强的办学实力。六、办学特色学校人才培养坚持以职业能力为核心，以知识、能力、素质为培养内涵，构建人文素质、理论与实践一体教学体系。一是以德育为载体，注重医学生“做人”教育。依托现代人文，实施素质教育贯穿人才培养全过程。重视学生“学会做人”的道德修养教育，使学生懂得“敬畏生命、关爱病人”，建立社会责任意识和服务意识，乐于为社会为他人奉献。二是以就业为导向，强化技能培养。依托学校与医院行业的紧密合作，做到“三早三突出”，即“早接触社会、早接触专业、早接触临床和突出实验、实训、实习三个关键环节”，帮助学生尽早了解和树立起职业思想。三是以能力为中心，鼓励特长发展。在提高学生专业技能的基础上，创造各种条件培养学生的特长和爱好，进一步提高了学生的综合素质和就业竞争力，为学生走向社会、更好地生活奠定基础。学校个人、团体在省市的艺术文化比赛中屡获殊荣。七、对外交流学校积极开展多种形式的对外交流与合作，逐步树立与国际教育接轨的教育意识，发展特色优势专业教育、拓宽教学思路，提高师生的国际交往能力。与菲律宾马尼拉圣堡罗大学，圣虔诚大学签订交流协议，每年互派师生进行文化交流。与香港理工大学护理学院合作，引进先进的护理教育改革思路；香港理工大学派遣师生到学校进行交流，并共同深入到农村，为少年儿童进行健康知识教育与指导。与台湾中山医学大学合作，邀请台湾的专家学者来校讲学，同时我校输送教师赴台进修学习。与澳门镜湖护理学院合作，选拔优秀应届毕业生赴澳门的医院进行临床实习。学校还与美国、加拿大、日本等国外多家院校和教育机构进行教育、学术、培训合作与交流。八、“十三五”规划发展目标：按照构建职业教育体系要求，引领职业教育科学发展，通过深化改革，以内涵建设为着力点，不断提高办学质量、办学水平、彰显办学特色，实现提升办学层次的目标。将学校创建成省内有地位、国内有影响，特色鲜明，集学历教育、短期培训和社会服务为一体的应用型医学本科院校。 | AB42: / | AC42: http://www.zqmc.net/ | AD42: http://zhaosheng.zqmc.edu.cn/ | AE42: 0758/2857067 | AF42: 校本部：广东省肇庆市端州区西江南路6号；鼎湖校区：广东省肇庆市鼎湖区新城北18区团结路1号；新区校区：广东省肇庆市新区丰乐路12号； | AG42: / | AH42: 662 | AI42: https://baike.baidu.com/item/%E8%82%87%E5%BA%86%E5%8C%BB%E5%AD%A6%E9%99%A2 | AJ42: https://gaokao.chsi.com.cn/zsgs/zhangcheng/listZszc//schId/2049.dhtml | AK42: /
A43: 38 | B43: =C43 -> 0 | D43: 依据学考 | E43: 13810 | F43: 肇庆医学院 | G43: 604 | H43: 360 | I43: / | J43: 360 | K43: / | L43: 376 | M43: / | N43: 24896 | O43: / | P43: =IFERROR(AVERAGE(L43:M43),"/") -> 376 | Q43: =IFERROR(AVERAGE(N43:O43),"/") -> 24896 | R43: 广东省 | S43: 肇庆市 | T43: 广东省 | U43: 普通本科 | V43: 广东省 | W43: 公办 | X43: 三线城市 | Y43: / | Z43: 省属高等/公立/高等专科学校 | AA43: 一、办学历程肇庆医学高等专科学校是经国家教育部批准成立了一所公立全日制专科层次的普通高等院校。学校地处首批中国优秀旅游城市、国家历史文化名城——肇庆市。学校本着“育人为本、质量立校、人才强校、特色兴校”的办学理念，坚持“立足广东辐射全国、面向基层、服务社会”的办学定位，以服务为宗旨、以就业为导向、以职业能力培养为本位，走“校院合作、医教结合”的发展道路，培养“下得去，用得上、留得住”高素质应用型卫生人才。有效发挥了为区域经济发展提供卫生智力支持和人才保证的教育功能。学校办学历史悠久。1958年建校，前身为中山医学院肇庆分院，后更名为广东省肇庆卫生学校。1994年、2000年学校被国家教委、教育部授予重点中专学校称号。1993年、1999年与广东医学院、中山医科大学联合办学，分别设立广东医学院肇庆教学部和中山医科大学肇庆教学点。2004年5月经教育部批准升格为全日制普通高等专科学校，成为我省唯一一所独立设置的医学专科学校。50多年来，学校为国家输送了50000多名的医疗卫生技术人才，很多毕业生成为了行业的精英骨干。二、校区校貌学校现有三个校区：端州校区、鼎湖校区和北校区。端州坐落在景色宜人的西江畔，鼎湖校区毗邻国家4A级旅游风景区鼎湖山。总占地面积512亩，总建筑面积21万平方米。校园环境幽雅，办学基础设施完善。学校建有8个校内实验实训基地，,拥有各类实验、实训、仿真、模拟技能训练室132个，各实验室配备有现代化的电教设备，充分利用现代信息技术开发虚拟实验，进行综合实验项目训练。学校建有现代化的学术报告厅、图书馆、运动场，室内篮、排球运动场、体操房、乒乓球活动室以及学生公寓，为学生提供了良好的学习生活环境。三、附属医院学校现拥有3所直属附属医院，其中第一附属医院（肇庆市第一人民医院）是一所集医疗、教学、科研、预防、保健和康复功能于一体的大型综合性“三级甲等”医院，1995年通过评审成为“爱婴医院”，1996年、1998年分别被省卫生厅评为“广东省高等医学院校教学医院”、省“百家文明医院”；第二附属医院（肇庆市第二人民医院）是集医疗教学科研预防保健康复为一体的三级综合医院和三级妇幼保健院；肇庆医专附属医院（肇庆市口腔医院）是一所集医疗、预防、保健、康复为一体的具有专科特色的“二级甲等”综合医院。是广东医学院、肇庆医学高等专科学校等医学院校的临床教学和实践基地之一。同时也是肇庆市全国医师资格实践技能考试基地。医院医疗教学仪器设备齐全，拥有口腔科、眼科、甲状腺专科等特色业。目前，学校正在加大非直属医院创建工作，到2015年末，将拥有包括高要市人民医院在内的非直属附属医院8所，学校临床教学实力将进一步增强。此外，学校与广东省人民医院、广东武警总队医院、中山大学第三附属医院等省内外130余所二甲以上优质医院共建校外实习基地。为学生提供了功能齐备，管理规范的校外实训基地。四、师资队伍学校现有专兼职教师700多人，教师队伍以中高级职称为主。学校遵循“立足培养，大力引进”的原则，采取一系列激励措施，加强高学历、高职称教师的引进；重视教学名师、教师骨干的培养；支持鼓励在职教师深造。选拔优秀教师赴境内外的一流院校如台湾中山医学大学、菲律宾马尼拉圣保罗大学、香港理工大学、中山大学等进行学习培训。坚持“医教结合”的发展道路，培养出一支“双师型”的师资队伍，在教学、医疗和科研上发挥了重要作用。通过院校（企）合作，构建动态的兼职教师资源库，完善兼职教师聘任制度，初步形成一支数量适宜、结构合理、专兼结合的师资队伍。拥有省市级教学名师、拔尖人才、专业带头人22人。143人次担任教育部高职高专医学类、相关医学类教学指导委员会、全国卫生职业教育教学指导委员会、省、市各学会委员及行业专家。学校教师认真投身于科教研工作，积极参与教材编写及论文发表，教科研项目屡屡在各级成果评比中获奖。五、专业教学学校设有临床医学系、医技系、药学系、护理系、中医系、口腔系、医学基础部、公共基础部、思想政治理论课教学部。学校现开设临床医学、口腔医学、中医学、护理、涉外护理、助产、药学、中药、药品经营与管理、医学影像技术、医学检验技术、卫生检验与检疫技术、卫生财会统计等13个专业；设有康复类学科，开设针灸推拿、康复治疗技术、中医康复技术、健康管理等4个专业，形成了应用医学类和健康管理类学科专业体系。专业设置以市场经济为导向，紧盯社会经济的发展需求，省重点专业有护理专业、临床医学专业、助产专业，其中护理专业是省示范性专业、临床医学和助产专业也是中央财政支持的重点专业；口腔医学专业、中医学专业、药学专业、医学检验技术专业为省“十二五”重点建设专业。康复治疗技术专业、医学影像技术专业为校级重点建设专业。学校是教育部、卫生部等六部委发文确定的《我国护理紧缺人才培养培训基地》。护理和临床医学专业的实训基地得到中央和省级财政的重点扶持。学校口腔医学是与中山大学光华口腔医学院联合办学的重点专业。学校附属医院（肇庆市口腔医院）也得到中山医光华口腔医学院的大力扶持。学校的医学影像、康复治疗技术、社区护理是香港华夏基金会项目资助的项目，具有较强的办学实力。六、办学特色学校人才培养坚持以职业能力为核心，以知识、能力、素质为培养内涵，构建人文素质、理论与实践一体教学体系。一是以德育为载体，注重医学生“做人”教育。依托现代人文，实施素质教育贯穿人才培养全过程。重视学生“学会做人”的道德修养教育，使学生懂得“敬畏生命、关爱病人”，建立社会责任意识和服务意识，乐于为社会为他人奉献。二是以就业为导向，强化技能培养。依托学校与医院行业的紧密合作，做到“三早三突出”，即“早接触社会、早接触专业、早接触临床和突出实验、实训、实习三个关键环节”，帮助学生尽早了解和树立起职业思想。三是以能力为中心，鼓励特长发展。在提高学生专业技能的基础上，创造各种条件培养学生的特长和爱好，进一步提高了学生的综合素质和就业竞争力，为学生走向社会、更好地生活奠定基础。学校个人、团体在省市的艺术文化比赛中屡获殊荣。七、对外交流学校积极开展多种形式的对外交流与合作，逐步树立与国际教育接轨的教育意识，发展特色优势专业教育、拓宽教学思路，提高师生的国际交往能力。与菲律宾马尼拉圣堡罗大学，圣虔诚大学签订交流协议，每年互派师生进行文化交流。与香港理工大学护理学院合作，引进先进的护理教育改革思路；香港理工大学派遣师生到学校进行交流，并共同深入到农村，为少年儿童进行健康知识教育与指导。与台湾中山医学大学合作，邀请台湾的专家学者来校讲学，同时我校输送教师赴台进修学习。与澳门镜湖护理学院合作，选拔优秀应届毕业生赴澳门的医院进行临床实习。学校还与美国、加拿大、日本等国外多家院校和教育机构进行教育、学术、培训合作与交流。八、“十三五”规划发展目标：按照构建职业教育体系要求，引领职业教育科学发展，通过深化改革，以内涵建设为着力点，不断提高办学质量、办学水平、彰显办学特色，实现提升办学层次的目标。将学校创建成省内有地位、国内有影响，特色鲜明，集学历教育、短期培训和社会服务为一体的应用型医学本科院校。 | AB43: / | AC43: http://www.zqmc.net/ | AD43: http://zhaosheng.zqmc.edu.cn/ | AE43: 0758/2857067 | AF43: 校本部：广东省肇庆市端州区西江南路6号；鼎湖校区：广东省肇庆市鼎湖区新城北18区团结路1号；新区校区：广东省肇庆市新区丰乐路12号； | AG43: / | AH43: 662 | AI43: https://baike.baidu.com/item/%E8%82%87%E5%BA%86%E5%8C%BB%E5%AD%A6%E9%99%A2 | AJ43: https://gaokao.chsi.com.cn/zsgs/zhangcheng/listZszc//schId/2049.dhtml | AK43: /
A44: 39 | B44: =C44 -> 0 | D44: 依据学考 | E44: 12040 | F44: 广州民航职业技术学院 | G44: 605 | H44: 80 | I44: 120 | J44: 80 | K44: 120 | L44: 376 | M44: 387 | N44: 24754 | O44: 29178 | P44: =IFERROR(AVERAGE(L44:M44),"/") -> 381.5 | Q44: =IFERROR(AVERAGE(N44:O44),"/") -> 26966 | R44: 广东省 | S44: 广州市 | T44: 广东省 | U44: 专科（高职） | V44: 交通运输部（中国民用航空局） | W44: 公办 | X44: 一线城市 | Y44: 部委院校/省部共建/双高计划/高水平专业群建设单位/国家级示范/现代学徒制试点学院 | Z44: 示范高职/第四类高水平专业群C档 | AA44: 广州民航职业技术学院直属中国民用航空局，是民航内最早一所独立设置实施高等职业教育的全日制公办普通高校。学校1994年被国家教育部确定为全国首批十所试办五年制高职教育的学校之一；1999年经教育部、民航局批准成立；2010年被教育部、财政部确定为国家示范性高等职业院校，是全国百所、广东省四所之一，民航唯一一所国家示范性高等职业院校；2013年正式成为民航局与广东省“省部共建”院校；2016年被广东省教育厅、财政厅确定为“广东省一流高职院校建设计划立项建设单位”。//学校“立足民航，服务地方，面向世界”，坚持职业教育类型的办学定位，在全国率先提出并实施了基于行业标准的技术技能人才培养模式，形成了“依托行业、产学合作、双师双证、国际通用”的办学特色。//学校现有机场路校区、白云机场校区、花都赤坭校区三个校区，共占地1112亩。现有固定资产总值约10.05亿元，其中，教学、科研仪器设备资产值约2.39亿元，33架大中小型教学用飞机，140台飞机发动机，5万多台（件）飞机零部件和一大批专业设备。//学校教职工规模689人，其中，专任教师549人，具有硕士以上学位的教师425人，占专任教师比例为77%；具有双师素质的专业教师224人，占专业课教师数的比例为64%；具有行业企业一线工作经历的教师比例为44.8%；具有民航行业特有工种职业资格证书、职业技能鉴定考评员及教员证书、其他工种职业资格证书的教师比例为41%。//学校下设飞机维修工程学院、航空港管理学院、民航经营管理学院、人文社科学院、继续教育学院五个二级学院。面向31个省、市、自治区招生，现有21个专业26个专业方向，覆盖了民航维修和服务的关键岗位，在校生1.2余万人。新生报到率、毕业生就业率、专业对口率等方面均走在同类院校前列，其中，飞机机电设备维修、飞机结构修理、航空电子设备维修、航空地面设备维修、通用航空器维修等民航特有专业对口率均超过90%，优秀毕业生已成为技术骨干与管理人才。//学校以现代民用航空体系和航空产业链建设需求为导向，以飞机维修、民航运输等民航特有专业岗位（群）核心能力培养为主线，创新了“课证一体、中外融通、校企融合”的民航特有专业人才培养模式。制定了基于行业标准的民航特有专业课程教学标准，做到“行业标准入体系、职业标准入课程”，与民航行业企业合作共建民航飞机维修工程、航空港安全检查、航空服务、通用航空等民航特有专业的校企共享型“公共实训平台”，为全国其他院校的民航专业教学起到引领作用。//学校不断加强与美国、英国、加拿大、新加坡、香港等境外院校和航空企业合作，提升办学国际化水平；与斯里兰卡等“一带一路”沿线国家开展民航职业教育合作，实现教育资源对外输出；先后与美国西敏学院、马来西亚建设大学、台湾中华科技大学开展本科层次职业教育合作，搭建人才成长“立交桥”，实现民航职业教育体系中外衔接；通过国际合作与对外交流，促进了人才培养标准、师资、教材和管理国际化，实现了学校教育与国际接轨，提升了民航职业教育软实力。 | AB44: 学校源自1980年由原中国民航广州管理局举办的技工学校。1984年在此基础上成立“中国民航广州中等专业学校”，由民航广州地区管理局领导管理。1999年经教育部批准成立“广州民航职业技术学院”。2013年成为民航局与广东省“省部共建”院校，2019年被列入第四类高水平专业群建设单位（C档）。 2021年现代学徒制第三批试点验收暂缓通过。 | AC44: http://www.caac.net/ | AD44: https://www.gcac.edu.cn/sites/zsb/index.html | AE44: 020/86123135、86121941 | AF44: 机场路校区：广东省广州市白云区机场路向云西街10号,白云机场校区：广州市白云国际机场空港北横六路 | AG44: / | AH44: 2377 | AI44: https://baike.baidu.com/item/%E5%B9%BF%E5%B7%9E%E6%B0%91%E8%88%AA%E8%81%8C%E4%B8%9A%E6%8A%80%E6%9C%AF%E5%AD%A6%E9%99%A2 | AJ44: https://gaokao.chsi.com.cn/zsgs/zhangcheng/listZszc//schId/952.dhtml | AK44: /
A45: 40 | B45: =C45 -> 0 | D45: 依据学考 | E45: 12046 | F45: 广州职业技术大学 | G45: 601 | H45: 360 | I45: / | J45: 360 | K45: / | L45: 375 | M45: / | N45: 27274 | O45: / | P45: =IFERROR(AVERAGE(L45:M45),"/") -> 375 | Q45: =IFERROR(AVERAGE(N45:O45),"/") -> 27274 | R45: 广东省 | S45: 广州市 | T45: 广东省 | U45: 职业本科 | V45: 广东省 | W45: 公办 | X45: 一线城市 | Y45: 双高计划/高水平学校建设单位/国家级示范/现代学徒制试点学院 | Z45: 第二类高水平学校B档示范高职现代学徒 | AA45: 广州番禺职业技术学院(原名番禺理工学院、番禺职业技术学院)1993年筹建,1997年9月教育部正式批准备案,是全国首批、广州市属第一所公办全日制普通高等职业院校。2003年被广州市政府确定为市属高等职业教育龙头院校。2005年4月以“优秀”成绩通过教育部人才培养工作水平评估。2006年12月被教育部、财政部确定为“国家示范性高等职业院校建设计划”首批28所立项建设院校之一。2009年12月通过教育部、财政部的验收,被正式批准为首批国家示范性高等职业院校。2010年11月被广东省人民政府授予“广东省职业技术教育工作先进集体”称号。2014年5月荣获我国职业教育界的最高奖项——第四届黄炎培职业教育奖“优秀学校奖”。2014年7月被教育部评为“全国毕业生就业典型经验高校50强”。2016年11月成为广东省一流高职院校建设计划立项建设单位。2017年7月荣登“全国高职院校国际影响力50强”和“全国高职院校服务贡献50强”榜单。学校地处珠江三角洲腹地的广州市番禺区,占地2067亩,校舍建筑面积32.98万平方米,固定资产总值超过10.06亿元,其中教学科研仪器设备总值超过2.98亿元,图书馆面积3.07万平方米,馆内阅览座位4300多个,馆藏纸质图书123余万册、电子图书约2900GB、纸质期刊近880种、电子期刊8360余种,建有41个校内实训基地和176个校外实训基地,现有全日制在校生11769人,生源地分布于全国13个省(区)。校园峰峦起伏,碧波粼粼,繁花似锦,绿草如茵,是广州市花园式单位,2012年获评“全国职业院校魅力校园”,被誉为国内最美丽的大学之一。学校以高等职业技术教育为主,设有财经学院、管理学院、机电工程学院、建筑工程学院、人文社科学院、外语外贸学院、信息工程学院、艺术设计学院、珠宝学院、马克思主义学院、继续教育学院等十一个学院,开设44个紧贴珠三角地区产业结构和社会发展需求的专业。目前,学校拥有玩具设计与制造、计算机网络技术、金融管理、视觉传播设计与制作、酒店管理、珠宝首饰工艺及鉴定等6个国家示范性高职院校重点建设专业、1个全国职业院校国家级示范专业点、2个中央财政支持提升专业服务产业发展能力专业、2个省级协同育人平台、9个省级示范性专业、8个省级重点建设专业、12个省级品牌建设专业、8个市级特色专业学院、2个市级校企合作示范学院、2个产业学院、6个市级示范性专业、6个市级重点建设专业;15门国家级精品课程、25门省级精品课程和40门市级精品课程;14门国家级精品资源共享课程、31门省级精品开放(建设)课程和5门省级精品在线开放(建设)课程;1门国家精品视频公开课程、2门省级精品视频公开课;1个国家级校内实训基地、7个省级校内实训基地、9个市级校内实训基地和2个省级大学生校外实践教学基地、10个省级大学生校外实践教学基地(建设)项目、2个市级校外示范性实训基地。学校积极与企业、科研院所开展产学研合作,搭建应用技术研发平台,建有包括广东高校珠宝首饰工程技术开发中心、广东省珠宝首饰工程技术研究中心、广东省智慧职业教育大数据工程技术研究中心、广东省皮革智能产品3D打印应用工程技术研究中心、广东省绿色建造和检测工程技术研究中心等工程中心，以及广州市人文社科研究基地、广州市技术转移示范机构（中心）在内的39个科学研究机构（应用技术协同创新中心、研究基地等）。产出了一批以专利为代表的科技创新成果,专利申请、专利授权、有效专利、专利竞争力全部进入2017年中国大学专利排行榜500强,获2013年广州市专利创造贡献奖。承担了国家自然科学基金项目、国家社会科学基金项目(教育学)、全国教育规划项目、教育部人文社科项目等一批高层级的科研项目,公开发表一批有影响的科研教研论文,论文最高他引次数达604次。学校面向全国公开招聘优秀教师,拥有一支人员精干、结构合理、水平较高的师资队伍。现有教职工934人,专任教师545人,专任教师中具有高级职称者占30.09%,具有研究生学位者占70.46%,“双师”素质专任教师比例达70.28%。现有全国教育系统先进集体1个、全国职业教育先进单位1个,国家级教学团队2个、省级教学团队6个,有享受国务院政府特殊津贴专家3人、国家级教学名师5人、省级教学名师12人、市级教学名师6人。学校坚持走质量、规模、效益协调发展的内涵式发展之路,强化质量意识,以教师为主导,以学生为主体,以培养学生创新精神和职业能力为目标,积极探索教学改革,2001年以来,共有66项教学成果获得国家、省、市教学成果奖,其中,国家级教学成果一等奖1项、二等奖10项,广东省教学成果特等奖1项、一等奖11项、二等奖15项,广州市教学成果特等奖4项、一等奖12项。学校坚持以服务为宗旨,是国家计算机应用与软件技术专业领域技能型紧缺人才培养培训基地,中国玩具行业人才培训基地,广东省首批省级示范性软件学院建设学校,广东省高职高专师资培训基地、广东省中等职业学校师资培训基地、广州市专业技术人员继续教育基地、广州市中等职业学校教师(校长)培训中心,已成立国家职业技能鉴定所,可以开展19个工种的职业资格鉴定。学校广泛开展对外交流与合作,加强与海内外知名大学、同类职业技术学院及培训机构的联系,已与英国、美国、加拿大、芬兰、荷兰、意大利、新加坡、日本等国外高等教育机构和港澳台地区的教育机构及科技大学建立了教育交流与合作关系，同时积极拓展与“一带一路”沿线国家的教育交流合作。在设立海外研习基地、联合培养、专业及课程共建、学分互认、中外合作办学、质量管理体系建设、师资培训等方面开展了富有成效的交流与合作,促进了人才培养质量和国际化程度的提升。同时,学校发挥品牌专业和特色课程优势,吸引国际学生来校短期交换和修读课程,形成了较高的知名度和美誉度。2018年我校与新加坡南洋理工学院学生海外研习基地合作项目入选全国首批20个“中国—东盟高职院校特色合作项目”。学校围绕培养“一技之长+综合素质”的高素质、创新性技术技能人才的目标,实行以素质为基础,以能力为核心,以就业为导向,产学研结合的人才培养模式,积极实施“双证书”制度,大力培养学生的职业技能,毕业生以其适应性强、动手能力强、综合素质高而受到用人单位普遍欢迎。自2001年广东省首次公布高校毕业生就业率以来,学校毕业生就业率一直稳居全省高校前列,2004年、2005年和2008年三年位居全省所有本专科院校第一位。2010年,学校模具设计与制造专业2001届毕业生黄德智喜获“全国劳动模范”崇高荣誉,在北京人民大会堂受到党中央和国务院的隆重表彰。2018年，学校涉外文秘专业2002届毕业生王俊文荣获广东省五一劳动奖章。2018年,毕业生就业率达98.79%。番禺籍的原全国政协副主席霍英东,全国政协副主席、澳门特别行政区首任行政长官何厚铧,全国政协委员陈瑞球,以及何添、何善衡等港澳同胞和社会各界有识之士对学校的建设给予极大的关注和有力的资助,捐资兴建了霍英东学术交流中心、何厚铧大楼等一批教学、实训用房和学生宿舍,极大地促进了学校的发展。功崇惟志,天道酬勤。学校以习近平新时代中国特色社会义思想为指导，积极对接国家“一带一路”和粤港澳大湾区发展战略，坚持走以质量为核心的内涵式发展道路，以建设“中国特色、国际水准”的高职院校为目标，不断深化校企合作、产教融合体制机制改革，致力于为大湾区经济社会发展培养具有“一技之长+综合素质”的高素质、创新型技术技能人才。 | AB45: 学校的前身是1996年4月经广东省人民政府批准成立的番禺理工学院，于1993年筹建；1997年6月更名为番禺职业技术学院；1997年9月经国家教育委员会正式备案，由广州市和番禺市人民政府共同领导、番禺市直接管理；2006年起实行“市区共建，以区为主”的管理体制；2008年7月更名为广州番禺职业技术学院；2010年起实行“市区共建，以市为主”的管理体制；2006年12月被教育部、财政部确定为“国家示范性高等职业院校建设计划”首批立项建设院校，2009年12月通过验收，成为国家示范性高等职业院校；2019年12月入选中国特色高水平高职学校和专业建设单位。2025年6月中华人民共和国教育部同意以广州番禺职业技术学院为基础设立广州职业技术大学。 | AC45: http://www.gzpyp.edu.cn/ | AD45: http://zs.gzpyp.edu.cn/ | AE45: 020/34874086、84731206 | AF45: 广东省广州市番禺区市良路1342号 | AG45: https://www.720yun.com/t/f10jz0yavf3 | AH45: 426 | AI45: https://baike.baidu.com/item/%E5%B9%BF%E5%B7%9E%E7%95%AA%E7%A6%BA%E8%81%8C%E4%B8%9A%E6%8A%80%E6%9C%AF%E5%AD%A6%E9%99%A2 | AJ45: https://gaokao.chsi.com.cn/zsgs/zhangcheng/listZszc//schId/954.dhtml | AK45: /
A46: 41 | B46: =C46 -> 0 | D46: 依据学考 | E46: 12046 | F46: 广州职业技术大学 | G46: 606 | H46: 63 | I46: / | J46: 63 | K46: / | L46: 374 | M46: / | N46: 27603 | O46: / | P46: =IFERROR(AVERAGE(L46:M46),"/") -> 374 | Q46: =IFERROR(AVERAGE(N46:O46),"/") -> 27603 | R46: 广东省 | S46: 广州市 | T46: 广东省 | U46: 职业本科 | V46: 广东省 | W46: 公办 | X46: 一线城市 | Y46: 双高计划/高水平学校建设单位/国家级示范/现代学徒制试点学院 | Z46: 第二类高水平学校B档示范高职现代学徒 | AA46: 广州番禺职业技术学院(原名番禺理工学院、番禺职业技术学院)1993年筹建,1997年9月教育部正式批准备案,是全国首批、广州市属第一所公办全日制普通高等职业院校。2003年被广州市政府确定为市属高等职业教育龙头院校。2005年4月以“优秀”成绩通过教育部人才培养工作水平评估。2006年12月被教育部、财政部确定为“国家示范性高等职业院校建设计划”首批28所立项建设院校之一。2009年12月通过教育部、财政部的验收,被正式批准为首批国家示范性高等职业院校。2010年11月被广东省人民政府授予“广东省职业技术教育工作先进集体”称号。2014年5月荣获我国职业教育界的最高奖项——第四届黄炎培职业教育奖“优秀学校奖”。2014年7月被教育部评为“全国毕业生就业典型经验高校50强”。2016年11月成为广东省一流高职院校建设计划立项建设单位。2017年7月荣登“全国高职院校国际影响力50强”和“全国高职院校服务贡献50强”榜单。学校地处珠江三角洲腹地的广州市番禺区,占地2067亩,校舍建筑面积32.98万平方米,固定资产总值超过10.06亿元,其中教学科研仪器设备总值超过2.98亿元,图书馆面积3.07万平方米,馆内阅览座位4300多个,馆藏纸质图书123余万册、电子图书约2900GB、纸质期刊近880种、电子期刊8360余种,建有41个校内实训基地和176个校外实训基地,现有全日制在校生11769人,生源地分布于全国13个省(区)。校园峰峦起伏,碧波粼粼,繁花似锦,绿草如茵,是广州市花园式单位,2012年获评“全国职业院校魅力校园”,被誉为国内最美丽的大学之一。学校以高等职业技术教育为主,设有财经学院、管理学院、机电工程学院、建筑工程学院、人文社科学院、外语外贸学院、信息工程学院、艺术设计学院、珠宝学院、马克思主义学院、继续教育学院等十一个学院,开设44个紧贴珠三角地区产业结构和社会发展需求的专业。目前,学校拥有玩具设计与制造、计算机网络技术、金融管理、视觉传播设计与制作、酒店管理、珠宝首饰工艺及鉴定等6个国家示范性高职院校重点建设专业、1个全国职业院校国家级示范专业点、2个中央财政支持提升专业服务产业发展能力专业、2个省级协同育人平台、9个省级示范性专业、8个省级重点建设专业、12个省级品牌建设专业、8个市级特色专业学院、2个市级校企合作示范学院、2个产业学院、6个市级示范性专业、6个市级重点建设专业;15门国家级精品课程、25门省级精品课程和40门市级精品课程;14门国家级精品资源共享课程、31门省级精品开放(建设)课程和5门省级精品在线开放(建设)课程;1门国家精品视频公开课程、2门省级精品视频公开课;1个国家级校内实训基地、7个省级校内实训基地、9个市级校内实训基地和2个省级大学生校外实践教学基地、10个省级大学生校外实践教学基地(建设)项目、2个市级校外示范性实训基地。学校积极与企业、科研院所开展产学研合作,搭建应用技术研发平台,建有包括广东高校珠宝首饰工程技术开发中心、广东省珠宝首饰工程技术研究中心、广东省智慧职业教育大数据工程技术研究中心、广东省皮革智能产品3D打印应用工程技术研究中心、广东省绿色建造和检测工程技术研究中心等工程中心，以及广州市人文社科研究基地、广州市技术转移示范机构（中心）在内的39个科学研究机构（应用技术协同创新中心、研究基地等）。产出了一批以专利为代表的科技创新成果,专利申请、专利授权、有效专利、专利竞争力全部进入2017年中国大学专利排行榜500强,获2013年广州市专利创造贡献奖。承担了国家自然科学基金项目、国家社会科学基金项目(教育学)、全国教育规划项目、教育部人文社科项目等一批高层级的科研项目,公开发表一批有影响的科研教研论文,论文最高他引次数达604次。学校面向全国公开招聘优秀教师,拥有一支人员精干、结构合理、水平较高的师资队伍。现有教职工934人,专任教师545人,专任教师中具有高级职称者占30.09%,具有研究生学位者占70.46%,“双师”素质专任教师比例达70.28%。现有全国教育系统先进集体1个、全国职业教育先进单位1个,国家级教学团队2个、省级教学团队6个,有享受国务院政府特殊津贴专家3人、国家级教学名师5人、省级教学名师12人、市级教学名师6人。学校坚持走质量、规模、效益协调发展的内涵式发展之路,强化质量意识,以教师为主导,以学生为主体,以培养学生创新精神和职业能力为目标,积极探索教学改革,2001年以来,共有66项教学成果获得国家、省、市教学成果奖,其中,国家级教学成果一等奖1项、二等奖10项,广东省教学成果特等奖1项、一等奖11项、二等奖15项,广州市教学成果特等奖4项、一等奖12项。学校坚持以服务为宗旨,是国家计算机应用与软件技术专业领域技能型紧缺人才培养培训基地,中国玩具行业人才培训基地,广东省首批省级示范性软件学院建设学校,广东省高职高专师资培训基地、广东省中等职业学校师资培训基地、广州市专业技术人员继续教育基地、广州市中等职业学校教师(校长)培训中心,已成立国家职业技能鉴定所,可以开展19个工种的职业资格鉴定。学校广泛开展对外交流与合作,加强与海内外知名大学、同类职业技术学院及培训机构的联系,已与英国、美国、加拿大、芬兰、荷兰、意大利、新加坡、日本等国外高等教育机构和港澳台地区的教育机构及科技大学建立了教育交流与合作关系，同时积极拓展与“一带一路”沿线国家的教育交流合作。在设立海外研习基地、联合培养、专业及课程共建、学分互认、中外合作办学、质量管理体系建设、师资培训等方面开展了富有成效的交流与合作,促进了人才培养质量和国际化程度的提升。同时,学校发挥品牌专业和特色课程优势,吸引国际学生来校短期交换和修读课程,形成了较高的知名度和美誉度。2018年我校与新加坡南洋理工学院学生海外研习基地合作项目入选全国首批20个“中国—东盟高职院校特色合作项目”。学校围绕培养“一技之长+综合素质”的高素质、创新性技术技能人才的目标,实行以素质为基础,以能力为核心,以就业为导向,产学研结合的人才培养模式,积极实施“双证书”制度,大力培养学生的职业技能,毕业生以其适应性强、动手能力强、综合素质高而受到用人单位普遍欢迎。自2001年广东省首次公布高校毕业生就业率以来,学校毕业生就业率一直稳居全省高校前列,2004年、2005年和2008年三年位居全省所有本专科院校第一位。2010年,学校模具设计与制造专业2001届毕业生黄德智喜获“全国劳动模范”崇高荣誉,在北京人民大会堂受到党中央和国务院的隆重表彰。2018年，学校涉外文秘专业2002届毕业生王俊文荣获广东省五一劳动奖章。2018年,毕业生就业率达98.79%。番禺籍的原全国政协副主席霍英东,全国政协副主席、澳门特别行政区首任行政长官何厚铧,全国政协委员陈瑞球,以及何添、何善衡等港澳同胞和社会各界有识之士对学校的建设给予极大的关注和有力的资助,捐资兴建了霍英东学术交流中心、何厚铧大楼等一批教学、实训用房和学生宿舍,极大地促进了学校的发展。功崇惟志,天道酬勤。学校以习近平新时代中国特色社会义思想为指导，积极对接国家“一带一路”和粤港澳大湾区发展战略，坚持走以质量为核心的内涵式发展道路，以建设“中国特色、国际水准”的高职院校为目标，不断深化校企合作、产教融合体制机制改革，致力于为大湾区经济社会发展培养具有“一技之长+综合素质”的高素质、创新型技术技能人才。 | AB46: 学校的前身是1996年4月经广东省人民政府批准成立的番禺理工学院，于1993年筹建；1997年6月更名为番禺职业技术学院；1997年9月经国家教育委员会正式备案，由广州市和番禺市人民政府共同领导、番禺市直接管理；2006年起实行“市区共建，以区为主”的管理体制；2008年7月更名为广州番禺职业技术学院；2010年起实行“市区共建，以市为主”的管理体制；2006年12月被教育部、财政部确定为“国家示范性高等职业院校建设计划”首批立项建设院校，2009年12月通过验收，成为国家示范性高等职业院校；2019年12月入选中国特色高水平高职学校和专业建设单位。2025年6月中华人民共和国教育部同意以广州番禺职业技术学院为基础设立广州职业技术大学。 | AC46: http://www.gzpyp.edu.cn/ | AD46: http://zs.gzpyp.edu.cn/ | AE46: 020/34874086、84731206 | AF46: 广东省广州市番禺区市良路1342号 | AG46: https://www.720yun.com/t/f10jz0yavf3 | AH46: 426 | AI46: https://baike.baidu.com/item/%E5%B9%BF%E5%B7%9E%E7%95%AA%E7%A6%BA%E8%81%8C%E4%B8%9A%E6%8A%80%E6%9C%AF%E5%AD%A6%E9%99%A2 | AJ46: https://gaokao.chsi.com.cn/zsgs/zhangcheng/listZszc//schId/954.dhtml | AK46: /
A47: 42 | B47: =C47 -> 0 | D47: 依据学考 | E47: 12572 | F47: 广东科学技术职业学院 | G47: 601 | H47: 285 | I47: 650 | J47: 285 | K47: 650 | L47: 374 | M47: 387 | N47: 27489 | O47: 28148 | P47: =IFERROR(AVERAGE(L47:M47),"/") -> 380.5 | Q47: =IFERROR(AVERAGE(N47:O47),"/") -> 27818.5 | R47: 广东省 | S47: 广州市 | T47: 广东省 | U47: 专科（高职） | V47: 广东省 | W47: 公办 | X47: 一线城市 | Y47: 省属/双高计划/高水平专业群建设单位/国家级骨干/现代学徒制试点学院 | Z47: 第三类高水平专业群B档骨干高职现代学徒 | AA47: 学院是广东省人民政府1985年批准设立、教育部备案的一所全日制公办普通高等学院，正厅级建制。建院之初，学院名广东省科技干部进修学院，主要承担广东省科技管理干部的继续教育培训任务，被国家科技部称誉为“地方继续教育的一颗明珠”。1989年更名为广东省科技干部学院，1996年成为广东省首批举办普通高职教育的院校之一。2001年与珠海市政府合作共建珠海校区。2003年经教育部批准由成人高校改制为普通高等学院，并继续承担科技干部培训的任务。2008年5月，学院由广东省科技厅整建制划转广东省教育厅管理。学院于2008年12月以“优秀”成绩通过教育部高职高专人才培养工作评估。2010年被广东省政府授予“广东省职业技术教育工作先进集体”光荣称号。2010年被教育部、财政部确定为国家示范性骨干高职院校立项建设单位。2016年3月以“良好”成绩通过验收，成为国家示范性骨干高职院校。2016年7月被广东省科学技术厅确定为省“互联网+”创新创业示范校。2016年11月被广东省教育厅确定为一流高职院校立项建设单位。2019年7月被教育部确定为“国家优质专科高等职业院校”。2016、2017、2018连续三年入选全国高等职业院校服务贡献50强。2018年入选全国高等职业院校教学资源50强。2019年入选全国高等职业院校育人成效50强。2016年被国际创新创业博览会组委会授予“全国高职院校创新创业示范校”荣誉称号。学院现有珠海和广州两个校区，校园面积2012亩，建筑面积53.06万㎡（含在建工程：4.28万㎡）（其中：教室3.09万㎡，图书馆3.05万㎡，体育场馆0.98万㎡，实习实训场所15.55万㎡）。教学仪器设备2.16万台（套），教学科研仪器设备值25543.34万元。馆藏图书155.92万册、电子图书数字资源量7866GB。学院现有教职员工1320余人，其中专任教师1050人。专任教师中，正高职称70余人，副高职称270余人，拥有博士学位70余人，硕士学位660余人，双师素质教师950余人，专任教师“双师”素质比例达90%。全国教育系统先进集体1个，省级教学名师1人，南粤优秀教师9人，“千百十工程”省级培养对象5人，省高职教育专业领军人才培养对象3人，省优秀青年教师培养对象7人，珠海市特聘学者1人。学院全日制在校生23000多名，是在校生规模最大的省属高职院校。现设有计算机工程技术学院（软件学院）、大数据与人工智能学院、商学院、应用外语学院、旅游学院、文化与传媒学院、机器人学院、机械与汽车学院、建筑工程学院、艺术设计学院、财会与金融学院、体育健康学院、广州学院、马克思主义学院、国际合作学院、创新创业学院、继续教育学院等17个二级学院；设有广东省人才研究所、高职教育研究所、电子与信息技术研究所、软科学研究所等4个科研机构。学院现有招生专业48个，其中国家骨干高职院校重点建设专业5个，央财支持建设专业2个，省级示范专业5个，省级重点专业6个，广东省一类品牌专业1个、二类品牌专业12个。国家级精品资源共享课4门、国家精品课程5门、省级精品课程5门、省级精品资源共享课程22门，省精品在线开放课程3门，国家级备选专业教学资源库1个。获国家级、省级教学成果奖11项。学院加强校企合作办学，积极构建“校企精准对接、精准育人”人才培养模式，按照“一院一品”“一专业一特色一名企”的整体部署，将产业学院、项目班、订单班、现代学徒制等作为推进产教融合、“双精准”育人的重要举措，与微软中国、苹果、思科、华为、联想、金山软件、蓝盾股份、小米、一汽大众、横琴长隆、三一海洋重工等知名企业建立长期合作关系，大力加强学生技术技能培养。学院重视产学研合作、应用开发与成果转化，鼓励教师参与企业技术研发、提供技术服务，努力服务地方经济社会发展。仅2017、2018两年，学校各类科研与社会服务到款额达3942万元，首次获得国家社科基金项目1项,认定1/个国家级众创空间、1/个国家工作室、1/个省级中小企业服务示范平台；建成1个省级专业众创空间、31个协同创新和协同育人平台（其中省级及以上5个），培育10个高水平技术服务团队，社会培训58400余人日，对广东省创新创业示范市（区、县）的建设提供有效支撑。学院建有校内实训基地70多个、实训室240多个，校外实习实训基地800多个；建成中央财政支持实训基地4个，省级高职教育实训基地6个，省级大学生校外实践教学基地6个，省级公共实训中心2个，珠海市重点实验室1个，珠海市公共实验室1个。是国家科技部、省科技厅、教育厅、人事厅认定的“国家级星火培训基地”“广东科技人才基地”“广东省中职学院教师继续教育基地”“广东省专业技术人员继续教育基地”。学院积极构建对外开放新格局，稳步实施“走出去”战略，主动服务国家“一带一路”和粤港澳大湾区建设，加强与德国、法国、美国等职业教育发达国家和港澳台地区的交流与合作，先后与法国克莱蒙商学院、德国德累斯顿工业大学、美国北密歇根大学等签订了合作协议。2017年学校取得招收国际学生和港澳台学生资质，并启动招生工作。2018年获“广东省高等院校对外交流与合作先进集体”。学院学生在省级以上技能竞赛中屡获佳绩，尽显广科学子风采。近五年，学生获省级以上技能竞赛奖项600余项，其中在全国职业院校技能大赛（天津国赛）获奖30余项。如2018年全国职业院校技能大赛高职组导游服务一等奖，2017年全国职业院校技能大赛高职组建筑工程识图团体一等奖、英语口语一等奖，2017年全国大学生数学建模竞赛3项一等奖，2016年全国大学生数学建模竞赛3项一等奖，2015年全国职业院校技能大赛高职组计算机网络应用一等奖，第24届FIRA机器人世界杯大赛1项冠军，2017、2018、2019年连续三年获得中国机器人及人工智能大赛9项全国冠军。机械与汽车学院2016级胡智文同学作为广东省唯一代表荣获2017年度“劲牌阳光奖学金”特别奖暨“践行工匠精神先进个人”，成为全国获此殊荣的十名代表之一，在校期间先后获得国际级、国家级、省级、校级等各类奖项共20余项。一大批优秀毕业生脱颖而出，在各行各业做出突出成绩，得到社会广泛好评。如2006届毕业生谭倩茹同学，获“红棉杯”中国原创产品设计大赛金奖，其工业设计作品得到原广东省委书记张德江，省长黄华华同志的亲笔题词；研发95款手游APP的移动应用开发中心学生团队，被媒体誉为“最牛高职生”；2013届毕业生孙志斌，是国内首个获得思科网络学院全额奖学金赴美实习的高职生；2011届毕业生黄胜，受邀参加央视《奋斗》访谈栏目；2011届毕业生聂云宸创办喜茶品牌，进入福布斯2018年中国30岁以下精英榜单等。学院招生“进口”旺，现每年面向全国18个省（直辖市、自治区）招收全日制在校生8000人左右，广东省录取的新生均为第一志愿报考我院的考生。学院积极开展中高职衔接、三二分段、现代学徒制等多形式自主招生，以及本专科协同育人试点招生工作。毕业生就业“出口”畅，总体就业率均达98%以上。学院秉承“厚德、高能、求实、创新”的校训，坚持“质量立校、特色兴校、创新强校”的办学思路，积极构建“双精准”育人模式，着力打造“互联网+”科技特色，大力实施国际化发展战略，努力培养创新型技能人才，正为创建全国一流、国际知名高职院校而不懈努力。（2019年10月20日更新） | AB47: 学校成立于1985年，前身是广东省科技干部学院，2003年改制为普通高等学校，2004年被教育部、建设部确认为建设行业技能型紧缺人才培养培训工程试点高校，2010年被教育部、财政部确定为“国家示范性高职院校建设计划”骨干高职院校立项建设单位。2015年入选国家首批现代学徒制试点单位。2019年12月，被教育部、财政部列入第三类高水平专业群建设单位（B档）。 | AC47: http://www.gdit.edu.cn/ | AD47: https://www.gdit.edu.cn/zsb/main.htm | AE47: 0756/7796101,020/85297313 | AF47: 广州校区：广州市天河区科华街351号,珠海校区：珠海市金湾区珠海大道南侧 | AG47: https://www.720yun.com/t/096jupwvef3 | AH47: 1329 | AI47: https://baike.baidu.com/item/%E5%B9%BF%E4%B8%9C%E7%A7%91%E5%AD%A6%E6%8A%80%E6%9C%AF%E8%81%8C%E4%B8%9A%E5%AD%A6%E9%99%A2 | AJ47: https://gaokao.chsi.com.cn/zsgs/zhangcheng/listZszc//schId/1104.dhtml | AK47: /
A48: 43 | B48: =C48 -> 0 | D48: 依据学考 | E48: 12572 | F48: 广东科学技术职业学院 | G48: 603 | H48: 200 | I48: 460 | J48: 200 | K48: 460 | L48: 372 | M48: 389 | N48: 30794 | O48: 25840 | P48: =IFERROR(AVERAGE(L48:M48),"/") -> 380.5 | Q48: =IFERROR(AVERAGE(N48:O48),"/") -> 28317 | R48: 广东省 | S48: 广州市 | T48: 广东省 | U48: 专科（高职） | V48: 广东省 | W48: 公办 | X48: 一线城市 | Y48: 省属/双高计划/高水平专业群建设单位/国家级骨干/现代学徒制试点学院 | Z48: 第三类高水平专业群B档骨干高职现代学徒 | AA48: 学院是广东省人民政府1985年批准设立、教育部备案的一所全日制公办普通高等学院，正厅级建制。建院之初，学院名广东省科技干部进修学院，主要承担广东省科技管理干部的继续教育培训任务，被国家科技部称誉为“地方继续教育的一颗明珠”。1989年更名为广东省科技干部学院，1996年成为广东省首批举办普通高职教育的院校之一。2001年与珠海市政府合作共建珠海校区。2003年经教育部批准由成人高校改制为普通高等学院，并继续承担科技干部培训的任务。2008年5月，学院由广东省科技厅整建制划转广东省教育厅管理。学院于2008年12月以“优秀”成绩通过教育部高职高专人才培养工作评估。2010年被广东省政府授予“广东省职业技术教育工作先进集体”光荣称号。2010年被教育部、财政部确定为国家示范性骨干高职院校立项建设单位。2016年3月以“良好”成绩通过验收，成为国家示范性骨干高职院校。2016年7月被广东省科学技术厅确定为省“互联网+”创新创业示范校。2016年11月被广东省教育厅确定为一流高职院校立项建设单位。2019年7月被教育部确定为“国家优质专科高等职业院校”。2016、2017、2018连续三年入选全国高等职业院校服务贡献50强。2018年入选全国高等职业院校教学资源50强。2019年入选全国高等职业院校育人成效50强。2016年被国际创新创业博览会组委会授予“全国高职院校创新创业示范校”荣誉称号。学院现有珠海和广州两个校区，校园面积2012亩，建筑面积53.06万㎡（含在建工程：4.28万㎡）（其中：教室3.09万㎡，图书馆3.05万㎡，体育场馆0.98万㎡，实习实训场所15.55万㎡）。教学仪器设备2.16万台（套），教学科研仪器设备值25543.34万元。馆藏图书155.92万册、电子图书数字资源量7866GB。学院现有教职员工1320余人，其中专任教师1050人。专任教师中，正高职称70余人，副高职称270余人，拥有博士学位70余人，硕士学位660余人，双师素质教师950余人，专任教师“双师”素质比例达90%。全国教育系统先进集体1个，省级教学名师1人，南粤优秀教师9人，“千百十工程”省级培养对象5人，省高职教育专业领军人才培养对象3人，省优秀青年教师培养对象7人，珠海市特聘学者1人。学院全日制在校生23000多名，是在校生规模最大的省属高职院校。现设有计算机工程技术学院（软件学院）、大数据与人工智能学院、商学院、应用外语学院、旅游学院、文化与传媒学院、机器人学院、机械与汽车学院、建筑工程学院、艺术设计学院、财会与金融学院、体育健康学院、广州学院、马克思主义学院、国际合作学院、创新创业学院、继续教育学院等17个二级学院；设有广东省人才研究所、高职教育研究所、电子与信息技术研究所、软科学研究所等4个科研机构。学院现有招生专业48个，其中国家骨干高职院校重点建设专业5个，央财支持建设专业2个，省级示范专业5个，省级重点专业6个，广东省一类品牌专业1个、二类品牌专业12个。国家级精品资源共享课4门、国家精品课程5门、省级精品课程5门、省级精品资源共享课程22门，省精品在线开放课程3门，国家级备选专业教学资源库1个。获国家级、省级教学成果奖11项。学院加强校企合作办学，积极构建“校企精准对接、精准育人”人才培养模式，按照“一院一品”“一专业一特色一名企”的整体部署，将产业学院、项目班、订单班、现代学徒制等作为推进产教融合、“双精准”育人的重要举措，与微软中国、苹果、思科、华为、联想、金山软件、蓝盾股份、小米、一汽大众、横琴长隆、三一海洋重工等知名企业建立长期合作关系，大力加强学生技术技能培养。学院重视产学研合作、应用开发与成果转化，鼓励教师参与企业技术研发、提供技术服务，努力服务地方经济社会发展。仅2017、2018两年，学校各类科研与社会服务到款额达3942万元，首次获得国家社科基金项目1项,认定1/个国家级众创空间、1/个国家工作室、1/个省级中小企业服务示范平台；建成1个省级专业众创空间、31个协同创新和协同育人平台（其中省级及以上5个），培育10个高水平技术服务团队，社会培训58400余人日，对广东省创新创业示范市（区、县）的建设提供有效支撑。学院建有校内实训基地70多个、实训室240多个，校外实习实训基地800多个；建成中央财政支持实训基地4个，省级高职教育实训基地6个，省级大学生校外实践教学基地6个，省级公共实训中心2个，珠海市重点实验室1个，珠海市公共实验室1个。是国家科技部、省科技厅、教育厅、人事厅认定的“国家级星火培训基地”“广东科技人才基地”“广东省中职学院教师继续教育基地”“广东省专业技术人员继续教育基地”。学院积极构建对外开放新格局，稳步实施“走出去”战略，主动服务国家“一带一路”和粤港澳大湾区建设，加强与德国、法国、美国等职业教育发达国家和港澳台地区的交流与合作，先后与法国克莱蒙商学院、德国德累斯顿工业大学、美国北密歇根大学等签订了合作协议。2017年学校取得招收国际学生和港澳台学生资质，并启动招生工作。2018年获“广东省高等院校对外交流与合作先进集体”。学院学生在省级以上技能竞赛中屡获佳绩，尽显广科学子风采。近五年，学生获省级以上技能竞赛奖项600余项，其中在全国职业院校技能大赛（天津国赛）获奖30余项。如2018年全国职业院校技能大赛高职组导游服务一等奖，2017年全国职业院校技能大赛高职组建筑工程识图团体一等奖、英语口语一等奖，2017年全国大学生数学建模竞赛3项一等奖，2016年全国大学生数学建模竞赛3项一等奖，2015年全国职业院校技能大赛高职组计算机网络应用一等奖，第24届FIRA机器人世界杯大赛1项冠军，2017、2018、2019年连续三年获得中国机器人及人工智能大赛9项全国冠军。机械与汽车学院2016级胡智文同学作为广东省唯一代表荣获2017年度“劲牌阳光奖学金”特别奖暨“践行工匠精神先进个人”，成为全国获此殊荣的十名代表之一，在校期间先后获得国际级、国家级、省级、校级等各类奖项共20余项。一大批优秀毕业生脱颖而出，在各行各业做出突出成绩，得到社会广泛好评。如2006届毕业生谭倩茹同学，获“红棉杯”中国原创产品设计大赛金奖，其工业设计作品得到原广东省委书记张德江，省长黄华华同志的亲笔题词；研发95款手游APP的移动应用开发中心学生团队，被媒体誉为“最牛高职生”；2013届毕业生孙志斌，是国内首个获得思科网络学院全额奖学金赴美实习的高职生；2011届毕业生黄胜，受邀参加央视《奋斗》访谈栏目；2011届毕业生聂云宸创办喜茶品牌，进入福布斯2018年中国30岁以下精英榜单等。学院招生“进口”旺，现每年面向全国18个省（直辖市、自治区）招收全日制在校生8000人左右，广东省录取的新生均为第一志愿报考我院的考生。学院积极开展中高职衔接、三二分段、现代学徒制等多形式自主招生，以及本专科协同育人试点招生工作。毕业生就业“出口”畅，总体就业率均达98%以上。学院秉承“厚德、高能、求实、创新”的校训，坚持“质量立校、特色兴校、创新强校”的办学思路，积极构建“双精准”育人模式，着力打造“互联网+”科技特色，大力实施国际化发展战略，努力培养创新型技能人才，正为创建全国一流、国际知名高职院校而不懈努力。（2019年10月20日更新） | AB48: 学校成立于1985年，前身是广东省科技干部学院，2003年改制为普通高等学校，2004年被教育部、建设部确认为建设行业技能型紧缺人才培养培训工程试点高校，2010年被教育部、财政部确定为“国家示范性高职院校建设计划”骨干高职院校立项建设单位。2015年入选国家首批现代学徒制试点单位。2019年12月，被教育部、财政部列入第三类高水平专业群建设单位（B档）。 | AC48: http://www.gdit.edu.cn/ | AD48: https://www.gdit.edu.cn/zsb/main.htm | AE48: 0756/7796101,020/85297313 | AF48: 广州校区：广州市天河区科华街351号,珠海校区：珠海市金湾区珠海大道南侧 | AG48: https://www.720yun.com/t/096jupwvef3 | AH48: 1329 | AI48: https://baike.baidu.com/item/%E5%B9%BF%E4%B8%9C%E7%A7%91%E5%AD%A6%E6%8A%80%E6%9C%AF%E8%81%8C%E4%B8%9A%E5%AD%A6%E9%99%A2 | AJ48: https://gaokao.chsi.com.cn/zsgs/zhangcheng/listZszc//schId/1104.dhtml | AK48: /
A49: 44 | B49: =C49 -> 0 | D49: 依据学考 | E49: 12040 | F49: 广州民航职业技术学院 | G49: 604 | H49: 210 | I49: 240 | J49: 210 | K49: 240 | L49: 374 | M49: 387 | N49: 27902 | O49: 29114 | P49: =IFERROR(AVERAGE(L49:M49),"/") -> 380.5 | Q49: =IFERROR(AVERAGE(N49:O49),"/") -> 28508 | R49: 广东省 | S49: 广州市 | T49: 广东省 | U49: 专科（高职） | V49: 交通运输部（中国民用航空局） | W49: 公办 | X49: 一线城市 | Y49: 部委院校/省部共建/双高计划/高水平专业群建设单位/国家级示范/现代学徒制试点学院 | Z49: 示范高职/第四类高水平专业群C档 | AA49: 广州民航职业技术学院直属中国民用航空局，是民航内最早一所独立设置实施高等职业教育的全日制公办普通高校。学校1994年被国家教育部确定为全国首批十所试办五年制高职教育的学校之一；1999年经教育部、民航局批准成立；2010年被教育部、财政部确定为国家示范性高等职业院校，是全国百所、广东省四所之一，民航唯一一所国家示范性高等职业院校；2013年正式成为民航局与广东省“省部共建”院校；2016年被广东省教育厅、财政厅确定为“广东省一流高职院校建设计划立项建设单位”。//学校“立足民航，服务地方，面向世界”，坚持职业教育类型的办学定位，在全国率先提出并实施了基于行业标准的技术技能人才培养模式，形成了“依托行业、产学合作、双师双证、国际通用”的办学特色。//学校现有机场路校区、白云机场校区、花都赤坭校区三个校区，共占地1112亩。现有固定资产总值约10.05亿元，其中，教学、科研仪器设备资产值约2.39亿元，33架大中小型教学用飞机，140台飞机发动机，5万多台（件）飞机零部件和一大批专业设备。//学校教职工规模689人，其中，专任教师549人，具有硕士以上学位的教师425人，占专任教师比例为77%；具有双师素质的专业教师224人，占专业课教师数的比例为64%；具有行业企业一线工作经历的教师比例为44.8%；具有民航行业特有工种职业资格证书、职业技能鉴定考评员及教员证书、其他工种职业资格证书的教师比例为41%。//学校下设飞机维修工程学院、航空港管理学院、民航经营管理学院、人文社科学院、继续教育学院五个二级学院。面向31个省、市、自治区招生，现有21个专业26个专业方向，覆盖了民航维修和服务的关键岗位，在校生1.2余万人。新生报到率、毕业生就业率、专业对口率等方面均走在同类院校前列，其中，飞机机电设备维修、飞机结构修理、航空电子设备维修、航空地面设备维修、通用航空器维修等民航特有专业对口率均超过90%，优秀毕业生已成为技术骨干与管理人才。//学校以现代民用航空体系和航空产业链建设需求为导向，以飞机维修、民航运输等民航特有专业岗位（群）核心能力培养为主线，创新了“课证一体、中外融通、校企融合”的民航特有专业人才培养模式。制定了基于行业标准的民航特有专业课程教学标准，做到“行业标准入体系、职业标准入课程”，与民航行业企业合作共建民航飞机维修工程、航空港安全检查、航空服务、通用航空等民航特有专业的校企共享型“公共实训平台”，为全国其他院校的民航专业教学起到引领作用。//学校不断加强与美国、英国、加拿大、新加坡、香港等境外院校和航空企业合作，提升办学国际化水平；与斯里兰卡等“一带一路”沿线国家开展民航职业教育合作，实现教育资源对外输出；先后与美国西敏学院、马来西亚建设大学、台湾中华科技大学开展本科层次职业教育合作，搭建人才成长“立交桥”，实现民航职业教育体系中外衔接；通过国际合作与对外交流，促进了人才培养标准、师资、教材和管理国际化，实现了学校教育与国际接轨，提升了民航职业教育软实力。 | AB49: 学校源自1980年由原中国民航广州管理局举办的技工学校。1984年在此基础上成立“中国民航广州中等专业学校”，由民航广州地区管理局领导管理。1999年经教育部批准成立“广州民航职业技术学院”。2013年成为民航局与广东省“省部共建”院校，2019年被列入第四类高水平专业群建设单位（C档）。 2021年现代学徒制第三批试点验收暂缓通过。 | AC49: http://www.caac.net/ | AD49: https://www.gcac.edu.cn/sites/zsb/index.html | AE49: 020/86123135、86121941 | AF49: 机场路校区：广东省广州市白云区机场路向云西街10号,白云机场校区：广州市白云国际机场空港北横六路 | AG49: / | AH49: 2377 | AI49: https://baike.baidu.com/item/%E5%B9%BF%E5%B7%9E%E6%B0%91%E8%88%AA%E8%81%8C%E4%B8%9A%E6%8A%80%E6%9C%AF%E5%AD%A6%E9%99%A2 | AJ49: https://gaokao.chsi.com.cn/zsgs/zhangcheng/listZszc//schId/952.dhtml | AK49: /
A50: 45 | B50: =C50 -> 0 | D50: 依据学考 | E50: 12327 | F50: 佛山职业技术学院 | G50: 605 | H50: 130 | I50: 145 | J50: 130 | K50: 145 | L50: 372 | M50: 388 | N50: 31071 | O50: 27522 | P50: =IFERROR(AVERAGE(L50:M50),"/") -> 380 | Q50: =IFERROR(AVERAGE(N50:O50),"/") -> 29296.5 | R50: 广东省 | S50: 佛山市 | T50: 广东省 | U50: 专科（高职） | V50: 广东省 | W50: 公办 | X50: 新一线城市 | Y50: / | Z50: 省属高等/公立/高等专科学校 | AA50: 佛山职业技术学院于2000年6月正式挂牌成立，是一所全日制公办普通高等职业技术院校，经过多年的建设发展，学校已成广东省示范性高等职业院校建设单位、广东省一流高职院校建设单位。学校现为佛山市职业技术教育基地总部单位，佛山市职业教育校企合作联盟、园区校企协同合作育人联盟理事长单位，佛山市职业教育学会牵头单位。现有全日制在校生近万人。学校设有6个二级学院（机电工程学院、电子信息学院、汽车工程学院、工商管理学院、财经管理学院、马克思主义学院），35个专业，2个优势专业群（智能制造、光电技术），2个特色专业群（汽车技术、信息技术），5个省级重点专业（机械设计与制造、光伏工程技术、汽车检测与维修技术、物流管理、数控技术）/，7个省级品牌专业（电气自动化技术、工业机器人技术、物联网应用技术、电子信息工程技术、汽车车身维修技术专业、金融管理专业、国际贸易（跨境电商）），主持国家级专业教学资源库项目2项（新能源类国家级专业教学资源库、智能控制技术专业教学资源库）。专业布局重点面向智能制造、先进制造业、战略性新兴产业、高新技术产业、现代服务业。现有智能制造、光电技术、汽车技术、信息技术、金融服务等九大专业群，形成了以工为主，文、管、经、艺术协调发展的专业布局。学校坐落于三水国家级工业园区腹地，校园总占地面积962亩，建筑面积23.5万平方米，政府总投资11.8亿元，生均教学设备值达到2万元。现有3个中央财政支持实训基地、6个省级实训基地、2个省级公共实训中心、9个省级校外实践教学基地，24个校内实训基地（实训中心），235个校外实习实训基地。学生文化体育设施齐全，建设了学生活动中心、田径场、篮球场、网球场等各类场馆。学校秉承“修身/笃学/长技/创新”的校训精神，坚持“以德治校、人才强校、质量立校、特色兴校”的发展策略，围绕“立足地方、服务企业、质量为本、校企联动”的办学理念，主动适应佛山市和珠三角经济产业发展需求，按照“新产业引领新专业、强专业支撑强产业”的专业建设原则，全面实施“校企双元、工学结合”的人才培养模式改革，大力建设园区校企协同育人联盟、佛山市职业教育校企合作联盟，广东省协同育人平台—佛山市机械装备业政校企行协同育人基地，基本形成了依托一汽大众、青岛海尔、长安福特等龙头企业协同培养学生、依托佛山科勒、三水合成等骨干企业协同开展培训、科技服务等，依托诺尔贝机器人、南海增材制造加速器等中小微企业协同创新研发新产品的产教融合、校企合作模式。学校重视面向企业、社会大力开展继续教育和培训工作，年社会培训等指标大幅度增长，社会培训达116130人天，2018年比2016年增长57.67%。学校承担了建设省科技厅对口科教援疆项目，组建伽师校企合作共同体，与黑龙江能源职业技术学院共建“双佛绿色食品研发中心暨博士工作站”；在云浮建城镇东坑村建屋顶太阳能光伏发电站，帮扶脱贫攻坚；承接英德市新型职业农民培训项目/物流与电子商务培训，助力乡村振兴；职教帮扶广西贺州职业学院、罗定职业技术学院和揭阳职业技术学院；教师走进马来西亚等“一带一路”沿线国家开展技术服务，通过科技帮扶，促进区域协调发展，发挥学校的示范引领、辐射带动作用。学校在中外合作办学、师生交流、国际课程与标准引进等领域开展了广泛、深入的国际交流与合作。学校拓展对外合作网络，与多所高水平国境外院校建立合作关系；积极引进国境外优质教育资源，加强师资队伍国际化建设；成功引入德国职业教育的先进理念，与佛山市中德工业服务区合作，成立了佛山职业技术学院中德职业技术培训学院，成为广东省重点建设的6大品牌之一，并率先与全球知名企业——德国KUKA集团联合建立机器人应用技术与培训中心。学校与澳大利亚斯威本科技大学签署中澳会计专业本科2+2项目，与法国克莱蒙商学院签署中法国际管理本科2+2项目，实现国际班项目的学分互认。学校在提高人才培养质量方面取得较好成效。学生参加全国职业院校技能大赛获国家级奖项22项、省级奖项196项；国（境）外技能大赛获奖4项；科技学术类大赛省级获奖46项；以学生为第一发明人的专利授权3项。全国大学生数学建模竞赛专科组一等奖1项；2016届毕业生张展耀荣获团中央学校部、全国学联秘书处颁发的“2017年大学生创业英雄十强”。2017年、2018年我校在全国职业院校技能大赛高职组比赛中获奖总数分别位列全国第29、30位。学校毕业生广受社会欢迎，2018年招生工作中，普通高考文、理科第一志愿投档率均达到100%。毕业生就业率态势喜人，据省教育厅统计，2018年我校毕业生初次就业率为97.54%，高于全省高职高专院校平均水平，毕业生最终就业率99.89%，专业对口率为90.76%。“十三五”期间，学校将继续坚持以“合作办学、合作育人、合作就业、合作发展”为主线，按照培育工匠精神的要求，培养一大批深受社会好评的高素质技术技能人才，努力建成特色鲜明、国内一流、国际知名的高等职业技术学院。 | AB50: 2000年6月，经广东省人民政府批准、中华人民共和国教育部备案，佛山煤田职工地质学院与佛山市机电学校、佛山职工大学合并组建佛山职业技术学院。 | AC50: http://www.fspt.net/ | AD50: https://zs.fspt.edu.cn/ | AE50: 0757/87263121 | AF50: 佛山市三水区乐平镇职教路3号 | AG50: / | AH50: 2329 | AI50: https://baike.baidu.com/item/%E4%BD%9B%E5%B1%B1%E8%81%8C%E4%B8%9A%E6%8A%80%E6%9C%AF%E5%AD%A6%E9%99%A2 | AJ50: https://gaokao.chsi.com.cn/zsgs/zhangcheng/listZszc//schId/1018.dhtml | AK50: /
A51: 46 | B51: =C51 -> 0 | D51: 依据学考 | E51: 12327 | F51: 佛山职业技术学院 | G51: 602 | H51: 325 | I51: 360 | J51: 325 | K51: 360 | L51: 372 | M51: 387 | N51: 30826 | O51: 27945 | P51: =IFERROR(AVERAGE(L51:M51),"/") -> 379.5 | Q51: =IFERROR(AVERAGE(N51:O51),"/") -> 29385.5 | R51: 广东省 | S51: 佛山市 | T51: 广东省 | U51: 专科（高职） | V51: 广东省 | W51: 公办 | X51: 新一线城市 | Y51: / | Z51: 省属高等/公立/高等专科学校 | AA51: 佛山职业技术学院于2000年6月正式挂牌成立，是一所全日制公办普通高等职业技术院校，经过多年的建设发展，学校已成广东省示范性高等职业院校建设单位、广东省一流高职院校建设单位。学校现为佛山市职业技术教育基地总部单位，佛山市职业教育校企合作联盟、园区校企协同合作育人联盟理事长单位，佛山市职业教育学会牵头单位。现有全日制在校生近万人。学校设有6个二级学院（机电工程学院、电子信息学院、汽车工程学院、工商管理学院、财经管理学院、马克思主义学院），35个专业，2个优势专业群（智能制造、光电技术），2个特色专业群（汽车技术、信息技术），5个省级重点专业（机械设计与制造、光伏工程技术、汽车检测与维修技术、物流管理、数控技术）/，7个省级品牌专业（电气自动化技术、工业机器人技术、物联网应用技术、电子信息工程技术、汽车车身维修技术专业、金融管理专业、国际贸易（跨境电商）），主持国家级专业教学资源库项目2项（新能源类国家级专业教学资源库、智能控制技术专业教学资源库）。专业布局重点面向智能制造、先进制造业、战略性新兴产业、高新技术产业、现代服务业。现有智能制造、光电技术、汽车技术、信息技术、金融服务等九大专业群，形成了以工为主，文、管、经、艺术协调发展的专业布局。学校坐落于三水国家级工业园区腹地，校园总占地面积962亩，建筑面积23.5万平方米，政府总投资11.8亿元，生均教学设备值达到2万元。现有3个中央财政支持实训基地、6个省级实训基地、2个省级公共实训中心、9个省级校外实践教学基地，24个校内实训基地（实训中心），235个校外实习实训基地。学生文化体育设施齐全，建设了学生活动中心、田径场、篮球场、网球场等各类场馆。学校秉承“修身/笃学/长技/创新”的校训精神，坚持“以德治校、人才强校、质量立校、特色兴校”的发展策略，围绕“立足地方、服务企业、质量为本、校企联动”的办学理念，主动适应佛山市和珠三角经济产业发展需求，按照“新产业引领新专业、强专业支撑强产业”的专业建设原则，全面实施“校企双元、工学结合”的人才培养模式改革，大力建设园区校企协同育人联盟、佛山市职业教育校企合作联盟，广东省协同育人平台—佛山市机械装备业政校企行协同育人基地，基本形成了依托一汽大众、青岛海尔、长安福特等龙头企业协同培养学生、依托佛山科勒、三水合成等骨干企业协同开展培训、科技服务等，依托诺尔贝机器人、南海增材制造加速器等中小微企业协同创新研发新产品的产教融合、校企合作模式。学校重视面向企业、社会大力开展继续教育和培训工作，年社会培训等指标大幅度增长，社会培训达116130人天，2018年比2016年增长57.67%。学校承担了建设省科技厅对口科教援疆项目，组建伽师校企合作共同体，与黑龙江能源职业技术学院共建“双佛绿色食品研发中心暨博士工作站”；在云浮建城镇东坑村建屋顶太阳能光伏发电站，帮扶脱贫攻坚；承接英德市新型职业农民培训项目/物流与电子商务培训，助力乡村振兴；职教帮扶广西贺州职业学院、罗定职业技术学院和揭阳职业技术学院；教师走进马来西亚等“一带一路”沿线国家开展技术服务，通过科技帮扶，促进区域协调发展，发挥学校的示范引领、辐射带动作用。学校在中外合作办学、师生交流、国际课程与标准引进等领域开展了广泛、深入的国际交流与合作。学校拓展对外合作网络，与多所高水平国境外院校建立合作关系；积极引进国境外优质教育资源，加强师资队伍国际化建设；成功引入德国职业教育的先进理念，与佛山市中德工业服务区合作，成立了佛山职业技术学院中德职业技术培训学院，成为广东省重点建设的6大品牌之一，并率先与全球知名企业——德国KUKA集团联合建立机器人应用技术与培训中心。学校与澳大利亚斯威本科技大学签署中澳会计专业本科2+2项目，与法国克莱蒙商学院签署中法国际管理本科2+2项目，实现国际班项目的学分互认。学校在提高人才培养质量方面取得较好成效。学生参加全国职业院校技能大赛获国家级奖项22项、省级奖项196项；国（境）外技能大赛获奖4项；科技学术类大赛省级获奖46项；以学生为第一发明人的专利授权3项。全国大学生数学建模竞赛专科组一等奖1项；2016届毕业生张展耀荣获团中央学校部、全国学联秘书处颁发的“2017年大学生创业英雄十强”。2017年、2018年我校在全国职业院校技能大赛高职组比赛中获奖总数分别位列全国第29、30位。学校毕业生广受社会欢迎，2018年招生工作中，普通高考文、理科第一志愿投档率均达到100%。毕业生就业率态势喜人，据省教育厅统计，2018年我校毕业生初次就业率为97.54%，高于全省高职高专院校平均水平，毕业生最终就业率99.89%，专业对口率为90.76%。“十三五”期间，学校将继续坚持以“合作办学、合作育人、合作就业、合作发展”为主线，按照培育工匠精神的要求，培养一大批深受社会好评的高素质技术技能人才，努力建成特色鲜明、国内一流、国际知名的高等职业技术学院。 | AB51: 2000年6月，经广东省人民政府批准、中华人民共和国教育部备案，佛山煤田职工地质学院与佛山市机电学校、佛山职工大学合并组建佛山职业技术学院。 | AC51: http://www.fspt.net/ | AD51: https://zs.fspt.edu.cn/ | AE51: 0757/87263121 | AF51: 佛山市三水区乐平镇职教路3号 | AG51: / | AH51: 2329 | AI51: https://baike.baidu.com/item/%E4%BD%9B%E5%B1%B1%E8%81%8C%E4%B8%9A%E6%8A%80%E6%9C%AF%E5%AD%A6%E9%99%A2 | AJ51: https://gaokao.chsi.com.cn/zsgs/zhangcheng/listZszc//schId/1018.dhtml | AK51: /
A52: 47 | B52: =C52 -> 0 | D52: 依据学考 | E52: 12327 | F52: 佛山职业技术学院 | G52: 601 | H52: 187 | I52: 350 | J52: 189 | K52: 350 | L52: 373 | M52: 386 | N52: 29366 | O52: 30274 | P52: =IFERROR(AVERAGE(L52:M52),"/") -> 379.5 | Q52: =IFERROR(AVERAGE(N52:O52),"/") -> 29820 | R52: 广东省 | S52: 佛山市 | T52: 广东省 | U52: 专科（高职） | V52: 广东省 | W52: 公办 | X52: 新一线城市 | Y52: / | Z52: 省属高等/公立/高等专科学校 | AA52: 佛山职业技术学院于2000年6月正式挂牌成立，是一所全日制公办普通高等职业技术院校，经过多年的建设发展，学校已成广东省示范性高等职业院校建设单位、广东省一流高职院校建设单位。学校现为佛山市职业技术教育基地总部单位，佛山市职业教育校企合作联盟、园区校企协同合作育人联盟理事长单位，佛山市职业教育学会牵头单位。现有全日制在校生近万人。学校设有6个二级学院（机电工程学院、电子信息学院、汽车工程学院、工商管理学院、财经管理学院、马克思主义学院），35个专业，2个优势专业群（智能制造、光电技术），2个特色专业群（汽车技术、信息技术），5个省级重点专业（机械设计与制造、光伏工程技术、汽车检测与维修技术、物流管理、数控技术）/，7个省级品牌专业（电气自动化技术、工业机器人技术、物联网应用技术、电子信息工程技术、汽车车身维修技术专业、金融管理专业、国际贸易（跨境电商）），主持国家级专业教学资源库项目2项（新能源类国家级专业教学资源库、智能控制技术专业教学资源库）。专业布局重点面向智能制造、先进制造业、战略性新兴产业、高新技术产业、现代服务业。现有智能制造、光电技术、汽车技术、信息技术、金融服务等九大专业群，形成了以工为主，文、管、经、艺术协调发展的专业布局。学校坐落于三水国家级工业园区腹地，校园总占地面积962亩，建筑面积23.5万平方米，政府总投资11.8亿元，生均教学设备值达到2万元。现有3个中央财政支持实训基地、6个省级实训基地、2个省级公共实训中心、9个省级校外实践教学基地，24个校内实训基地（实训中心），235个校外实习实训基地。学生文化体育设施齐全，建设了学生活动中心、田径场、篮球场、网球场等各类场馆。学校秉承“修身/笃学/长技/创新”的校训精神，坚持“以德治校、人才强校、质量立校、特色兴校”的发展策略，围绕“立足地方、服务企业、质量为本、校企联动”的办学理念，主动适应佛山市和珠三角经济产业发展需求，按照“新产业引领新专业、强专业支撑强产业”的专业建设原则，全面实施“校企双元、工学结合”的人才培养模式改革，大力建设园区校企协同育人联盟、佛山市职业教育校企合作联盟，广东省协同育人平台—佛山市机械装备业政校企行协同育人基地，基本形成了依托一汽大众、青岛海尔、长安福特等龙头企业协同培养学生、依托佛山科勒、三水合成等骨干企业协同开展培训、科技服务等，依托诺尔贝机器人、南海增材制造加速器等中小微企业协同创新研发新产品的产教融合、校企合作模式。学校重视面向企业、社会大力开展继续教育和培训工作，年社会培训等指标大幅度增长，社会培训达116130人天，2018年比2016年增长57.67%。学校承担了建设省科技厅对口科教援疆项目，组建伽师校企合作共同体，与黑龙江能源职业技术学院共建“双佛绿色食品研发中心暨博士工作站”；在云浮建城镇东坑村建屋顶太阳能光伏发电站，帮扶脱贫攻坚；承接英德市新型职业农民培训项目/物流与电子商务培训，助力乡村振兴；职教帮扶广西贺州职业学院、罗定职业技术学院和揭阳职业技术学院；教师走进马来西亚等“一带一路”沿线国家开展技术服务，通过科技帮扶，促进区域协调发展，发挥学校的示范引领、辐射带动作用。学校在中外合作办学、师生交流、国际课程与标准引进等领域开展了广泛、深入的国际交流与合作。学校拓展对外合作网络，与多所高水平国境外院校建立合作关系；积极引进国境外优质教育资源，加强师资队伍国际化建设；成功引入德国职业教育的先进理念，与佛山市中德工业服务区合作，成立了佛山职业技术学院中德职业技术培训学院，成为广东省重点建设的6大品牌之一，并率先与全球知名企业——德国KUKA集团联合建立机器人应用技术与培训中心。学校与澳大利亚斯威本科技大学签署中澳会计专业本科2+2项目，与法国克莱蒙商学院签署中法国际管理本科2+2项目，实现国际班项目的学分互认。学校在提高人才培养质量方面取得较好成效。学生参加全国职业院校技能大赛获国家级奖项22项、省级奖项196项；国（境）外技能大赛获奖4项；科技学术类大赛省级获奖46项；以学生为第一发明人的专利授权3项。全国大学生数学建模竞赛专科组一等奖1项；2016届毕业生张展耀荣获团中央学校部、全国学联秘书处颁发的“2017年大学生创业英雄十强”。2017年、2018年我校在全国职业院校技能大赛高职组比赛中获奖总数分别位列全国第29、30位。学校毕业生广受社会欢迎，2018年招生工作中，普通高考文、理科第一志愿投档率均达到100%。毕业生就业率态势喜人，据省教育厅统计，2018年我校毕业生初次就业率为97.54%，高于全省高职高专院校平均水平，毕业生最终就业率99.89%，专业对口率为90.76%。“十三五”期间，学校将继续坚持以“合作办学、合作育人、合作就业、合作发展”为主线，按照培育工匠精神的要求，培养一大批深受社会好评的高素质技术技能人才，努力建成特色鲜明、国内一流、国际知名的高等职业技术学院。 | AB52: 2000年6月，经广东省人民政府批准、中华人民共和国教育部备案，佛山煤田职工地质学院与佛山市机电学校、佛山职工大学合并组建佛山职业技术学院。 | AC52: http://www.fspt.net/ | AD52: https://zs.fspt.edu.cn/ | AE52: 0757/87263121 | AF52: 佛山市三水区乐平镇职教路3号 | AG52: / | AH52: 2329 | AI52: https://baike.baidu.com/item/%E4%BD%9B%E5%B1%B1%E8%81%8C%E4%B8%9A%E6%8A%80%E6%9C%AF%E5%AD%A6%E9%99%A2 | AJ52: https://gaokao.chsi.com.cn/zsgs/zhangcheng/listZszc//schId/1018.dhtml | AK52: /
A53: 48 | B53: =C53 -> 0 | D53: 依据学考 | E53: 13943 | F53: 广州铁路职业技术学院 | G53: 602 | H53: 223 | I53: 226 | J53: 223 | K53: 226 | L53: 372 | M53: 384 | N53: 30792 | O53: 34063 | P53: =IFERROR(AVERAGE(L53:M53),"/") -> 378 | Q53: =IFERROR(AVERAGE(N53:O53),"/") -> 32427.5 | R53: 广东省 | S53: 广州市 | T53: 广东省 | U53: 专科（高职） | V53: 广东省 | W53: 公办 | X53: 一线城市 | Y53: 双高计划/高水平专业群建设单位/国家级骨干/现代学徒制试点学院 | Z53: 第三类高水平专业群B档骨干高职现代学徒 | AA53: 学校前身为成立于1975年的原铁道部部属学校广州铁路机械学校，2000年成立广州铁路职业技术学院，2004年9月由广州铁路（集团）公司（现名中国铁路广州局集团有限公司，简称广铁集团）移交广州市政府举办，是广东省唯一一所以培养轨道交通特有专业人才为主的全日制普通高等职业院校，是华南地区轨道交通行业企业员工培训的重要基地。现为国家骨干高等职业院校、国家优质专科高等职业院校、教育部首批现代学徒制试点院校、广东省一流高职院校建设单位，获“全国职业院校就业竞争力示范校”、“中国职业教育就业百强”/、“全国高等职业院校创新发明教育基地”、“广东省依法治校示范校”等荣誉称号。学院现有石门、凰岗、执信南校区和朝阳实训中心、花都工学结合示范园等多个校区，学院开设了铁道供电技术、机械制造与自动化、城市轨道交通运营管理、铁道信号与自动控制、城市轨道交通车辆技术、商务英语等34个专业，全日制在校学生近8000人，设有电气工程学院、机电工程学院、运输物流学院、信息工程学院、外语商贸学院、机车车辆学院、基础课部、马克思主义学院等8个教学院（部）。学院办学条件优良，师资力量雄厚。教学科研仪器设备总值2.5亿元；纸质藏书58万册、电子图书98万种；专任教师具有研究生学位教师占专任教师70.5%，高级职称教师占33.2%，专业教师“双师”素质教师达93.7%。现有省高等学校教学名师1人、“广东特支计划”教学名师2人、省职业教育“双师型”名教师工作室主持人1人、省级优秀教学团队6支、市科技创新团队6个。学院面向广东、湖南、江西、四川、河南、内蒙古等19省（区）招生；毕业生出口畅、就业质量高，毕业生初次就业率平均达98.47%，就业对口率平均达86.41%，平均薪酬达3752元/月，区域龙头企业“订单”比例达60%以上，毕业生专业对口率和薪酬水平位列广东省同类专科院校前茅。深圳市地铁集团有限公司2012年“全国五一劳动奖章”获得者谢东田、2014年广铁集团“火车头奖章”获得者吴华创、2014年广铁集团“全国铁路劳动模范”获得者赖泽团、广州地铁集团公司2014年“全国五一劳动奖章”获得者徐志标、党的十九大福建省党代表、“全国劳动模范”获得者陈承仪均为我院毕业生。学院加强内涵建设，硕果累累。现有国家级标志性成果109项，其中教学成果奖3项，学生技能竞赛奖19项，教师教学能力大赛奖3项，专业资源库1项，教学标准3项，发明专利13项，软件著作权16项，实用新型专利22项，外观专利5项。省级标志性成果221项，其中教学成果奖5项，学生技能竞赛奖53项，教师教学能力大赛奖24项，专业资源库3项，承办技能竞赛6项。2017年学院被中国高等院校知识产权研究会评为“全国高等职业院校创新发明教育基地”。产教深度融合，协同创新平台实，服务成效明显。学院充分发挥行业办学背景和政府大力支持的双重优势，成立了广东省示范职业教育集团——广州工业交通职教集团；牵头组建了华南“一带一路”轨道交通产教融合联盟（简称产教融合联盟），主动对接国家“一带一路”倡议和“中国高铁走出去”战略联合培养培训本土化人才，输出轨道交通职业教育教学与培训标准。对接产业链，与广铁集团、广州地铁、深圳地铁、东莞地铁、佛山地铁、港铁（深圳）公司等知名企业共同制定人才培养方案，率先成规模地开展“订单”培养，形成学校与企业、专业与职业、学生与岗位对接的人才培养机制。对接国家战略，加强国际合作，提升合作深度。学院全力服务国家“一带一路”倡议和高铁“走出去”战略，依托产教融合联盟，对接独联体、东南亚、非洲和粤港澳大湾区4个区域，拓展国际合作平台。经广东省教育厅批准，与白俄罗斯国立交通大学正式签署了联合培养铁道交通运营专业（高等专科学历教育全日制）中外合作办学项目协议。来自老挝4所高职院校的17名学历留学生，正式开启在学院的留学生活，他们是广州市属高职院校首批全日制学历教育留学生。学院正以习近平新时代中国特色社会主义思想为指导，牢固树立新发展理念，以立德树人为根本，坚持“依托行业，立足广州，辐射全国，面向世界”的办学定位，围绕办好新时代职业教育的新要求，聚焦国家轨道交通产业升级和粤港澳大湾区建设，构建学历教育与培训并重的现代职业教育体系，完善学院内部治理体系，产教融合深化复合型技术技能人才培养培训模式改革，打造“特色引领、骨干支撑、协同发展”的专业群，形成工学结合、知行合一的高素质技术技能人才培养体系，为创建中国特色、具有一定国际影响力的高水平职业院校而努力奋斗！ | AB53: 学校前身为成立于1975年的原铁道部部委属院校广州铁路机械学校，2000年6月由广州铁路机械学校、广州铁路运输职工大学与广州铁路成人中等专业学校合并组建广州铁路职业技术学院学校。 | AC53: http://www.gtxy.cn/ | AD53: https://www.gtxy.cn/zsxxw | AE53: 020/36004159、020/37431459、18211478104 | AF53: 广东省广州市白云区石井街庆隆中路100号 | AG53: https://www.720yun.com/t/86dj5ztvrk6 | AH53: 1770 | AI53: https://baike.baidu.com/item/%E5%B9%BF%E5%B7%9E%E9%93%81%E8%B7%AF%E8%81%8C%E4%B8%9A%E6%8A%80%E6%9C%AF%E5%AD%A6%E9%99%A2 | AJ53: https://gaokao.chsi.com.cn/zsgs/zhangcheng/listZszc//schId/6196002.dhtml | AK53: /
A54: 49 | B54: =C54 -> 0 | D54: 依据学考 | E54: 12572 | F54: 广东科学技术职业学院 | G54: 607 | H54: 70 | I54: 295 | J54: 70 | K54: 295 | L54: 372 | M54: 384 | N54: 31179 | O54: 34388 | P54: =IFERROR(AVERAGE(L54:M54),"/") -> 378 | Q54: =IFERROR(AVERAGE(N54:O54),"/") -> 32783.5 | R54: 广东省 | S54: 广州市 | T54: 广东省 | U54: 专科（高职） | V54: 广东省 | W54: 公办 | X54: 一线城市 | Y54: 省属/双高计划/高水平专业群建设单位/国家级骨干/现代学徒制试点学院 | Z54: 第三类高水平专业群B档骨干高职现代学徒 | AA54: 学院是广东省人民政府1985年批准设立、教育部备案的一所全日制公办普通高等学院，正厅级建制。建院之初，学院名广东省科技干部进修学院，主要承担广东省科技管理干部的继续教育培训任务，被国家科技部称誉为“地方继续教育的一颗明珠”。1989年更名为广东省科技干部学院，1996年成为广东省首批举办普通高职教育的院校之一。2001年与珠海市政府合作共建珠海校区。2003年经教育部批准由成人高校改制为普通高等学院，并继续承担科技干部培训的任务。2008年5月，学院由广东省科技厅整建制划转广东省教育厅管理。学院于2008年12月以“优秀”成绩通过教育部高职高专人才培养工作评估。2010年被广东省政府授予“广东省职业技术教育工作先进集体”光荣称号。2010年被教育部、财政部确定为国家示范性骨干高职院校立项建设单位。2016年3月以“良好”成绩通过验收，成为国家示范性骨干高职院校。2016年7月被广东省科学技术厅确定为省“互联网+”创新创业示范校。2016年11月被广东省教育厅确定为一流高职院校立项建设单位。2019年7月被教育部确定为“国家优质专科高等职业院校”。2016、2017、2018连续三年入选全国高等职业院校服务贡献50强。2018年入选全国高等职业院校教学资源50强。2019年入选全国高等职业院校育人成效50强。2016年被国际创新创业博览会组委会授予“全国高职院校创新创业示范校”荣誉称号。学院现有珠海和广州两个校区，校园面积2012亩，建筑面积53.06万㎡（含在建工程：4.28万㎡）（其中：教室3.09万㎡，图书馆3.05万㎡，体育场馆0.98万㎡，实习实训场所15.55万㎡）。教学仪器设备2.16万台（套），教学科研仪器设备值25543.34万元。馆藏图书155.92万册、电子图书数字资源量7866GB。学院现有教职员工1320余人，其中专任教师1050人。专任教师中，正高职称70余人，副高职称270余人，拥有博士学位70余人，硕士学位660余人，双师素质教师950余人，专任教师“双师”素质比例达90%。全国教育系统先进集体1个，省级教学名师1人，南粤优秀教师9人，“千百十工程”省级培养对象5人，省高职教育专业领军人才培养对象3人，省优秀青年教师培养对象7人，珠海市特聘学者1人。学院全日制在校生23000多名，是在校生规模最大的省属高职院校。现设有计算机工程技术学院（软件学院）、大数据与人工智能学院、商学院、应用外语学院、旅游学院、文化与传媒学院、机器人学院、机械与汽车学院、建筑工程学院、艺术设计学院、财会与金融学院、体育健康学院、广州学院、马克思主义学院、国际合作学院、创新创业学院、继续教育学院等17个二级学院；设有广东省人才研究所、高职教育研究所、电子与信息技术研究所、软科学研究所等4个科研机构。学院现有招生专业48个，其中国家骨干高职院校重点建设专业5个，央财支持建设专业2个，省级示范专业5个，省级重点专业6个，广东省一类品牌专业1个、二类品牌专业12个。国家级精品资源共享课4门、国家精品课程5门、省级精品课程5门、省级精品资源共享课程22门，省精品在线开放课程3门，国家级备选专业教学资源库1个。获国家级、省级教学成果奖11项。学院加强校企合作办学，积极构建“校企精准对接、精准育人”人才培养模式，按照“一院一品”“一专业一特色一名企”的整体部署，将产业学院、项目班、订单班、现代学徒制等作为推进产教融合、“双精准”育人的重要举措，与微软中国、苹果、思科、华为、联想、金山软件、蓝盾股份、小米、一汽大众、横琴长隆、三一海洋重工等知名企业建立长期合作关系，大力加强学生技术技能培养。学院重视产学研合作、应用开发与成果转化，鼓励教师参与企业技术研发、提供技术服务，努力服务地方经济社会发展。仅2017、2018两年，学校各类科研与社会服务到款额达3942万元，首次获得国家社科基金项目1项,认定1/个国家级众创空间、1/个国家工作室、1/个省级中小企业服务示范平台；建成1个省级专业众创空间、31个协同创新和协同育人平台（其中省级及以上5个），培育10个高水平技术服务团队，社会培训58400余人日，对广东省创新创业示范市（区、县）的建设提供有效支撑。学院建有校内实训基地70多个、实训室240多个，校外实习实训基地800多个；建成中央财政支持实训基地4个，省级高职教育实训基地6个，省级大学生校外实践教学基地6个，省级公共实训中心2个，珠海市重点实验室1个，珠海市公共实验室1个。是国家科技部、省科技厅、教育厅、人事厅认定的“国家级星火培训基地”“广东科技人才基地”“广东省中职学院教师继续教育基地”“广东省专业技术人员继续教育基地”。学院积极构建对外开放新格局，稳步实施“走出去”战略，主动服务国家“一带一路”和粤港澳大湾区建设，加强与德国、法国、美国等职业教育发达国家和港澳台地区的交流与合作，先后与法国克莱蒙商学院、德国德累斯顿工业大学、美国北密歇根大学等签订了合作协议。2017年学校取得招收国际学生和港澳台学生资质，并启动招生工作。2018年获“广东省高等院校对外交流与合作先进集体”。学院学生在省级以上技能竞赛中屡获佳绩，尽显广科学子风采。近五年，学生获省级以上技能竞赛奖项600余项，其中在全国职业院校技能大赛（天津国赛）获奖30余项。如2018年全国职业院校技能大赛高职组导游服务一等奖，2017年全国职业院校技能大赛高职组建筑工程识图团体一等奖、英语口语一等奖，2017年全国大学生数学建模竞赛3项一等奖，2016年全国大学生数学建模竞赛3项一等奖，2015年全国职业院校技能大赛高职组计算机网络应用一等奖，第24届FIRA机器人世界杯大赛1项冠军，2017、2018、2019年连续三年获得中国机器人及人工智能大赛9项全国冠军。机械与汽车学院2016级胡智文同学作为广东省唯一代表荣获2017年度“劲牌阳光奖学金”特别奖暨“践行工匠精神先进个人”，成为全国获此殊荣的十名代表之一，在校期间先后获得国际级、国家级、省级、校级等各类奖项共20余项。一大批优秀毕业生脱颖而出，在各行各业做出突出成绩，得到社会广泛好评。如2006届毕业生谭倩茹同学，获“红棉杯”中国原创产品设计大赛金奖，其工业设计作品得到原广东省委书记张德江，省长黄华华同志的亲笔题词；研发95款手游APP的移动应用开发中心学生团队，被媒体誉为“最牛高职生”；2013届毕业生孙志斌，是国内首个获得思科网络学院全额奖学金赴美实习的高职生；2011届毕业生黄胜，受邀参加央视《奋斗》访谈栏目；2011届毕业生聂云宸创办喜茶品牌，进入福布斯2018年中国30岁以下精英榜单等。学院招生“进口”旺，现每年面向全国18个省（直辖市、自治区）招收全日制在校生8000人左右，广东省录取的新生均为第一志愿报考我院的考生。学院积极开展中高职衔接、三二分段、现代学徒制等多形式自主招生，以及本专科协同育人试点招生工作。毕业生就业“出口”畅，总体就业率均达98%以上。学院秉承“厚德、高能、求实、创新”的校训，坚持“质量立校、特色兴校、创新强校”的办学思路，积极构建“双精准”育人模式，着力打造“互联网+”科技特色，大力实施国际化发展战略，努力培养创新型技能人才，正为创建全国一流、国际知名高职院校而不懈努力。（2019年10月20日更新） | AB54: 学校成立于1985年，前身是广东省科技干部学院，2003年改制为普通高等学校，2004年被教育部、建设部确认为建设行业技能型紧缺人才培养培训工程试点高校，2010年被教育部、财政部确定为“国家示范性高职院校建设计划”骨干高职院校立项建设单位。2015年入选国家首批现代学徒制试点单位。2019年12月，被教育部、财政部列入第三类高水平专业群建设单位（B档）。 | AC54: http://www.gdit.edu.cn/ | AD54: https://www.gdit.edu.cn/zsb/main.htm | AE54: 0756/7796101,020/85297313 | AF54: 广州校区：广州市天河区科华街351号,珠海校区：珠海市金湾区珠海大道南侧 | AG54: https://www.720yun.com/t/096jupwvef3 | AH54: 1329 | AI54: https://baike.baidu.com/item/%E5%B9%BF%E4%B8%9C%E7%A7%91%E5%AD%A6%E6%8A%80%E6%9C%AF%E8%81%8C%E4%B8%9A%E5%AD%A6%E9%99%A2 | AJ54: https://gaokao.chsi.com.cn/zsgs/zhangcheng/listZszc//schId/1104.dhtml | AK54: /
A55: 50 | B55: =C55 -> 0 | D55: 依据学考 | E55: 12040 | F55: 广州民航职业技术学院 | G55: 603 | H55: 140 | I55: 140 | J55: 140 | K55: 140 | L55: 371 | M55: 384 | N55: 33191 | O55: 34229 | P55: =IFERROR(AVERAGE(L55:M55),"/") -> 377.5 | Q55: =IFERROR(AVERAGE(N55:O55),"/") -> 33710 | R55: 广东省 | S55: 广州市 | T55: 广东省 | U55: 专科（高职） | V55: 交通运输部（中国民用航空局） | W55: 公办 | X55: 一线城市 | Y55: 部委院校/省部共建/双高计划/高水平专业群建设单位/国家级示范/现代学徒制试点学院 | Z55: 示范高职/第四类高水平专业群C档 | AA55: 广州民航职业技术学院直属中国民用航空局，是民航内最早一所独立设置实施高等职业教育的全日制公办普通高校。学校1994年被国家教育部确定为全国首批十所试办五年制高职教育的学校之一；1999年经教育部、民航局批准成立；2010年被教育部、财政部确定为国家示范性高等职业院校，是全国百所、广东省四所之一，民航唯一一所国家示范性高等职业院校；2013年正式成为民航局与广东省“省部共建”院校；2016年被广东省教育厅、财政厅确定为“广东省一流高职院校建设计划立项建设单位”。//学校“立足民航，服务地方，面向世界”，坚持职业教育类型的办学定位，在全国率先提出并实施了基于行业标准的技术技能人才培养模式，形成了“依托行业、产学合作、双师双证、国际通用”的办学特色。//学校现有机场路校区、白云机场校区、花都赤坭校区三个校区，共占地1112亩。现有固定资产总值约10.05亿元，其中，教学、科研仪器设备资产值约2.39亿元，33架大中小型教学用飞机，140台飞机发动机，5万多台（件）飞机零部件和一大批专业设备。//学校教职工规模689人，其中，专任教师549人，具有硕士以上学位的教师425人，占专任教师比例为77%；具有双师素质的专业教师224人，占专业课教师数的比例为64%；具有行业企业一线工作经历的教师比例为44.8%；具有民航行业特有工种职业资格证书、职业技能鉴定考评员及教员证书、其他工种职业资格证书的教师比例为41%。//学校下设飞机维修工程学院、航空港管理学院、民航经营管理学院、人文社科学院、继续教育学院五个二级学院。面向31个省、市、自治区招生，现有21个专业26个专业方向，覆盖了民航维修和服务的关键岗位，在校生1.2余万人。新生报到率、毕业生就业率、专业对口率等方面均走在同类院校前列，其中，飞机机电设备维修、飞机结构修理、航空电子设备维修、航空地面设备维修、通用航空器维修等民航特有专业对口率均超过90%，优秀毕业生已成为技术骨干与管理人才。//学校以现代民用航空体系和航空产业链建设需求为导向，以飞机维修、民航运输等民航特有专业岗位（群）核心能力培养为主线，创新了“课证一体、中外融通、校企融合”的民航特有专业人才培养模式。制定了基于行业标准的民航特有专业课程教学标准，做到“行业标准入体系、职业标准入课程”，与民航行业企业合作共建民航飞机维修工程、航空港安全检查、航空服务、通用航空等民航特有专业的校企共享型“公共实训平台”，为全国其他院校的民航专业教学起到引领作用。//学校不断加强与美国、英国、加拿大、新加坡、香港等境外院校和航空企业合作，提升办学国际化水平；与斯里兰卡等“一带一路”沿线国家开展民航职业教育合作，实现教育资源对外输出；先后与美国西敏学院、马来西亚建设大学、台湾中华科技大学开展本科层次职业教育合作，搭建人才成长“立交桥”，实现民航职业教育体系中外衔接；通过国际合作与对外交流，促进了人才培养标准、师资、教材和管理国际化，实现了学校教育与国际接轨，提升了民航职业教育软实力。 | AB55: 学校源自1980年由原中国民航广州管理局举办的技工学校。1984年在此基础上成立“中国民航广州中等专业学校”，由民航广州地区管理局领导管理。1999年经教育部批准成立“广州民航职业技术学院”。2013年成为民航局与广东省“省部共建”院校，2019年被列入第四类高水平专业群建设单位（C档）。 2021年现代学徒制第三批试点验收暂缓通过。 | AC55: http://www.caac.net/ | AD55: https://www.gcac.edu.cn/sites/zsb/index.html | AE55: 020/86123135、86121941 | AF55: 机场路校区：广东省广州市白云区机场路向云西街10号,白云机场校区：广州市白云国际机场空港北横六路 | AG55: / | AH55: 2377 | AI55: https://baike.baidu.com/item/%E5%B9%BF%E5%B7%9E%E6%B0%91%E8%88%AA%E8%81%8C%E4%B8%9A%E6%8A%80%E6%9C%AF%E5%AD%A6%E9%99%A2 | AJ55: https://gaokao.chsi.com.cn/zsgs/zhangcheng/listZszc//schId/952.dhtml | AK55: /
A56: 51 | B56: =C56 -> 0 | D56: 依据学考 | E56: 13943 | F56: 广州铁路职业技术学院 | G56: 601 | H56: 233 | I56: 315 | J56: 233 | K56: 315 | L56: 373 | M56: 382 | N56: 29492 | O56: 38901 | P56: =IFERROR(AVERAGE(L56:M56),"/") -> 377.5 | Q56: =IFERROR(AVERAGE(N56:O56),"/") -> 34196.5 | R56: 广东省 | S56: 广州市 | T56: 广东省 | U56: 专科（高职） | V56: 广东省 | W56: 公办 | X56: 一线城市 | Y56: 双高计划/高水平专业群建设单位/国家级骨干/现代学徒制试点学院 | Z56: 第三类高水平专业群B档骨干高职现代学徒 | AA56: 学校前身为成立于1975年的原铁道部部属学校广州铁路机械学校，2000年成立广州铁路职业技术学院，2004年9月由广州铁路（集团）公司（现名中国铁路广州局集团有限公司，简称广铁集团）移交广州市政府举办，是广东省唯一一所以培养轨道交通特有专业人才为主的全日制普通高等职业院校，是华南地区轨道交通行业企业员工培训的重要基地。现为国家骨干高等职业院校、国家优质专科高等职业院校、教育部首批现代学徒制试点院校、广东省一流高职院校建设单位，获“全国职业院校就业竞争力示范校”、“中国职业教育就业百强”/、“全国高等职业院校创新发明教育基地”、“广东省依法治校示范校”等荣誉称号。学院现有石门、凰岗、执信南校区和朝阳实训中心、花都工学结合示范园等多个校区，学院开设了铁道供电技术、机械制造与自动化、城市轨道交通运营管理、铁道信号与自动控制、城市轨道交通车辆技术、商务英语等34个专业，全日制在校学生近8000人，设有电气工程学院、机电工程学院、运输物流学院、信息工程学院、外语商贸学院、机车车辆学院、基础课部、马克思主义学院等8个教学院（部）。学院办学条件优良，师资力量雄厚。教学科研仪器设备总值2.5亿元；纸质藏书58万册、电子图书98万种；专任教师具有研究生学位教师占专任教师70.5%，高级职称教师占33.2%，专业教师“双师”素质教师达93.7%。现有省高等学校教学名师1人、“广东特支计划”教学名师2人、省职业教育“双师型”名教师工作室主持人1人、省级优秀教学团队6支、市科技创新团队6个。学院面向广东、湖南、江西、四川、河南、内蒙古等19省（区）招生；毕业生出口畅、就业质量高，毕业生初次就业率平均达98.47%，就业对口率平均达86.41%，平均薪酬达3752元/月，区域龙头企业“订单”比例达60%以上，毕业生专业对口率和薪酬水平位列广东省同类专科院校前茅。深圳市地铁集团有限公司2012年“全国五一劳动奖章”获得者谢东田、2014年广铁集团“火车头奖章”获得者吴华创、2014年广铁集团“全国铁路劳动模范”获得者赖泽团、广州地铁集团公司2014年“全国五一劳动奖章”获得者徐志标、党的十九大福建省党代表、“全国劳动模范”获得者陈承仪均为我院毕业生。学院加强内涵建设，硕果累累。现有国家级标志性成果109项，其中教学成果奖3项，学生技能竞赛奖19项，教师教学能力大赛奖3项，专业资源库1项，教学标准3项，发明专利13项，软件著作权16项，实用新型专利22项，外观专利5项。省级标志性成果221项，其中教学成果奖5项，学生技能竞赛奖53项，教师教学能力大赛奖24项，专业资源库3项，承办技能竞赛6项。2017年学院被中国高等院校知识产权研究会评为“全国高等职业院校创新发明教育基地”。产教深度融合，协同创新平台实，服务成效明显。学院充分发挥行业办学背景和政府大力支持的双重优势，成立了广东省示范职业教育集团——广州工业交通职教集团；牵头组建了华南“一带一路”轨道交通产教融合联盟（简称产教融合联盟），主动对接国家“一带一路”倡议和“中国高铁走出去”战略联合培养培训本土化人才，输出轨道交通职业教育教学与培训标准。对接产业链，与广铁集团、广州地铁、深圳地铁、东莞地铁、佛山地铁、港铁（深圳）公司等知名企业共同制定人才培养方案，率先成规模地开展“订单”培养，形成学校与企业、专业与职业、学生与岗位对接的人才培养机制。对接国家战略，加强国际合作，提升合作深度。学院全力服务国家“一带一路”倡议和高铁“走出去”战略，依托产教融合联盟，对接独联体、东南亚、非洲和粤港澳大湾区4个区域，拓展国际合作平台。经广东省教育厅批准，与白俄罗斯国立交通大学正式签署了联合培养铁道交通运营专业（高等专科学历教育全日制）中外合作办学项目协议。来自老挝4所高职院校的17名学历留学生，正式开启在学院的留学生活，他们是广州市属高职院校首批全日制学历教育留学生。学院正以习近平新时代中国特色社会主义思想为指导，牢固树立新发展理念，以立德树人为根本，坚持“依托行业，立足广州，辐射全国，面向世界”的办学定位，围绕办好新时代职业教育的新要求，聚焦国家轨道交通产业升级和粤港澳大湾区建设，构建学历教育与培训并重的现代职业教育体系，完善学院内部治理体系，产教融合深化复合型技术技能人才培养培训模式改革，打造“特色引领、骨干支撑、协同发展”的专业群，形成工学结合、知行合一的高素质技术技能人才培养体系，为创建中国特色、具有一定国际影响力的高水平职业院校而努力奋斗！ | AB56: 学校前身为成立于1975年的原铁道部部委属院校广州铁路机械学校，2000年6月由广州铁路机械学校、广州铁路运输职工大学与广州铁路成人中等专业学校合并组建广州铁路职业技术学院学校。 | AC56: http://www.gtxy.cn/ | AD56: https://www.gtxy.cn/zsxxw | AE56: 020/36004159、020/37431459、18211478104 | AF56: 广东省广州市白云区石井街庆隆中路100号 | AG56: https://www.720yun.com/t/86dj5ztvrk6 | AH56: 1770 | AI56: https://baike.baidu.com/item/%E5%B9%BF%E5%B7%9E%E9%93%81%E8%B7%AF%E8%81%8C%E4%B8%9A%E6%8A%80%E6%9C%AF%E5%AD%A6%E9%99%A2 | AJ56: https://gaokao.chsi.com.cn/zsgs/zhangcheng/listZszc//schId/6196002.dhtml | AK56: /
A57: 52 | B57: =C57 -> 0 | D57: 依据学考 | E57: 14066 | F57: 中山职业技术学院 | G57: 601 | H57: 105 | I57: 80 | J57: 105 | K57: 80 | L57: 369 | M57: 385 | N57: 35254 | O57: 33194 | P57: =IFERROR(AVERAGE(L57:M57),"/") -> 377 | Q57: =IFERROR(AVERAGE(N57:O57),"/") -> 34224 | R57: 广东省 | S57: 中山市 | T57: 广东省 | U57: 专科（高职） | V57: 广东省 | W57: 公办 | X57: 三线城市 | Y57: 现代学徒制试点学院 | Z57: 现代学徒 | AA57: 中山职业技术学院位于我国伟大民主革命先行者孙中山先生的故乡—广东省中山市，是市政府投资兴办的全日制普通高等学校。成立于2006年6月，是“广东省示范性高等职业院校”和“广东省一流高职院校建设单位”，入榜“全国高职院校服务贡献50强”，先后荣获“黄炎培职业教育优秀学校奖”“全国高职院校创新创业教育工作先进单位”“广东省知识产权示范事业单位”“广东省首批大学生创新创业教育示范学校”“广东省安全文明校园”等荣誉称号。历年学生参加全国职业院校技能大赛总分保持全省高职院校前五名，用人单位满意度排名全省高职院校第二名，学校整体办学实力位居全省高职院校前列。学校设有素质教育中心、思想政治理论课教学部、经济管理学院、电子信息工程学院、机电工程学院、艺术设计学院和创业教育学院，现有全日制学生7300余人，成人教育在籍学生8000余人。学校大力实施教育教学改革，紧贴中山产业结构特点实施“一镇一品一专业”专业布局，建成与珠三角区域专业镇先进制造业、现代服务业、战略性新兴产业等高度对接的35个专业和5大专业群，实现“专业/产业”“人才/市场”无缝对接。拥有一批紧贴国家重点产业和中山支柱产业的骨干专业，省级一类品牌建设专业1个，省级二类品牌建设专业5个，省级重点建设专业16个，电梯维护与管理、灯具设计与工艺、创业管理是全国高职高专首开专业。现有省级质量工程项目34项、中央财政支持实训基地3个、省级重点实训基地8个，教学设备总值达1.6亿元。学校发扬“敢为天下先”的创新精神，“政校企”合作办学体制机制改革示范全国。学校与专业镇深度产教融合，校企合作专业覆盖面超过90%，在古镇镇“国家火炬计划照明器材生产基地”成立“古镇灯饰学院”，在南区“国家火炬计划电梯特色产业基地”成立“南区电梯学院”，在“中国休闲服装生产基地”沙溪镇成立“沙溪纺织服装学院”，在小榄镇商贸物流园区成立“小榄学院”，在“中国红木产业之都”大涌镇成立“红木家居学院”。将办学边界从中等城市向下延伸至乡镇，使教育科研资源辐射到镇区企业、社区，有效促进当地产业发展和城镇化进程。率先探索混合所有制办学体制，目前，5个产业学院均形成镇校二元或多元投资结构，构建了董（理）事会领导下的院长负责制，其中小榄学院的工商管理专业和南区电梯学院的电梯工程技术专业还率先试行了现代学徒制。学校积极服务区域创新驱动发展战略，致力于服务专业镇产业转型升级和中小微企业技术创新，以学校“总部”为主体，与多个专业镇合作联盟式协同发展，形成“总部+基地”的产学研协同创新格局。近百名教师作为省部产学研科技特派员分别派驻农村、镇区，协助企业开展科技攻关，派驻人数和科技服务项目数位列全省高校前茅。办学以来，学校承担教科研立项课题540余项，其中国家火炬计划项目1项，国家级、省级课题56项，70多项科技成果逐步实现技术转移，并形成产业化生产。学校产学研园入围国家发改委“十三五”产教融合发展工程项目（全国百强，全省仅5所高职院校立项），产学研综合服务成果得到国家教育体制改革领导小组的高度肯定。学校是国内最早探索创新创业教育的高职院校之一，探索构建了普及化、融合化、专业化“三化并进”创新创业教育路径体系，形成了“分层施教、系统推进、全面覆盖”的创新创业教育工作特色。连续两年获评全国高职院校创新创业教育工作先进单位，是广东省高职院校创业教育教学指导委员会主任委员单位和广东省大学生创新创业教育首批示范校。学校运营管理的中山市大学生创业孵化基地荣获“全国创业孵化示范基地”称号，成为广东省唯一一个国家级创业孵化基地和国家级众创空间。创新创业蔚然成风，涌现出大批投身新产业、新业态、新模式的师生创客。学校搭建面向专业镇人口素质提升的继续教育服务平台，累计承接各类培训20余万人次。贯彻服务“一带一路”建设，积极开展对外交流与国际化办学，先后和香港、澳门、台湾、新加坡、马来西亚、韩国、英国、美国、澳大利亚、德国、老挝、瑞士等多个国家和地区知名大学建立合作关系。学校大力实施能工巧匠落户工程、教学名师培养工程、专业骨干培优工程、教师转型提升工程和高级人才引进工程，打破人事政策壁垒，大量引进职教专家、企业技术骨干、能工巧匠等，构建了一支专兼结合、素质优良、结构合理的“双师型”教学团队。目前教职员工603人，其中专任教师441人，双师素质教师占比80%，具有企业工作经历占比85%，拥有一批全国技术能手、中国工艺美术大师、广东省技术能手、广东省工艺美术大师、广东特支计划教学名师、省级教学名师、千百十工程培养对象、中山市优秀专家、拔尖人才等，以明阳风电集团董事长张传卫等为代表的一大批企业家、技术能手受聘学校客座教授、兼职教师。学校以创建“特色鲜明、国内一流、世界有影响”的现代化高职院校为目标，秉承“修德、砺能、笃行、创新”校训精神，坚持“育人为本、工学结合、创新发展、服务社会”办学理念，全面加强内涵建设，不断提升办学水平，努力为广东实现“四个走在全国前列”作出新贡献。 | AB57: 2004年12月，中山职业技术学院（筹）开始筹备 。于2006年6月20日挂牌成立 。2013年11月，被确定为广东省示范性职业院校。2016年9月7日，学校获广东省一流高职院校建设单位 。2020年9月23日，学校获“中国创新创业成果交易会成果转化基地”授牌 。2022年1月，学校获批为国家自然科学基金依托单位 。2023年1月5日，中山职业技术学院广东省省级大学科技园揭牌 。12月，中山职业技术学院成立中山市首个高校妇女联合会 。 | AC57: http://www.zspt.cn/ | AD57: http://zs.zspt.cn | AE57: 0760/88269288 | AF57: 广东省中山市东区博爱七路25号 | AG57: https://www.720yun.com/t/6a52b9z5uti | AH57: 1464 | AI57: https://baike.baidu.com/item/%E4%B8%AD%E5%B1%B1%E8%81%8C%E4%B8%9A%E6%8A%80%E6%9C%AF%E5%AD%A6%E9%99%A2 | AJ57: https://gaokao.chsi.com.cn/zsgs/zhangcheng/listZszc//schId/5163160.dhtml | AK57: /
A58: 53 | B58: =C58 -> 0 | D58: 依据学考 | E58: 12572 | F58: 广东科学技术职业学院 | G58: 602 | H58: 211 | I58: 617 | J58: 211 | K58: 617 | L58: 370 | M58: 384 | N58: 34955 | O58: 34453 | P58: =IFERROR(AVERAGE(L58:M58),"/") -> 377 | Q58: =IFERROR(AVERAGE(N58:O58),"/") -> 34704 | R58: 广东省 | S58: 广州市 | T58: 广东省 | U58: 专科（高职） | V58: 广东省 | W58: 公办 | X58: 一线城市 | Y58: 省属/双高计划/高水平专业群建设单位/国家级骨干/现代学徒制试点学院 | Z58: 第三类高水平专业群B档骨干高职现代学徒 | AA58: 学院是广东省人民政府1985年批准设立、教育部备案的一所全日制公办普通高等学院，正厅级建制。建院之初，学院名广东省科技干部进修学院，主要承担广东省科技管理干部的继续教育培训任务，被国家科技部称誉为“地方继续教育的一颗明珠”。1989年更名为广东省科技干部学院，1996年成为广东省首批举办普通高职教育的院校之一。2001年与珠海市政府合作共建珠海校区。2003年经教育部批准由成人高校改制为普通高等学院，并继续承担科技干部培训的任务。2008年5月，学院由广东省科技厅整建制划转广东省教育厅管理。学院于2008年12月以“优秀”成绩通过教育部高职高专人才培养工作评估。2010年被广东省政府授予“广东省职业技术教育工作先进集体”光荣称号。2010年被教育部、财政部确定为国家示范性骨干高职院校立项建设单位。2016年3月以“良好”成绩通过验收，成为国家示范性骨干高职院校。2016年7月被广东省科学技术厅确定为省“互联网+”创新创业示范校。2016年11月被广东省教育厅确定为一流高职院校立项建设单位。2019年7月被教育部确定为“国家优质专科高等职业院校”。2016、2017、2018连续三年入选全国高等职业院校服务贡献50强。2018年入选全国高等职业院校教学资源50强。2019年入选全国高等职业院校育人成效50强。2016年被国际创新创业博览会组委会授予“全国高职院校创新创业示范校”荣誉称号。学院现有珠海和广州两个校区，校园面积2012亩，建筑面积53.06万㎡（含在建工程：4.28万㎡）（其中：教室3.09万㎡，图书馆3.05万㎡，体育场馆0.98万㎡，实习实训场所15.55万㎡）。教学仪器设备2.16万台（套），教学科研仪器设备值25543.34万元。馆藏图书155.92万册、电子图书数字资源量7866GB。学院现有教职员工1320余人，其中专任教师1050人。专任教师中，正高职称70余人，副高职称270余人，拥有博士学位70余人，硕士学位660余人，双师素质教师950余人，专任教师“双师”素质比例达90%。全国教育系统先进集体1个，省级教学名师1人，南粤优秀教师9人，“千百十工程”省级培养对象5人，省高职教育专业领军人才培养对象3人，省优秀青年教师培养对象7人，珠海市特聘学者1人。学院全日制在校生23000多名，是在校生规模最大的省属高职院校。现设有计算机工程技术学院（软件学院）、大数据与人工智能学院、商学院、应用外语学院、旅游学院、文化与传媒学院、机器人学院、机械与汽车学院、建筑工程学院、艺术设计学院、财会与金融学院、体育健康学院、广州学院、马克思主义学院、国际合作学院、创新创业学院、继续教育学院等17个二级学院；设有广东省人才研究所、高职教育研究所、电子与信息技术研究所、软科学研究所等4个科研机构。学院现有招生专业48个，其中国家骨干高职院校重点建设专业5个，央财支持建设专业2个，省级示范专业5个，省级重点专业6个，广东省一类品牌专业1个、二类品牌专业12个。国家级精品资源共享课4门、国家精品课程5门、省级精品课程5门、省级精品资源共享课程22门，省精品在线开放课程3门，国家级备选专业教学资源库1个。获国家级、省级教学成果奖11项。学院加强校企合作办学，积极构建“校企精准对接、精准育人”人才培养模式，按照“一院一品”“一专业一特色一名企”的整体部署，将产业学院、项目班、订单班、现代学徒制等作为推进产教融合、“双精准”育人的重要举措，与微软中国、苹果、思科、华为、联想、金山软件、蓝盾股份、小米、一汽大众、横琴长隆、三一海洋重工等知名企业建立长期合作关系，大力加强学生技术技能培养。学院重视产学研合作、应用开发与成果转化，鼓励教师参与企业技术研发、提供技术服务，努力服务地方经济社会发展。仅2017、2018两年，学校各类科研与社会服务到款额达3942万元，首次获得国家社科基金项目1项,认定1/个国家级众创空间、1/个国家工作室、1/个省级中小企业服务示范平台；建成1个省级专业众创空间、31个协同创新和协同育人平台（其中省级及以上5个），培育10个高水平技术服务团队，社会培训58400余人日，对广东省创新创业示范市（区、县）的建设提供有效支撑。学院建有校内实训基地70多个、实训室240多个，校外实习实训基地800多个；建成中央财政支持实训基地4个，省级高职教育实训基地6个，省级大学生校外实践教学基地6个，省级公共实训中心2个，珠海市重点实验室1个，珠海市公共实验室1个。是国家科技部、省科技厅、教育厅、人事厅认定的“国家级星火培训基地”“广东科技人才基地”“广东省中职学院教师继续教育基地”“广东省专业技术人员继续教育基地”。学院积极构建对外开放新格局，稳步实施“走出去”战略，主动服务国家“一带一路”和粤港澳大湾区建设，加强与德国、法国、美国等职业教育发达国家和港澳台地区的交流与合作，先后与法国克莱蒙商学院、德国德累斯顿工业大学、美国北密歇根大学等签订了合作协议。2017年学校取得招收国际学生和港澳台学生资质，并启动招生工作。2018年获“广东省高等院校对外交流与合作先进集体”。学院学生在省级以上技能竞赛中屡获佳绩，尽显广科学子风采。近五年，学生获省级以上技能竞赛奖项600余项，其中在全国职业院校技能大赛（天津国赛）获奖30余项。如2018年全国职业院校技能大赛高职组导游服务一等奖，2017年全国职业院校技能大赛高职组建筑工程识图团体一等奖、英语口语一等奖，2017年全国大学生数学建模竞赛3项一等奖，2016年全国大学生数学建模竞赛3项一等奖，2015年全国职业院校技能大赛高职组计算机网络应用一等奖，第24届FIRA机器人世界杯大赛1项冠军，2017、2018、2019年连续三年获得中国机器人及人工智能大赛9项全国冠军。机械与汽车学院2016级胡智文同学作为广东省唯一代表荣获2017年度“劲牌阳光奖学金”特别奖暨“践行工匠精神先进个人”，成为全国获此殊荣的十名代表之一，在校期间先后获得国际级、国家级、省级、校级等各类奖项共20余项。一大批优秀毕业生脱颖而出，在各行各业做出突出成绩，得到社会广泛好评。如2006届毕业生谭倩茹同学，获“红棉杯”中国原创产品设计大赛金奖，其工业设计作品得到原广东省委书记张德江，省长黄华华同志的亲笔题词；研发95款手游APP的移动应用开发中心学生团队，被媒体誉为“最牛高职生”；2013届毕业生孙志斌，是国内首个获得思科网络学院全额奖学金赴美实习的高职生；2011届毕业生黄胜，受邀参加央视《奋斗》访谈栏目；2011届毕业生聂云宸创办喜茶品牌，进入福布斯2018年中国30岁以下精英榜单等。学院招生“进口”旺，现每年面向全国18个省（直辖市、自治区）招收全日制在校生8000人左右，广东省录取的新生均为第一志愿报考我院的考生。学院积极开展中高职衔接、三二分段、现代学徒制等多形式自主招生，以及本专科协同育人试点招生工作。毕业生就业“出口”畅，总体就业率均达98%以上。学院秉承“厚德、高能、求实、创新”的校训，坚持“质量立校、特色兴校、创新强校”的办学思路，积极构建“双精准”育人模式，着力打造“互联网+”科技特色，大力实施国际化发展战略，努力培养创新型技能人才，正为创建全国一流、国际知名高职院校而不懈努力。（2019年10月20日更新） | AB58: 学校成立于1985年，前身是广东省科技干部学院，2003年改制为普通高等学校，2004年被教育部、建设部确认为建设行业技能型紧缺人才培养培训工程试点高校，2010年被教育部、财政部确定为“国家示范性高职院校建设计划”骨干高职院校立项建设单位。2015年入选国家首批现代学徒制试点单位。2019年12月，被教育部、财政部列入第三类高水平专业群建设单位（B档）。 | AC58: http://www.gdit.edu.cn/ | AD58: https://www.gdit.edu.cn/zsb/main.htm | AE58: 0756/7796101,020/85297313 | AF58: 广州校区：广州市天河区科华街351号,珠海校区：珠海市金湾区珠海大道南侧 | AG58: https://www.720yun.com/t/096jupwvef3 | AH58: 1329 | AI58: https://baike.baidu.com/item/%E5%B9%BF%E4%B8%9C%E7%A7%91%E5%AD%A6%E6%8A%80%E6%9C%AF%E8%81%8C%E4%B8%9A%E5%AD%A6%E9%99%A2 | AJ58: https://gaokao.chsi.com.cn/zsgs/zhangcheng/listZszc//schId/1104.dhtml | AK58: /
... A61: 56 | B61: =C61 -> 0 | D61: 依据学考 | E61: 14066 | F61: 中山职业技术学院 | G61: 602 | H61: 100 | I61: 140 | J61: 100 | K61: 140 | L61: 367 | M61: 382 | N61: 39289 | O61: 39176 | P61: =IFERROR(AVERAGE(L61:M61),"/") -> 374.5 | Q61: =IFERROR(AVERAGE(N61:O61),"/") -> 39232.5 | R61: 广东省 | S61: 中山市 | T61: 广东省 | U61: 专科（高职） | V61: 广东省 | W61: 公办 | X61: 三线城市 | Y61: 现代学徒制试点学院 | Z61: 现代学徒 | AA61: 中山职业技术学院位于我国伟大民主革命先行者孙中山先生的故乡—广东省中山市，是市政府投资兴办的全日制普通高等学校。成立于2006年6月，是“广东省示范性高等职业院校”和“广东省一流高职院校建设单位”，入榜“全国高职院校服务贡献50强”，先后荣获“黄炎培职业教育优秀学校奖”“全国高职院校创新创业教育工作先进单位”“广东省知识产权示范事业单位”“广东省首批大学生创新创业教育示范学校”“广东省安全文明校园”等荣誉称号。历年学生参加全国职业院校技能大赛总分保持全省高职院校前五名，用人单位满意度排名全省高职院校第二名，学校整体办学实力位居全省高职院校前列。学校设有素质教育中心、思想政治理论课教学部、经济管理学院、电子信息工程学院、机电工程学院、艺术设计学院和创业教育学院，现有全日制学生7300余人，成人教育在籍学生8000余人。学校大力实施教育教学改革，紧贴中山产业结构特点实施“一镇一品一专业”专业布局，建成与珠三角区域专业镇先进制造业、现代服务业、战略性新兴产业等高度对接的35个专业和5大专业群，实现“专业/产业”“人才/市场”无缝对接。拥有一批紧贴国家重点产业和中山支柱产业的骨干专业，省级一类品牌建设专业1个，省级二类品牌建设专业5个，省级重点建设专业16个，电梯维护与管理、灯具设计与工艺、创业管理是全国高职高专首开专业。现有省级质量工程项目34项、中央财政支持实训基地3个、省级重点实训基地8个，教学设备总值达1.6亿元。学校发扬“敢为天下先”的创新精神，“政校企”合作办学体制机制改革示范全国。学校与专业镇深度产教融合，校企合作专业覆盖面超过90%，在古镇镇“国家火炬计划照明器材生产基地”成立“古镇灯饰学院”，在南区“国家火炬计划电梯特色产业基地”成立“南区电梯学院”，在“中国休闲服装生产基地”沙溪镇成立“沙溪纺织服装学院”，在小榄镇商贸物流园区成立“小榄学院”，在“中国红木产业之都”大涌镇成立“红木家居学院”。将办学边界从中等城市向下延伸至乡镇，使教育科研资源辐射到镇区企业、社区，有效促进当地产业发展和城镇化进程。率先探索混合所有制办学体制，目前，5个产业学院均形成镇校二元或多元投资结构，构建了董（理）事会领导下的院长负责制，其中小榄学院的工商管理专业和南区电梯学院的电梯工程技术专业还率先试行了现代学徒制。学校积极服务区域创新驱动发展战略，致力于服务专业镇产业转型升级和中小微企业技术创新，以学校“总部”为主体，与多个专业镇合作联盟式协同发展，形成“总部+基地”的产学研协同创新格局。近百名教师作为省部产学研科技特派员分别派驻农村、镇区，协助企业开展科技攻关，派驻人数和科技服务项目数位列全省高校前茅。办学以来，学校承担教科研立项课题540余项，其中国家火炬计划项目1项，国家级、省级课题56项，70多项科技成果逐步实现技术转移，并形成产业化生产。学校产学研园入围国家发改委“十三五”产教融合发展工程项目（全国百强，全省仅5所高职院校立项），产学研综合服务成果得到国家教育体制改革领导小组的高度肯定。学校是国内最早探索创新创业教育的高职院校之一，探索构建了普及化、融合化、专业化“三化并进”创新创业教育路径体系，形成了“分层施教、系统推进、全面覆盖”的创新创业教育工作特色。连续两年获评全国高职院校创新创业教育工作先进单位，是广东省高职院校创业教育教学指导委员会主任委员单位和广东省大学生创新创业教育首批示范校。学校运营管理的中山市大学生创业孵化基地荣获“全国创业孵化示范基地”称号，成为广东省唯一一个国家级创业孵化基地和国家级众创空间。创新创业蔚然成风，涌现出大批投身新产业、新业态、新模式的师生创客。学校搭建面向专业镇人口素质提升的继续教育服务平台，累计承接各类培训20余万人次。贯彻服务“一带一路”建设，积极开展对外交流与国际化办学，先后和香港、澳门、台湾、新加坡、马来西亚、韩国、英国、美国、澳大利亚、德国、老挝、瑞士等多个国家和地区知名大学建立合作关系。学校大力实施能工巧匠落户工程、教学名师培养工程、专业骨干培优工程、教师转型提升工程和高级人才引进工程，打破人事政策壁垒，大量引进职教专家、企业技术骨干、能工巧匠等，构建了一支专兼结合、素质优良、结构合理的“双师型”教学团队。目前教职员工603人，其中专任教师441人，双师素质教师占比80%，具有企业工作经历占比85%，拥有一批全国技术能手、中国工艺美术大师、广东省技术能手、广东省工艺美术大师、广东特支计划教学名师、省级教学名师、千百十工程培养对象、中山市优秀专家、拔尖人才等，以明阳风电集团董事长张传卫等为代表的一大批企业家、技术能手受聘学校客座教授、兼职教师。学校以创建“特色鲜明、国内一流、世界有影响”的现代化高职院校为目标，秉承“修德、砺能、笃行、创新”校训精神，坚持“育人为本、工学结合、创新发展、服务社会”办学理念，全面加强内涵建设，不断提升办学水平，努力为广东实现“四个走在全国前列”作出新贡献。 | AB61: 2004年12月，中山职业技术学院（筹）开始筹备 。于2006年6月20日挂牌成立 。2013年11月，被确定为广东省示范性职业院校。2016年9月7日，学校获广东省一流高职院校建设单位 。2020年9月23日，学校获“中国创新创业成果交易会成果转化基地”授牌 。2022年1月，学校获批为国家自然科学基金依托单位 。2023年1月5日，中山职业技术学院广东省省级大学科技园揭牌 。12月，中山职业技术学院成立中山市首个高校妇女联合会 。 | AC61: http://www.zspt.cn/ | AD61: http://zs.zspt.cn | AE61: 0760/88269288 | AF61: 广东省中山市东区博爱七路25号 | AG61: https://www.720yun.com/t/6a52b9z5uti | AH61: 1464 | AI61: https://baike.baidu.com/item/%E4%B8%AD%E5%B1%B1%E8%81%8C%E4%B8%9A%E6%8A%80%E6%9C%AF%E5%AD%A6%E9%99%A2 | AJ61: https://gaokao.chsi.com.cn/zsgs/zhangcheng/listZszc//schId/5163160.dhtml | AK61: /
